Workbook
Name _Toc233296974: Evalueringshieraki!$B$4
Name _Toc233296977: Evalueringshieraki!$B$5
Name _Toc233296984: 'Production Plan'!$E$13
Name _Toc233296986: 'Production Plan'!$E$19
Name _Toc233296997: 'Production Plan'!$E$71
Name _Toc233297011: 'Production Plan'!$D$173

Sheet Production Plan
A1: # | B1: ReqID | C1: Document | D1: Section (Headline) | E1: Subsection | F1: Requirement title | G1: Requirement | H1: Besvarelsesvejledning | I1: Requirement type | J1: Action | K1: Faktor | L1: Kvalitetskriterium | M1: Vægt (point) | N1: Round #1 | O1: Responsible | P1: Reviewer | Q1: Module | R1: Can we meet the requirement? | S1: Comment | T1: Commitment needed? | U1: Risk Element? | V1: Cost Driver | W1: Link to answer document | X1: Status (phase) | Y1: Status (%)
A2: 1 | B2: 4.1.1. | C2: Bilag 2 - Kravspecifikation | D2: Tidsplan (15%) | E2: Implementering og tidsplan | F2: Implementeringsplan | G2: Implementeringsplan Leverandøren skal beskrive sin samlede plan for implementering af Løsningen hos Kunden. Beskrivelsen skal omfatte punkterne i Bilag 11 Dokumentations, pkt. 7: Det vægtes positivt, at:  Leverandøren demonstrerer en klar forståelse for Kundens it-miljø og de tekniske forudsætninger, herunder relevante integrationer, snitflader, datamigrering og sikkerhedsmæssige forhold.  Tidsplanen afspejler Kundens organisation og implementeringens kompleksitet.  Leverandøren giver en sammenhængende og realistisk faseopdeling af implementeringsforløbet med klare milepæle og godkendelsespunkter, der sikrer, at Kunden kan godkende afslutning af en fase, før næste fase igangsættes.  Leverandøren tydeligt beskriver kendte risici og faldgruber i implementeringsforløbet, samt konkrete mitigerende tiltag.  At tidsplanen tager højde for, at Ordregiver har en løbende drift der skal varetages og perioder med begrænsede ressourcer | H2: Informationskravet besvares ved at Leverandøren vedhæfter eget bilag og udfylder tabel 5.4. (Detaljeret tidsplan) i Bilag 1 - Implementering | I2: IK - Informationskrav | J2: =IF(I2="IK - Informationskrav","Answer",(IF(I2="K - Konkurrencekrav","Check",(IF(I2="MK - Mindstekrav","Verify",""))))) -> Answer | K2: 2 | L2: 1 | M2: 4 | O2: Cristina | S2: Evt. koordiner med Kaare AOP: OBS at Eskalering sker i overensstemmelse med den i bilag 1 – Implementering gældende samarbejdsorganisation, f.eks. driftsgruppen eller jf. Kontraktens afsnit 31 vedr. Tvister. - denne skal derfor tage højde for dette. | W2: Bilag 2 - 4.1.1 - Implementeringsplan.docx | X2: Not Started | Y2: =IF(X2="Not Started",0%,IF(X2="Read",1%,IF(X2="Started",50%,IF(X2="Ready for review",70%,IF(X2="Reviewed - Content",80%,IF(X2="Reviewed - Format",90%,IF(X2="Done",100%,""))))))) -> 0
A3: 2 | B3: 4.2.1. | C3: Bilag 2 - Kravspecifikation | D3: Tidsplan (15%) | E3: Tidsplan for optioner | F3: Tidsplan for optioner | G3: Tidsplan for optioner Leverandøren bedes redegøre for hvornår optionerne, jf. punkt 5.4. (5.4.1. & 5.4.2.) i nærværende bilag, kan forventes færdigleveret efter Kunden har kaldt optioner. Leverandøren skal indregne alle relevante faktorer, såsom udvikling af integrationen, men også forhold hos Kunden som Leverandøren er bekendt med ud fra nærværende materiale samt tilhørende bilag. Det vægter positivt at - optionen tilbydes til levering så tæt på Overtagelsesdagen, som muligt. - tidligste dato for Kundens kald af optionen er så tæt på Kontraktindgåelsesdatoen, som muligt. | H3: Informationskravet besvares ved at Leverandøren vedhæfter eget bilag. | I3: IK - Informationskrav | J3: =IF(I3="IK - Informationskrav","Answer",(IF(I3="K - Konkurrencekrav","Check",(IF(I3="MK - Mindstekrav","Verify",""))))) -> Answer | K3: 1 | L3: 1 | M3: 8 | O3: Cristina | W3: Bilag 2 - 4.2.1 - Tidsplan for optioner.docx | X3: Not Started | Y3: =IF(X3="Not Started",0%,IF(X3="Read",1%,IF(X3="Started",50%,IF(X3="Ready for review",70%,IF(X3="Reviewed - Content",80%,IF(X3="Reviewed - Format",90%,IF(X3="Done",100%,""))))))) -> 0
A4: 3 | B4: 5.1.1.1. | C4: Bilag 2 - Kravspecifikation | D4: Generelle krav | E4: Test og prøver | F4: Prøveplan | G4: Prøveplan Leverandøren skal beskrive teststrategien og redegøre for hvorledes aktiviteterne bedst påviser, at kravene i Bilag 2 (Kravspecifikation) efterleves. Det vægtes positivt, at:  Leverandøren beskriver teststrategien på en måde, så den tydelig beskriver, hvilken teststrategi Leverandøren anvender for at sikre, at Løsningen lever op til Kundens krav  Leverandøren beskriver eksempler på prøveplaner og testrapport med angivelse af ansvarsfordeling, testprincipper, metoder og værktøjer mm.  Leverandøren beskriver hvordan og i hvilken grad testcases udledes af Kundens krav  Hvordan dokumenteres og sikres kvalitet og stabilitet under test og prøver, f.eks. ved brug af dedikerede testværktøjer såsom Azure DevOps el.lign. | H4: Informationskravet besvares ved at Leverandøren vedhæfter eget bilag. | I4: IK - Informationskrav | J4: =IF(I4="IK - Informationskrav","Answer",(IF(I4="K - Konkurrencekrav","Check",(IF(I4="MK - Mindstekrav","Verify",""))))) -> Answer | K4: 2 | L4: 2 | M4: =Evalueringshieraki!$Q$16 -> 0.97087379 | O4: Cristina | W4: Bilag 2 - 5.1.1.1 - Prøveplan.docx | X4: Not Started | Y4: =IF(X4="Not Started",0%,IF(X4="Read",1%,IF(X4="Started",50%,IF(X4="Ready for review",70%,IF(X4="Reviewed - Content",80%,IF(X4="Reviewed - Format",90%,IF(X4="Done",100%,""))))))) -> 0
A5: 4 | B5: 5.1.2.1. | C5: Bilag 2 - Kravspecifikation | D5: Generelle krav | E5: Uddannelse | F5: Uddannelse | G5: Uddannelse Leverandøren skal levere en uddannelsesplan, der medfører at de forskellige typer af Brugere er i stand til at anvende Systemet ved idriftsættelse. Besvarelsen bør tage udgangspunkt i nærværende krav samt Bilag 1 (Implementering) pkt. 7 og Bilag 11 (Dokumentation) pkt. 7. Leverandøren skal i besvarelsen redegøre for deres undervisningstilbud i Løsningen, herunder de(n) tilknyttede instruktørers undervisningserfaring. Det vægtes positivt, at: - at der for de enkelte kurser er klare, konkrete og realistiske læringsmål - at det viser organiseringen af den tilbudte undervisning - at uddannelsen i videst muligt omfang tager afsæt i de forskellige Brugeres faglige profil og relevante arbejdsgange - at kurserne i videst muligt omfang behandler Kundens centrale arbejdsgange - at instruktører er erfarne i at undervise og kender målgruppens hverdag | H5: Informationskravet besvares i Leverandørens eget bilag. | I5: IK - Informationskrav | J5: =IF(I5="IK - Informationskrav","Answer",(IF(I5="K - Konkurrencekrav","Check",(IF(I5="MK - Mindstekrav","Verify",""))))) -> Answer | K5: 1 | L5: 3 | M5: 30 | O5: Anton | P5: Tony, Cristian | W5: Bilag 2 - 5.1.2.1 - Uddannelse.docx | X5: Started | Y5: =IF(X5="Not Started",0%,IF(X5="Read",1%,IF(X5="Started",50%,IF(X5="Ready for review",70%,IF(X5="Reviewed - Content",80%,IF(X5="Reviewed - Format",90%,IF(X5="Done",100%,""))))))) -> 0.5
A6: 5 | B6: 5.1.3.1. | C6: Bilag 2 - Kravspecifikation | D6: Generelle krav | E6: Data migrering og konvertering | F6: Migreringsplan | G6: Migreringsplan Leverandøren skal levere en migreringsplan og bedes redegøre for hvordan migrering fra Kundens eksisterende system til Systemet vil forløbe med udgangspunkt i kravene i Bilag 1 Implementering, pkt. 6. Migreringsplanens udformning og indhold skal følge Bilag 11 (Dokumentation) pkt. 7. Det vægter positivt at: - dataintegritet af migreringen valideres løbende, f.eks. gennem checksum, tests og overvågning. - data håndteres sikkert, f.eks. ved kryptering. - data migreres og konverteres så automatisk som muligt. - der er indtænkt processer for håndtering af fejl - datamigrering påvirker Brugerens arbejde mindst muligt - besvarelsen indeholder flere konkrete eksempler og detaljer vedr. migreringsaktiviteter. | H6: Informationskravet besvares i Leverandørens eget bilag. | I6: IK - Informationskrav | J6: =IF(I6="IK - Informationskrav","Answer",(IF(I6="K - Konkurrencekrav","Check",(IF(I6="MK - Mindstekrav","Verify",""))))) -> Answer | K6: 2 | L6: 1 | M6: 8 | O6: Kaare | S6: Koordiner med Cristina. | W6: Bilag 2 - 5.1.3.1 - Migreringsplan.docx | X6: Not Started | Y6: =IF(X6="Not Started",0%,IF(X6="Read",1%,IF(X6="Started",50%,IF(X6="Ready for review",70%,IF(X6="Reviewed - Content",80%,IF(X6="Reviewed - Format",90%,IF(X6="Done",100%,""))))))) -> 0
A7: 6 | B7: 5.2.1.1. | C7: Bilag 2 - Kravspecifikation | D7: Funktionelle krav | E7: Journalisering, dokumenthåndtering og sagsoverblik | F7: Opmærkning af sager og dokumenter | G7: Opmærkning af sager og dokumenter Både sager og dokumenter skal kunne opmærkes, struktureres eller tildeles ”tags” på baggrund af emne, type, kategori m.m. som gør det lettere at søge, sortere og få overblik over data. Løsningen skal give mulighed for sortering på fx indsendelser, dato, emne, teknisk kapitel (fra BOM), fase (fra BOM, bl.a. 'ansøgning', 'under arbejde', 'efter endt arbejde' osv.). Det vægtes positivt, at Leverandøren i sin besvarelse demonstrerer, at Løsningen understøtter:  at data og dokumentation automatisk inddeles i en logisk og overskuelig struktur på sagen  at sagsbehandlere fleksibelt kan tilpasse strukturen til den enkelte sag eller sagstype  at "tag"-funktionen giver mulighed for at tagge på tværs af evt. dokumentstruktur og dokumenttyper  at sortering kan foretages på flere parametre samtidigt (fx fase og dato kombineret)  at sortering og inddeling er konsistent på tværs af sager og sagstyper, så der sikres ensartethed i sagsbehandlingen  at nye sorteringsparametre kan tilføjes uden behov for systemudvikling  At man hurtigt kan se, hvad der er sagsbehandlet og hvad der udestår. | I7: IK - Informationskrav | J7: =IF(I7="IK - Informationskrav","Answer",(IF(I7="K - Konkurrencekrav","Check",(IF(I7="MK - Mindstekrav","Verify",""))))) -> Answer | K7: 1 | L7: 2 | M7: =Evalueringshieraki!$P$16 -> 0.48543689 | O7: Bjørn Henrik | W7: Bilag 2 - 5.2.1.1 - Opmærkning af sager og dokumenter.docx | X7: Not Started | Y7: =IF(X7="Not Started",0%,IF(X7="Read",1%,IF(X7="Started",50%,IF(X7="Ready for review",70%,IF(X7="Reviewed - Content",80%,IF(X7="Reviewed - Format",90%,IF(X7="Done",100%,""))))))) -> 0
A8: 7 | B8: 5.2.1.2. | C8: Bilag 2 - Kravspecifikation | D8: Funktionelle krav | E8: Journalisering, dokumenthåndtering og sagsoverblik | F8: Konfliktløsning | G8: Konfliktløsning Løsningen skal kunne initiere/kalde en konfliktsøgning der foretages af andet system. Det være sig GIS, en robot eller AI løsning. Initieringen kan være på baggrund af en matrikel, BFE-nr., adresse eller lignende (som altså kan medsendes i kaldet til det eksterne system) Det vægtes positivt, at Leverandøren i sin besvarelse demonstrerer, at Løsningen understøtter:  at konfliktsøgningen kan sættes til at køre automatisk ved oprettelse af nye sager  at sagsbehandler adviseres tydeligt, hvis der identificeres konflikter  at det angives hvis der er adressebeskyttelse eller fortrolighed  at konfliktsøgningen kan gemmes som et dokument på sagen, meget gerne automatisk | I8: IK - Informationskrav | J8: =IF(I8="IK - Informationskrav","Answer",(IF(I8="K - Konkurrencekrav","Check",(IF(I8="MK - Mindstekrav","Verify",""))))) -> Answer | K8: 1 | L8: 2 | M8: =Evalueringshieraki!$P$16 -> 0.48543689 | O8: Arve | T8: Yes | W8: Bilag 2 - 5.2.1.2 - Konfliktløsning.docx | X8: Not Started | Y8: =IF(X8="Not Started",0%,IF(X8="Read",1%,IF(X8="Started",50%,IF(X8="Ready for review",70%,IF(X8="Reviewed - Content",80%,IF(X8="Reviewed - Format",90%,IF(X8="Done",100%,""))))))) -> 0
A9: 8 | B9: 5.2.1.3. | C9: Bilag 2 - Kravspecifikation | D9: Funktionelle krav | E9: Journalisering, dokumenthåndtering og sagsoverblik | F9: - | G9: Smidig journalisering af data/dokumentation på sagen fx ved ”drag & drop” (BOM/mail/blanketter/erhvervsportal). Dog også mulighed for manuel upload til journalisering. | I9: K - Konkurrencekrav | J9: =IF(I9="IK - Informationskrav","Answer",(IF(I9="K - Konkurrencekrav","Check",(IF(I9="MK - Mindstekrav","Verify",""))))) -> Check | K9: 1 | L9: 2 | M9: =Evalueringshieraki!$P$16 -> 0.48543689 | O9: Arve | R9: 1. Fully met | S9: Drag'n'drop from BOM? - Har BOM automatisk journalføring i vår BOM integrasjon (Må løftes inn i P&B) -Har skjemaimport, men må estimeres. | T9: Yes | X9: Not Started | Y9: =IF(X9="Not Started",0%,IF(X9="Read",1%,IF(X9="Started",50%,IF(X9="Ready for review",70%,IF(X9="Reviewed - Content",80%,IF(X9="Reviewed - Format",90%,IF(X9="Done",100%,""))))))) -> 0
A10: 9 | B10: 5.2.1.4. | C10: Bilag 2 - Kravspecifikation | D10: Funktionelle krav | E10: Journalisering, dokumenthåndtering og sagsoverblik | F10: - | G10: Løsningen skal kunne give et samlet overblik over tidligere og nuværende sager. | I10: K - Konkurrencekrav | J10: =IF(I10="IK - Informationskrav","Answer",(IF(I10="K - Konkurrencekrav","Check",(IF(I10="MK - Mindstekrav","Verify",""))))) -> Check | K10: 1 | L10: 2 | M10: =Evalueringshieraki!$P$16 -> 0.48543689 | O10: Anton | R10: 1. Fully met | X10: Ready for review | Y10: =IF(X10="Not Started",0%,IF(X10="Read",1%,IF(X10="Started",50%,IF(X10="Ready for review",70%,IF(X10="Reviewed - Content",80%,IF(X10="Reviewed - Format",90%,IF(X10="Done",100%,""))))))) -> 0.7
A11: 10 | B11: 5.2.1.5. | C11: Bilag 2 - Kravspecifikation | D11: Funktionelle krav | E11: Journalisering, dokumenthåndtering og sagsoverblik | F11: - | G11: Det skal være muligt at søge på og i sagernes dokumenter. | I11: K - Konkurrencekrav | J11: =IF(I11="IK - Informationskrav","Answer",(IF(I11="K - Konkurrencekrav","Check",(IF(I11="MK - Mindstekrav","Verify",""))))) -> Check | K11: 1 | L11: 2 | M11: =Evalueringshieraki!$P$16 -> 0.48543689 | O11: Anton | R11: 1. Fully met | X11: Ready for review | Y11: =IF(X11="Not Started",0%,IF(X11="Read",1%,IF(X11="Started",50%,IF(X11="Ready for review",70%,IF(X11="Reviewed - Content",80%,IF(X11="Reviewed - Format",90%,IF(X11="Done",100%,""))))))) -> 0.7
A12: 11 | B12: 5.2.1.6. | C12: Bilag 2 - Kravspecifikation | D12: Funktionelle krav | E12: Journalisering, dokumenthåndtering og sagsoverblik | F12: Understøttelse af Elektronisk Sags- og Dokumenthåndtering | G12: Understøttelse af Elektronisk Sags- og Dokumenthåndtering Leverandøren bedes redegøre for i hvilket omfang Løsningen kan understøtte Brugeren i at løfte journaliseringspligt, jf. offentliglovens § 15. Det vægter positivt at: - Kunden kan opsætte regler for hvem der kan redigere, slette fejloprettede sager eller genåbne afsluttede sager. - Løsningen understøtter automatisk journalisering - Dokumenter modtaget på sagerne journaliseres. - Notater nemt kan journaliseres af Brugeren. - Kommunikation der initieres eller modtages af systemet automatisk journaliseres på sagen. - Journaliserede elementer er tydeligt dateret. - Journaliseret indhold er opmærket så det er tydeligt hvad indholdet er. - Mulighed for KLE-opmærkning af sager | I12: IK - Informationskrav | J12: =IF(I12="IK - Informationskrav","Answer",(IF(I12="K - Konkurrencekrav","Check",(IF(I12="MK - Mindstekrav","Verify",""))))) -> Answer | K12: 2 | L12: 2 | M12: =Evalueringshieraki!$Q$16 -> 0.97087379 | O12: Anita | W12: Bilag 2 - 5.2.1.6 - Understøttelse af Elektronisk Sags- og Dokumenthåndtering.docx | X12: Read | Y12: =IF(X12="Not Started",0%,IF(X12="Read",1%,IF(X12="Started",50%,IF(X12="Ready for review",70%,IF(X12="Reviewed - Content",80%,IF(X12="Reviewed - Format",90%,IF(X12="Done",100%,""))))))) -> 0.01
A13: 12 | B13: 5.2.2.1. | C13: Bilag 2 - Kravspecifikation | D13: Funktionelle krav | E13: Hentning og opdatering af ejendomsdata | F13: Ejendomsdata | G13: IK Ejendomsdata Løsningen skal hente og anvende nedenstående ejendomsdata fra Datafordeleren:  Adresser inklusive vejnavn, husnummer, postnummer og postdistrikt.  Bygningsnummer.  Bestemt fast ejendomsnummer (herefter ”BFE”) for grund, ejerlejlighed og Bygning på fremmed grund (herefter ”BPFG”)  Matrikelnummer og ejerlav.  Ejerlejlighedsnummer.  Bygningens anvendelseskode (fx parcelhus, erhverv, institution).  Bygningens opførelses år.  Bebygget areal og samlet bygningsareal.  Antal bolig- og erhvervsenheder.  Energikilde og varmeinstallation.  Ejerforhold fra Ejerfortegnelsen (herefter ”EJF”), herunder oplysninger om hvem der råder over fast ejendom.  Ejendomsbeliggenhedsregistret (herefter ”EBR”), herunder referencer mellem ejendomme og adresser/beliggenhedsbetegnelser. Løsningens skal sikre opdatering af ejendomsdata på alle verserende sager mindst én gang i døgnet, og både historiske og aktuelle data skal vises på sagerne. Ejendomsdata skal være søgbare - både enkeltvis og i kombination med øvrige data. Det vægtes positivt at  at sagsbehandlere kan søge på alle ejendomsdata og finde både aktuelle og historiske sager, enkeltvis eller i kombination med øvrige søgekriterier, herunder ved brug af AND/OR-logik eller avancerede filtre  at ejendomsdata kan danne udgangspunkt for filtrering, lister og sortering af fremsøgte sager, samt at søgeresultater kan eksporteres til gængse formater (fx Excel, CSV)  at ejendomsdata fremgår samlet og overskueligt på den enkelte sag  at sagsbehandlere, teams og enheder notificeres automatisk, når ejendomsdata ændres på verserende sager  at ændringer i ejendomsdata tilføjes sagen med angivelse af tidsstempel og brugeridentitet, uden at tidligere data slettes | I13: IK - Informationskrav | J13: =IF(I13="IK - Informationskrav","Answer",(IF(I13="K - Konkurrencekrav","Check",(IF(I13="MK - Mindstekrav","Verify",""))))) -> Answer | K13: 1 | L13: 2 | M13: =Evalueringshieraki!$P$16 -> 0.48543689 | O13: Axel | R13: 1. Fully met | S13: Vi kan det allerede i eDoc, en stor del er (vist) allerede flyttet til P360 | T13: Yes | W13: Bilag 2 - 5.2.2.1 - Ejendomsdata.docx | X13: Ready for review | Y13: =IF(X13="Not Started",0%,IF(X13="Read",1%,IF(X13="Started",50%,IF(X13="Ready for review",70%,IF(X13="Reviewed - Content",80%,IF(X13="Reviewed - Format",90%,IF(X13="Done",100%,""))))))) -> 0.7
A14: 13 | B14: 5.2.3.1. | C14: Bilag 2 - Kravspecifikation | D14: Funktionelle krav | E14: Registrering af ejere og interessenter | F14: - | G14: Løsningen understøtter registrering af skift af ansøger eller ejer (medejer, historisk ansøger eller ejer) og øvrige interessenter. | I14: K - Konkurrencekrav | J14: =IF(I14="IK - Informationskrav","Answer",(IF(I14="K - Konkurrencekrav","Check",(IF(I14="MK - Mindstekrav","Verify",""))))) -> Check | K14: 1 | L14: 2 | M14: =Evalueringshieraki!$P$16 -> 0.48543689 | O14: Axel | S14: Kan vi i eDoc, ved Aalborg har meldt en bug ind på det, vil kræve merge af kode samt bugfix | T14: Yes | X14: Ready for review | Y14: =IF(X14="Not Started",0%,IF(X14="Read",1%,IF(X14="Started",50%,IF(X14="Ready for review",70%,IF(X14="Reviewed - Content",80%,IF(X14="Reviewed - Format",90%,IF(X14="Done",100%,""))))))) -> 0.7
A15: 14 | B15: 5.2.3.2. | C15: Bilag 2 - Kravspecifikation | D15: Funktionelle krav | E15: Registrering af ejere og interessenter | F15: - | G15: Løsningen understøtter registrering af eventuelt flere matrikler på sagen, som skal bruges af sagsbehandlerne. | I15: K - Konkurrencekrav | J15: =IF(I15="IK - Informationskrav","Answer",(IF(I15="K - Konkurrencekrav","Check",(IF(I15="MK - Mindstekrav","Verify",""))))) -> Check | K15: 1 | L15: 2 | M15: =Evalueringshieraki!$P$16 -> 0.48543689 | O15: Bjørn Henrik | R15: 1. Fully met | X15: Not Started | Y15: =IF(X15="Not Started",0%,IF(X15="Read",1%,IF(X15="Started",50%,IF(X15="Ready for review",70%,IF(X15="Reviewed - Content",80%,IF(X15="Reviewed - Format",90%,IF(X15="Done",100%,""))))))) -> 0
A16: 15 | B16: 5.2.3.3. | C16: Bilag 2 - Kravspecifikation | D16: Funktionelle krav | E16: Registrering af ejere og interessenter | F16: - | G16: Løsningen understøtter opslag på sager på matriklen (afsluttede og igangværende) | I16: K - Konkurrencekrav | J16: =IF(I16="IK - Informationskrav","Answer",(IF(I16="K - Konkurrencekrav","Check",(IF(I16="MK - Mindstekrav","Verify",""))))) -> Check | K16: 1 | L16: 2 | M16: =Evalueringshieraki!$P$16 -> 0.48543689 | O16: Anton | R16: 1. Fully met | X16: Ready for review | Y16: =IF(X16="Not Started",0%,IF(X16="Read",1%,IF(X16="Started",50%,IF(X16="Ready for review",70%,IF(X16="Reviewed - Content",80%,IF(X16="Reviewed - Format",90%,IF(X16="Done",100%,""))))))) -> 0.7
A17: 16 | B17: 5.2.3.4. | C17: Bilag 2 - Kravspecifikation | D17: Funktionelle krav | E17: Registrering af ejere og interessenter | F17: - | G17: Opslag på interessenten for at finde øvrige oprettede sager ved eks. mistet certifikat for rådgivere. | I17: K - Konkurrencekrav | J17: =IF(I17="IK - Informationskrav","Answer",(IF(I17="K - Konkurrencekrav","Check",(IF(I17="MK - Mindstekrav","Verify",""))))) -> Check | K17: 1 | L17: 2 | M17: =Evalueringshieraki!$P$16 -> 0.48543689 | O17: Anton | R17: 1. Fully met | X17: Ready for review | Y17: =IF(X17="Not Started",0%,IF(X17="Read",1%,IF(X17="Started",50%,IF(X17="Ready for review",70%,IF(X17="Reviewed - Content",80%,IF(X17="Reviewed - Format",90%,IF(X17="Done",100%,""))))))) -> 0.7
A18: 17 | B18: 5.2.3.5. | C18: Bilag 2 - Kravspecifikation | D18: Funktionelle krav | E18: Registrering af ejere og interessenter | F18: Interessent roller | G18: Interessent roller Sagsbehandlerne har brug for at kunne notere hvilken rolle de enkelte interessenter har/har haft på sagen. Leverandøren bedes redegøre for hvordan rollerne til interessenter kan tildeles og evt. ændres. Det vægtes positivt at - kunden kan anvende faste kategorier - at interessenter kan fremsøges på baggrund af deres roller | I18: IK - Informationskrav | J18: =IF(I18="IK - Informationskrav","Answer",(IF(I18="K - Konkurrencekrav","Check",(IF(I18="MK - Mindstekrav","Verify",""))))) -> Answer | K18: 1 | L18: 2 | M18: =Evalueringshieraki!$P$16 -> 0.48543689 | O18: Anita | W18: Bilag 2 - 5.2.3.5 - Interessent roller.docx | X18: Not Started | Y18: =IF(X18="Not Started",0%,IF(X18="Read",1%,IF(X18="Started",50%,IF(X18="Ready for review",70%,IF(X18="Reviewed - Content",80%,IF(X18="Reviewed - Format",90%,IF(X18="Done",100%,""))))))) -> 0
A19: 18 | B19: 5.2.4.1. | C19: Bilag 2 - Kravspecifikation | D19: Funktionelle krav | E19: Registrering, søgning og visning af sagsdata | F19: Sagsopslag og visning | G19: Sagsopslag og visning Brugerne skal kunne slå en sag op og se sagsbehandler, enhed, team, område samt ændre sagsdata ifm. sagens behandling. | I19: K - Konkurrencekrav | J19: =IF(I19="IK - Informationskrav","Answer",(IF(I19="K - Konkurrencekrav","Check",(IF(I19="MK - Mindstekrav","Verify",""))))) -> Check | K19: 1 | L19: 2 | M19: =Evalueringshieraki!$P$16 -> 0.48543689 | O19: Anton | R19: 1. Fully met | X19: Ready for review | Y19: =IF(X19="Not Started",0%,IF(X19="Read",1%,IF(X19="Started",50%,IF(X19="Ready for review",70%,IF(X19="Reviewed - Content",80%,IF(X19="Reviewed - Format",90%,IF(X19="Done",100%,""))))))) -> 0.7
A20: 19 | B20: 5.2.4.2. | C20: Bilag 2 - Kravspecifikation | D20: Funktionelle krav | E20: Registrering, søgning og visning af sagsdata | F20: Løbende registrering af sagsændringer | G20: Løbende registrering af sagsændringer Der skal løbende kunne registreres fx ændrede indsendelser, skift af team, enhed, sagsbehandler, sagsbehandling, om-registrering af sager ved evt. fejlvisitering/servicemålsager/lovliggørelse, ændringer af sagsstatus eks. dato for afgørelse. | I20: K - Konkurrencekrav | J20: =IF(I20="IK - Informationskrav","Answer",(IF(I20="K - Konkurrencekrav","Check",(IF(I20="MK - Mindstekrav","Verify",""))))) -> Check | K20: 1 | L20: 2 | M20: =Evalueringshieraki!$P$16 -> 0.48543689 | O20: Bjørn Henrik | R20: 1. Fully met | X20: Not Started | Y20: =IF(X20="Not Started",0%,IF(X20="Read",1%,IF(X20="Started",50%,IF(X20="Ready for review",70%,IF(X20="Reviewed - Content",80%,IF(X20="Reviewed - Format",90%,IF(X20="Done",100%,""))))))) -> 0
A21: 20 | B21: 5.2.4.3. | C21: Bilag 2 - Kravspecifikation | D21: Funktionelle krav | E21: Registrering, søgning og visning af sagsdata | F21: Søgning, sortering, filtrering og eksport | G21: Søgning, sortering, filtrering og eksport Sager skal kunne fremsøges på alle relevante sagsdata. Søgeresultaterne skal kunne sorteres, filtreres og eksporteres (fx til Excel) Det vægtes positivt, at Leverandøren i sin besvarelse demonstrerer, at Løsningen understøtter:  fritekst- og nøgleordssøgning  søgning på specifikke sætninger (frase søgning)  kombinerede søgekriterier (fx AND/OR-logik eller avancerede filtre)  sortering og filtrering af søgeresultater  eksport til gængse formater (fx Excel, CSV)  at sagsdata, herunder enhed og team, kan tilgås og ændres direkte fra søgeresultater eller sagsopslag uden unødige mellemtrin | I21: IK - Informationskrav | J21: =IF(I21="IK - Informationskrav","Answer",(IF(I21="K - Konkurrencekrav","Check",(IF(I21="MK - Mindstekrav","Verify",""))))) -> Answer | K21: 1 | L21: 2 | M21: =Evalueringshieraki!$P$16 -> 0.48543689 | O21: Anita | W21: Bilag 2 - 5.2.4.3 - Søgning, sortering, filtrering og eksport.docx | X21: Not Started | Y21: =IF(X21="Not Started",0%,IF(X21="Read",1%,IF(X21="Started",50%,IF(X21="Ready for review",70%,IF(X21="Reviewed - Content",80%,IF(X21="Reviewed - Format",90%,IF(X21="Done",100%,""))))))) -> 0
A22: 21 | B22: 5.2.5.1. | C22: Bilag 2 - Kravspecifikation | D22: Funktionelle krav | E22: Integration til GIS løsning | F22: GIS visning af sager | G22: GIS visning af sager Brugeren kan gennem løsningen tilgå en visning af Kundens GIS-løsning, med mulighed for præ-definerede filtre/overlays så man kan se relevant info fra Kundens GIS-løsning. Kundens GIS-løsning, vil automatisk have byggesagsejendommen i fokus for sagsbehandleren, så mest data er tilgængeligt, hurtigst muligt. Det vægtes positivt, at Leverandøren i sin besvarelse demonstrerer, at løsningen understøtter: • at GIS-visningen åbnes direkte i Løsningen uden unødige mellemtrin eller skift af applikation (fx dybe links fra løsning til GIS på relevant adresse/matrikel) • at præ-definerede filtre og overlays kan tilpasses af Kunden uden behov for systemudvikling • at GIS-visningen automatisk centrerer sig om den relevante ejendom med mest muligt data tilgængeligt fra første visning • at GIS-visningen giver mulighed for at identificere eventuelle konflikter og relevante oplysninger om ejendommen på tværs af lag og filtre • At visningen kan gemmes på sagen som dokumentation | I22: IK - Informationskrav | J22: =IF(I22="IK - Informationskrav","Answer",(IF(I22="K - Konkurrencekrav","Check",(IF(I22="MK - Mindstekrav","Verify",""))))) -> Answer | K22: 1 | L22: 2 | M22: =Evalueringshieraki!$P$16 -> 0.48543689 | O22: Husein | W22: Bilag 2 - 5.2.5.1 - GIS visning af sager.docx | X22: Not Started | Y22: =IF(X22="Not Started",0%,IF(X22="Read",1%,IF(X22="Started",50%,IF(X22="Ready for review",70%,IF(X22="Reviewed - Content",80%,IF(X22="Reviewed - Format",90%,IF(X22="Done",100%,""))))))) -> 0
A23: 22 | B23: B2-01 | C23: Bilag 2 - Kravspecifikation | D23: Funktionelle krav | E23: Sagsbehandling af byggesager og anmeldelser | F23: Sagsbehandling af byggesager og anmeldelser | G23: Løsningen skal understøtte modtagelse, oprettelse og sagsbehandling af de sagstyper, der er beskrevet i kravspecifikationens begrebsliste og faglige ramme, herunder byggetilladelser, anmeldelser, ibrugtagningstilladelser, lovliggørelsessager og klagesager. Som fagsystem skal løsningen understøtte udarbejdelse af myndighedsdokumentation og kommunikation med ansøgere mfl. Samtidig skal løsningen kunne give overblik over både de enkelte sager og deres status samt understøtte visitation, prioritering og opfølgning på sager og sagstyper. | I23: MK - Minimumskrav | J23: =IF(I23="IK - Informationskrav","Answer",(IF(I23="K - Konkurrencekrav","Check",(IF(I23="MK - Minimumskrav","Verify",""))))) -> Verify | O23: Bjørn Henrik | S23: Konfigurasjon | X23: Not Started | Y23: =IF(X23="Not Started",0%,IF(X23="Read",1%,IF(X23="Started",50%,IF(X23="Ready for review",70%,IF(X23="Reviewed - Content",80%,IF(X23="Reviewed - Format",90%,IF(X23="Done",100%,""))))))) -> 0
A24: 23 | B24: 5.2.6.1. | C24: Bilag 2 - Kravspecifikation | D24: Funktionelle krav | E24: Sagsbehandling af byggesager og anmeldelser | F24: - | G24: Brugeren kan tilgå en liste af sager på samme ejendom – brugeren kan vælge mellem at se sager på hele ejendommen, den konkrete adresse, BFE eller matrikel. | I24: K - Konkurrencekrav | J24: =IF(I24="IK - Informationskrav","Answer",(IF(I24="K - Konkurrencekrav","Check",(IF(I24="MK - Minimumskrav","Verify",""))))) -> Check | K24: 1 | L24: 2 | M24: =Evalueringshieraki!$P$16 -> 0.48543689 | O24: Husein | X24: Not Started | Y24: =IF(X24="Not Started",0%,IF(X24="Read",1%,IF(X24="Started",50%,IF(X24="Ready for review",70%,IF(X24="Reviewed - Content",80%,IF(X24="Reviewed - Format",90%,IF(X24="Done",100%,""))))))) -> 0
A25: 24 | B25: 5.2.6.2. | C25: Bilag 2 - Kravspecifikation | D25: Funktionelle krav | E25: Sagsbehandling af byggesager og anmeldelser | F25: - | G25: Brugeren kan hente/oprette relevante arbejdsdokumenter. Brugeren gemmer sit arbejde direkte i fagsystemet. Arbejdsdokumenter kan omfatte, men er ikke begrænset til: • Mangelbreve • Byggetilladelser • Ibrugtagningstilladelser • Afslag eller afvisninger på byggesager • Påbud/varsel om påbud • Høringer • Orienteringsbreve • Brev om forhåndsdialog • Lovliggørelser • Dispensationer • Mails | I25: K - Konkurrencekrav | J25: =IF(I25="IK - Informationskrav","Answer",(IF(I25="K - Konkurrencekrav","Check",(IF(I25="MK - Mindstekrav","Verify",""))))) -> Check | K25: 1 | L25: 2 | M25: =Evalueringshieraki!$P$16 -> 0.48543689 | O25: Anton | R25: 1. Fully met | X25: Ready for review | Y25: =IF(X25="Not Started",0%,IF(X25="Read",1%,IF(X25="Started",50%,IF(X25="Ready for review",70%,IF(X25="Reviewed - Content",80%,IF(X25="Reviewed - Format",90%,IF(X25="Done",100%,""))))))) -> 0.7
A26: 25 | B26: 5.2.6.3. | C26: Bilag 2 - Kravspecifikation | D26: Funktionelle krav | E26: Sagsbehandling af byggesager og anmeldelser | F26: Sags/journalnoter | G26: Sags/journalnoter Leverandøren bedes beskrive hvordan sagsbehandlere med adgang til en given sag kan notere relevante bemærkninger på sagen – f.eks. telefonnotater. Det vægtes positivt hvis: - Det noteres et centralt sted på sagen, som alle med relevant adgang kan tilgå. - Bemærkninger kan tidsstemples og knyttes til den bruger, som har oprettet dem. - Det er muligt at skelne mellem interne bemærkninger og bemærkninger der må deles med eksterne parter. - Tidligere bemærkninger forbliver synlige og kan ikke slettes eller redigeres af andre end den oprindelige ophavsmand eller administrator. - Brugeren kan notificeres, tagges eller på anden måde gøres opmærksom på en bemærkning der er relevant for vedkommende. - Disse noter kan udskrives og gemmes samlet om ønsket | I26: IK - Informationskrav | J26: =IF(I26="IK - Informationskrav","Answer",(IF(I26="K - Konkurrencekrav","Check",(IF(I26="MK - Mindstekrav","Verify",""))))) -> Answer | K26: 1 | L26: 2 | M26: =Evalueringshieraki!$P$16 -> 0.48543689 | O26: Bjørn Henrik | S26: Is this just Notes and note summaries? | W26: Bilag 2 - 5.2.6.3 - Sags-journalnoter.docx | X26: Not Started | Y26: =IF(X26="Not Started",0%,IF(X26="Read",1%,IF(X26="Started",50%,IF(X26="Ready for review",70%,IF(X26="Reviewed - Content",80%,IF(X26="Reviewed - Format",90%,IF(X26="Done",100%,""))))))) -> 0
A27: 26 | B27: 5.2.6.4. | C27: Bilag 2 - Kravspecifikation | D27: Funktionelle krav | E27: Sagsbehandling af byggesager og anmeldelser | F27: Overblik på sagen | G27: Overblik på sagen Leverandøren bedes beskrive hvordan brugeren, efter at have åbnet en given sag, kan få et overblik over sagens indhold og de seneste hændelser på sagen. Det vægtes positivt hvis: - Brugeren fra sagens forside, let kan tilgå yderligere oplysninger, - Overblikket er overskueligt - Det er ukompliceret at identificere seneste hændelser på sagen. | I27: IK - Informationskrav | J27: =IF(I27="IK - Informationskrav","Answer",(IF(I27="K - Konkurrencekrav","Check",(IF(I27="MK - Mindstekrav","Verify",""))))) -> Answer | K27: 1 | L27: 2 | M27: =Evalueringshieraki!$P$16 -> 0.48543689 | O27: Bjørn Henrik | W27: Bilag 2 - 5.2.6.4 - Overblik på sagen.docx | X27: Not Started | Y27: =IF(X27="Not Started",0%,IF(X27="Read",1%,IF(X27="Started",50%,IF(X27="Ready for review",70%,IF(X27="Reviewed - Content",80%,IF(X27="Reviewed - Format",90%,IF(X27="Done",100%,""))))))) -> 0
A28: 27 | B28: 5.2.6.5. | C28: Bilag 2 - Kravspecifikation | D28: Funktionelle krav | E28: Sagsbehandling af byggesager og anmeldelser | F28: Ansøgninger og anmeldelser på sagen | G28: Ansøgninger og anmeldelser på sagen Brugeren skal ud fra sagens visning kunne se hvilke aktive og afsluttede ansøgninger og anmeldelser, der er knyttet til den pågældende sag. Løsningen skal sikre at væsentlige datoer for sagsbehandlingen kan både søges, vises og indgå i rapporter. Det gælder fx dato for modtagelse, for fyldestgørende, for afslag, for byggetilladelse mm. Det vægtes positivt hvis: - Tilknyttede ansøgninger og anmeldelser fremgår samlet og overskueligt direkte fra sagens visning, med tydelig angivelse af status for hver enkelt. - Brugeren kan tilpasse hvilke datofelter der vises i sagens overblik, så de mest relevante datoer fremhæves for den konkrete sagstype. - Væsentlige datoer kan danne grundlag for automatiske påmindelser eller advarsler, fx ved overskridelse af servicemål eller frister. - Rapporter med datooplysninger kan eksporteres i et format der understøtter videre bearbejdning, fx Excel eller CSV. | I28: IK - Informationskrav | J28: =IF(I28="IK - Informationskrav","Answer",(IF(I28="K - Konkurrencekrav","Check",(IF(I28="MK - Mindstekrav","Verify",""))))) -> Answer | K28: 1 | L28: 2 | M28: =Evalueringshieraki!$P$16 -> 0.48543689 | O28: Linn | W28: Bilag 2 - 5.2.6.5 - Ansøgninger og anmeldelser på sagen.docx | X28: Not Started | Y28: =IF(X28="Not Started",0%,IF(X28="Read",1%,IF(X28="Started",50%,IF(X28="Ready for review",70%,IF(X28="Reviewed - Content",80%,IF(X28="Reviewed - Format",90%,IF(X28="Done",100%,""))))))) -> 0
A29: 28 | B29: 5.2.6.6. | C29: Bilag 2 - Kravspecifikation | D29: Funktionelle krav | E29: Sagsbehandling af byggesager og anmeldelser | F29: Overblik på sagsdokumenter | G29: Overblik på sagsdokumenter Leverandøren bedes beskrive hvordan brugeren kan emnemarkere, sortere og tilgå sagens dokumenter. Det vægtes positivt hvis: - Dokumenter kan tildeles brugerdefinerede kategorier eller dokumenttyper, som kan anvendes til filtrering og søgning på tværs af sagen. - Brugeren kan flytte, omdøbe og organisere dokumenter direkte i fagsystemet uden at forlade sagen. - Ændringer i dokumenthåndteringen logges, så det er muligt at se hvem der har foretaget ændringer og hvornår. | I29: IK - Informationskrav | J29: =IF(I29="IK - Informationskrav","Answer",(IF(I29="K - Konkurrencekrav","Check",(IF(I29="MK - Mindstekrav","Verify",""))))) -> Answer | K29: 1 | L29: 2 | M29: =Evalueringshieraki!$P$16 -> 0.48543689 | O29: Morten | W29: Bilag 2 - 5.2.6.6 - Overblik på sagsdokumenter.docx | X29: Not Started | Y29: =IF(X29="Not Started",0%,IF(X29="Read",1%,IF(X29="Started",50%,IF(X29="Ready for review",70%,IF(X29="Reviewed - Content",80%,IF(X29="Reviewed - Format",90%,IF(X29="Done",100%,""))))))) -> 0
A30: 29 | B30: 5.2.7.1. | C30: Bilag 2 - Kravspecifikation | D30: Funktionelle krav | E30: Styring af sagsportefølje | F30: Sagsoverblik og adviseringer | G30: Sagsoverblik og adviseringer En sagsbehandler eller et team kan se et overblik over sager som de har ansvaret for, i løsningen. Dette overblik giver information om adviseringer – fx overskredne frister, indkommende dokumentation eller lign. Overblikket viser hvor mange sager af forskellige typer som en sagsbehandler eller et team, har ansvar for. Bruger kan tilgå enkeltsager via overblikket. | I30: K - Konkurrencekrav | J30: =IF(I30="IK - Informationskrav","Answer",(IF(I30="K - Konkurrencekrav","Check",(IF(I30="MK - Mindstekrav","Verify",""))))) -> Check | K30: 1 | L30: 2 | M30: =Evalueringshieraki!$P$16 -> 0.48543689 | O30: Morten | S30: The dashboard is supposed to give notifications? Does it show new documents are created from the desktop? | X30: Not Started | Y30: =IF(X30="Not Started",0%,IF(X30="Read",1%,IF(X30="Started",50%,IF(X30="Ready for review",70%,IF(X30="Reviewed - Content",80%,IF(X30="Reviewed - Format",90%,IF(X30="Done",100%,""))))))) -> 0
A31: 30 | B31: 5.2.7.2. | C31: Bilag 2 - Kravspecifikation | D31: Funktionelle krav | E31: Styring af sagsportefølje | F31: Tilpasset overbliksvisning og sortering | G31: Tilpasset overbliksvisning og sortering Leverandøren bedes give en udtømmende beskrivelse af, hvordan Løsningen understøtter tilpasning og sortering af overbliksvisningen, herunder: Brugere kan opsætte sin egen visning af dette overblik så de fx ét sted kun ser de sager, som er relevante nu og undgår at se sager, som afventer andre – fx ansøger, kollega og lign. De afventende sager skal kunne ses for sig, i samme overbliksvisning. Opsætning af overbliksvisning skal kunne tilpasses individuelt, både til enkelte brugere og til teams med prædefineret opsætning. Bruger kan sortere på forskellige parametre, fx emner, dato, sagsfase, tags, prioriteringer. Systemet skal give mulighed for at skifte mellem forskellige overbliksvisninger. Det vægtes positivt, at Leverandøren i sin besvarelse demonstrerer, at Løsningen understøtter:  at brugere kan oprette og gemme flere personlige overbliksvisninger og frit skifte imellem dem  at teams kan dele og anvende fælles prædefineret overbliksvisninger  at afventende sager præsenteres tydeligt adskilt fra aktive sager i samme overbliksvisning  at sortering kan foretages på tværs af flere parametre samtidigt (fx sagsfase og dato kombineret)  at adviseringer om overskredne frister og indkommende dokumentation fremhæves tydeligt i overblikket  at overbliksvisningen kan tilpasses uden behov for systemudvikling | I31: IK - Informationskrav | J31: =IF(I31="IK - Informationskrav","Answer",(IF(I31="K - Konkurrencekrav","Check",(IF(I31="MK - Mindstekrav","Verify",""))))) -> Answer | K31: 1 | L31: 2 | M31: =Evalueringshieraki!$P$16 -> 0.48543689 | O31: Morten | W31: Bilag 2 - 5.2.7.2 - Tilpasset overbliksvisning og sortering.docx | X31: Not Started | Y31: =IF(X31="Not Started",0%,IF(X31="Read",1%,IF(X31="Started",50%,IF(X31="Ready for review",70%,IF(X31="Reviewed - Content",80%,IF(X31="Reviewed - Format",90%,IF(X31="Done",100%,""))))))) -> 0
A32: 31 | B32: 5.2.8.1. | C32: Bilag 2 - Kravspecifikation | D32: Funktionelle krav | E32: Understøttelse af alle sagstyper | F32: - | G32: Sager skal kunne inddeles i forskellige typer i relation til typer af sager, ejendomme og byggeri, således at sagskategorien svarer til den type af byggeri eller sag, der er omfattet af sagen. | I32: K - Konkurrencekrav | J32: =IF(I32="IK - Informationskrav","Answer",(IF(I32="K - Konkurrencekrav","Check",(IF(I32="MK - Mindstekrav","Verify",""))))) -> Check | K32: 1 | L32: 2 | M32: =Evalueringshieraki!$P$16 -> 0.48543689 | O32: Bjørn Henrik | X32: Not Started | Y32: =IF(X32="Not Started",0%,IF(X32="Read",1%,IF(X32="Started",50%,IF(X32="Ready for review",70%,IF(X32="Reviewed - Content",80%,IF(X32="Reviewed - Format",90%,IF(X32="Done",100%,""))))))) -> 0
A33: 32 | B33: 5.2.8.2 | C33: Bilag 2 - Kravspecifikation | D33: Funktionelle krav | E33: Understøttelse af alle sagstyper | F33: - | G33: Sager skal kunne fordeles til enheder, teams og brugere baseret på type af sager. | I33: K - Konkurrencekrav | J33: =IF(I33="IK - Informationskrav","Answer",(IF(I33="K - Konkurrencekrav","Check",(IF(I33="MK - Mindstekrav","Verify",""))))) -> Check | K33: 1 | L33: 2 | M33: =Evalueringshieraki!$P$16 -> 0.48543689 | O33: Bjørn Henrik | X33: Not Started | Y33: =IF(X33="Not Started",0%,IF(X33="Read",1%,IF(X33="Started",50%,IF(X33="Ready for review",70%,IF(X33="Reviewed - Content",80%,IF(X33="Reviewed - Format",90%,IF(X33="Done",100%,""))))))) -> 0
A34: 33 | B34: 5.2.8.3. | C34: Bilag 2 - Kravspecifikation | D34: Funktionelle krav | E34: Understøttelse af alle sagstyper | F34: - | G34: Brugere skal kunne fremsøge sager filtreret på typer af sager og få et overblik. Det skal fremgå af sagen, hvilken type den er. | I34: K - Konkurrencekrav | J34: =IF(I34="IK - Informationskrav","Answer",(IF(I34="K - Konkurrencekrav","Check",(IF(I34="MK - Mindstekrav","Verify",""))))) -> Check | K34: 1 | L34: 2 | M34: =Evalueringshieraki!$P$16 -> 0.48543689 | O34: Anton | R34: 1. Fully met | X34: Ready for review | Y34: =IF(X34="Not Started",0%,IF(X34="Read",1%,IF(X34="Started",50%,IF(X34="Ready for review",70%,IF(X34="Reviewed - Content",80%,IF(X34="Reviewed - Format",90%,IF(X34="Done",100%,""))))))) -> 0.7
A35: 34 | B35: 5.2.8.4. | C35: Bilag 2 - Kravspecifikation | D35: Funktionelle krav | E35: Understøttelse af alle sagstyper | F35: Sagsstatus | G35: sagsstatus Brugeren kan ud fra sagsvisningen tydeligt se sagens status, dvs. hvor langt en sag er nået i processen, samt hvor initiativpligten ligger og hvem der er ansvarlig for sagen. Ligesom manglende data eller udestående procestrin bør fremgå af sagens statusmarkeringer. Det vægtes positivt hvis: - Sagens status vises visuelt og intuitivt, fx via en proceslinje eller statusindikator, der tydeligt markerer gennemførte, igangværende og udestående faser. - Initiativpligten fremgår eksplicit af sagens visning, så det er klart om bolden ligger hos ansøger, sagsbehandler eller en tredjepart. - Brugeren adviseres automatisk når manglende data eller udestående procestrin blokerer for videre sagsbehandling, fx via en synlig advarsel eller notifikation direkte på sagen. - Det er muligt at konfigurere hvilke felter og procestrin der er obligatoriske for den enkelte sagstype, så statusmarkeringerne afspejler kravene til den konkrete sag. | I35: IK - Informationskrav | J35: =IF(I35="IK - Informationskrav","Answer",(IF(I35="K - Konkurrencekrav","Check",(IF(I35="MK - Mindstekrav","Verify",""))))) -> Answer | K35: 1 | L35: 2 | M35: =Evalueringshieraki!$P$16 -> 0.48543689 | O35: Bjørn Henrik | W35: Bilag 2 - 5.2.8.4 - Sagsstatus.docx | X35: Not Started | Y35: =IF(X35="Not Started",0%,IF(X35="Read",1%,IF(X35="Started",50%,IF(X35="Ready for review",70%,IF(X35="Reviewed - Content",80%,IF(X35="Reviewed - Format",90%,IF(X35="Done",100%,""))))))) -> 0
A36: 35 | B36: 5.2.8.5. | C36: Bilag 2 - Kravspecifikation | D36: Funktionelle krav | E36: Understøttelse af alle sagstyper | F36: Håndtering af modtaget information | G36: Håndtering af modtaget information Løsningen skal kunne håndtere indkomne dokumentationer/data efter sagens status (hvor i processen sagen er). Det vægtes positivt hvis: - Løsningen automatisk kategoriserer eller placerer indkomne dokumenter og data i relation til den fase af processen, hvori de er modtaget. - Brugeren adviseres når der indkommer dokumentation på en sag. | I36: IK - Informationskrav | J36: =IF(I36="IK - Informationskrav","Answer",(IF(I36="K - Konkurrencekrav","Check",(IF(I36="MK - Mindstekrav","Verify",""))))) -> Answer | K36: 1 | L36: 2 | M36: =Evalueringshieraki!$P$16 -> 0.48543689 | O36: Bjørn Henrik | W36: Bilag 2 - 5.2.8.5 - Håndtering af modtaget information.docx | X36: Not Started | Y36: =IF(X36="Not Started",0%,IF(X36="Read",1%,IF(X36="Started",50%,IF(X36="Ready for review",70%,IF(X36="Reviewed - Content",80%,IF(X36="Reviewed - Format",90%,IF(X36="Done",100%,""))))))) -> 0
A37: 36 | B37: 5.2.8.6. | C37: Bilag 2 - Kravspecifikation | D37: Funktionelle krav | E37: Understøttelse af alle sagstyper | F37: - | G37: Overblik over alle afgørelser på sagen. | I37: K - Konkurrencekrav | J37: =IF(I37="IK - Informationskrav","Answer",(IF(I37="K - Konkurrencekrav","Check",(IF(I37="MK - Mindstekrav","Verify",""))))) -> Check | K37: 1 | L37: 2 | M37: =Evalueringshieraki!$P$16 -> 0.48543689 | O37: Bjørn Henrik | R37: 1. Fully met | S37: We should ask a question about this - IF we see any issues with it - otherwise we let it stand. | X37: Not Started | Y37: =IF(X37="Not Started",0%,IF(X37="Read",1%,IF(X37="Started",50%,IF(X37="Ready for review",70%,IF(X37="Reviewed - Content",80%,IF(X37="Reviewed - Format",90%,IF(X37="Done",100%,""))))))) -> 0
A38: 37 | B38: 5.2.8.7. | C38: Bilag 2 - Kravspecifikation | D38: Funktionelle krav | E38: Understøttelse af alle sagstyper | F38: - | G38: Man skal ikke kunne arbejde videre på en afsluttet sag. Det skal dog være muligt at genåbne en lukket sag (for brugere med særlig rettighed). | I38: K - Konkurrencekrav | J38: =IF(I38="IK - Informationskrav","Answer",(IF(I38="K - Konkurrencekrav","Check",(IF(I38="MK - Mindstekrav","Verify",""))))) -> Check | K38: 1 | L38: 2 | M38: =Evalueringshieraki!$P$16 -> 0.48543689 | O38: Anton | R38: 1. Fully met | X38: Ready for review | Y38: =IF(X38="Not Started",0%,IF(X38="Read",1%,IF(X38="Started",50%,IF(X38="Ready for review",70%,IF(X38="Reviewed - Content",80%,IF(X38="Reviewed - Format",90%,IF(X38="Done",100%,""))))))) -> 0.7
A39: 38 | B39: 5.2.8.8. | C39: Bilag 2 - Kravspecifikation | D39: Funktionelle krav | E39: Understøttelse af alle sagstyper | F39: Kommunikation | G39: Kommunikation Brugeren kan via systemet gennemføre dialog og kommunikation med ansøgere og interessenter gennem Digital Post, landsdækkende ansøgningsportal (BOM) og e-mail eller tilsvarende kommunikationsplatform. Det vægtes positivt hvis: - Kommunikation via Digital Post, BOM og e-mail kan initieres og håndteres samlet fra ét sted i fagsystemet, uden at brugeren skal skifte mellem separate platforme. - Kommunikation med ansøgere og interessenter, foretaget gennem Systemets kommunikationskanaler, automatisk journaliseres og knyttes til den relevante sag. - Brugeren kan anvende foruddefinerede skabeloner til standardiseret kommunikation, som kan tilpasses den konkrete sag og den relevante modtager. - Man skal kunne se, hvis modtagelse/afsendelse fejler | I39: IK - Informationskrav | J39: =IF(I39="IK - Informationskrav","Answer",(IF(I39="K - Konkurrencekrav","Check",(IF(I39="MK - Mindstekrav","Verify",""))))) -> Answer | K39: 1 | L39: 2 | M39: =Evalueringshieraki!$P$16 -> 0.48543689 | O39: Morten | S39: PnB tar ansvaret for BOM, resten er standard funksjonalitet? | W39: Bilag 2 - 5.2.8.8 - Kommunikation.docx | X39: Not Started | Y39: =IF(X39="Not Started",0%,IF(X39="Read",1%,IF(X39="Started",50%,IF(X39="Ready for review",70%,IF(X39="Reviewed - Content",80%,IF(X39="Reviewed - Format",90%,IF(X39="Done",100%,""))))))) -> 0
A40: 39 | B40: 5.2.8.9. | C40: Bilag 2 - Kravspecifikation | D40: Funktionelle krav | E40: Understøttelse af alle sagstyper | F40: - | G40: Systemet kan opdatere sagsstatus for byggesager gennem kommunikation via landsdækkende ansøgningsportal Byg og Miljø (BOM). | I40: K - Konkurrencekrav | J40: =IF(I40="IK - Informationskrav","Answer",(IF(I40="K - Konkurrencekrav","Check",(IF(I40="MK - Mindstekrav","Verify",""))))) -> Check | K40: 1 | L40: 2 | M40: =Evalueringshieraki!$P$16 -> 0.48543689 | O40: Arve | R40: 1. Fully met | S40: BOM integrasjon | X40: Not Started | Y40: =IF(X40="Not Started",0%,IF(X40="Read",1%,IF(X40="Started",50%,IF(X40="Ready for review",70%,IF(X40="Reviewed - Content",80%,IF(X40="Reviewed - Format",90%,IF(X40="Done",100%,""))))))) -> 0
A41: 40 | B41: 5.2.8.10. | C41: Bilag 2 - Kravspecifikation | D41: Funktionelle krav | E41: Understøttelse af alle sagstyper | F41: - | G41: Når brugeren udarbejder dokumenter på baggrund af skabeloner, skal løsningen trække data til dokumentet med grundoplysninger fra sagen (fx adresse, ejer, osv.). Det vægtes positivt hvis: - Løsningen understøtter Dynamic Templates, så dokumenter automatisk genereres med relevante sagsdata uden manuel indtastning. - Skabeloner kan tilpasses til forskellige sagstyper, så de grundoplysninger der trækkes ind i dokumentet, er relevante for den konkrete sagskategori. - Brugeren får en tydelig indikation af hvilke felter der er automatisk udfyldt fra sagen, og hvilke felter der kræver manuel udfyldning. | I41: IK - Informationskrav | J41: =IF(I41="IK - Informationskrav","Answer",(IF(I41="K - Konkurrencekrav","Check",(IF(I41="MK - Mindstekrav","Verify",""))))) -> Answer | K41: 1 | L41: 2 | M41: =Evalueringshieraki!$P$16 -> 0.48543689 | O41: Olga | W41: Bilag 2 - 5.2.8.10. - Skabeloner.DOC | X41: Ready for review | Y41: =IF(X41="Not Started",0%,IF(X41="Read",1%,IF(X41="Started",50%,IF(X41="Ready for review",70%,IF(X41="Reviewed - Content",80%,IF(X41="Reviewed - Format",90%,IF(X41="Done",100%,""))))))) -> 0.7
A42: 41 | B42: 5.2.8.11. | C42: Bilag 2 - Kravspecifikation | D42: Funktionelle krav | E42: Understøttelse af alle sagstyper | F42: Dokumenthåndtering i løsningen | G42: Dokumenthåndtering i løsningen Brugeren redigerer i dokumentet og udfylder yderligere data. Brugeren gemmer dokumentet direkte i systemet. Det vægtes positivt hvis: - Dokumentet kan åbnes og redigeres aktiveres direkte fra fagsystemet med redigering i fx Word eller lign. - Løsningen understøtter samtidighed, så flere brugere kan arbejde på det samme dokument simultant. - Dokumentet gemmes automatisk løbende under redigering, så data ikke mistes ved fx nedbrud eller utilsigtet lukning. | I42: IK - Informationskrav | J42: =IF(I42="IK - Informationskrav","Answer",(IF(I42="K - Konkurrencekrav","Check",(IF(I42="MK - Mindstekrav","Verify",""))))) -> Answer | K42: 1 | L42: 2 | M42: =Evalueringshieraki!$P$16 -> 0.48543689 | O42: Anita | R42: 1. Fully met | S42: Do we have a teams/Sharepoint integration in Plan and Build? AOP: It will be P360 Flow with P&B fnctionality - integration exists. | W42: Bilag 2 - 5.2.8.11 - Dokumenthåndtering i løsningen.docx | X42: Read | Y42: =IF(X42="Not Started",0%,IF(X42="Read",1%,IF(X42="Started",50%,IF(X42="Ready for review",70%,IF(X42="Reviewed - Content",80%,IF(X42="Reviewed - Format",90%,IF(X42="Done",100%,""))))))) -> 0.01
A43: 42 | B43: 5.2.8.12. | C43: Bilag 2 - Kravspecifikation | D43: Funktionelle krav | E43: Understøttelse af alle sagstyper | F43: - | G43: Dokumenter kan markeres som ’kladde’ så de ikke medtages i fx aktindsigt, og så andre ikke er i tvivl om, hvorvidt dokumentet er afsendt eller klar til afsendelse. | I43: K - Konkurrencekrav | J43: =IF(I43="IK - Informationskrav","Answer",(IF(I43="K - Konkurrencekrav","Check",(IF(I43="MK - Mindstekrav","Verify",""))))) -> Check | K43: 1 | L43: 2 | M43: =Evalueringshieraki!$P$16 -> 0.48543689 | O43: Anton | R43: 1. Fully met | X43: Ready for review | Y43: =IF(X43="Not Started",0%,IF(X43="Read",1%,IF(X43="Started",50%,IF(X43="Ready for review",70%,IF(X43="Reviewed - Content",80%,IF(X43="Reviewed - Format",90%,IF(X43="Done",100%,""))))))) -> 0.7
A44: 43 | B44: 5.2.8.13. | C44: Bilag 2 - Kravspecifikation | D44: Funktionelle krav | E44: Understøttelse af alle sagstyper | F44: - | G44: Brugere med særlige rettigheder kan oprette, ændre og dele skabeloner som kan anvendes af alle eller udvalgte brugergrupper. | I44: K - Konkurrencekrav | J44: =IF(I44="IK - Informationskrav","Answer",(IF(I44="K - Konkurrencekrav","Check",(IF(I44="MK - Minimumskravkrav","Verify",""))))) -> Check | K44: 1 | L44: 2 | M44: =Evalueringshieraki!$P$16 -> 0.48543689 | O44: Morten | S44: The category is casetypes, so i asume they are talking about Case Templates. Will they be available in PnB? | X44: Not Started | Y44: =IF(X44="Not Started",0%,IF(X44="Read",1%,IF(X44="Started",50%,IF(X44="Ready for review",70%,IF(X44="Reviewed - Content",80%,IF(X44="Reviewed - Format",90%,IF(X44="Done",100%,""))))))) -> 0
A45: 44 | B45: B2-02 | C45: Bilag 2 - Kravspecifikation | D45: Funktionelle krav | E45: Udveksling af data med BOM. | F45: - | G45: Alle ansøgninger til Københavns Kommune som oprettes i BOM skal kunne sagsbehandles i løsningen. | I45: MK - Minimumskrav | J45: =IF(I45="IK - Informationskrav","Answer",(IF(I45="K - Konkurrencekrav","Check",(IF(I45="MK - Minimumskrav","Verify",""))))) -> Verify | O45: Arve | R45: 1. Fully met | S45: BOM integrasjon | X45: Not Started | Y45: =IF(X45="Not Started",0%,IF(X45="Read",1%,IF(X45="Started",50%,IF(X45="Ready for review",70%,IF(X45="Reviewed - Content",80%,IF(X45="Reviewed - Format",90%,IF(X45="Done",100%,""))))))) -> 0
A46: 45 | B46: B2-03 | C46: Bilag 2 - Kravspecifikation | D46: Funktionelle krav | E46: Udveksling af data med BOM. | F46: - | G46: Systemet skal kunne udveksle sagsrelaterede data med ansøgningsportalen BOM på byggesager (status, dokumentation, frister mm). De kategorier, statusmarkeringer mm som anvendes i BOM overføres også til løsningen på både sagsdata og dokumenter. Handlinger i Løsningen kan udløse handlinger i BOM på baggrund af definerede forretningsregler fx ændre initiativpligt i BOM efter afsendelse af mangelbrev til ansøger. | I46: MK - Minimumskrav | J46: =IF(I46="IK - Informationskrav","Answer",(IF(I46="K - Konkurrencekrav","Check",(IF(I46="MK - Minimumskrav","Verify",""))))) -> Verify | O46: Arve | S46: BOM integrasjon | X46: Not Started | Y46: =IF(X46="Not Started",0%,IF(X46="Read",1%,IF(X46="Started",50%,IF(X46="Ready for review",70%,IF(X46="Reviewed - Content",80%,IF(X46="Reviewed - Format",90%,IF(X46="Done",100%,""))))))) -> 0
A47: 46 | B47: B2-04 | C47: Bilag 2 - Kravspecifikation | D47: Funktionelle krav | E47: Udveksling af data med BOM. | F47: - | G47: Alle byggeansøgninger fra BOM overføres og opdateres løbende. Kunden får oplysninger om seneste aktivitet. Bruger/Sagsbehandler får besked om nye aktiviteter. Systemet giver besked ved fejl i overførsler. | I47: MK - Minimumskrav | J47: =IF(I47="IK - Informationskrav","Answer",(IF(I47="K - Konkurrencekrav","Check",(IF(I47="MK - Minimumskrav","Verify",""))))) -> Verify | O47: Arve | S47: BOM integrasjon | X47: Not Started | Y47: =IF(X47="Not Started",0%,IF(X47="Read",1%,IF(X47="Started",50%,IF(X47="Ready for review",70%,IF(X47="Reviewed - Content",80%,IF(X47="Reviewed - Format",90%,IF(X47="Done",100%,""))))))) -> 0
A48: 47 | B48: 5.2.9.1. | C48: Bilag 2 - Kravspecifikation | D48: Funktionelle krav | E48: Udveksling af data med BOM. | F48: - | G48: Data fra BOM skal være søgbare i løsningen | I48: K - Konkurrencekrav | J48: =IF(I48="IK - Informationskrav","Answer",(IF(I48="K - Konkurrencekrav","Check",(IF(I48="MK - Minimumskrav","Verify",""))))) -> Check | K48: 1 | L48: 2 | M48: =Evalueringshieraki!$P$16 -> 0.48543689 | O48: Arve | S48: BOM integrasjon | X48: Not Started | Y48: =IF(X48="Not Started",0%,IF(X48="Read",1%,IF(X48="Started",50%,IF(X48="Ready for review",70%,IF(X48="Reviewed - Content",80%,IF(X48="Reviewed - Format",90%,IF(X48="Done",100%,""))))))) -> 0
A49: 48 | B49: 5.2.9.2. | C49: Bilag 2 - Kravspecifikation | D49: Funktionelle krav | E49: Udveksling af data med BOM. | F49: - | G49: Ændringer i data og dokumenter i BOM skal overføres til løsningen og opdatere den relevante sag. Ændringer i en sag skal fremgå tydeligt. | I49: K - Konkurrencekrav | J49: =IF(I49="IK - Informationskrav","Answer",(IF(I49="K - Konkurrencekrav","Check",(IF(I49="MK - Minimumskrav","Verify",""))))) -> Check | K49: 1 | L49: 2 | M49: =Evalueringshieraki!$P$16 -> 0.48543689 | O49: Arve | S49: BOM integrasjon | X49: Not Started | Y49: =IF(X49="Not Started",0%,IF(X49="Read",1%,IF(X49="Started",50%,IF(X49="Ready for review",70%,IF(X49="Reviewed - Content",80%,IF(X49="Reviewed - Format",90%,IF(X49="Done",100%,""))))))) -> 0
A50: 49 | B50: 5.2.9.3. | C50: Bilag 2 - Kravspecifikation | D50: Funktionelle krav | E50: Udveksling af data med BOM. | F50: - | G50: De ansøgningsfaser, dokumentkategorier og sagstyper som anvendes i BOM skal overføres så disse fremgår i løsningen. | I50: K - Konkurrencekrav | J50: =IF(I50="IK - Informationskrav","Answer",(IF(I50="K - Konkurrencekrav","Check",(IF(I50="MK - Minimumskrav","Verify",""))))) -> Check | K50: 1 | L50: 2 | M50: =Evalueringshieraki!$P$16 -> 0.48543689 | O50: Arve | S50: BOM integrasjon | X50: Not Started | Y50: =IF(X50="Not Started",0%,IF(X50="Read",1%,IF(X50="Started",50%,IF(X50="Ready for review",70%,IF(X50="Reviewed - Content",80%,IF(X50="Reviewed - Format",90%,IF(X50="Done",100%,""))))))) -> 0
A51: 50 | B51: 5.2.9.4. | C51: Bilag 2 - Kravspecifikation | D51: Funktionelle krav | E51: Udveksling af data med BOM. | F51: - | G51: Data skal kunne filtreres på oplysninger fra BOM, fx dato, indsendelses nummer, krav-kategorier, ansøger mm. | I51: K - Konkurrencekrav | J51: =IF(I51="IK - Informationskrav","Answer",(IF(I51="K - Konkurrencekrav","Check",(IF(I51="MK - Minimumskrav","Verify",""))))) -> Check | K51: 1 | L51: 2 | M51: =Evalueringshieraki!$P$16 -> 0.48543689 | O51: Arve | S51: BOM integrasjon | X51: Not Started | Y51: =IF(X51="Not Started",0%,IF(X51="Read",1%,IF(X51="Started",50%,IF(X51="Ready for review",70%,IF(X51="Reviewed - Content",80%,IF(X51="Reviewed - Format",90%,IF(X51="Done",100%,""))))))) -> 0
A52: 51 | B52: 5.2.9.5. | C52: Bilag 2 - Kravspecifikation | D52: Funktionelle krav | E52: Udveksling af data med BOM. | F52: - | G52: Data skal kunne markeres som værende enten behandlet/ikke-behandlet eller modtaget/ikke-modtaget. | I52: K - Konkurrencekrav | J52: =IF(I52="IK - Informationskrav","Answer",(IF(I52="K - Konkurrencekrav","Check",(IF(I52="MK - Minimumskrav","Verify",""))))) -> Check | K52: 1 | L52: 2 | M52: =Evalueringshieraki!$P$16 -> 0.48543689 | O52: Arve | S52: BOM integrasjon | X52: Not Started | Y52: =IF(X52="Not Started",0%,IF(X52="Read",1%,IF(X52="Started",50%,IF(X52="Ready for review",70%,IF(X52="Reviewed - Content",80%,IF(X52="Reviewed - Format",90%,IF(X52="Done",100%,""))))))) -> 0
A53: 52 | B53: 5.2.9.6. | C53: Bilag 2 - Kravspecifikation | D53: Funktionelle krav | E53: Udveksling af data med BOM. | F53: - | G53: Løsningen skal kunne differentiere/markere de enkelte indsendelser fra BOM af både data og dokumenter. | I53: K - Konkurrencekrav | J53: =IF(I53="IK - Informationskrav","Answer",(IF(I53="K - Konkurrencekrav","Check",(IF(I53="MK - Minimumskrav","Verify",""))))) -> Check | K53: 1 | L53: 2 | M53: =Evalueringshieraki!$P$16 -> 0.48543689 | O53: Arve | S53: BOM integrasjon | X53: Not Started | Y53: =IF(X53="Not Started",0%,IF(X53="Read",1%,IF(X53="Started",50%,IF(X53="Ready for review",70%,IF(X53="Reviewed - Content",80%,IF(X53="Reviewed - Format",90%,IF(X53="Done",100%,""))))))) -> 0
A54: 53 | B54: 5.2.9.7. | C54: Bilag 2 - Kravspecifikation | D54: Funktionelle krav | E54: Udveksling af data med BOM. | F54: - | G54: Data/enkelte indsendelser skal kunne markeres som annulleret/ikke relevant. | I54: K - Konkurrencekrav | J54: =IF(I54="IK - Informationskrav","Answer",(IF(I54="K - Konkurrencekrav","Check",(IF(I54="MK - Minimumskrav","Verify",""))))) -> Check | K54: 1 | L54: 2 | M54: =Evalueringshieraki!$P$16 -> 0.48543689 | O54: Arve | S54: BOM integrasjon | X54: Not Started | Y54: =IF(X54="Not Started",0%,IF(X54="Read",1%,IF(X54="Started",50%,IF(X54="Ready for review",70%,IF(X54="Reviewed - Content",80%,IF(X54="Reviewed - Format",90%,IF(X54="Done",100%,""))))))) -> 0
A55: 54 | B55: 5.2.10.1. | C55: Bilag 2 - Kravspecifikation | D55: Funktionelle krav | E55: Dataafgrænsning af sager | F55: Dataafgrænsning af sager | G55: Dataafgrænsning af sager Leverandøren bedes beskrive hvordan der arbejdes med skærmede sager og dokumenter ud fra følsomhedsniveau. Beskrivelsen bør vise hvordan brugeren tildeler sager følsomhedsniveauer eller afskærmning, samt hvordan sager fremgår i søgninger og oversigter som begrænsede eller maskerede. Det vægtes positivt hvis: - Løsningen desuden kan sættes op så visse konkrete matrikler, adresser eller BFE’er automatisk får fortrolighed på alle sager. - Brugeren nemt kan tildele følsomhedsniveau - Brugeren tydeligt kan se at en sag er maskeret og at Brugeren har/ikke har adgang til at se denne. - Administrator kan vedligeholde følsomhedshedsniveauer på sagstyper - Administrator kan opsætte forretningsregler baseret på følsomhed, såsom hvilke sager der skal overføres til FilArkiv. | I55: IK - Informationskrav | J55: =IF(I55="IK - Informationskrav","Answer",(IF(I55="K - Konkurrencekrav","Check",(IF(I55="MK - Minimumskrav","Verify",""))))) -> Answer | K55: 1 | L55: 2 | M55: =Evalueringshieraki!$P$16 -> 0.48543689 | O55: Axel | S55: They have a specific field in edoc called "følsomhed" not sure if it translates to access code in 360 | W55: Bilag 2 - 5.2.10.1 - Dataafgrænsning af sager.docx | X55: Not Started | Y55: =IF(X55="Not Started",0%,IF(X55="Read",1%,IF(X55="Started",50%,IF(X55="Ready for review",70%,IF(X55="Reviewed - Content",80%,IF(X55="Reviewed - Format",90%,IF(X55="Done",100%,""))))))) -> 0
A56: 55 | B56: B2-05 | C56: Bilag 2 - Kravspecifikation | D56: Funktionelle krav | E56: Sagsbehandlingstid og tilbageværende servicemålstid for BOM | F56: Sagsbehandlingstid og tilbageværende servicemålstid for BOM | G56: Løsningen skal kunne håndtere BOM servicemåltid både for sager indsendt gennem BOM og for sager oprettet direkte i systemet. Løsningen skal understøtte automatisk (visse hændelser sender besked til BOM) og manuel styring af tidtællingen i forbindelse med centrale hændelser i sagsforløbet, herunder afsendelse af mangelbreve og afgørelser samt modtagelse af yderligere dokumentation. Formålet er at sikre, at sagsbehandlere og ledelse til enhver tid har overblik over både sagsbehandlingstid (se krav ovenfor) og overholdelse af/opgørelse af BOM servicemål. I denne sammenhæng vær opmærksom på forskellen mellem tidsregistrering (medarbejdernes forbrugte timer) i kravene ovenfor, og optælling af sagsbehandlingstid og servicemåltid som defineret i BOM. | I56: MK - Minimumskrav | J56: =IF(I56="IK - Informationskrav","Answer",(IF(I56="K - Konkurrencekrav","Check",(IF(I56="MK - Minimumskrav","Verify",""))))) -> Verify | O56: Axel | S56: Støttes dette i eDoc? | X56: Not Started | Y56: =IF(X56="Not Started",0%,IF(X56="Read",1%,IF(X56="Started",50%,IF(X56="Ready for review",70%,IF(X56="Reviewed - Content",80%,IF(X56="Reviewed - Format",90%,IF(X56="Done",100%,""))))))) -> 0
A57: 56 | B57: 5.2.11.1. | C57: Bilag 2 - Kravspecifikation | D57: Funktionelle krav | E57: Sagsbehandlingstid og tilbageværende servicemålstid for BOM | F57: Sagsbehandlingstid og servicemålstid | G57: Sagsbehandlingstid og servicemålstid Løsningen skal kunne vise både sagsbehandlingstid (se krav ovenfor) og status på servicemålstid fra BOM. Det vægtes positivt at  Sagsbehandlingstid og servicemålstid fremstår overskuelig på oversigt over sager  Sagsbehandlingstid og servicemålstid fremstår overskuelig når den enkelte sag åbnes | H57: For de nedenstående IK-krav, vil det generelt vægtes positivt, at Leverandøren i sin besvarelse af nærværende afsnit demonstrerer: - at Løsningen understøtter en høj grad af automatik i styringen af sagsbehandlingstider, således at tidtælling startes og stoppes som en naturlig følge af handlinger i systemet uden manuel indgriben - at Løsningen understøtter en tydelig og intuitiv visning af sagsbehandlingstider og tilbageværende servicemål, som er let tilgængelig for både sagsbehandlere og ledelse - at Løsningen håndterer sager fra BOM og oprettet direkte i løsningen på en ensartet og overskuelig måde - at Løsningen kan udsende notifikationer eller advarsler til relevante brugere, når servicemål nærmer sig udløb - at Løsningen giver mulighed for at tilpasse regler for tidtælling og bero-perioder uden behov for systemudvikling - at alle ændringer i tidtælling, herunder manuelle stop og starter, logges automatisk med tidsstempel og brugeridentitet af hensyn til dokumentation og sporbarhed | I57: IK - Informationskrav | J57: =IF(I57="IK - Informationskrav","Answer",(IF(I57="K - Konkurrencekrav","Check",(IF(I57="MK - Minimumskrav","Verify",""))))) -> Answer | K57: 1 | L57: 2 | M57: =Evalueringshieraki!$P$16 -> 0.48543689 | O57: Axel | S57: Støttes dette i eDoc? | W57: Bilag 2 - 5.2.11.1 - Sagsbehandlingstid og servicemålstid.docx | X57: Not Started | Y57: =IF(X57="Not Started",0%,IF(X57="Read",1%,IF(X57="Started",50%,IF(X57="Ready for review",70%,IF(X57="Reviewed - Content",80%,IF(X57="Reviewed - Format",90%,IF(X57="Done",100%,""))))))) -> 0
A58: 57 | B58: 5.2.11.2. | C58: Bilag 2 - Kravspecifikation | D58: Funktionelle krav | E58: Sagsbehandlingstid og tilbageværende servicemålstid for BOM | F58: Servicemålstid start/stop | G58: Servicemålstid start/stop Løsningen skal kunne stoppe og starte servicemålstid både manuelt og automatisk som følge af en handling i systemet (eks. afsendelse af mangelbrev eller afgørelse). Leverandøren bedes illustreres i hvilket omfang dette kan ske automatisk. Det vægtes positivt at  Automatisk servicemålstid kan kobles til sagsbehandlingsprocessen  At man på sagen kan se status/historik for start/stop af servicemålstid | H58: For de nedenstående IK-krav, vil det generelt vægtes positivt, at Leverandøren i sin besvarelse af nærværende afsnit demonstrerer: - at Løsningen understøtter en høj grad af automatik i styringen af sagsbehandlingstider, således at tidtælling startes og stoppes som en naturlig følge af handlinger i systemet uden manuel indgriben - at Løsningen understøtter en tydelig og intuitiv visning af sagsbehandlingstider og tilbageværende servicemål, som er let tilgængelig for både sagsbehandlere og ledelse - at Løsningen håndterer sager fra BOM og oprettet direkte i løsningen på en ensartet og overskuelig måde - at Løsningen kan udsende notifikationer eller advarsler til relevante brugere, når servicemål nærmer sig udløb - at Løsningen giver mulighed for at tilpasse regler for tidtælling og bero-perioder uden behov for systemudvikling - at alle ændringer i tidtælling, herunder manuelle stop og starter, logges automatisk med tidsstempel og brugeridentitet af hensyn til dokumentation og sporbarhed | I58: IK - Informationskrav | J58: =IF(I58="IK - Informationskrav","Answer",(IF(I58="K - Konkurrencekrav","Check",(IF(I58="MK - Minimumskrav","Verify",""))))) -> Answer | K58: 1 | L58: 2 | M58: =Evalueringshieraki!$P$16 -> 0.48543689 | O58: Bjørn Henrik | S58: Konfigarsjon via milepæler i den generiske tidsbergningsmetoden | W58: Bilag 2 - 5.2.11.2 - Servicemålstid start-stop.docx | X58: Not Started | Y58: =IF(X58="Not Started",0%,IF(X58="Read",1%,IF(X58="Started",50%,IF(X58="Ready for review",70%,IF(X58="Reviewed - Content",80%,IF(X58="Reviewed - Format",90%,IF(X58="Done",100%,""))))))) -> 0
A59: 58 | B59: 5.2.11.3 | C59: Bilag 2 - Kravspecifikation | D59: Funktionelle krav | E59: Sagsbehandlingstid og tilbageværende servicemålstid for BOM | F59: Sagsbehandlingstid for ikke-BOM sager | G59: Sagsbehandlingstid for ikke-BOM sager For sager som ikke er søgt gennem BOM, skal løsningen selv lave en optælling og vise den samlede sagsbehandlingstid. Tiden skal kunne stoppes og startes manuelt, så den sættes i bero fx når der afsendes mangelbreve og afgørelse samt ved modtagelse af yderligere dokumentation.  Sagsbehandlingstid fremstår overskuelig på oversigt over sager  Sagsbehandlingstid fremstår overskuelig når den enkelte sag åbnes  At man på sagen kan se status/historik for start/stop af servicemålstid | H59: For de nedenstående IK-krav, vil det generelt vægtes positivt, at Leverandøren i sin besvarelse af nærværende afsnit demonstrerer: - at Løsningen understøtter en høj grad af automatik i styringen af sagsbehandlingstider, således at tidtælling startes og stoppes som en naturlig følge af handlinger i systemet uden manuel indgriben - at Løsningen understøtter en tydelig og intuitiv visning af sagsbehandlingstider og tilbageværende servicemål, som er let tilgængelig for både sagsbehandlere og ledelse - at Løsningen håndterer sager fra BOM og oprettet direkte i løsningen på en ensartet og overskuelig måde - at Løsningen kan udsende notifikationer eller advarsler til relevante brugere, når servicemål nærmer sig udløb - at Løsningen giver mulighed for at tilpasse regler for tidtælling og bero-perioder uden behov for systemudvikling - at alle ændringer i tidtælling, herunder manuelle stop og starter, logges automatisk med tidsstempel og brugeridentitet af hensyn til dokumentation og sporbarhed | I59: IK - Informationskrav | J59: =IF(I59="IK - Informationskrav","Answer",(IF(I59="K - Konkurrencekrav","Check",(IF(I59="MK - Minimumskrav","Verify",""))))) -> Answer | K59: 1 | L59: 2 | M59: =Evalueringshieraki!$P$16 -> 0.48543689 | O59: Bjørn Henrik | S59: Konfigarsjon via milepæler i den generiske tidsbergningsmetoden | W59: Bilag 2 - 5.2.11.3 - Sagsbehandlingstid for ikke-BOM sager.docx | X59: Not Started | Y59: =IF(X59="Not Started",0%,IF(X59="Read",1%,IF(X59="Started",50%,IF(X59="Ready for review",70%,IF(X59="Reviewed - Content",80%,IF(X59="Reviewed - Format",90%,IF(X59="Done",100%,""))))))) -> 0
A60: 59 | B60: B2-06 | C60: Bilag 2 - Kravspecifikation | D60: Funktionelle krav | E60: Sagsflow og processer | F60: Sagsflow og processer | G60: Som fagsystem for OBY skal løsningen understøtte de hovedprocesser som danner udgangspunkt for de enkelte sagstyper. Der er flere hovedprocesser i sagsbehandlingen, og nogle sager gennemføres i parallelle sagsforløb. Der arbejdes kontinuerligt med optimering af processer, hvorfor løsningen også skal understøtte en løbende justering eller oprettelse af nye processer og at tilpasningen kan gennemføres af kundens administratorer. | I60: MK - Minimumskrav | J60: =IF(I60="IK - Informationskrav","Answer",(IF(I60="K - Konkurrencekrav","Check",(IF(I60="MK - Minimumskrav","Verify",""))))) -> Verify | O60: Morten | R60: 1. Fully met | S60: Could the phrase "the system should support the mainprocesses" be interpretated so, that they can just define these along the way? | X60: Not Started | Y60: =IF(X60="Not Started",0%,IF(X60="Read",1%,IF(X60="Started",50%,IF(X60="Ready for review",70%,IF(X60="Reviewed - Content",80%,IF(X60="Reviewed - Format",90%,IF(X60="Done",100%,""))))))) -> 0
A61: 60 | B61: B2-07 | C61: Bilag 2 - Kravspecifikation | D61: Funktionelle krav | E61: Sagsflow og processer | F61: Sagsflow og processer | G61: Løsningen skal i høj grad understøtte forretningens processer, vi skitserer her behovene og er åbne for at tilrette eksisterende processer til leverandørens anbefalede procesfunktionalitet. | I61: MK - Minimumskrav | J61: =IF(I61="IK - Informationskrav","Answer",(IF(I61="K - Konkurrencekrav","Check",(IF(I61="MK - Minimumskrav","Verify",""))))) -> Verify | O61: Bjørn Henrik | X61: Not Started | Y61: =IF(X61="Not Started",0%,IF(X61="Read",1%,IF(X61="Started",50%,IF(X61="Ready for review",70%,IF(X61="Reviewed - Content",80%,IF(X61="Reviewed - Format",90%,IF(X61="Done",100%,""))))))) -> 0
A62: 61 | B62: 5.2.12.1. | C62: Bilag 2 - Kravspecifikation | D62: Funktionelle krav | E62: Sagsflow og processer | F62: Sagens overblik | G62: Sagens overblik Leverandøren bedes beskrive, hvordan Løsningen understøtter et godt overblik på den enkelte sag. Det vægtes positivt, når man slår en sag op, at:  Det skal være nemt at se, hvilken type af sag og sagens oplysninger, når en sag slås op. (f.eks. BOM el. manuelt oprettet)  Hvilke aktiviteter er gennemført, og hvem har haft ansvar – hvor ligger sagen henne nu og hvem/hvad afventer den. (En historik/log på sagen)  Hvis sagen er afgjort - skal afgørelsens udfald fremgå.  Hvis sagen er lukket – skal status på, hvordan den er lukket fremgå.  Datoer for afgørelser og udsendelser skal fremgå af sagen. (F.eks. Byggetilladelse (BT) dato, Ibrugtagnings (IBT) dato osv.)  Hvis sagen har relationer til andre sager – Oplysninger på relaterede sager skal fremgå af den sag man har slået op. (F.eks. hvordan den er afsluttet (f.eks. med afslag, BT., udtalelse osv.), afgørelsesudfald mm.) | I62: IK - Informationskrav | J62: =IF(I62="IK - Informationskrav","Answer",(IF(I62="K - Konkurrencekrav","Check",(IF(I62="MK - Minimumskrav","Verify",""))))) -> Answer | K62: 1 | L62: 2 | M62: =Evalueringshieraki!$P$16 -> 0.48543689 | O62: Morten | T62: Yes | W62: Bilag 2 - 5.2.12.1 - Sagens overblik.docx | X62: Not Started | Y62: =IF(X62="Not Started",0%,IF(X62="Read",1%,IF(X62="Started",50%,IF(X62="Ready for review",70%,IF(X62="Reviewed - Content",80%,IF(X62="Reviewed - Format",90%,IF(X62="Done",100%,""))))))) -> 0
A63: 62 | B63: 5.2.12.2 | C63: Bilag 2 - Kravspecifikation | D63: Funktionelle krav | E63: Sagsflow og processer | F63: Understøtte sagsflow | G63: Understøtte sagsflow Leverandøren bedes beskrive, hvordan løsningen understøtter en ensartet og optimeret arbejdsgang, herunder hvordan løsningen sikrer at sagsbehandlere/andre brugere hurtigere får overblik over sagen og er ikke i tvivl om, hvad næste handling er. Herudover bedes Leverandøren beskrive, hvordan løsningens funktionalitet sikrer at der er overblik over alle sager og de ikke kan ’tabes’ dvs. mangle information om fx sagsansvarlig, enhed og sagsstatus, hvordan der dannes grundlag for at kunne driftsstyre pba. data, samt registreringen er informationskilde, når vi rapporterer til ledelse, politikere og borgere. Det vægtes positivt, at oplysninger som bl.a. er vigtige for sagsbehandlingen, er tilgængelige og:  Brugeren kan tildele opgaver eller sager til kolleger direkte fra fagsystemet.  Brugeren kan markere en sag eller opgave som klar til viderebehandling af en anden bruger eller et andet team.  Systemet understøtter notifikationer ved interne overleveringer, så modtageren adviseres automatisk.  Det er muligt at følge en sags interne historik, herunder hvem der har haft sagen, og hvornår den er overleveret. | I63: IK - Informationskrav | J63: =IF(I63="IK - Informationskrav","Answer",(IF(I63="K - Konkurrencekrav","Check",(IF(I63="MK - Minimumskrav","Verify",""))))) -> Answer | K63: 1 | L63: 2 | M63: =Evalueringshieraki!$P$16 -> 0.48543689 | O63: Morten | W63: Bilag 2 - 5.2.12.2 - Understøtte sagsflow.docx | X63: Not Started | Y63: =IF(X63="Not Started",0%,IF(X63="Read",1%,IF(X63="Started",50%,IF(X63="Ready for review",70%,IF(X63="Reviewed - Content",80%,IF(X63="Reviewed - Format",90%,IF(X63="Done",100%,""))))))) -> 0
A64: 63 | B64: B2-08 | C64: Bilag 2 - Kravspecifikation | D64: Funktionelle krav | E64: Sagsstandarder | F64: Sagsstandarder | G64: Løsningen er proces-understøttende og skal kunne håndtere at forskellige sagstyper behandles forskelligt og derfor har forskellige processer. Løsningen skal kunne understøtte dette, undervejs i hele forløbet og guide brugeren gennem alle relevante trin, ved hjælp af relevante værktøjer. | I64: MK - Minimumskrav | J64: =IF(I64="IK - Informationskrav","Answer",(IF(I64="K - Konkurrencekrav","Check",(IF(I64="MK - Minimumskrav","Verify",""))))) -> Verify | O64: Anton | R64: 1. Fully met | X64: Ready for review | Y64: =IF(X64="Not Started",0%,IF(X64="Read",1%,IF(X64="Started",50%,IF(X64="Ready for review",70%,IF(X64="Reviewed - Content",80%,IF(X64="Reviewed - Format",90%,IF(X64="Done",100%,""))))))) -> 0.7
A65: 64 | B65: B2-09 | C65: Bilag 2 - Kravspecifikation | D65: Funktionelle krav | E65: Sagsstandarder | F65: Sagsstandarder | G65: Det skal være muligt for brugere med særlig tilladelse at oprette nye og ændre eksisterende sagsskabeloner/sagsforløb. | I65: MK - Minimumskrav | J65: =IF(I65="IK - Informationskrav","Answer",(IF(I65="K - Konkurrencekrav","Check",(IF(I65="MK - Minimumskrav","Verify",""))))) -> Verify | O65: Anita | R65: 1. Fully met | S65: Administrator | X65: Ready for review | Y65: =IF(X65="Not Started",0%,IF(X65="Read",1%,IF(X65="Started",50%,IF(X65="Ready for review",70%,IF(X65="Reviewed - Content",80%,IF(X65="Reviewed - Format",90%,IF(X65="Done",100%,""))))))) -> 0.7
A66: 65 | B66: 5.2.13.1. | C66: Bilag 2 - Kravspecifikation | D66: Funktionelle krav | E66: Sagsstandarder | F66: Sagsoprettelse via standardskabelon | G66: Sagsoprettelse via standardskabelon Leverandøren bedes beskrive hvordan man i løsningen opretter sager via standard sagsskabeloner. Det vægtes positivt hvis: - Det er muligt at understøtte oprettelse af veldefinerede typer af sager, med individuelle sagsskabeloner både manuelt og automatisk oprettede sager. - Den enkelte sagsskabelon indeholder de relevante sagsoplysninger. F.eks. Sagstype, sagsejerskab, og hvilke trin, der skal oprettes til sagsbehandlingen. - Der kan ad hoc tilføjes nye handlinger/sagshandlinger | I66: IK - Informationskrav | J66: =IF(I66="IK - Informationskrav","Answer",(IF(I66="K - Konkurrencekrav","Check",(IF(I66="MK - Minimumskrav","Verify",""))))) -> Answer | K66: 1 | L66: 2 | M66: =Evalueringshieraki!$P$16 -> 0.48543689 | O66: Axel | P66: Jarle | S66: Case templates in PLan and build? | W66: Bilag 2 - 5.2.13.1 - Sagsoprettelse via standardskabelon.docx | X66: Not Started | Y66: =IF(X66="Not Started",0%,IF(X66="Read",1%,IF(X66="Started",50%,IF(X66="Ready for review",70%,IF(X66="Reviewed - Content",80%,IF(X66="Reviewed - Format",90%,IF(X66="Done",100%,""))))))) -> 0
A67: 66 | B67: 5.2.13.2. | C67: Bilag 2 - Kravspecifikation | D67: Funktionelle krav | E67: Sagsstandarder | F67: Standardsagers procesunderstøttelse | G67: Standardsagers procesunderstøttelse Leverandøren bedes beskrive hvordan man i løsningen sikrer en prædefineret sagsbehandlingsproces via sagsskabelonerne. Det vægter positivt hvis: - Brugeren kan ikke ”lukke/forlade” en sag, hvis den ikke er korrekt registreret. - Brugerens som udgangspunkt ikke kan undvige det prædefineret forløb, men i stedet bliver gjort opmærksom på, at man ikke følger processen. - Løsningen kender den givne proces og man kan se relevant info for trinnet. - Løsningen automatisk kan skifte sagens status når definerede events/handlinger er gennemført. - Løsningen automatisk kan sende sagen til den enhed, som har ansvar for næste sagsfase/sagsstatus, når fasen lukkes eller status ændres - Udførte opgaver markeres som gennemført - Sideløbende sagsgange kan håndteres, således at sagen ligger hos ét team/enhed, men kan visiteres til bidrag fra anden enhed, i eller udenfor OBY. - Løsningen understøtter en ensartet og optimeret arbejdsgang, der giver ensartede sagsforløb. | I67: IK - Informationskrav | J67: =IF(I67="IK - Informationskrav","Answer",(IF(I67="K - Konkurrencekrav","Check",(IF(I67="MK - Minimumskrav","Verify",""))))) -> Answer | K67: 1 | L67: 2 | M67: =Evalueringshieraki!$P$16 -> 0.48543689 | O67: Axel | P67: Jarle | S67: Case templates in PLan and build? | W67: Bilag 2 - 5.2.13.2 - Standardsagers procesunderstøttelse.docx | X67: Not Started | Y67: =IF(X67="Not Started",0%,IF(X67="Read",1%,IF(X67="Started",50%,IF(X67="Ready for review",70%,IF(X67="Reviewed - Content",80%,IF(X67="Reviewed - Format",90%,IF(X67="Done",100%,""))))))) -> 0
A68: 67 | B68: B2-10 | C68: Bilag 2 - Kravspecifikation | D68: Funktionelle krav | E68: Advis og notifikationer | F68: Advis og notifikationer | G68: Løsningen skal indeholde en advis-funktion, så der afsendes notifikation til brugerne når ny data modtages, tidsfrister udløber eller sagernes status ændres. | I68: MK - Minimumskrav | J68: =IF(I68="IK - Informationskrav","Answer",(IF(I68="K - Konkurrencekrav","Check",(IF(I68="MK - Minimumskrav","Verify",""))))) -> Verify | O68: Morten | R68: 1. Fully met | S68: Minimum requirement for "notification when due dates are reached" - are we confident we solve this enough places to say yes? | X68: Not Started | Y68: =IF(X68="Not Started",0%,IF(X68="Read",1%,IF(X68="Started",50%,IF(X68="Ready for review",70%,IF(X68="Reviewed - Content",80%,IF(X68="Reviewed - Format",90%,IF(X68="Done",100%,""))))))) -> 0
A69: 68 | B69: 5.2.14.1. | C69: Bilag 2 - Kravspecifikation | D69: Funktionelle krav | E69: Advis og notifikationer | F69: Advis funktion | G69: Advis funktion Leverandøren bedes beskrive løsningens advis-funktion. Det vægtes positivt hvis: - Funktionen afsender notifikation, når nye data eller sager modtages, sagsfrister udløber mm. - Funktionen giver sagsbehandlere/teams/enheder overblik over seneste hændelser i sager, de er ansvarlige for. - Hvis brugeren præsenteres for aktuelle advis på løsningens ”forside”, når der logges på - hvis brugeren kan vælge at modtage udvalgte advis pr mail | I69: IK - Informationskrav | J69: =IF(I69="IK - Informationskrav","Answer",(IF(I69="K - Konkurrencekrav","Check",(IF(I69="MK - Minimumskrav","Verify",""))))) -> Answer | K69: 1 | L69: 2 | M69: =Evalueringshieraki!$P$16 -> 0.48543689 | O69: Anton | W69: Bilag 2 - 5.2.14.1 - Advis funktion.docx | X69: Not Started | Y69: =IF(X69="Not Started",0%,IF(X69="Read",1%,IF(X69="Started",50%,IF(X69="Ready for review",70%,IF(X69="Reviewed - Content",80%,IF(X69="Reviewed - Format",90%,IF(X69="Done",100%,""))))))) -> 0
A70: 69 | B70: 5.2.14.2. | C70: Bilag 2 - Kravspecifikation | D70: Funktionelle krav | E70: Advis og notifikationer | F70: Tilpasning af advis | G70: Tilpasning af advis Løsningen giver mulighed for at tilpasse individuelt og på teams/enheds niveau, hvilke advis der modtages. Så den enkelte kun modtager de advis som er relevante for deres opgaver/rolle. Leverandøren bedes redegør for hvilke muligheder der er for at opsætte advis henholdsvis individuelt og ”pushe” advis til faste brugerroller/grupper. Det vægtes positivt hvis: - Advis vises overskueligt og let tilgængeligt | I70: IK - Informationskrav | J70: =IF(I70="IK - Informationskrav","Answer",(IF(I70="K - Konkurrencekrav","Check",(IF(I70="MK - Minimumskrav","Verify",""))))) -> Answer | K70: 1 | L70: 2 | M70: =Evalueringshieraki!$P$16 -> 0.48543689 | O70: Anton | W70: Bilag 2 - 5.2.14.2 - Tilpasning af advis.docx | X70: Not Started | Y70: =IF(X70="Not Started",0%,IF(X70="Read",1%,IF(X70="Started",50%,IF(X70="Ready for review",70%,IF(X70="Reviewed - Content",80%,IF(X70="Reviewed - Format",90%,IF(X70="Done",100%,""))))))) -> 0
A71: 70 | B71: B2-11 | C71: Bilag 2 - Kravspecifikation | D71: Funktionelle krav | E71: Arkivering af sager | F71: Arkivering af sager | G71: Som fagsystem skal løsningen opbevare alle afsluttede sager, da sagerne ikke er omfattet af slettefrister. Københavns Kommune udstiller desuden alle afsluttede, ikke-fortrolige sager i det offentlige byggesagsarkiv via løsningen FilArkiv. | I71: MK - Minimumskrav | J71: =IF(I71="IK - Informationskrav","Answer",(IF(I71="K - Konkurrencekrav","Check",(IF(I71="MK - Minimumskrav","Verify",""))))) -> Verify | O71: Anton | R71: 1. Fully met | X71: Ready for review | Y71: =IF(X71="Not Started",0%,IF(X71="Read",1%,IF(X71="Started",50%,IF(X71="Ready for review",70%,IF(X71="Reviewed - Content",80%,IF(X71="Reviewed - Format",90%,IF(X71="Done",100%,""))))))) -> 0.7
A72: 71 | B72: 5.2.15.1. | C72: Bilag 2 - Kravspecifikation | D72: Funktionelle krav | E72: Arkivering af sager | F72: Markering af dokumenter til FilArkiv | G72: Markering af dokumenter til FilArkiv Løsningen skal gøre det muligt, løbende at markere de dokumenter, som skal uploades til FilArkiv ved sagens afslutning. | I72: K - Konkurrencekrav | J72: =IF(I72="IK - Informationskrav","Answer",(IF(I72="K - Konkurrencekrav","Check",(IF(I72="MK - Minimumskrav","Verify",""))))) -> Check | K72: 1 | L72: 2 | M72: =Evalueringshieraki!$P$16 -> 0.48543689 | O72: Arve | S72: Filarkiv fra eDoc | X72: Not Started | Y72: =IF(X72="Not Started",0%,IF(X72="Read",1%,IF(X72="Started",50%,IF(X72="Ready for review",70%,IF(X72="Reviewed - Content",80%,IF(X72="Reviewed - Format",90%,IF(X72="Done",100%,""))))))) -> 0
A73: 72 | B73: 5.2.15.2. | C73: Bilag 2 - Kravspecifikation | D73: Funktionelle krav | E73: Arkivering af sager | F73: Håndtering af navne- og adressebeskyttelse | G73: Håndtering af navne- og adressebeskyttelse For sager som har navne- og adressebeskyttelse skal løsningen give en advis, om at man er ved at overføre en sag med navne- og adressebeskyttelse. Sagen skal stadig overføres, men med en advis. | I73: K - Konkurrencekrav | J73: =IF(I73="IK - Informationskrav","Answer",(IF(I73="K - Konkurrencekrav","Check",(IF(I73="MK - Minimumskrav","Verify",""))))) -> Check | K73: 1 | L73: 2 | M73: =Evalueringshieraki!$P$16 -> 0.48543689 | O73: Arve | S73: We have adress and name protection in CPR integrtaion - but it probably wont give notification | X73: Not Started | Y73: =IF(X73="Not Started",0%,IF(X73="Read",1%,IF(X73="Started",50%,IF(X73="Ready for review",70%,IF(X73="Reviewed - Content",80%,IF(X73="Reviewed - Format",90%,IF(X73="Done",100%,""))))))) -> 0
A74: 73 | B74: 5.2.15.3. | C74: Bilag 2 - Kravspecifikation | D74: Funktionelle krav | E74: Arkivering af sager | F74: Overførsel af sagens data og dokumentation | G74: Overførsel af sagens data og dokumentation Når sagen afsluttes og overførsel til FilArkiv aktiveres, skal sagens data og den udvalgte dokumentation overføres. Det skal være muligt at genuploade en sag til FilArkiv – f.eks. hvis den genoptages. | I74: K - Konkurrencekrav | J74: =IF(I74="IK - Informationskrav","Answer",(IF(I74="K - Konkurrencekrav","Check",(IF(I74="MK - Minimumskrav","Verify",""))))) -> Check | K74: 1 | L74: 2 | M74: =Evalueringshieraki!$P$16 -> 0.48543689 | O74: Arve | X74: Not Started | Y74: =IF(X74="Not Started",0%,IF(X74="Read",1%,IF(X74="Started",50%,IF(X74="Ready for review",70%,IF(X74="Reviewed - Content",80%,IF(X74="Reviewed - Format",90%,IF(X74="Done",100%,""))))))) -> 0
A75: 74 | B75: 5.2.15.4. | C75: Bilag 2 - Kravspecifikation | D75: Funktionelle krav | E75: Arkivering af sager | F75: Status på overførsel og fejlhåndtering | G75: Status på overførsel og fejlhåndtering Leverandøren bedes give en udtømmende beskrivelse af, hvordan Løsningen understøtter visning af overførselsstatus til FilArkiv, herunder:  hvordan brugeren kan følge status på overførslen  hvordan fejl på enkeltdokumenter håndteres og præsenteres for brugeren Det vægtes positivt, at Leverandøren i sin besvarelse demonstrerer, at Løsningen understøtter:  at fejlede dokumenter tydeligt identificeres med angivelse af årsag til fejl  at brugeren kan genstarte overførslen af fejlede dokumenter uden at skulle overføre hele sagen på ny  at brugeren notificeres, når overførslen er fuldført eller fejler  at der logges automatisk med tidsstempel og brugeridentitet ved gennemførte overførsler | I75: IK - Informationskrav | J75: =IF(I75="IK - Informationskrav","Answer",(IF(I75="K - Konkurrencekrav","Check",(IF(I75="MK - Minimumskrav","Verify",""))))) -> Answer | K75: 1 | L75: 2 | M75: =Evalueringshieraki!$P$16 -> 0.48543689 | O75: Axel | P75: Merge project | T75: Yes | W75: Bilag 2 - 5.2.15.4 - Status på overførsel og fejlhåndtering.docx | X75: Not Started | Y75: =IF(X75="Not Started",0%,IF(X75="Read",1%,IF(X75="Started",50%,IF(X75="Ready for review",70%,IF(X75="Reviewed - Content",80%,IF(X75="Reviewed - Format",90%,IF(X75="Done",100%,""))))))) -> 0
A76: 75 | B76: B2-12 | C76: Bilag 2 - Kravspecifikation | D76: Funktionelle krav | E76: Rapporter, statistik og ledelsesinformation | F76: Rapporter, statistik og ledelsesinformation | G76: Løsningen skal sikre, at der løbende kan følges op på servicemålsoverholdelse – både på tværs af sagskategorier og på den enkelte sag og sagsbehandler. | I76: MK - Minimumskrav | J76: =IF(I76="IK - Informationskrav","Answer",(IF(I76="K - Konkurrencekrav","Check",(IF(I76="MK - Minimumskrav","Verify",""))))) -> Verify | O76: Bjørn Henrik | Q76: Plan & Build 360 | R76: 2. Partly met | S76: This is regarding overview of the case handling deadlines in the solution. We just need to implement the danish model for deadlines and show it in a good way on our dashboards. | T76: Yes | U76: No | V76: No | X76: Started | Y76: =IF(X76="Not Started",0%,IF(X76="Read",1%,IF(X76="Started",50%,IF(X76="Ready for review",70%,IF(X76="Reviewed - Content",80%,IF(X76="Reviewed - Format",90%,IF(X76="Done",100%,""))))))) -> 0.5
A77: 76 | B77: B2-13 | C77: Bilag 2 - Kravspecifikation | D77: Funktionelle krav | E77: Rapporter, statistik og ledelsesinformation | F77: Rapporter, statistik og ledelsesinformation | G77: Løsningen skal kunne levere data til både rapporter og oversigter, samt levere data til anvendelse til LIS og løbende driftsstyring. | I77: MK - Minimumskrav | J77: =IF(I77="IK - Informationskrav","Answer",(IF(I77="K - Konkurrencekrav","Check",(IF(I77="MK - Minimumskrav","Verify",""))))) -> Verify | O77: Bjørn Henrik | Q77: Management Reporting API | R77: 1. Fully met | S77: Should use the Management Reporting API for this. The customer can then use this data to create dashboards with daily updates in Power BI or similar programs. | X77: Started | Y77: =IF(X77="Not Started",0%,IF(X77="Read",1%,IF(X77="Started",50%,IF(X77="Ready for review",70%,IF(X77="Reviewed - Content",80%,IF(X77="Reviewed - Format",90%,IF(X77="Done",100%,""))))))) -> 0.5
A78: 77 | B78: 5.2.16.1. | C78: Bilag 2 - Kravspecifikation | D78: Funktionelle krav | E78: Rapporter, statistik og ledelsesinformation | F78: Håndtering af servicemålssager | G78: Håndtering af servicemålssager Løsningen skal kunne håndtere byggesager, hvortil der er aftalt et servicemål fra KL. | I78: K - Konkurrencekrav | J78: =IF(I78="IK - Informationskrav","Answer",(IF(I78="K - Konkurrencekrav","Check",(IF(I78="MK - Minimumskrav","Verify",""))))) -> Check | K78: 1 | L78: 2 | M78: =Evalueringshieraki!$P$16 -> 0.48543689 | O78: Bjørn Henrik | Q78: Plan & Build 360 | R78: 1. Fully met | S78: We need to create stages and processes that reflects their needs in these types of cases, but this is expected work going into this. 360 Flow will be the solution here. | X78: Started | Y78: =IF(X78="Not Started",0%,IF(X78="Read",1%,IF(X78="Started",50%,IF(X78="Ready for review",70%,IF(X78="Reviewed - Content",80%,IF(X78="Reviewed - Format",90%,IF(X78="Done",100%,""))))))) -> 0.5
A79: 78 | B79: 5.2.16.2. | C79: Bilag 2 - Kravspecifikation | D79: Funktionelle krav | E79: Rapporter, statistik og ledelsesinformation | F79: Data på tværs af servicemålskategorier | G79: Data på tværs af servicemålskategorier Leverandøren bedes give en beskrivelse af, hvordan Løsningen kan levere data på servicemål. Kunden ønsker at data leveres over b.la.:  antal af åbne, afgjorte og lukkede sager (fordelt på servicemålskategorierne),  overholdelsesprocent pr. kategori, og  gennemsnitlige antal behandlingsdage. Det vægtes positivt, at Leverandøren i sin besvarelse demonstrerer, at Løsningen understøtter:  at data præsenteres i en overskuelig og visuel visning, fx i form af dashboards eller grafer  at data kan filtreres og grupperes på tværs af servicemålskategorier og tidsperioder  at overholdelsesprocent og gennemsnitlige behandlingsdage beregnes og opdateres automatisk  at data kan eksporteres til gængse formater (fx Excel, CSV) til brug for rapportering og ledelsesinformation. LIS generelt. | I79: IK - Informationskrav | J79: =IF(I79="IK - Informationskrav","Answer",(IF(I79="K - Konkurrencekrav","Check",(IF(I79="MK - Minimumskrav","Verify",""))))) -> Answer | K79: 1 | L79: 2 | M79: =Evalueringshieraki!$P$16 -> 0.48543689 | O79: Bjørn Henrik | P79: Bjørn Tore | Q79: Management Reporting API | R79: 2. Partly met | S79: We can solve this with showing some of this information/functionality directly in the solution, but most of it will be solved with Management Reporting API. I guess we will score lower here, as we cannpt show a lot of this data in our own solution, but rely on 3rd party solutions like Power BI. | W79: Bilag 2 - 5.2.16.2 - Data på tværs af servicemålskategorier.docx | X79: Started | Y79: =IF(X79="Not Started",0%,IF(X79="Read",1%,IF(X79="Started",50%,IF(X79="Ready for review",70%,IF(X79="Reviewed - Content",80%,IF(X79="Reviewed - Format",90%,IF(X79="Done",100%,""))))))) -> 0.5
A80: 79 | B80: 5.2.16.3. | C80: Bilag 2 - Kravspecifikation | D80: Funktionelle krav | E80: Rapporter, statistik og ledelsesinformation | F80: Data på enkelte sager | G80: Leverandøren bedes give en beskrivelse af, hvordan Løsningen kan levere nedenstående data, samt om denne data kan leveres både samlet og til den enkelte sagsbehandler:  type af servicemålsag, der er tale om,  tilbageværende visitationsdage og  servicemålsdage på den enkelte sag. Det vægtes positivt, at Leverandøren i sin besvarelse demonstrerer, at Løsningen understøtter: • at tilbageværende visitationsdage og servicemålsdage beregnes og opdateres automatisk på den enkelte sag (trækkes direkte fra BOM hvor muligt) • at sagsbehandlere og ledelse adviseres automatisk, når servicemål nærmer sig udløb • at data præsenteres tydeligt og tilgængeligt direkte fra den enkelte sag • at der kan genereres oversigter over servicemålsdata både samlet og pr. sagsbehandler • at data kan eksporteres til gængse formater (fx Excel, CSV). LIS generelt. | I80: IK - Informationskrav | J80: =IF(I80="IK - Informationskrav","Answer",(IF(I80="K - Konkurrencekrav","Check",(IF(I80="MK - Minimumskrav","Verify",""))))) -> Answer | K80: 1 | L80: 2 | M80: =Evalueringshieraki!$P$16 -> 0.48543689 | O80: Bjørn Henrik | Q80: Plan & Build 360/BOM-integration | R80: 2. Partly met | S80: Need commitment for reminder to case handler/leader when a case/application is approaching deadline. "Visitasjonsdage" is a sort of screening that is done before the case is fully distributed. Might be solved with a seperate stage for screening, with it's own deadline. This will make overview of the cases and reporting easier. | T80: Yes | U80: No | V80: No | W80: Bilag 2 - 5.2.16.3 - Data på enkelte sager.docx | X80: Started | Y80: =IF(X80="Not Started",0%,IF(X80="Read",1%,IF(X80="Started",50%,IF(X80="Ready for review",70%,IF(X80="Reviewed - Content",80%,IF(X80="Reviewed - Format",90%,IF(X80="Done",100%,""))))))) -> 0.5
A81: 80 | B81: B2-14 | C81: Bilag 2 - Kravspecifikation | D81: Funktionelle krav | E81: Håndtering af tidsregistrering. | F81: Håndtering af tidsregistrering. | G81: Løsningen skal gøre det let og hurtigt for brugerne at registrere tidsforbrug direkte på konkrete sager, med så få klik som muligt. Den registrerede tid skal danne grundlag for ledelsesinformation og driftsstyring, herunder overblik over ressourceforbrug på tværs af sager, samt udgangspunkt for eventuel fakturering af sagsbehandlingstiden. Det er vigtigt at være opmærksom på at med tidsregistrering menes de timer som reelt er brugt på behandling af sagen for den respektive sagsbehandler. Dette må ikke forveksles med Servicemål sagsbehandlingstid – som er tiden i dage, fra ansøgningen er fuldt oplyst og til den er afgjort. Sidstnævnte er det som b.la. indgår i de statsligt fastsatte Servicemål. | I81: MK - Minimumskrav | J81: =IF(I81="IK - Informationskrav","Answer",(IF(I81="K - Konkurrencekrav","Check",(IF(I81="MK - Minimumskrav","Verify",""))))) -> Verify | O81: Bjørn Henrik | S81: Sjekke eDoc for eksisterende funk der | X81: Not Started | Y81: =IF(X81="Not Started",0%,IF(X81="Read",1%,IF(X81="Started",50%,IF(X81="Ready for review",70%,IF(X81="Reviewed - Content",80%,IF(X81="Reviewed - Format",90%,IF(X81="Done",100%,""))))))) -> 0
A82: 81 | B82: 5.2.17.1. | C82: Bilag 2 - Kravspecifikation | D82: Funktionelle krav | E82: Håndtering af tidsregistrering. | F82: Registrering af tid på sager | G82: Registrering af tid på sager Leverandøren bedes give en beskrivelse af, hvordan Løsningen gør det nemt el. automatisk for sagsbehandler at tidsregistrere, samt give mulighed for at ændre eksisterende tidsregistreringer. Brugerne skal let kunne indtaste tidsforbrug på konkrete sager. Brugeren kan direkte (med så få klik som muligt) indtaste tidsforbrug på en given sag og systemet registrerer selv navn på den bruger, der er logget ind. Det skal være muligt at få et overblik over brugerens indtastede tidsregistreringer per dag/uge/måned. Det skal være muligt for brugeren at vælge individuelt, om registreret tid ikke skal faktureres. Det skal være muligt at eksisterende tidsregistreringer kan ændres med angivelse af årsag til ændringen Det vægtes positivt, at Løsningen understøtter:  at tidsregistrering kan foretages med så få klik som muligt direkte fra en given sag  at brugeren har en intuitiv og overskuelig oversigt over egne tidsregistreringer per dag, uge og måned fordelt på sagerne  at tidsregistrering på andet arbejde end sagsbehandling kan kategoriseres  at ændringer i tidsregistreringer logges automatisk med tidsstempel og brugeridentitet af hensyn til sporbarhed | I82: IK - Informationskrav | J82: =IF(I82="IK - Informationskrav","Answer",(IF(I82="K - Konkurrencekrav","Check",(IF(I82="MK - Minimumskrav","Verify",""))))) -> Answer | K82: 1 | L82: 2 | M82: =Evalueringshieraki!$P$16 -> 0.48543689 | O82: Bjørn Henrik | S82: Sjekke eDoc for eksisterende funk der | W82: Bilag 2 - 5.2.17.1 - Registrering af tid på sager.docx | X82: Not Started | Y82: =IF(X82="Not Started",0%,IF(X82="Read",1%,IF(X82="Started",50%,IF(X82="Ready for review",70%,IF(X82="Reviewed - Content",80%,IF(X82="Reviewed - Format",90%,IF(X82="Done",100%,""))))))) -> 0
A83: 82 | B83: 5.2.17.2. | C83: Bilag 2 - Kravspecifikation | D83: Funktionelle krav | E83: Håndtering af tidsregistrering. | F83: Registrering af anden tid | G83: Registrering af anden tid For at opnå fuldt overblik over den anvendte tid, ønsker vi at registrere den tid som ikke bruges direkte på sager, men på andre aktiviteter, som fx oplæring, møder. I dag oprettes fiktive sager til fx møder hvor tiden registreres. Leverandøren bedes give en beskrivelse af, hvordan Løsningen kan honorere ovenstående behov. Det vægtes positivt, at Leverandøren i sin besvarelse demonstrerer, at Løsningen understøtter:  at det er let og intuitivt at finde/tilgå sådanne sager  at disse sagers tidsregistrering kan udtrækkes på samme måde som for andre sager | I83: IK - Informationskrav | J83: =IF(I83="IK - Informationskrav","Answer",(IF(I83="K - Konkurrencekrav","Check",(IF(I83="MK - Minimumskrav","Verify",""))))) -> Answer | K83: 1 | L83: 2 | M83: =Evalueringshieraki!$P$16 -> 0.48543689 | O83: Bjørn Henrik | S83: Sjekke eDoc for eksisterende funk der | W83: Bilag 2 - 5.2.17.2 - Registrering af anden tid.docx | X83: Not Started | Y83: =IF(X83="Not Started",0%,IF(X83="Read",1%,IF(X83="Started",50%,IF(X83="Ready for review",70%,IF(X83="Reviewed - Content",80%,IF(X83="Reviewed - Format",90%,IF(X83="Done",100%,""))))))) -> 0
A84: 83 | B84: 5.2.17.3. | C84: Bilag 2 - Kravspecifikation | D84: Funktionelle krav | E84: Håndtering af tidsregistrering. | F84: Visning af tidsregistreringer | G84: Visning af tidsregistreringer Leverandøren bedes give en beskrivelse af, hvordan Løsningen fremstiller den registrerede tid for den enkelte sagsbehandler, så det er muligt for sagsbehandleren og ledere, at følge med live og historisk i tidsregistreringer. Det vægtes positivt, at Leverandøren i sin besvarelse demonstrerer, at Løsningen understøtter:  at tidsregistreringer præsenteres i en overskuelig visning for både sagsbehandler og leder  at data kan filtreres og grupperes på tværs af sagsbehandlere, teams, sager, tidskategorier og tidsperioder  at data kan eksporteres til gængse formater (fx Excel, CSV) til efterbehandling udenfor løsningen. LIS generelt.  at ledere kan få overblik over tidsforbrug på tværs af sagsbehandlere, teams, sager og opgavepuljer | I84: IK - Informationskrav | J84: =IF(I84="IK - Informationskrav","Answer",(IF(I84="K - Konkurrencekrav","Check",(IF(I84="MK - Minimumskrav","Verify",""))))) -> Answer | K84: 1 | L84: 2 | M84: =Evalueringshieraki!$P$16 -> 0.48543689 | O84: Bjørn Henrik | S84: Sjekke eDoc for eksisterende funk der | W84: Bilag 2 - 5.2.17.3 - Visning af tidsregistreringer.docx | X84: Not Started | Y84: =IF(X84="Not Started",0%,IF(X84="Read",1%,IF(X84="Started",50%,IF(X84="Ready for review",70%,IF(X84="Reviewed - Content",80%,IF(X84="Reviewed - Format",90%,IF(X84="Done",100%,""))))))) -> 0
A85: 84 | B85: 5.2.17.4. | C85: Bilag 2 - Kravspecifikation | D85: Funktionelle krav | E85: Håndtering af tidsregistrering. | F85: Registreringstyper | G85: Registreringstyper Løsningen skal give sagsbehandleren mulighed for at foretage nedenstående registreringer:  Sagsbehandlers arbejdstid på en sag  Sagsbehandlers arbejdstid på andet end sager  Flere registreringer af arbejdstid på samme sag  Registrering af tidskategorier (f.eks. forskellige typer af andet tid og ikke fakturerbare tid) | I85: K - Konkurrencekrav | J85: =IF(I85="IK - Informationskrav","Answer",(IF(I85="K - Konkurrencekrav","Check",(IF(I85="MK - Minimumskrav","Verify",""))))) -> Check | K85: 1 | L85: 2 | M85: =Evalueringshieraki!$P$16 -> 0.48543689 | O85: Bjørn Henrik | S85: Sjekke eDoc for eksisterende funk der | X85: Not Started | Y85: =IF(X85="Not Started",0%,IF(X85="Read",1%,IF(X85="Started",50%,IF(X85="Ready for review",70%,IF(X85="Reviewed - Content",80%,IF(X85="Reviewed - Format",90%,IF(X85="Done",100%,""))))))) -> 0
A86: 85 | B86: 5.2.17.5. | C86: Bilag 2 - Kravspecifikation | D86: Funktionelle krav | E86: Håndtering af tidsregistrering. | F86: Driftsstyring og ledelsesoverblik | G86: Driftsstyring og ledelsesoverblik Ledelsen skal kunne se, hvor meget tid der bruges på sagsbehandling og andet tid. At registreret tid fremgår på alle sager, og at det på sager uden tidsregistrering fremgår at der ingen registrering er (fx ved værdien nul eller et tomt felt). Der kan dannes udgangspunkt for en evt. fakturering af sagsbehandlingstiden Registrerede timer skal kunne opsamles til driftsstyring og ledelsesinformation. Det vægtes positivt, at Løsningen understøtter:  visuelle oversigter eller dashboards over tidsforbrug på tværs af sager, teams, brugere og tidsperioder  mulighed for at filtrere og gruppere tidsdata efter fx sagstype, bruger, enhed eller team  eksport af tidsdata til gængse formater (fx Excel, CSV) til brug for driftsstyring og fakturering  automatisk dannelse af faktureringsgrundlag baseret på registrerede timer | I86: IK - Informationskrav | J86: =IF(I86="IK - Informationskrav","Answer",(IF(I86="K - Konkurrencekrav","Check",(IF(I86="MK - Minimumskrav","Verify",""))))) -> Answer | K86: 1 | L86: 2 | M86: =Evalueringshieraki!$P$16 -> 0.48543689 | O86: Bjørn Henrik | S86: Sjekke eDoc for eksisterende funk der | W86: Bilag 2 - 5.2.17.5 - Driftsstyring og ledelsesoverblik.docx | X86: Not Started | Y86: =IF(X86="Not Started",0%,IF(X86="Read",1%,IF(X86="Started",50%,IF(X86="Ready for review",70%,IF(X86="Reviewed - Content",80%,IF(X86="Reviewed - Format",90%,IF(X86="Done",100%,""))))))) -> 0
A87: 86 | B87: B2-15 | C87: Bilag 2 - Kravspecifikation | D87: Funktionelle krav | E87: Ledelsesinformation – LIS. | F87: Ledelsesinformation – LIS. | G87: Fremstillet data skal kunne efterbehandles eksternt i tredjeparts rapporteringsværktøjer. | I87: MK - Minimumskrav | J87: =IF(I87="IK - Informationskrav","Answer",(IF(I87="K - Konkurrencekrav","Check",(IF(I87="MK - Minimumskrav","Verify",""))))) -> Verify | O87: Morten | R87: 1. Fully met | S87: Eksport av data til 3d part -> Management reporting API | X87: Not Started | Y87: =IF(X87="Not Started",0%,IF(X87="Read",1%,IF(X87="Started",50%,IF(X87="Ready for review",70%,IF(X87="Reviewed - Content",80%,IF(X87="Reviewed - Format",90%,IF(X87="Done",100%,""))))))) -> 0
A88: 87 | B88: 5.2.18.1. | C88: Bilag 2 - Kravspecifikation | D88: Funktionelle krav | E88: Ledelsesinformation – LIS. | F88: Rapportering og dataoverførsel | G88: Rapportering og dataoverførsel Leverandøren bedes give en beskrivelse af, hvordan data kan: 1. opstilles via løsningens rapporteringsværktøjer 2. overføres til ekstern behandling i tredjeparts rapporteringsværktøj/datawarehouse. Det vægtes positivt, at Leverandøren i sin besvarelse demonstrerer, at Løsningen understøtter: - at data kan præsenteres og opstilles direkte i Løsningens egne rapporteringsværktøjer - at rapporter kan tilpasses og konfigureres af Kunden uden behov for systemudvikling - at data kan eksporteres til gængse formater (fx Excel, CSV) til ekstern efterbehandling. LIS generelt. - at Løsningen understøtter integration til tredjeparts rapporteringsværktøjer og datawarehouses – f.eks. PowerBI - at der kan foretages udtræk på tværs af sagstyper, tidsperioder og øvrige parametre, herunder fx tidsregistreringer, servicemålsoverholdelse og igangværende sager - at udtræk kan automatiseres og planlægges til faste tidspunkter uden manuel indgriben | I88: IK - Informationskrav | J88: =IF(I88="IK - Informationskrav","Answer",(IF(I88="K - Konkurrencekrav","Check",(IF(I88="MK - Minimumskrav","Verify",""))))) -> Answer | K88: 1 | L88: 2 | M88: =Evalueringshieraki!$P$16 -> 0.48543689 | O88: Morten | P88: Bjørn tore | Q88: Management Reporting API | W88: Bilag 2 - 5.2.18.1 - Rapportering og dataoverførsel.docx | X88: Not Started | Y88: =IF(X88="Not Started",0%,IF(X88="Read",1%,IF(X88="Started",50%,IF(X88="Ready for review",70%,IF(X88="Reviewed - Content",80%,IF(X88="Reviewed - Format",90%,IF(X88="Done",100%,""))))))) -> 0
A89: 88 | B89: B2-16 | C89: Bilag 2 - Kravspecifikation | D89: Funktionelle krav | E89: Anvendelse af AI og algoritmer. | F89: Anvendelse af AI og algoritmer. | G89: Som del af det forretningsmæssige mål om effektiv og ensartet sagsbehandling er der i OBY-fokus på kontinuerlig optimering af arbejdsgange og udnyttelse af teknologiske muligheder, for at supplere eller støtte sagsbehandlingen. Der arbejdes på nuværende tidspunkt med implementering af en AI baseret selvstændig løsning til støtte i sagsbehandlingen. Der er derfor ønske om at kende til leverandørens planer omkring AI på den tilbudte løsning. | I89: MK - Minimumskrav | J89: =IF(I89="IK - Informationskrav","Answer",(IF(I89="K - Konkurrencekrav","Check",(IF(I89="MK - Minimumskrav","Verify",""))))) -> Verify | O89: Morten | R89: 1. Fully met | X89: Not Started | Y89: =IF(X89="Not Started",0%,IF(X89="Read",1%,IF(X89="Started",50%,IF(X89="Ready for review",70%,IF(X89="Reviewed - Content",80%,IF(X89="Reviewed - Format",90%,IF(X89="Done",100%,""))))))) -> 0
A90: 89 | B90: 5.2.19.1. | C90: Bilag 2 - Kravspecifikation | D90: Funktionelle krav | E90: Anvendelse af AI og algoritmer. | F90: Anvendelse af AI og algoritmer | G90: Anvendelse af AI og algoritmer Leverandøren bedes give en beskrivelse af hvorvidt løsningen anvender eller har planer for anvendelse af AI. Det vægtes positivt at - der gives eksempler på konkrete områder, som anvender/planlægger at anvende AI - der fx vedlægges roadmap der viser seneste, og kommende AI baserede funktionalitet - der skelnes klart mellem eksisterende og planlagte funktioner, samt hvorvidt disse er tilkøb eller inkluderet i standardlicenser | I90: IK - Informationskrav | J90: =IF(I90="IK - Informationskrav","Answer",(IF(I90="K - Konkurrencekrav","Check",(IF(I90="MK - Minimumskrav","Verify",""))))) -> Answer | K90: 1 | L90: 2 | M90: =Evalueringshieraki!$P$16 -> 0.48543689 | O90: Morten | W90: Bilag 2 - 5.2.19.1 - Anvendelse af AI og algoritmer.docx | X90: Not Started | Y90: =IF(X90="Not Started",0%,IF(X90="Read",1%,IF(X90="Started",50%,IF(X90="Ready for review",70%,IF(X90="Reviewed - Content",80%,IF(X90="Reviewed - Format",90%,IF(X90="Done",100%,""))))))) -> 0
A91: 90 | B91: 5.3.1.1. | C91: Bilag 2 - Kravspecifikation | D91: Non-funktionelle krav | E91: Forvaltningsretlige krav til IT-systemer i det offentlige | F91: Autentiske kopier af kommunikation | G91: Autentiske kopier af kommunikation Systemet skal understøtte autentiske kopier og bevaring af disse, så al myndighedskommunikation der genereres og afsendes via systemet til, skal kunne rekonstrueres. | I91: MK - Minimumskrav | J91: =IF(I91="IK - Informationskrav","Answer",(IF(I91="K - Konkurrencekrav","Check",(IF(I91="MK - Minimumskrav","Verify",""))))) -> Verify | L91: 2 | O91: Anton | R91: 1. Fully met | X91: Ready for review | Y91: =IF(X91="Not Started",0%,IF(X91="Read",1%,IF(X91="Started",50%,IF(X91="Ready for review",70%,IF(X91="Reviewed - Content",80%,IF(X91="Reviewed - Format",90%,IF(X91="Done",100%,""))))))) -> 0.7
A92: 91 | B92: 5.3.1.2. | C92: Bilag 2 - Kravspecifikation | D92: Non-funktionelle krav | E92: Forvaltningsretlige krav til IT-systemer i det offentlige | F92: PDF/A-formaterne | G92: PDF/A-formaterne Ikke-redigerbare Dokumenter, som Kunden sender elektronisk til Borgere og virksomheder via Systemet, skal udsendes i PDF/A-1a eller højere. | I92: MK - Minimumskrav | J92: =IF(I92="IK - Informationskrav","Answer",(IF(I92="K - Konkurrencekrav","Check",(IF(I92="MK - Minimumskrav","Verify",""))))) -> Verify | L92: 2 | O92: Anton | R92: 1. Fully met | X92: Ready for review | Y92: =IF(X92="Not Started",0%,IF(X92="Read",1%,IF(X92="Started",50%,IF(X92="Ready for review",70%,IF(X92="Reviewed - Content",80%,IF(X92="Reviewed - Format",90%,IF(X92="Done",100%,""))))))) -> 0.7
A93: 92 | B93: 5.3.1.3. | C93: Bilag 2 - Kravspecifikation | D93: Non-funktionelle krav | E93: Forvaltningsretlige krav til IT-systemer i det offentlige | F93: Automatisk datering af breve | G93: Automatisk datering af breve Udgående breve skal dateres med dags dato automatisk i Systemet. | I93: MK - Minimumskrav | J93: =IF(I93="IK - Informationskrav","Answer",(IF(I93="K - Konkurrencekrav","Check",(IF(I93="MK - Minimumskrav","Verify",""))))) -> Verify | L93: 2 | O93: Anton | R93: 1. Fully met | X93: Ready for review | Y93: =IF(X93="Not Started",0%,IF(X93="Read",1%,IF(X93="Started",50%,IF(X93="Ready for review",70%,IF(X93="Reviewed - Content",80%,IF(X93="Reviewed - Format",90%,IF(X93="Done",100%,""))))))) -> 0.7
A94: 93 | B94: 5.3.1.4. | C94: Bilag 2 - Kravspecifikation | D94: Non-funktionelle krav | E94: Forvaltningsretlige krav til IT-systemer i det offentlige | F94: Notatpligt | G94: Notatpligt Systemet skal understøtte, at en Bruger kan tilknytte notater til sager, således at Kundens notatpligt kan overholdes og at Kunden ligeledes kan dokumentere at den er overholdt. | I94: MK - Minimumskrav | J94: =IF(I94="IK - Informationskrav","Answer",(IF(I94="K - Konkurrencekrav","Check",(IF(I94="MK - Minimumskrav","Verify",""))))) -> Verify | L94: 2 | O94: Morten | R94: 1. Fully met | S94: Can we solve this with simple notes? MJ: Either notes or regular documents. This tender is obviously not created as a document manegement mindset | X94: Not Started | Y94: =IF(X94="Not Started",0%,IF(X94="Read",1%,IF(X94="Started",50%,IF(X94="Ready for review",70%,IF(X94="Reviewed - Content",80%,IF(X94="Reviewed - Format",90%,IF(X94="Done",100%,""))))))) -> 0
A95: 94 | B95: 5.3.1.5. | C95: Bilag 2 - Kravspecifikation | D95: Non-funktionelle krav | E95: Forvaltningsretlige krav til IT-systemer i det offentlige | F95: Understøttelse af aktindsigter | G95: Understøttelse af aktindsigter Leverandøren bedes redegøre for, hvordan Systemet understøtter Brugeren i at imødekomme anmodninger om aktindsigt og partsindsigt jf. Offentlighedsloven §7 og Forvaltningslovens §9. Det vægtes positivt, at: - Systemet understøtter Brugeren i at imødekomme anmodninger om aktindsigt, f.eks. ved at kunne producere en aktliste - Systemet kan modtage anmodning om aktindsigt via Digital Post. - den enkelte database i Systemet indrettes på en måde, så det er muligt ved få og enkle kommandoer at få foretaget dataudtræk. | I95: IK - Informationskrav | J95: =IF(I95="IK - Informationskrav","Answer",(IF(I95="K - Konkurrencekrav","Check",(IF(I95="MK - Minimumskrav","Verify",""))))) -> Answer | K95: 1 | L95: 2 | M95: =Evalueringshieraki!$P$16 -> 0.48543689 | O95: Morten | S95: Do we have an ifar module in PnB? | W95: Bilag 2 - 5.3.1.5 - Understøttelse af aktindsigter.docx | X95: Not Started | Y95: =IF(X95="Not Started",0%,IF(X95="Read",1%,IF(X95="Started",50%,IF(X95="Ready for review",70%,IF(X95="Reviewed - Content",80%,IF(X95="Reviewed - Format",90%,IF(X95="Done",100%,""))))))) -> 0
A96: 95 | B96: 5.3.1.1.1. | C96: Bilag 2 - Kravspecifikation | D96: Non-funktionelle krav | E96: Arkivering | F96: Arkivering til Stadsarkivet | G96: Arkivering til Stadsarkivet Systemet skal understøtte udtræk af de bevaringsværdige data, som er omfattet af Stadsarkivets gældende retningslinjer, således at Kunden eller Leverandøren kan udarbejde en systemuafhængig arkiveringsversion til aflevering til Stadsarkivet. Arkivering afregnes på fastpris i henhold til tilbudslisten. | I96: MK - Minimumskrav | J96: =IF(I96="IK - Informationskrav","Answer",(IF(I96="K - Konkurrencekrav","Check",(IF(I96="MK - Minimumskrav","Verify",""))))) -> Verify | L96: 2 | O96: Kaare | X96: Not Started | Y96: =IF(X96="Not Started",0%,IF(X96="Read",1%,IF(X96="Started",50%,IF(X96="Ready for review",70%,IF(X96="Reviewed - Content",80%,IF(X96="Reviewed - Format",90%,IF(X96="Done",100%,""))))))) -> 0
A97: 96 | B97: 5.3.1.1.2. | C97: Bilag 2 - Kravspecifikation | D97: Non-funktionelle krav | E97: Arkivering | F97: Sletning af bevaringsværdige data | G97: Sletning af bevaringsværdige data Leverandøren skal sikre, at Systemet ikke sletter bevaringsværdige data, før der er gennemført godkendt aflevering af en arkiveringsversion. Sletning skal kunne fravælges, og ikke ske automatisk uden godkendelse. | I97: MK - Minimumskrav | J97: =IF(I97="IK - Informationskrav","Answer",(IF(I97="K - Konkurrencekrav","Check",(IF(I97="MK - Minimumskrav","Verify",""))))) -> Verify | L97: 2 | O97: Kaare | X97: Not Started | Y97: =IF(X97="Not Started",0%,IF(X97="Read",1%,IF(X97="Started",50%,IF(X97="Ready for review",70%,IF(X97="Reviewed - Content",80%,IF(X97="Reviewed - Format",90%,IF(X97="Done",100%,""))))))) -> 0
A98: 97 | B98: B2-17 | C98: Bilag 2 - Kravspecifikation | D98: Non-funktionelle krav | E98: Arkitektur | F98: Arkitektur | G98: Kunden definerer arkitektur som Systemets struktur og logiske opbygning samt sammenhæng med det omkringliggende systemlandskab. Kunden har et fokus på, at nye systemer vil passe ind i kommunens eksisterende og fremtidige arkitektur, og stiller derfor bestemte krav til arkitekturen. Systemer skal være opbygget på bestemte måder for at sikre, at de individuelt kan være velfungerende samt at de samtidigt kan indgå effektivt i det samlede systemlandskab og skabe mest mulig værdi for forretningen. | I98: MK - Minimumskrav | J98: =IF(I98="IK - Informationskrav","Answer",(IF(I98="K - Konkurrencekrav","Check",(IF(I98="MK - Minimumskrav","Verify",""))))) -> Verify | O98: Anita | S98: MK - But what are they actually asking us to deliver? AOP: They are asking us to respect their architecture principles as they explain them in bilag 2. Summed up they are: - SaaS som leveringsmodel - Løst koblet arkitektur. - Konfiguration frem for udvikling - Åbne standarder og API-first - Automatisering af arbejdsgange - Data som fælles aktiv - Segmentering og forsvar i dybden - Central identitets- og adgangsstyring - Centraliseret logning og sikkerhedsovervågning - Fælles integrationsplatform | X98: Not Started | Y98: =IF(X98="Not Started",0%,IF(X98="Read",1%,IF(X98="Started",50%,IF(X98="Ready for review",70%,IF(X98="Reviewed - Content",80%,IF(X98="Reviewed - Format",90%,IF(X98="Done",100%,""))))))) -> 0
A99: 98 | B99: 5.3.2.1 | C99: Bilag 2 - Kravspecifikation | D99: Non-funktionelle krav | E99: Arkitektur | F99: Hosting og miljøer | G99: Hosting og miljøer Leverandøren er ansvarlig for hosting af Løsningens miljøer (SaaS). Løsningens miljøer skal være adskilte. Løsningen skal som minimum bestå af: - Produktionsmiljø - Kundens sandkassemiljø, til løbende undervisning og intern test – forventet op til 50 samtidige brugere. Miljøet skal så vidt muligt afspejle produktionsmiljøet, såfremt det ikke er muligt at anvende testintegrationer, kan der anvendes simulerede integrationer (stubs). - Leverandørens testmiljø. | I99: MK - Minimumskrav | J99: =IF(I99="IK - Informationskrav","Answer",(IF(I99="K - Konkurrencekrav","Check",(IF(I99="MK - Minimumskrav","Verify",""))))) -> Verify | L99: 2 | O99: Anton | R99: 1. Fully met | X99: Ready for review | Y99: =IF(X99="Not Started",0%,IF(X99="Read",1%,IF(X99="Started",50%,IF(X99="Ready for review",70%,IF(X99="Reviewed - Content",80%,IF(X99="Reviewed - Format",90%,IF(X99="Done",100%,""))))))) -> 0.7
A100: 99 | B100: 5.3.2.2 | C100: Bilag 2 - Kravspecifikation | D100: Non-funktionelle krav | E100: Arkitektur | F100: Løst koblet arkitektur | G100: Løst koblet arkitektur Leverandøren bedes redegøre for Systemets interne arkitektur, herunder hvordan Systemets moduler og komponenter er organiseret, samt hvordan de kommunikerer og udveksler data med hinanden. Leverandøren kan vælge at vedlægge et diagram, der illustrerer arkitekturen. Det vægtes positivt, at: - Systemet består af velafgrænsede moduler eller services (fx løst koblede services eller microservices), der hver især har klart definerede ansvarsområder. - arkitekturen er baseret på anerkendte softwaredesignprincipper (fx Clean Architecture, Hexagonal Architecture eller tilsvarende), som fremmer testbarhed, uafhængighed af frameworks og udskiftelighed af komponenter. - Systemet er lagdelt, med tydelig adskillelse mellem brugergrænseflade, forretningslogik og dataadgang, uden bindinger på tværs. - brugergrænsefladen er adskilt fra forretningslogikken, så brugergrænsefladen kan udskiftes uafhængigt af kernefunktionaliteten. - arkitekturen understøtter adskillelse af hyppigt foranderlige dele af processerne fra mere stabile dele, fx ved anvendelse af en regelmotor, i overensstemmelse med den fælleskommunale rammearkitektur, Princip 2, AR 2.6 “Adskil det foranderlige fra det uforanderlige”. | I100: IK - Informationskrav | J100: =IF(I100="IK - Informationskrav","Answer",(IF(I100="K - Konkurrencekrav","Check",(IF(I100="MK - Minimumskrav","Verify",""))))) -> Answer | K100: 1 | L100: 2 | M100: =Evalueringshieraki!$P$16 -> 0.48543689 | O100: Morten | W100: Bilag 2 - 5.3.2.2 - Løst koblet arkitektur.docx | X100: Not Started | Y100: =IF(X100="Not Started",0%,IF(X100="Read",1%,IF(X100="Started",50%,IF(X100="Ready for review",70%,IF(X100="Reviewed - Content",80%,IF(X100="Reviewed - Format",90%,IF(X100="Done",100%,""))))))) -> 0
...

Sheet IK-krav
A1: # | B1: ReqID | C1: Document | D1: Section (Headline) | E1: Subsection | F1: Requirement title | G1: Requirement | H1: Besvarelsesvejledning | I1: Requirement type | J1: Action | K1: Round #1 | L1: Responsible | M1: Reviewer | N1: Module | O1: Can we meet the requirement? | P1: Comment | Q1: Commitment needed? | R1: Risk Element? | S1: Cost Driver | T1: Link to answer document | U1: Status (phase) | V1: Status (%)
A2: 1 | B2: 4.1.1. | C2: Bilag 2 - Kravspecifikation | D2: Tidsplan (15%) | E2: Implementering og tidsplan | F2: Implementeringsplan | G2: Implementeringsplan Leverandøren skal beskrive sin samlede plan for implementering af Løsningen hos Kunden. Beskrivelsen skal omfatte punkterne i Bilag 11 Dokumentations, pkt. 7: Det vægtes positivt, at:  Leverandøren demonstrerer en klar forståelse for Kundens it-miljø og de tekniske forudsætninger, herunder relevante integrationer, snitflader, datamigrering og sikkerhedsmæssige forhold.  Tidsplanen afspejler Kundens organisation og implementeringens kompleksitet.  Leverandøren giver en sammenhængende og realistisk faseopdeling af implementeringsforløbet med klare milepæle og godkendelsespunkter, der sikrer, at Kunden kan godkende afslutning af en fase, før næste fase igangsættes.  Leverandøren tydeligt beskriver kendte risici og faldgruber i implementeringsforløbet, samt konkrete mitigerende tiltag.  At tidsplanen tager højde for, at Ordregiver har en løbende drift der skal varetages og perioder med begrænsede ressourcer | H2: Informationskravet besvares ved at Leverandøren vedhæfter eget bilag og udfylder tabel 5.4. (Detaljeret tidsplan) i Bilag 1 - Implementering | I2: IK - Informationskrav | J2: Answer | L2: Cristina
A3: 2 | B3: 4.2.1. | C3: Bilag 2 - Kravspecifikation | D3: Tidsplan (15%) | E3: Tidsplan for optioner | F3: Tidsplan for optioner | G3: Tidsplan for optioner Leverandøren bedes redegøre for hvornår optionerne, jf. punkt 5.4. (5.4.1. & 5.4.2.) i nærværende bilag, kan forventes færdigleveret efter Kunden har kaldt optioner. Leverandøren skal indregne alle relevante faktorer, såsom udvikling af integrationen, men også forhold hos Kunden som Leverandøren er bekendt med ud fra nærværende materiale samt tilhørende bilag. Det vægter positivt at - optionen tilbydes til levering så tæt på Overtagelsesdagen, som muligt. - tidligste dato for Kundens kald af optionen er så tæt på Kontraktindgåelsesdatoen, som muligt. | H3: Informationskravet besvares ved at Leverandøren vedhæfter eget bilag. | I3: IK - Informationskrav | J3: Answer | L3: Cristina
A4: 3 | B4: 5.1.1.1. | C4: Bilag 2 - Kravspecifikation | D4: Generelle krav | E4: Test og prøver | F4: Prøveplan | G4: Prøveplan Leverandøren skal beskrive teststrategien og redegøre for hvorledes aktiviteterne bedst påviser, at kravene i Bilag 2 (Kravspecifikation) efterleves. Det vægtes positivt, at:  Leverandøren beskriver teststrategien på en måde, så den tydelig beskriver, hvilken teststrategi Leverandøren anvender for at sikre, at Løsningen lever op til Kundens krav  Leverandøren beskriver eksempler på prøveplaner og testrapport med angivelse af ansvarsfordeling, testprincipper, metoder og værktøjer mm.  Leverandøren beskriver hvordan og i hvilken grad testcases udledes af Kundens krav  Hvordan dokumenteres og sikres kvalitet og stabilitet under test og prøver, f.eks. ved brug af dedikerede testværktøjer såsom Azure DevOps el.lign. | H4: Informationskravet besvares ved at Leverandøren vedhæfter eget bilag. | I4: IK - Informationskrav | J4: Answer | L4: Cristina
A5: 4 | B5: 5.1.2.1. | C5: Bilag 2 - Kravspecifikation | D5: Generelle krav | E5: Uddannelse | F5: Uddannelse | G5: Uddannelse Leverandøren skal levere en uddannelsesplan, der medfører at de forskellige typer af Brugere er i stand til at anvende Systemet ved idriftsættelse. Besvarelsen bør tage udgangspunkt i nærværende krav samt Bilag 1 (Implementering) pkt. 7 og Bilag 11 (Dokumentation) pkt. 7. Leverandøren skal i besvarelsen redegøre for deres undervisningstilbud i Løsningen, herunder de(n) tilknyttede instruktørers undervisningserfaring. Det vægtes positivt, at: - at der for de enkelte kurser er klare, konkrete og realistiske læringsmål - at det viser organiseringen af den tilbudte undervisning - at uddannelsen i videst muligt omfang tager afsæt i de forskellige Brugeres faglige profil og relevante arbejdsgange - at kurserne i videst muligt omfang behandler Kundens centrale arbejdsgange - at instruktører er erfarne i at undervise og kender målgruppens hverdag | H5: Informationskravet besvares i Leverandørens eget bilag. | I5: IK - Informationskrav | J5: Answer | L5: Anton | M5: Tony, Cristian
A6: 5 | B6: 5.1.3.1. | C6: Bilag 2 - Kravspecifikation | D6: Generelle krav | E6: Data migrering og konvertering | F6: Migreringsplan | G6: Migreringsplan Leverandøren skal levere en migreringsplan og bedes redegøre for hvordan migrering fra Kundens eksisterende system til Systemet vil forløbe med udgangspunkt i kravene i Bilag 1 Implementering, pkt. 6. Migreringsplanens udformning og indhold skal følge Bilag 11 (Dokumentation) pkt. 7. Det vægter positivt at: - dataintegritet af migreringen valideres løbende, f.eks. gennem checksum, tests og overvågning. - data håndteres sikkert, f.eks. ved kryptering. - data migreres og konverteres så automatisk som muligt. - der er indtænkt processer for håndtering af fejl - datamigrering påvirker Brugerens arbejde mindst muligt - besvarelsen indeholder flere konkrete eksempler og detaljer vedr. migreringsaktiviteter. | H6: Informationskravet besvares i Leverandørens eget bilag. | I6: IK - Informationskrav | J6: Answer | L6: Kaare
A7: 6 | B7: 5.2.1.1. | C7: Bilag 2 - Kravspecifikation | D7: Funktionelle krav | E7: Journalisering, dokumenthåndtering og sagsoverblik | F7: Opmærkning af sager og dokumenter | G7: Opmærkning af sager og dokumenter Både sager og dokumenter skal kunne opmærkes, struktureres eller tildeles ”tags” på baggrund af emne, type, kategori m.m. som gør det lettere at søge, sortere og få overblik over data. Løsningen skal give mulighed for sortering på fx indsendelser, dato, emne, teknisk kapitel (fra BOM), fase (fra BOM, bl.a. 'ansøgning', 'under arbejde', 'efter endt arbejde' osv.). Det vægtes positivt, at Leverandøren i sin besvarelse demonstrerer, at Løsningen understøtter:  at data og dokumentation automatisk inddeles i en logisk og overskuelig struktur på sagen  at sagsbehandlere fleksibelt kan tilpasse strukturen til den enkelte sag eller sagstype  at "tag"-funktionen giver mulighed for at tagge på tværs af evt. dokumentstruktur og dokumenttyper  at sortering kan foretages på flere parametre samtidigt (fx fase og dato kombineret)  at sortering og inddeling er konsistent på tværs af sager og sagstyper, så der sikres ensartethed i sagsbehandlingen  at nye sorteringsparametre kan tilføjes uden behov for systemudvikling  At man hurtigt kan se, hvad der er sagsbehandlet og hvad der udestår. | I7: IK - Informationskrav | J7: Answer | L7: PnB
A8: 7 | B8: 5.2.1.2. | C8: Bilag 2 - Kravspecifikation | D8: Funktionelle krav | E8: Journalisering, dokumenthåndtering og sagsoverblik | F8: Konfliktløsning | G8: Konfliktløsning Løsningen skal kunne initiere/kalde en konfliktsøgning der foretages af andet system. Det være sig GIS, en robot eller AI løsning. Initieringen kan være på baggrund af en matrikel, BFE-nr., adresse eller lignende (som altså kan medsendes i kaldet til det eksterne system) Det vægtes positivt, at Leverandøren i sin besvarelse demonstrerer, at Løsningen understøtter:  at konfliktsøgningen kan sættes til at køre automatisk ved oprettelse af nye sager  at sagsbehandler adviseres tydeligt, hvis der identificeres konflikter  at det angives hvis der er adressebeskyttelse eller fortrolighed  at konfliktsøgningen kan gemmes som et dokument på sagen, meget gerne automatisk | I8: IK - Informationskrav | J8: Answer | L8: PnB
A9: 8 | B9: 5.2.1.6. | C9: Bilag 2 - Kravspecifikation | D9: Funktionelle krav | E9: Journalisering, dokumenthåndtering og sagsoverblik | F9: Understøttelse af Elektronisk Sags- og Dokumenthåndtering | G9: Understøttelse af Elektronisk Sags- og Dokumenthåndtering Leverandøren bedes redegøre for i hvilket omfang Løsningen kan understøtte Brugeren i at løfte journaliseringspligt, jf. offentliglovens § 15. Det vægter positivt at: - Kunden kan opsætte regler for hvem der kan redigere, slette fejloprettede sager eller genåbne afsluttede sager. - Løsningen understøtter automatisk journalisering - Dokumenter modtaget på sagerne journaliseres. - Notater nemt kan journaliseres af Brugeren. - Kommunikation der initieres eller modtages af systemet automatisk journaliseres på sagen. - Journaliserede elementer er tydeligt dateret. - Journaliseret indhold er opmærket så det er tydeligt hvad indholdet er. - Mulighed for KLE-opmærkning af sager | I9: IK - Informationskrav | J9: Answer
A10: 9 | B10: 5.2.2.1. | C10: Bilag 2 - Kravspecifikation | D10: Funktionelle krav | E10: Hentning og opdatering af ejendomsdata | F10: Ejendomsdata | G10: IK Ejendomsdata Løsningen skal hente og anvende nedenstående ejendomsdata fra Datafordeleren:  Adresser inklusive vejnavn, husnummer, postnummer og postdistrikt.  Bygningsnummer.  Bestemt fast ejendomsnummer (herefter ”BFE”) for grund, ejerlejlighed og Bygning på fremmed grund (herefter ”BPFG”)  Matrikelnummer og ejerlav.  Ejerlejlighedsnummer.  Bygningens anvendelseskode (fx parcelhus, erhverv, institution).  Bygningens opførelses år.  Bebygget areal og samlet bygningsareal.  Antal bolig- og erhvervsenheder.  Energikilde og varmeinstallation.  Ejerforhold fra Ejerfortegnelsen (herefter ”EJF”), herunder oplysninger om hvem der råder over fast ejendom.  Ejendomsbeliggenhedsregistret (herefter ”EBR”), herunder referencer mellem ejendomme og adresser/beliggenhedsbetegnelser. Løsningens skal sikre opdatering af ejendomsdata på alle verserende sager mindst én gang i døgnet, og både historiske og aktuelle data skal vises på sagerne. Ejendomsdata skal være søgbare - både enkeltvis og i kombination med øvrige data. Det vægtes positivt at  at sagsbehandlere kan søge på alle ejendomsdata og finde både aktuelle og historiske sager, enkeltvis eller i kombination med øvrige søgekriterier, herunder ved brug af AND/OR-logik eller avancerede filtre  at ejendomsdata kan danne udgangspunkt for filtrering, lister og sortering af fremsøgte sager, samt at søgeresultater kan eksporteres til gængse formater (fx Excel, CSV)  at ejendomsdata fremgår samlet og overskueligt på den enkelte sag  at sagsbehandlere, teams og enheder notificeres automatisk, når ejendomsdata ændres på verserende sager  at ændringer i ejendomsdata tilføjes sagen med angivelse af tidsstempel og brugeridentitet, uden at tidligere data slettes | I10: IK - Informationskrav | J10: Answer
A11: 10 | B11: 5.2.3.5. | C11: Bilag 2 - Kravspecifikation | D11: Funktionelle krav | E11: Registrering af ejere og interessenter | F11: Interessent roller | G11: Interessent roller Sagsbehandlerne har brug for at kunne notere hvilken rolle de enkelte interessenter har/har haft på sagen. Leverandøren bedes redegøre for hvordan rollerne til interessenter kan tildeles og evt. ændres. Det vægtes positivt at - kunden kan anvende faste kategorier - at interessenter kan fremsøges på baggrund af deres roller | I11: IK - Informationskrav | J11: Answer
A12: 11 | B12: 5.2.4.3. | C12: Bilag 2 - Kravspecifikation | D12: Funktionelle krav | E12: Registrering, søgning og visning af sagsdata | F12: Søgning, sortering, filtrering og eksport | G12: Søgning, sortering, filtrering og eksport Sager skal kunne fremsøges på alle relevante sagsdata. Søgeresultaterne skal kunne sorteres, filtreres og eksporteres (fx til Excel) Det vægtes positivt, at Leverandøren i sin besvarelse demonstrerer, at Løsningen understøtter:  fritekst- og nøgleordssøgning  søgning på specifikke sætninger (frase søgning)  kombinerede søgekriterier (fx AND/OR-logik eller avancerede filtre)  sortering og filtrering af søgeresultater  eksport til gængse formater (fx Excel, CSV)  at sagsdata, herunder enhed og team, kan tilgås og ændres direkte fra søgeresultater eller sagsopslag uden unødige mellemtrin | I12: IK - Informationskrav | J12: Answer
A13: 12 | B13: 5.2.5.1. | C13: Bilag 2 - Kravspecifikation | D13: Funktionelle krav | E13: Integration til GIS løsning | F13: GIS visning af sager | G13: GIS visning af sager Brugeren kan gennem løsningen tilgå en visning af Kundens GIS-løsning, med mulighed for præ-definerede filtre/overlays så man kan se relevant info fra Kundens GIS-løsning. Kundens GIS-løsning, vil automatisk have byggesagsejendommen i fokus for sagsbehandleren, så mest data er tilgængeligt, hurtigst muligt. Det vægtes positivt, at Leverandøren i sin besvarelse demonstrerer, at løsningen understøtter: • at GIS-visningen åbnes direkte i Løsningen uden unødige mellemtrin eller skift af applikation (fx dybe links fra løsning til GIS på relevant adresse/matrikel) • at præ-definerede filtre og overlays kan tilpasses af Kunden uden behov for systemudvikling • at GIS-visningen automatisk centrerer sig om den relevante ejendom med mest muligt data tilgængeligt fra første visning • at GIS-visningen giver mulighed for at identificere eventuelle konflikter og relevante oplysninger om ejendommen på tværs af lag og filtre • At visningen kan gemmes på sagen som dokumentation | I13: IK - Informationskrav | J13: Answer
A14: 13 | B14: 5.2.6.3. | C14: Bilag 2 - Kravspecifikation | D14: Funktionelle krav | E14: Sagsbehandling af byggesager og anmeldelser | F14: Sags/journalnoter | G14: Sags/journalnoter Leverandøren bedes beskrive hvordan sagsbehandlere med adgang til en given sag kan notere relevante bemærkninger på sagen – f.eks. telefonnotater. Det vægtes positivt hvis: - Det noteres et centralt sted på sagen, som alle med relevant adgang kan tilgå. - Bemærkninger kan tidsstemples og knyttes til den bruger, som har oprettet dem. - Det er muligt at skelne mellem interne bemærkninger og bemærkninger der må deles med eksterne parter. - Tidligere bemærkninger forbliver synlige og kan ikke slettes eller redigeres af andre end den oprindelige ophavsmand eller administrator. - Brugeren kan notificeres, tagges eller på anden måde gøres opmærksom på en bemærkning der er relevant for vedkommende. - Disse noter kan udskrives og gemmes samlet om ønsket | I14: IK - Informationskrav | J14: Answer
A15: 14 | B15: 5.2.6.4. | C15: Bilag 2 - Kravspecifikation | D15: Funktionelle krav | E15: Sagsbehandling af byggesager og anmeldelser | F15: Overblik på sagen | G15: Overblik på sagen Leverandøren bedes beskrive hvordan brugeren, efter at have åbnet en given sag, kan få et overblik over sagens indhold og de seneste hændelser på sagen. Det vægtes positivt hvis: - Brugeren fra sagens forside, let kan tilgå yderligere oplysninger, - Overblikket er overskueligt - Det er ukompliceret at identificere seneste hændelser på sagen. | I15: IK - Informationskrav | J15: Answer
A16: 15 | B16: 5.2.6.5. | C16: Bilag 2 - Kravspecifikation | D16: Funktionelle krav | E16: Sagsbehandling af byggesager og anmeldelser | F16: Ansøgninger og anmeldelser på sagen | G16: Ansøgninger og anmeldelser på sagen Brugeren skal ud fra sagens visning kunne se hvilke aktive og afsluttede ansøgninger og anmeldelser, der er knyttet til den pågældende sag. Løsningen skal sikre at væsentlige datoer for sagsbehandlingen kan både søges, vises og indgå i rapporter. Det gælder fx dato for modtagelse, for fyldestgørende, for afslag, for byggetilladelse mm. Det vægtes positivt hvis: - Tilknyttede ansøgninger og anmeldelser fremgår samlet og overskueligt direkte fra sagens visning, med tydelig angivelse af status for hver enkelt. - Brugeren kan tilpasse hvilke datofelter der vises i sagens overblik, så de mest relevante datoer fremhæves for den konkrete sagstype. - Væsentlige datoer kan danne grundlag for automatiske påmindelser eller advarsler, fx ved overskridelse af servicemål eller frister. - Rapporter med datooplysninger kan eksporteres i et format der understøtter videre bearbejdning, fx Excel eller CSV. | I16: IK - Informationskrav | J16: Answer
A17: 16 | B17: 5.2.6.6. | C17: Bilag 2 - Kravspecifikation | D17: Funktionelle krav | E17: Sagsbehandling af byggesager og anmeldelser | F17: Overblik på sagsdokumenter | G17: Overblik på sagsdokumenter Leverandøren bedes beskrive hvordan brugeren kan emnemarkere, sortere og tilgå sagens dokumenter. Det vægtes positivt hvis: - Dokumenter kan tildeles brugerdefinerede kategorier eller dokumenttyper, som kan anvendes til filtrering og søgning på tværs af sagen. - Brugeren kan flytte, omdøbe og organisere dokumenter direkte i fagsystemet uden at forlade sagen. - Ændringer i dokumenthåndteringen logges, så det er muligt at se hvem der har foretaget ændringer og hvornår. | I17: IK - Informationskrav | J17: Answer
A18: 17 | B18: 5.2.7.2. | C18: Bilag 2 - Kravspecifikation | D18: Funktionelle krav | E18: Styring af sagsportefølje | F18: Tilpasset overbliksvisning og sortering | G18: Tilpasset overbliksvisning og sortering Leverandøren bedes give en udtømmende beskrivelse af, hvordan Løsningen understøtter tilpasning og sortering af overbliksvisningen, herunder: Brugere kan opsætte sin egen visning af dette overblik så de fx ét sted kun ser de sager, som er relevante nu og undgår at se sager, som afventer andre – fx ansøger, kollega og lign. De afventende sager skal kunne ses for sig, i samme overbliksvisning. Opsætning af overbliksvisning skal kunne tilpasses individuelt, både til enkelte brugere og til teams med prædefineret opsætning. Bruger kan sortere på forskellige parametre, fx emner, dato, sagsfase, tags, prioriteringer. Systemet skal give mulighed for at skifte mellem forskellige overbliksvisninger. Det vægtes positivt, at Leverandøren i sin besvarelse demonstrerer, at Løsningen understøtter:  at brugere kan oprette og gemme flere personlige overbliksvisninger og frit skifte imellem dem  at teams kan dele og anvende fælles prædefineret overbliksvisninger  at afventende sager præsenteres tydeligt adskilt fra aktive sager i samme overbliksvisning  at sortering kan foretages på tværs af flere parametre samtidigt (fx sagsfase og dato kombineret)  at adviseringer om overskredne frister og indkommende dokumentation fremhæves tydeligt i overblikket  at overbliksvisningen kan tilpasses uden behov for systemudvikling | I18: IK - Informationskrav | J18: Answer
A19: 18 | B19: 5.2.8.4. | C19: Bilag 2 - Kravspecifikation | D19: Funktionelle krav | E19: Understøttelse af alle sagstyper | F19: Sagsstatus | G19: sagsstatus Brugeren kan ud fra sagsvisningen tydeligt se sagens status, dvs. hvor langt en sag er nået i processen, samt hvor initiativpligten ligger og hvem der er ansvarlig for sagen. Ligesom manglende data eller udestående procestrin bør fremgå af sagens statusmarkeringer. Det vægtes positivt hvis: - Sagens status vises visuelt og intuitivt, fx via en proceslinje eller statusindikator, der tydeligt markerer gennemførte, igangværende og udestående faser. - Initiativpligten fremgår eksplicit af sagens visning, så det er klart om bolden ligger hos ansøger, sagsbehandler eller en tredjepart. - Brugeren adviseres automatisk når manglende data eller udestående procestrin blokerer for videre sagsbehandling, fx via en synlig advarsel eller notifikation direkte på sagen. - Det er muligt at konfigurere hvilke felter og procestrin der er obligatoriske for den enkelte sagstype, så statusmarkeringerne afspejler kravene til den konkrete sag. | I19: IK - Informationskrav | J19: Answer
A20: 19 | B20: 5.2.8.5. | C20: Bilag 2 - Kravspecifikation | D20: Funktionelle krav | E20: Understøttelse af alle sagstyper | F20: Håndtering af modtaget information | G20: Håndtering af modtaget information Løsningen skal kunne håndtere indkomne dokumentationer/data efter sagens status (hvor i processen sagen er). Det vægtes positivt hvis: - Løsningen automatisk kategoriserer eller placerer indkomne dokumenter og data i relation til den fase af processen, hvori de er modtaget. - Brugeren adviseres når der indkommer dokumentation på en sag. | I20: IK - Informationskrav | J20: Answer
... A24: 23 | B24: 5.2.10.1. | C24: Bilag 2 - Kravspecifikation | D24: Funktionelle krav | E24: Dataafgrænsning af sager | F24: Dataafgrænsning af sager | G24: Dataafgrænsning af sager Leverandøren bedes beskrive hvordan der arbejdes med skærmede sager og dokumenter ud fra følsomhedsniveau. Beskrivelsen bør vise hvordan brugeren tildeler sager følsomhedsniveauer eller afskærmning, samt hvordan sager fremgår i søgninger og oversigter som begrænsede eller maskerede. Det vægtes positivt hvis: - Løsningen desuden kan sættes op så visse konkrete matrikler, adresser eller BFE’er automatisk får fortrolighed på alle sager. - Brugeren nemt kan tildele følsomhedsniveau - Brugeren tydeligt kan se at en sag er maskeret og at Brugeren har/ikke har adgang til at se denne. - Administrator kan vedligeholde følsomhedshedsniveauer på sagstyper - Administrator kan opsætte forretningsregler baseret på følsomhed, såsom hvilke sager der skal overføres til FilArkiv. | I24: IK - Informationskrav | J24: Answer
A25: 24 | B25: 5.2.11.1. | C25: Bilag 2 - Kravspecifikation | D25: Funktionelle krav | E25: Sagsbehandlingstid og tilbageværende servicemålstid for BOM | F25: Sagsbehandlingstid og servicemålstid | G25: Sagsbehandlingstid og servicemålstid Løsningen skal kunne vise både sagsbehandlingstid (se krav ovenfor) og status på servicemålstid fra BOM. Det vægtes positivt at  Sagsbehandlingstid og servicemålstid fremstår overskuelig på oversigt over sager  Sagsbehandlingstid og servicemålstid fremstår overskuelig når den enkelte sag åbnes | H25: For de nedenstående IK-krav, vil det generelt vægtes positivt, at Leverandøren i sin besvarelse af nærværende afsnit demonstrerer: - at Løsningen understøtter en høj grad af automatik i styringen af sagsbehandlingstider, således at tidtælling startes og stoppes som en naturlig følge af handlinger i systemet uden manuel indgriben - at Løsningen understøtter en tydelig og intuitiv visning af sagsbehandlingstider og tilbageværende servicemål, som er let tilgængelig for både sagsbehandlere og ledelse - at Løsningen håndterer sager fra BOM og oprettet direkte i løsningen på en ensartet og overskuelig måde - at Løsningen kan udsende notifikationer eller advarsler til relevante brugere, når servicemål nærmer sig udløb - at Løsningen giver mulighed for at tilpasse regler for tidtælling og bero-perioder uden behov for systemudvikling - at alle ændringer i tidtælling, herunder manuelle stop og starter, logges automatisk med tidsstempel og brugeridentitet af hensyn til dokumentation og sporbarhed | I25: IK - Informationskrav | J25: Answer
A26: 25 | B26: 5.2.11.2. | C26: Bilag 2 - Kravspecifikation | D26: Funktionelle krav | E26: Sagsbehandlingstid og tilbageværende servicemålstid for BOM | F26: Servicemålstid start/stop | G26: Servicemålstid start/stop Løsningen skal kunne stoppe og starte servicemålstid både manuelt og automatisk som følge af en handling i systemet (eks. afsendelse af mangelbrev eller afgørelse). Leverandøren bedes illustreres i hvilket omfang dette kan ske automatisk. Det vægtes positivt at  Automatisk servicemålstid kan kobles til sagsbehandlingsprocessen  At man på sagen kan se status/historik for start/stop af servicemålstid | H26: For de nedenstående IK-krav, vil det generelt vægtes positivt, at Leverandøren i sin besvarelse af nærværende afsnit demonstrerer: - at Løsningen understøtter en høj grad af automatik i styringen af sagsbehandlingstider, således at tidtælling startes og stoppes som en naturlig følge af handlinger i systemet uden manuel indgriben - at Løsningen understøtter en tydelig og intuitiv visning af sagsbehandlingstider og tilbageværende servicemål, som er let tilgængelig for både sagsbehandlere og ledelse - at Løsningen håndterer sager fra BOM og oprettet direkte i løsningen på en ensartet og overskuelig måde - at Løsningen kan udsende notifikationer eller advarsler til relevante brugere, når servicemål nærmer sig udløb - at Løsningen giver mulighed for at tilpasse regler for tidtælling og bero-perioder uden behov for systemudvikling - at alle ændringer i tidtælling, herunder manuelle stop og starter, logges automatisk med tidsstempel og brugeridentitet af hensyn til dokumentation og sporbarhed | I26: IK - Informationskrav | J26: Answer
A27: 26 | B27: 5.2.11.3 | C27: Bilag 2 - Kravspecifikation | D27: Funktionelle krav | E27: Sagsbehandlingstid og tilbageværende servicemålstid for BOM | F27: Sagsbehandlingstid for ikke-BOM sager | G27: Sagsbehandlingstid for ikke-BOM sager For sager som ikke er søgt gennem BOM, skal løsningen selv lave en optælling og vise den samlede sagsbehandlingstid. Tiden skal kunne stoppes og startes manuelt, så den sættes i bero fx når der afsendes mangelbreve og afgørelse samt ved modtagelse af yderligere dokumentation.  Sagsbehandlingstid fremstår overskuelig på oversigt over sager  Sagsbehandlingstid fremstår overskuelig når den enkelte sag åbnes  At man på sagen kan se status/historik for start/stop af servicemålstid | H27: For de nedenstående IK-krav, vil det generelt vægtes positivt, at Leverandøren i sin besvarelse af nærværende afsnit demonstrerer: - at Løsningen understøtter en høj grad af automatik i styringen af sagsbehandlingstider, således at tidtælling startes og stoppes som en naturlig følge af handlinger i systemet uden manuel indgriben - at Løsningen understøtter en tydelig og intuitiv visning af sagsbehandlingstider og tilbageværende servicemål, som er let tilgængelig for både sagsbehandlere og ledelse - at Løsningen håndterer sager fra BOM og oprettet direkte i løsningen på en ensartet og overskuelig måde - at Løsningen kan udsende notifikationer eller advarsler til relevante brugere, når servicemål nærmer sig udløb - at Løsningen giver mulighed for at tilpasse regler for tidtælling og bero-perioder uden behov for systemudvikling - at alle ændringer i tidtælling, herunder manuelle stop og starter, logges automatisk med tidsstempel og brugeridentitet af hensyn til dokumentation og sporbarhed | I27: IK - Informationskrav | J27: Answer
A28: 27 | B28: 5.2.12.1. | C28: Bilag 2 - Kravspecifikation | D28: Funktionelle krav | E28: Sagsflow og processer | F28: Sagens overblik | G28: Sagens overblik Leverandøren bedes beskrive, hvordan Løsningen understøtter et godt overblik på den enkelte sag. Det vægtes positivt, når man slår en sag op, at:  Det skal være nemt at se, hvilken type af sag og sagens oplysninger, når en sag slås op. (f.eks. BOM el. manuelt oprettet)  Hvilke aktiviteter er gennemført, og hvem har haft ansvar – hvor ligger sagen henne nu og hvem/hvad afventer den. (En historik/log på sagen)  Hvis sagen er afgjort - skal afgørelsens udfald fremgå.  Hvis sagen er lukket – skal status på, hvordan den er lukket fremgå.  Datoer for afgørelser og udsendelser skal fremgå af sagen. (F.eks. Byggetilladelse (BT) dato, Ibrugtagnings (IBT) dato osv.)  Hvis sagen har relationer til andre sager – Oplysninger på relaterede sager skal fremgå af den sag man har slået op. (F.eks. hvordan den er afsluttet (f.eks. med afslag, BT., udtalelse osv.), afgørelsesudfald mm.) | I28: IK - Informationskrav | J28: Answer
A29: 28 | B29: 5.2.12.2 | C29: Bilag 2 - Kravspecifikation | D29: Funktionelle krav | E29: Sagsflow og processer | F29: Understøtte sagsflow | G29: Understøtte sagsflow Leverandøren bedes beskrive, hvordan løsningen understøtter en ensartet og optimeret arbejdsgang, herunder hvordan løsningen sikrer at sagsbehandlere/andre brugere hurtigere får overblik over sagen og er ikke i tvivl om, hvad næste handling er. Herudover bedes Leverandøren beskrive, hvordan løsningens funktionalitet sikrer at der er overblik over alle sager og de ikke kan ’tabes’ dvs. mangle information om fx sagsansvarlig, enhed og sagsstatus, hvordan der dannes grundlag for at kunne driftsstyre pba. data, samt registreringen er informationskilde, når vi rapporterer til ledelse, politikere og borgere. Det vægtes positivt, at oplysninger som bl.a. er vigtige for sagsbehandlingen, er tilgængelige og:  Brugeren kan tildele opgaver eller sager til kolleger direkte fra fagsystemet.  Brugeren kan markere en sag eller opgave som klar til viderebehandling af en anden bruger eller et andet team.  Systemet understøtter notifikationer ved interne overleveringer, så modtageren adviseres automatisk.  Det er muligt at følge en sags interne historik, herunder hvem der har haft sagen, og hvornår den er overleveret. | I29: IK - Informationskrav | J29: Answer
A30: 29 | B30: 5.2.13.1. | C30: Bilag 2 - Kravspecifikation | D30: Funktionelle krav | E30: Sagsstandarder | F30: Sagsoprettelse via standardskabelon | G30: Sagsoprettelse via standardskabelon Leverandøren bedes beskrive hvordan man i løsningen opretter sager via standard sagsskabeloner. Det vægtes positivt hvis: - Det er muligt at understøtte oprettelse af veldefinerede typer af sager, med individuelle sagsskabeloner både manuelt og automatisk oprettede sager. - Den enkelte sagsskabelon indeholder de relevante sagsoplysninger. F.eks. Sagstype, sagsejerskab, og hvilke trin, der skal oprettes til sagsbehandlingen. - Der kan ad hoc tilføjes nye handlinger/sagshandlinger | I30: IK - Informationskrav | J30: Answer
A31: 30 | B31: 5.2.13.2. | C31: Bilag 2 - Kravspecifikation | D31: Funktionelle krav | E31: Sagsstandarder | F31: Standardsagers procesunderstøttelse | G31: Standardsagers procesunderstøttelse Leverandøren bedes beskrive hvordan man i løsningen sikrer en prædefineret sagsbehandlingsproces via sagsskabelonerne. Det vægter positivt hvis: - Brugeren kan ikke ”lukke/forlade” en sag, hvis den ikke er korrekt registreret. - Brugerens som udgangspunkt ikke kan undvige det prædefineret forløb, men i stedet bliver gjort opmærksom på, at man ikke følger processen. - Løsningen kender den givne proces og man kan se relevant info for trinnet. - Løsningen automatisk kan skifte sagens status når definerede events/handlinger er gennemført. - Løsningen automatisk kan sende sagen til den enhed, som har ansvar for næste sagsfase/sagsstatus, når fasen lukkes eller status ændres - Udførte opgaver markeres som gennemført - Sideløbende sagsgange kan håndteres, således at sagen ligger hos ét team/enhed, men kan visiteres til bidrag fra anden enhed, i eller udenfor OBY. - Løsningen understøtter en ensartet og optimeret arbejdsgang, der giver ensartede sagsforløb. | I31: IK - Informationskrav | J31: Answer
A32: 31 | B32: 5.2.14.1. | C32: Bilag 2 - Kravspecifikation | D32: Funktionelle krav | E32: Advis og notifikationer | F32: Advis funktion | G32: Advis funktion Leverandøren bedes beskrive løsningens advis-funktion. Det vægtes positivt hvis: - Funktionen afsender notifikation, når nye data eller sager modtages, sagsfrister udløber mm. - Funktionen giver sagsbehandlere/teams/enheder overblik over seneste hændelser i sager, de er ansvarlige for. - Hvis brugeren præsenteres for aktuelle advis på løsningens ”forside”, når der logges på - hvis brugeren kan vælge at modtage udvalgte advis pr mail | I32: IK - Informationskrav | J32: Answer
A33: 32 | B33: 5.2.14.2. | C33: Bilag 2 - Kravspecifikation | D33: Funktionelle krav | E33: Advis og notifikationer | F33: Tilpasning af advis | G33: Tilpasning af advis Løsningen giver mulighed for at tilpasse individuelt og på teams/enheds niveau, hvilke advis der modtages. Så den enkelte kun modtager de advis som er relevante for deres opgaver/rolle. Leverandøren bedes redegør for hvilke muligheder der er for at opsætte advis henholdsvis individuelt og ”pushe” advis til faste brugerroller/grupper. Det vægtes positivt hvis: - Advis vises overskueligt og let tilgængeligt | I33: IK - Informationskrav | J33: Answer
A34: 33 | B34: 5.2.15.4. | C34: Bilag 2 - Kravspecifikation | D34: Funktionelle krav | E34: Arkivering af sager | F34: Status på overførsel og fejlhåndtering | G34: Status på overførsel og fejlhåndtering Leverandøren bedes give en udtømmende beskrivelse af, hvordan Løsningen understøtter visning af overførselsstatus til FilArkiv, herunder:  hvordan brugeren kan følge status på overførslen  hvordan fejl på enkeltdokumenter håndteres og præsenteres for brugeren Det vægtes positivt, at Leverandøren i sin besvarelse demonstrerer, at Løsningen understøtter:  at fejlede dokumenter tydeligt identificeres med angivelse af årsag til fejl  at brugeren kan genstarte overførslen af fejlede dokumenter uden at skulle overføre hele sagen på ny  at brugeren notificeres, når overførslen er fuldført eller fejler  at der logges automatisk med tidsstempel og brugeridentitet ved gennemførte overførsler | I34: IK - Informationskrav | J34: Answer
A35: 34 | B35: 5.2.16.2. | C35: Bilag 2 - Kravspecifikation | D35: Funktionelle krav | E35: Rapporter, statistik og ledelsesinformation | F35: Data på tværs af servicemålskategorier | G35: Data på tværs af servicemålskategorier Leverandøren bedes give en beskrivelse af, hvordan Løsningen kan levere data på servicemål. Kunden ønsker at data leveres over b.la.:  antal af åbne, afgjorte og lukkede sager (fordelt på servicemålskategorierne),  overholdelsesprocent pr. kategori, og  gennemsnitlige antal behandlingsdage. Det vægtes positivt, at Leverandøren i sin besvarelse demonstrerer, at Løsningen understøtter:  at data præsenteres i en overskuelig og visuel visning, fx i form af dashboards eller grafer  at data kan filtreres og grupperes på tværs af servicemålskategorier og tidsperioder  at overholdelsesprocent og gennemsnitlige behandlingsdage beregnes og opdateres automatisk  at data kan eksporteres til gængse formater (fx Excel, CSV) til brug for rapportering og ledelsesinformation. LIS generelt. | I35: IK - Informationskrav | J35: Answer
A36: 35 | B36: 5.2.16.3. | C36: Bilag 2 - Kravspecifikation | D36: Funktionelle krav | E36: Rapporter, statistik og ledelsesinformation | F36: Data på enkelte sager | G36: Leverandøren bedes give en beskrivelse af, hvordan Løsningen kan levere nedenstående data, samt om denne data kan leveres både samlet og til den enkelte sagsbehandler:  type af servicemålsag, der er tale om,  tilbageværende visitationsdage og  servicemålsdage på den enkelte sag. Det vægtes positivt, at Leverandøren i sin besvarelse demonstrerer, at Løsningen understøtter: • at tilbageværende visitationsdage og servicemålsdage beregnes og opdateres automatisk på den enkelte sag (trækkes direkte fra BOM hvor muligt) • at sagsbehandlere og ledelse adviseres automatisk, når servicemål nærmer sig udløb • at data præsenteres tydeligt og tilgængeligt direkte fra den enkelte sag • at der kan genereres oversigter over servicemålsdata både samlet og pr. sagsbehandler • at data kan eksporteres til gængse formater (fx Excel, CSV). LIS generelt. | I36: IK - Informationskrav | J36: Answer
A37: 36 | B37: 5.2.17.1. | C37: Bilag 2 - Kravspecifikation | D37: Funktionelle krav | E37: Håndtering af tidsregistrering. | F37: Registrering af tid på sager | G37: Registrering af tid på sager Leverandøren bedes give en beskrivelse af, hvordan Løsningen gør det nemt el. automatisk for sagsbehandler at tidsregistrere, samt give mulighed for at ændre eksisterende tidsregistreringer. Brugerne skal let kunne indtaste tidsforbrug på konkrete sager. Brugeren kan direkte (med så få klik som muligt) indtaste tidsforbrug på en given sag og systemet registrerer selv navn på den bruger, der er logget ind. Det skal være muligt at få et overblik over brugerens indtastede tidsregistreringer per dag/uge/måned. Det skal være muligt for brugeren at vælge individuelt, om registreret tid ikke skal faktureres. Det skal være muligt at eksisterende tidsregistreringer kan ændres med angivelse af årsag til ændringen Det vægtes positivt, at Løsningen understøtter:  at tidsregistrering kan foretages med så få klik som muligt direkte fra en given sag  at brugeren har en intuitiv og overskuelig oversigt over egne tidsregistreringer per dag, uge og måned fordelt på sagerne  at tidsregistrering på andet arbejde end sagsbehandling kan kategoriseres  at ændringer i tidsregistreringer logges automatisk med tidsstempel og brugeridentitet af hensyn til sporbarhed | I37: IK - Informationskrav | J37: Answer
A38: 37 | B38: 5.2.17.2. | C38: Bilag 2 - Kravspecifikation | D38: Funktionelle krav | E38: Håndtering af tidsregistrering. | F38: Registrering af anden tid | G38: Registrering af anden tid For at opnå fuldt overblik over den anvendte tid, ønsker vi at registrere den tid som ikke bruges direkte på sager, men på andre aktiviteter, som fx oplæring, møder. I dag oprettes fiktive sager til fx møder hvor tiden registreres. Leverandøren bedes give en beskrivelse af, hvordan Løsningen kan honorere ovenstående behov. Det vægtes positivt, at Leverandøren i sin besvarelse demonstrerer, at Løsningen understøtter:  at det er let og intuitivt at finde/tilgå sådanne sager  at disse sagers tidsregistrering kan udtrækkes på samme måde som for andre sager | I38: IK - Informationskrav | J38: Answer
A39: 38 | B39: 5.2.17.3. | C39: Bilag 2 - Kravspecifikation | D39: Funktionelle krav | E39: Håndtering af tidsregistrering. | F39: Visning af tidsregistreringer | G39: Visning af tidsregistreringer Leverandøren bedes give en beskrivelse af, hvordan Løsningen fremstiller den registrerede tid for den enkelte sagsbehandler, så det er muligt for sagsbehandleren og ledere, at følge med live og historisk i tidsregistreringer. Det vægtes positivt, at Leverandøren i sin besvarelse demonstrerer, at Løsningen understøtter:  at tidsregistreringer præsenteres i en overskuelig visning for både sagsbehandler og leder  at data kan filtreres og grupperes på tværs af sagsbehandlere, teams, sager, tidskategorier og tidsperioder  at data kan eksporteres til gængse formater (fx Excel, CSV) til efterbehandling udenfor løsningen. LIS generelt.  at ledere kan få overblik over tidsforbrug på tværs af sagsbehandlere, teams, sager og opgavepuljer | I39: IK - Informationskrav | J39: Answer
... A62: 61 | B62: 5.3.8.2.8.2. | C62: Bilag 2 - Kravspecifikation | D62: Non-funktionelle krav | E62: Kundens SIEM-system | F62: Logudtræk og logoverførsel til Kundens SIEM-system | G62: Logudtræk og logoverførsel til Kundens SIEM-system Leverandøren bedes redegøre for, hvordan Logs kan overføres til Kundens SIEM- system, samt hvor ofte disse kan overføres. Det vægtes positivt, at: - logudtræk i Systemet er så tæt på realtid som muligt. - logoverførsel til Kundens SIEM-system kan gøres periodisk og jo oftere i døgnet logoverførslen sker, desto bedre. - logs anvender tegnsæt UTF-8 | I62: IK - Informationskrav | J62: Answer
A63: 62 | B63: Tilbudsbrevet | C63: Tilbudsbrevet | D63: Tilbudsbrevet | E63: Tilbudsbrevet | F63: Tilbudsbrevet | G63: Udfyld tilbudsbrevet | I63: MK - Minimumskrav | J63: Answer | L63: Anita | U63: Not Started | V63: =IF(U63="Not Started",0%,IF(U63="Started",50%,IF(U63="Ready for review",70%,IF(U63="Reviewed - Content",80%,IF(U63="Reviewed - Format",90%,IF(U63="Done",100%,"")))))) -> 0
A64: 63 | B64: Tilbudsliste | C64: Tilbudsliste | D64: Tilbudsliste | E64: Tilbudsliste | F64: Tilbudsliste | G64: Udfyld Tilbudsliste | I64: MK - Minimumskrav | J64: Answer | L64: Hans | P64: Støtte fra Anton | U64: Not Started | V64: =IF(U64="Not Started",0%,IF(U64="Started",50%,IF(U64="Ready for review",70%,IF(U64="Reviewed - Content",80%,IF(U64="Reviewed - Format",90%,IF(U64="Done",100%,"")))))) -> 0
A65: 64 | B65: Licensbetingelser | C65: Bilag 5 - Licensbetingelser | D65: Licensbetingelser | E65: Licensbetingelser | F65: Licensbetingelser | G65: Udfyld Licensbetingelser | I65: MK - Minimumskrav | J65: Answer | L65: Anita | U65: Not Started | V65: =IF(U65="Not Started",0%,IF(U65="Started",50%,IF(U65="Ready for review",70%,IF(U65="Reviewed - Content",80%,IF(U65="Reviewed - Format",90%,IF(U65="Done",100%,"")))))) -> 0
A66: 65 | B66: Underleverandør (hvis anvendes) | C66: Bilag 7 - Underleverandør (hvis anvendes) | D66: Underleverandør (hvis anvendes) | E66: Underleverandør (hvis anvendes) | F66: Underleverandør (hvis anvendes) | G66: Udfyld Underleverandør (hvis anvendes) | I66: MK - Minimumskrav | J66: Answer | L66: Anita | U66: Not Started | V66: =IF(U66="Not Started",0%,IF(U66="Started",50%,IF(U66="Ready for review",70%,IF(U66="Reviewed - Content",80%,IF(U66="Reviewed - Format",90%,IF(U66="Done",100%,"")))))) -> 0
A67: 66 | B67: Egenerklæring vedrørende russiske enheder m.v. | C67: Bilag 14 - Egenerklæring vedrørende russiske enheder m.v. | D67: Egenerklæring vedrørende russiske enheder m.v. | E67: Egenerklæring vedrørende russiske enheder m.v. | F67: Egenerklæring vedrørende russiske enheder m.v. | G67: Udfyld Egenerklæring vedrørende russiske enheder m.v. | I67: MK - Minimumskrav | J67: Answer | L67: Anita | P67: Skal underskrives af Bent | U67: Not Started | V67: =IF(U67="Not Started",0%,IF(U67="Started",50%,IF(U67="Ready for review",70%,IF(U67="Reviewed - Content",80%,IF(U67="Reviewed - Format",90%,IF(U67="Done",100%,"")))))) -> 0

Sheet Timeline
A1: Item | B1: Deadline | C1: Comment
A2: Tender material published | B2: Tors 25. juni | D2: done
A3: Material and requests sent to stakeholders | B3: Fre 26. juni | D3: done
A4: Kick-off meeting | B4: Tirs 30. Juni | D4: booked
A5: Initial Solution Review | B5: Ons 2. Juli | D5: booked
A6: Initial guiding price meeting | B6: Fre 6 Juli | D6: booked
A7: Initial Legal review
A8: Initial SLA and servicegoal review | B8: Fre 3. Juli | D8: booked
A9: DG1 | B9: Fre 2. Juli | D9: booked
A10: 2md solution review | B10: 7. juli | D10: booked
A11: Holidays
A12: Final SLA and servicegoals review | B12: Fre 24. juli | D12: booked
A13: Rough draft deadline | B13: Man 10. august | D13: booked
A14: Deadline (soft) for questions | B14: fre 7. august | C14: Disse vil blive besvaret | D14: booked
A15: Legal review | B15: Tors 13. august | D15: booked
A16: Finance review | B16: Tors 13. august | D16: booked
A17: Product commitments | B17: Fre 14. august | D17: booked
A18: Deadline (hard) for questions | B18: fre 21. august | C18: Disse vil kun blive besvaret, hvis ikke unødigt byrdefuldt for kunden. | D18: booked
A19: Last answer from the customer | B19: Lør 22. august | D19: -
A20: Send material for DG2 L2 | B20: Man 24. august før 10 | D20: -
A21: DG2 L2 | B21: Tirs 25. august kl. 10 | D21: booked
A22: Close for Edits | B22: Ons 25. august kl. 12 | D22: booked
A23: Hand-in | B23: fre 28. august inden kl. 15 | D23: booked
A24: Customer response | B24: ukendt | D24: -
A25: Award decision | B25: ukendt | D25: -
A26: Go-live | B26: ukendt | D26: -

Sheet Status
C8: Total numer of Requirements | D8: =COUNTIF('Production Plan'!B:B,"<>")-1 -> 218 | G8: Total numer of IK- Requirements | H8: =COUNTIF('IK-krav'!B:B,"<>")-1 -> 66
E11: Af alle krav | G11: Af IK-krav
E12: # of requirements | F12: % | G12: # of requirements | H12: %
C13: Not Started | E13: =COUNTIF('Production Plan'!X:X,Status!$C$13) -> 161 | F13: =E13/$D$8 -> 0.73853211 | G13: =COUNTIF('IK-krav'!U:U,Status!C13) -> 5 | H13: =G13/$D$8 -> 0.02293578
C14: Started | E14: =COUNTIF('Production Plan'!X:X,Status!C14) -> 17 | F14: =E14/$D$8 -> 0.077981651 | G14: =COUNTIF('IK-krav'!U:U,Status!C14) -> 0 | H14: =G14/$D$8 -> 0
C15: Ready for review | E15: =COUNTIF('Production Plan'!X:X,Status!C15) -> 31 | F15: =E15/$D$8 -> 0.14220183 | G15: =COUNTIF('IK-krav'!U:U,Status!C15) -> 0 | H15: =G15/$D$8 -> 0
C16: Reviewed - Content | E16: =COUNTIF('Production Plan'!X:X,Status!C16) -> 0 | F16: =E16/$D$8 -> 0 | G16: =COUNTIF('IK-krav'!U:U,Status!C16) -> 0 | H16: =G16/$D$8 -> 0
C17: Reviewed - Format | E17: =COUNTIF('Production Plan'!X:X,Status!C17) -> 0 | F17: =E17/$D$8 -> 0 | G17: =COUNTIF('IK-krav'!U:U,Status!C17) -> 0 | H17: =G17/$D$8 -> 0
C18: Done | E18: =COUNTIF('Production Plan'!X:X,Status!C18) -> 5 | F18: =E18/$D$8 -> 0.02293578 | G18: =COUNTIF('IK-krav'!U:U,Status!C18) -> 0 | H18: =G18/$D$8 -> 0
C19: Total | E19: =SUM(E13:E18) -> 214 | F19: =SUM(F13:F18) -> 0.98165138 | G19: =SUM(G13:G18) -> 5 | H19: =SUM(H13:H18) -> 0.02293578
C20: Missing | E20: =$D$8-E19 -> 4 | F20: =100%-F19 -> 0.018348624 | G20: =$D$8-G19 -> 213 | H20: =100%-H19 -> 0.97706422
E27: Af alle krav | G27: Af IK-krav
C28: Responsible | E28: # of Requirements | F28: % | G28: # of requirements | H28: %
C29: Anton | E29: =COUNTIF('Production Plan'!O:O,C29) -> 29 | F29: =E29/$D$8 -> 0.13302752 | G29: =COUNTIF('IK-krav'!U:U,E29) -> 0 | H29: =G29/$D$8 -> 0
C30: Olga | E30: =COUNTIF('Production Plan'!O:O,C30) -> 15 | F30: =E30/$D$8 -> 0.068807339 | G30: =COUNTIF('IK-krav'!U:U,E30) -> 0 | H30: =G30/$D$8 -> 0
C31: Husein | E31: =COUNTIF('Production Plan'!O:O,C31) -> 2 | F31: =E31/$D$8 -> 0.0091743119 | G31: =COUNTIF('IK-krav'!U:U,E31) -> 0 | H31: =G31/$D$8 -> 0
C32: Bjørn Henrik | E32: =COUNTIF('Production Plan'!O:O,C32) -> 25 | F32: =E32/$D$8 -> 0.1146789 | G32: =COUNTIF('IK-krav'!U:U,E32) -> 0 | H32: =G32/$D$8 -> 0
C33: Linn | E33: =COUNTIF('Production Plan'!O:O,C33) -> 1 | F33: =E33/$D$8 -> 0.004587156 | G33: =COUNTIF('IK-krav'!U:U,E33) -> 0 | H33: =G33/$D$8 -> 0
C34: Jan Olav | E34: =COUNTIF('Production Plan'!O:O,C34) -> 0 | F34: =E34/$D$8 -> 0 | G34: =COUNTIF('IK-krav'!U:U,E34) -> 0 | H34: =G34/$D$8 -> 0
C35: Cristina | E35: =COUNTIF('Production Plan'!O:O,C35) -> 17 | F35: =E35/$D$8 -> 0.077981651 | G35: =COUNTIF('IK-krav'!U:U,E35) -> 0 | H35: =G35/$D$8 -> 0
C36: Kaare | E36: =COUNTIF('Production Plan'!O:O,C36) -> 6 | F36: =E36/$D$8 -> 0.027522936 | G36: =COUNTIF('IK-krav'!U:U,E36) -> 0 | H36: =G36/$D$8 -> 0
C37: Arve | E37: =COUNTIF('Production Plan'!O:O,C37) -> 16 | F37: =E37/$D$8 -> 0.073394495 | G37: =COUNTIF('IK-krav'!U:U,E37) -> 0 | H37: =G37/$D$8 -> 0
C38: Tone | E38: =COUNTIF('Production Plan'!O:O,C38) -> 0 | F38: =E38/$D$8 -> 0 | G38: =COUNTIF('IK-krav'!U:U,E38) -> 0 | H38: =G38/$D$8 -> 0
C39: CloudOps | E39: =COUNTIF('Production Plan'!O:O,C39) -> 11 | F39: =E39/$D$8 -> 0.050458716 | G39: =COUNTIF('IK-krav'!U:U,E39) -> 0 | H39: =G39/$D$8 -> 0
C40: Axel | E40: =COUNTIF('Production Plan'!O:O,C40) -> 11 | F40: =E40/$D$8 -> 0.050458716 | G40: =COUNTIF('IK-krav'!U:U,E40) -> 0 | H40: =G40/$D$8 -> 0
... C45: Morten | E45: =COUNTIF('Production Plan'!O:O,C45) -> 30 | F45: =E45/$D$8 -> 0.13761468 | G45: =COUNTIF('IK-krav'!U:U,E45) -> 0 | H45: =G45/$D$8 -> 0
C46: Total | E46: =SUM(E29:E45) -> 217 | F46: =SUM(F29:F45) -> 0.99541284 | G46: =SUM(G29:G45) -> 0 | H46: =SUM(H29:H45) -> 0
C47: Missing | E47: =$D$8-E46 -> 1 | F47: =100%-F46 -> 0.004587156 | G47: =$D$8-G46 -> 218 | H47: =100%-H46 -> 1

Sheet Q&A
A1: # | B1: Relates to requirement ID | C1: Sender | D1: Question | E1: Sent Date | F1: Answer | G1: Received Date | H1: Comment
A2: 1 | B2: 5.1.3.1 | C2: Tieto | D2: Kan Ordregiver oplyse: 1. Estimeret datamængde i KMD Nova der skal migreres (antal sager og dokumenter)? 2. Datamodel eller eksportformat fra KMD Nova? 3. Om der gælder krav til bevarelse af sagsbehandlingstider og frister ved migrering til den nye løsning?
A3: 2 | B3: 5.2.1.2 | C3: Tieto | D3: Kravet angiver at Løsningen skal kalde "et andet system" til konfliktsøgning (GIS, robot eller AIløsning), men specificerer ikke hvilket konkret system der menes. Bilag 1 nævner GIS (SpatialSuite) via dynamiske links, men konfliktsøgning via eksternt systemkald er ikke nærmere beskrevet. Kan Ordregiver præcisere: 1. Om konfliktsøgningen skal ske via GIS (SpatialSuite), et dedikeret robot-/AI-system, eller andet? 2. Om der eksisterer en snitfladebeskrivelse for dette system?
A4: 4 | B4: 5.2.11.1 | C4: Tieto | D4: Kravet refererer til "krav ovenfor" om sagsbehandlingstid uden at specificere præcist hvilke krav der menes. Kan Ordregiver præcisere hvilke konkrete krav der refereres til? Foreligger der en formel definition af sagsbehandlingstid med start- og stopkriterier der gælder for alle sagstyper i KK's kontekst?
A5: 5 | B5: 5.3.7.1.6 | C5: Tieto | D5: Det fjerde bullet point under kravet til Systemets rettighedsmodel ser ud til at være trunkeret. Teksten lyder: "understøtter dataafgrænsning på baggrund af sagstyper, f.eks. baseret". Sætningen slutter her uden videre indhold. Kan Ordregiver fremsende den fuldstændige kravtekst for dette bullet point? Hvad er de konkrete dataafgrænsningsparametre som Systemet skal understøtte (fx sagsstatus, sagstype, enhed, geografisk afgrænsning eller andet)?
A6: 6 | B6: 5.3.7.1.7 | C6: Tieto | D6: "Dataafgrænsningsparameteret" nævnes som grundlag for rettighedsmodellen. Bilag 1 angiver at adgangsstyring sker via "FKA eller Entra ID". Kan Ordregiver præcisere om "dataafgrænsningsparameteret" er et specifikt felt eller attribut i FKA/Entra ID, og i givet fald fremsende den relevante del af rollemodellen der definerer dette parameter?
A7: 7 | B7: 5.4.1.1 | C7: Tieto | D7: Optionskravet om Opus Debitor angiver to alternative integrationsmetoder (FK-ØKO eller KMD G19 via SFTP), men specificerer ikke hvilken KK foretrækker. Ønsker Ordregiver at Leverandøren tilbyder begge integrationsmetoder?
A8: 8 | B8: 5.2.4.3 [IK] 5.2.2.1 [IK] 5.3.8.1.2 [IK] 5.3.8.1.4 [K] 5.3.8.2.2.1 [MK] 5.3.5.2 [IK] | C8: Tieto | D8: Følgende krav i Bilag 2 indeholder brede formuleringer: - 5.2.4.3 [IK] - 5.2.2.1 [IK] - 5.3.8.1.2 [IK] - 5.3.8.1.4 [K] - 5.3.8.2.2.1 [MK] - 5.3.5.2 [IK] Leverandøren anmoder om præcisering af scope på følgende punkter: 1. Krav 5.2.4.3: Hvad definerer "alle relevante sagsdata", og foreligger der en fuldstændig liste over de datafelter der skal kunne søges på? 2. Krav 5.3.8.1.2 og 5.3.8.1.4: Hvad forstås ved "uden begrænsning" i forbindelse med udstilling af data via API? 3. Krav 5.3.8.2.2.1: Skal samtlige ni grunddataregistre (CPR, CVR, BBR, Ejerfortegnelse, Matriklen, Ejendomsbeliggenhed, DAR, Danske stednavne, Ejendomsvurderinger) være fuldt integreret ved Overtagelsesdagen, eller er der en prioriteret rækkefølge? 4. Krav 5.2.2.1: Daglig opdatering af ejendomsdata på "alle verserende sager" kan udgøre et massivt load. Kan Ordregiver oplyse det forventede maksimale antal samtidige verserende sager som opdateringen skal køre på?
A9: 9 | B9: Opfordringsskrivelse og Bilag 2 | C9: Tieto | D9: I Opfordringsskrivelsen angives det, at vægtningen mellem områderne er som følger: - Implementering, installation og konfigurering: 2 = op til 20 point - Funktionalitet: 5 = op til 50 point - Uddannelse: 3 = op til 30 point. I bilag 2 - krvasspecifikation er der dog angivet følgende opdeling: - Tidsplan: 15% - Opfyldelse af forretningsmål: 85%. Dette virker som modsætninger. Kan kunden specificere hvilket forhold, der er gældende?
A10: 10 | B10: Opfordringsskrivelse | C10: Tieto | D10: Tilbudsfristen er fastsat til 28. august 2026 kl. 15.00, og spørgsmålsfristen til 21. august 2026 kl. 23.59. Tilbudsmaterialet er omfattende og indeholder detaljerede krav til besvarelse af 61 informationskrav samt væsentlige krav til dokumentation, prissætning og implementeringsplanlægning. En forlængelse af tilbudsfristen med 2-3 uger vil give tilbudsgiverne bedre mulighed for at udarbejde gennemarbejdede og velunderbyggede tilbud med høj kvalitet. Det vil samtidig give Ordregiver et stærkere grundlag for evalueringen gennem mere fyldestgørende beskrivelser, mere gennemtænkte implementeringsplaner og et mere retvisende sammenligningsgrundlag mellem tilbuddene. Vil Ordregiver på den baggrund overveje at forlænge tilbudsfristen med 2-3 uger?
A11: 11 | B11: Opfordringsskrivelse og Bilag 2 | C11: Tieto | D11: I gennemgangen af udbudsmaterialet har Tilbudsgiver konstateret en tilsyneladende uoverensstemmelse mellem beskrivelsen af pointberegningen i henholdsvis Bilag 2 afsnit 3 og Opfordringsskrivelsen pkt. 8.1.1. Bilag 2 afsnit 3 angiver, at hvert krav er tildelt en faktor, der udtrykker den vægtning kravet indgår med i beregningen af den samlede score for det pågældende delkriterie. Dette indebærer en faktor-vægtet gennemsnitsberegning. Opfordringsskrivelsen pkt. 8.1.1 angiver derimod, at Ordregiver "beregner gennemsnittet af de tildelte point", og det illustrerende eksempel viser et simpelt, uvejet gennemsnit uden anvendelse af faktorer. Tilbudsgiver bemærker herudover, at eksemplet i Opfordringsskrivelsen refererer til kravnumre (herunder 5.1.4.1 og 5.1.5.1), der ikke ses at fremgå af Bilag 2, ligesom de delkriterie-vægte der anvendes i eksemplets afsluttende beregning (3/4/3) afviger fra de vægte der fremgår af evalueringstabellen (2/5/3). Vil det være muligt for Ordregiver at angive om pointberegningen inden for hvert kvalitetskriterium foretages som en faktor-vægtet gennemsnitsberegning i overensstemmelse med Bilag 2 afsnit 3, eller som et simpelt uvejet gennemsnit i overensstemmelse med eksemplet i Opfordringsskrivelsen?
A12: 12 | B12: Bilag 2 | C12: Tieto | D12: Kravspecifikationen beskriver, at løsningen skal understøtte flere forskellige sagstyper, men angiver ikke omfanget af den nuværende eller forventede fremtidige anvendelse. Vil Ordregiver oplyse: hvor mange forskellige sagstyper der aktuelt anvendes i den eksisterende løsning, hvor mange af disse der forventes migreret til den nye løsning ved idriftsættelse, om Ordregiver forventer, at antallet af sagstyper vil blive udvidet i kontraktperioden, og i givet fald i hvilket omtrentligt omfang? Disse oplysninger vil give tilbudsgiverne et bedre grundlag for at vurdere omfanget af konfiguration, migrering og den fremtidige vedligeholdelse af sagstyperne.
A13: 13 | B13: Bilag 2 | C13: Tieto | D13: Ordregiver har tildelt to forskellige informationskrav samme krav-id 5.3.5.2, selv om de vedrører forskellige emner: Vedhæftede filtyper Håndtering af kompromitterende indhold Kan Ordregiver bekræfte, at der er tale om en redaktionel fejl, og oplyse den korrekte krav-id for de to informationskrav, så der ikke opstår tvivl ved henvisninger i tilbudsbesvarelsen?
... A17: 17 | B17: Kontrakten | C17: Mandip | D17: Spørgsmål vedrørende erstatningsloft og databeskyttelsesretligt ansvar Kontraktens pkt. 21.1 fastsætter et erstatningsloft på DKK 5.000.000, men undtager udtrykkeligt Leverandørens manglende overholdelse af databeskyttelseslovgivningen fra dette loft. Det betyder, at erstatningsansvaret ved overtrædelse af databeskyttelsesreglerne i princippet er ubegrænset. En ubegrænset eksponering for databeskyttelsesretlige krav er ikke proportional med det underliggende kontraktforhold og svarer ikke til markedspraksis for tilsvarende it-kontrakter i den offentlige sektor. Tilbudsgiver er endvidere underlagt Datatilsynets selvstændige håndhævelse og Kundens eventuelle bødepåbud i medfør af databeskyttelsesforordningen, hvilket i sig selv udgør en betydelig og reel sanktionsrisiko uden for kontrakten. En ubegrænset kontraktuel eksponering herudover medfører, at Tilbudsgiver nødvendigvis må indregne en betydelig risikomargin i prissætningen, som Kunden betaler uanset om risikoen materialiserer sig. Det er endvidere ikke muligt for Leverandøren at forsikre sig fuldt ud imod dette ansvar. Markedet for cyberansvarsforsikring opererer med definerede dækningslofter, og et ubegrænset kontraktuelt ansvar vil enten falde uden for forsikringsdækningens rammer eller alene kunne dækkes mod uforholdsmæssigt høje præmier. Seriøse leverandører vil derfor have vanskeligt ved at afgive tilbud i udbuddet, da de ved at acceptere sådanne vilkår ikke alene risikerer at skulle betale meget betydelige erstatningsbeløb, men også risikerer at bringe virksomhedens fortsatte drift i fare. De leverandører, som vælger at afgive tilbud på disse vilkår, har enten ikke forstået den risiko, de påtager sig, eller accepterer en risiko, som de reelt ikke vil kunne bære, hvis der opstår en situation, hvor der skal betales erstatning. Tilbudsgiver bemærker i den forbindelse, at databeskyttelsesforordningens artikel 82 og 83 i sig selv regulerer det civilretlige erstatningsansvar og de administrative bøder, der kan pålægges den part, som ikke har opfyldt sine retlige forpligtelser. En yderligere ubegrænset kontraktuel eksponering er på denne baggrund ikke nødvendig for at sikre Kundens interesser. Vil Ordregiver acceptere, at erstatningsloftet i pkt. 21.1 også finder anvendelse på krav, der udspringer af Leverandørens manglende overholdelse af databeskyttelseslovgivningen, dog med undtagelse af tilfælde, der kan henføres til grov uagtsomhed eller forsætlige forhold hos Leverandøren?
A18: 18
A19: 19
A20: 20

Sheet Commitment
A1: Req ID | B1: Included | C1: Requirement | D1: Non-standard element | E1: Effect if not included | F1: Issue description | G1: Committer | H1: Comitted date | I1: Conditions for commitment | J1: Comment
A2: ='Production Plan'!B2 -> 4.1.1. | B2: =VLOOKUP(A2,'Production Plan'!B:T,14,FALSE) -> Cristina | C2: =VLOOKUP(A2,'Production Plan'!B:G,5,FALSE) -> Implementeringsplan | D2: Describe | E2: Disqualification/Non-conditional | F2: Issue as we don't have this solution | G2: Name | H2: 46023 | I2: Conditional upon winning.
A3: ='Production Plan'!B3 -> 4.2.1. | B3: =VLOOKUP(A3,'Production Plan'!B:T,14,FALSE) -> Cristina
A4: ='Production Plan'!B4 -> 5.1.1.1. | B4: =VLOOKUP(A4,'Production Plan'!B:T,14,FALSE) -> Cristina
A5: ='Production Plan'!B5 -> 5.1.2.1. | B5: =VLOOKUP(A5,'Production Plan'!B:T,14,FALSE) -> Anton
A6: ='Production Plan'!B6 -> 5.1.3.1. | B6: =VLOOKUP(A6,'Production Plan'!B:T,14,FALSE) -> Kaare
A7: ='Production Plan'!B7 -> 5.2.1.1. | B7: =VLOOKUP(A7,'Production Plan'!B:T,14,FALSE) -> Bjørn Henrik
A8: ='Production Plan'!B8 -> 5.2.1.2. | B8: =VLOOKUP(A8,'Production Plan'!B:T,14,FALSE) -> Arve
A9: ='Production Plan'!B9 -> 5.2.1.3. | B9: =VLOOKUP(A9,'Production Plan'!B:T,14,FALSE) -> Arve
A10: ='Production Plan'!B10 -> 5.2.1.4. | B10: =VLOOKUP(A10,'Production Plan'!B:T,14,FALSE) -> Anton
A11: ='Production Plan'!B11 -> 5.2.1.5. | B11: =VLOOKUP(A11,'Production Plan'!B:T,14,FALSE) -> Anton
A12: ='Production Plan'!B12 -> 5.2.1.6. | B12: =VLOOKUP(A12,'Production Plan'!B:T,14,FALSE) -> Anita
A13: ='Production Plan'!B13 -> 5.2.2.1. | B13: =VLOOKUP(A13,'Production Plan'!B:T,14,FALSE) -> Axel
A14: ='Production Plan'!B14 -> 5.2.3.1. | B14: =VLOOKUP(A14,'Production Plan'!B:T,14,FALSE) -> Axel
... A22: ='Production Plan'!B22 -> 5.2.5.1. | B22: =VLOOKUP(A22,'Production Plan'!B:T,14,FALSE) -> Husein
A23: ='Production Plan'!B24 -> 5.2.6.1. | B23: =VLOOKUP(A23,'Production Plan'!B:T,14,FALSE) -> Husein
A24: ='Production Plan'!B25 -> 5.2.6.2. | B24: =VLOOKUP(A24,'Production Plan'!B:T,14,FALSE) -> Anton
A25: ='Production Plan'!B26 -> 5.2.6.3. | B25: =VLOOKUP(A25,'Production Plan'!B:T,14,FALSE) -> Bjørn Henrik
A26: ='Production Plan'!B27 -> 5.2.6.4. | B26: =VLOOKUP(A26,'Production Plan'!B:T,14,FALSE) -> Bjørn Henrik
A27: ='Production Plan'!B28 -> 5.2.6.5. | B27: =VLOOKUP(A27,'Production Plan'!B:T,14,FALSE) -> Linn
A28: ='Production Plan'!B29 -> 5.2.6.6. | B28: =VLOOKUP(A28,'Production Plan'!B:T,14,FALSE) -> Morten
A29: ='Production Plan'!B30 -> 5.2.7.1. | B29: =VLOOKUP(A29,'Production Plan'!B:T,14,FALSE) -> Morten
A30: ='Production Plan'!B31 -> 5.2.7.2. | B30: =VLOOKUP(A30,'Production Plan'!B:T,14,FALSE) -> Morten
A31: ='Production Plan'!B32 -> 5.2.8.1. | B31: =VLOOKUP(A31,'Production Plan'!B:T,14,FALSE) -> Bjørn Henrik
A32: ='Production Plan'!B33 -> 5.2.8.2 | B32: =VLOOKUP(A32,'Production Plan'!B:T,14,FALSE) -> Bjørn Henrik
A33: ='Production Plan'!B34 -> 5.2.8.3. | B33: =VLOOKUP(A33,'Production Plan'!B:T,14,FALSE) -> Anton
A34: ='Production Plan'!B35 -> 5.2.8.4. | B34: =VLOOKUP(A34,'Production Plan'!B:T,14,FALSE) -> Bjørn Henrik
... A43: ='Production Plan'!B44 -> 5.2.8.13. | B43: =VLOOKUP(A43,'Production Plan'!B:T,14,FALSE) -> Morten
A44: ='Production Plan'!B48 -> 5.2.9.1. | B44: =VLOOKUP(A44,'Production Plan'!B:T,14,FALSE) -> Arve
A45: ='Production Plan'!B49 -> 5.2.9.2. | B45: =VLOOKUP(A45,'Production Plan'!B:T,14,FALSE) -> Arve
A46: ='Production Plan'!B50 -> 5.2.9.3. | B46: =VLOOKUP(A46,'Production Plan'!B:T,14,FALSE) -> Arve
A47: ='Production Plan'!B51 -> 5.2.9.4. | B47: =VLOOKUP(A47,'Production Plan'!B:T,14,FALSE) -> Arve
A48: ='Production Plan'!B52 -> 5.2.9.5. | B48: =VLOOKUP(A48,'Production Plan'!B:T,14,FALSE) -> Arve
A49: ='Production Plan'!B53 -> 5.2.9.6. | B49: =VLOOKUP(A49,'Production Plan'!B:T,14,FALSE) -> Arve
A50: ='Production Plan'!B54 -> 5.2.9.7. | B50: =VLOOKUP(A50,'Production Plan'!B:T,14,FALSE) -> Arve
A51: ='Production Plan'!B55 -> 5.2.10.1. | B51: =VLOOKUP(A51,'Production Plan'!B:T,14,FALSE) -> Axel
A52: ='Production Plan'!B57 -> 5.2.11.1. | B52: =VLOOKUP(A52,'Production Plan'!B:T,14,FALSE) -> Axel
A53: ='Production Plan'!B58 -> 5.2.11.2. | B53: =VLOOKUP(A53,'Production Plan'!B:T,14,FALSE) -> Bjørn Henrik
A54: ='Production Plan'!B59 -> 5.2.11.3 | B54: =VLOOKUP(A54,'Production Plan'!B:T,14,FALSE) -> Bjørn Henrik
A55: ='Production Plan'!B62 -> 5.2.12.1. | B55: =VLOOKUP(A55,'Production Plan'!B:T,14,FALSE) -> Morten
A56: ='Production Plan'!B63 -> 5.2.12.2 | B56: =VLOOKUP(A56,'Production Plan'!B:T,14,FALSE) -> Morten
A57: ='Production Plan'!B66 -> 5.2.13.1. | B57: =VLOOKUP(A57,'Production Plan'!B:T,14,FALSE) -> Axel
A58: ='Production Plan'!B67 -> 5.2.13.2. | B58: =VLOOKUP(A58,'Production Plan'!B:T,14,FALSE) -> Axel
A59: ='Production Plan'!B69 -> 5.2.14.1. | B59: =VLOOKUP(A59,'Production Plan'!B:T,14,FALSE) -> Anton
A60: ='Production Plan'!B70 -> 5.2.14.2. | B60: =VLOOKUP(A60,'Production Plan'!B:T,14,FALSE) -> Anton
A61: ='Production Plan'!B72 -> 5.2.15.1. | B61: =VLOOKUP(A61,'Production Plan'!B:T,14,FALSE) -> Arve
A62: ='Production Plan'!B73 -> 5.2.15.2. | B62: =VLOOKUP(A62,'Production Plan'!B:T,14,FALSE) -> Arve
A63: ='Production Plan'!B74 -> 5.2.15.3. | B63: =VLOOKUP(A63,'Production Plan'!B:T,14,FALSE) -> Arve
A64: ='Production Plan'!B75 -> 5.2.15.4. | B64: =VLOOKUP(A64,'Production Plan'!B:T,14,FALSE) -> Axel
A65: ='Production Plan'!B78 -> 5.2.16.1. | B65: =VLOOKUP(A65,'Production Plan'!B:T,14,FALSE) -> Bjørn Henrik
A66: ='Production Plan'!B79 -> 5.2.16.2. | B66: =VLOOKUP(A66,'Production Plan'!B:T,14,FALSE) -> Bjørn Henrik
A67: ='Production Plan'!B80 -> 5.2.16.3. | B67: =VLOOKUP(A67,'Production Plan'!B:T,14,FALSE) -> Bjørn Henrik
A68: ='Production Plan'!B82 -> 5.2.17.1. | B68: =VLOOKUP(A68,'Production Plan'!B:T,14,FALSE) -> Bjørn Henrik
A69: ='Production Plan'!B83 -> 5.2.17.2. | B69: =VLOOKUP(A69,'Production Plan'!B:T,14,FALSE) -> Bjørn Henrik
A70: ='Production Plan'!B84 -> 5.2.17.3. | B70: =VLOOKUP(A70,'Production Plan'!B:T,14,FALSE) -> Bjørn Henrik
A71: ='Production Plan'!B85 -> 5.2.17.4. | B71: =VLOOKUP(A71,'Production Plan'!B:T,14,FALSE) -> Bjørn Henrik
A72: ='Production Plan'!B86 -> 5.2.17.5. | B72: =VLOOKUP(A72,'Production Plan'!B:T,14,FALSE) -> Bjørn Henrik
A73: ='Production Plan'!B88 -> 5.2.18.1. | B73: =VLOOKUP(A73,'Production Plan'!B:T,14,FALSE) -> Morten
A74: ='Production Plan'!B90 -> 5.2.19.1. | B74: =VLOOKUP(A74,'Production Plan'!B:T,14,FALSE) -> Morten
A75: ='Production Plan'!B91 -> 5.3.1.1. | B75: =VLOOKUP(A75,'Production Plan'!B:T,14,FALSE) -> Anton
A76: ='Production Plan'!B92 -> 5.3.1.2. | B76: =VLOOKUP(A76,'Production Plan'!B:T,14,FALSE) -> Anton
A77: ='Production Plan'!B93 -> 5.3.1.3. | B77: =VLOOKUP(A77,'Production Plan'!B:T,14,FALSE) -> Anton
A78: ='Production Plan'!B94 -> 5.3.1.4. | B78: =VLOOKUP(A78,'Production Plan'!B:T,14,FALSE) -> Morten
A79: ='Production Plan'!B95 -> 5.3.1.5. | B79: =VLOOKUP(A79,'Production Plan'!B:T,14,FALSE) -> Morten
A80: ='Production Plan'!B96 -> 5.3.1.1.1. | B80: =VLOOKUP(A80,'Production Plan'!B:T,14,FALSE) -> Kaare
A81: ='Production Plan'!B97 -> 5.3.1.1.2. | B81: =VLOOKUP(A81,'Production Plan'!B:T,14,FALSE) -> Kaare
A82: ='Production Plan'!B99 -> 5.3.2.1 | B82: =VLOOKUP(A82,'Production Plan'!B:T,14,FALSE) -> Anton
A83: ='Production Plan'!B100 -> 5.3.2.2 | B83: =VLOOKUP(A83,'Production Plan'!B:T,14,FALSE) -> Morten
A84: ='Production Plan'!B101 -> 5.3.2.3 | B84: =VLOOKUP(A84,'Production Plan'!B:T,14,FALSE) -> CloudOps
A85: ='Production Plan'!B102 -> 5.3.2.4 | B85: =VLOOKUP(A85,'Production Plan'!B:T,14,FALSE) -> CloudOps
A86: ='Production Plan'!B103 -> 5.3.2.5 | B86: =VLOOKUP(A86,'Production Plan'!B:T,14,FALSE) -> CloudOps
A87: ='Production Plan'!B104 -> 5.3.3.1.1 | B87: =VLOOKUP(A87,'Production Plan'!B:T,14,FALSE) -> Morten
A88: ='Production Plan'!B105 -> 5.3.3.1.2 | B88: =VLOOKUP(A88,'Production Plan'!B:T,14,FALSE) -> Olga
A89: ='Production Plan'!B106 -> 5.3.3.2.1 | B89: =VLOOKUP(A89,'Production Plan'!B:T,14,FALSE) -> Anton
A90: ='Production Plan'!B107 -> 5.3.4.1 | B90: =VLOOKUP(A90,'Production Plan'!B:T,14,FALSE) -> Anton
A91: ='Production Plan'!B108 -> 5.3.4.2 | B91: =VLOOKUP(A91,'Production Plan'!B:T,14,FALSE) -> Morten
A92: ='Production Plan'!B109 -> 5.3.4.3 | B92: =VLOOKUP(A92,'Production Plan'!B:T,14,FALSE) -> Anton
A93: ='Production Plan'!B110 -> 5.3.4.4 | B93: =VLOOKUP(A93,'Production Plan'!B:T,14,FALSE) -> Morten
... A135: ='Production Plan'!B152 -> 5.3.8.1.5. | B135: =VLOOKUP(A135,'Production Plan'!B:T,14,FALSE) -> Olga
A136: ='Production Plan'!B154 -> 5.3.8.2.1.1. | B136: =VLOOKUP(A136,'Production Plan'!B:T,14,FALSE) -> Axel
A137: ='Production Plan'!B156 -> 5.3.8.2.2.1. | B137: =VLOOKUP(A137,'Production Plan'!B:T,14,FALSE) -> Axel
A138: ='Production Plan'!B157 -> 5.3.8.2.2.2. | B138: =VLOOKUP(A138,'Production Plan'!B:T,14,FALSE) -> Olga
A139: ='Production Plan'!B158 -> 5.3.8.2.3.1. | B139: =VLOOKUP(A139,'Production Plan'!B:T,14,FALSE) -> Mithun
A140: ='Production Plan'!B159 -> 5.3.8.2.3.2. | B140: =VLOOKUP(A140,'Production Plan'!B:T,14,FALSE) -> Mithun
A141: ='Production Plan'!B160 -> 5.3.8.2.4.1. | B141: =VLOOKUP(A141,'Production Plan'!B:T,14,FALSE) -> Kaare
A142: ='Production Plan'!B161 -> 5.3.8.2.5.1. | B142: =VLOOKUP(A142,'Production Plan'!B:T,14,FALSE) -> Mithun
A143: ='Production Plan'!B162 -> 5.3.8.2.5.2. | B143: =VLOOKUP(A143,'Production Plan'!B:T,14,FALSE) -> Mithun
A144: ='Production Plan'!B163 -> 5.3.8.2.6.1 | B144: =VLOOKUP(A144,'Production Plan'!B:T,14,FALSE) -> Mithun
A145: ='Production Plan'!B164 -> 5.3.8.2.7.1.1. | B145: =VLOOKUP(A145,'Production Plan'!B:T,14,FALSE) -> Olga
A146: ='Production Plan'!B165 -> 5.3.8.2.7.1.2. | B146: =VLOOKUP(A146,'Production Plan'!B:T,14,FALSE) -> Olga
A147: ='Production Plan'!B166 -> 5.3.8.2.7.1.3. | B147: =VLOOKUP(A147,'Production Plan'!B:T,14,FALSE) -> Olga
A148: ='Production Plan'!B167 -> 5.3.8.2.7.1.4. | B148: =VLOOKUP(A148,'Production Plan'!B:T,14,FALSE) -> Olga
... A150: ='Production Plan'!B169 -> 5.3.8.2.7.2.2. | B150: =VLOOKUP(A150,'Production Plan'!B:T,14,FALSE) -> Olga
A151: ='Production Plan'!B171 -> 5.3.8.2.8.1. | B151: =VLOOKUP(A151,'Production Plan'!B:T,14,FALSE) -> CloudOps
A152: ='Production Plan'!B172 -> 5.3.8.2.8.2. | B152: =VLOOKUP(A152,'Production Plan'!B:T,14,FALSE) -> Willy
A153: ='Production Plan'!B173 -> 5.4.1.1. | B153: =VLOOKUP(A153,'Production Plan'!B:T,14,FALSE) -> Mithun
A154: ='Production Plan'!B174 -> 5.4.2.1. | B154: =VLOOKUP(A154,'Production Plan'!B:T,14,FALSE) -> Mithun
A155: ='Production Plan'!B175 -> B1-01 | B155: =VLOOKUP(A155,'Production Plan'!B:T,14,FALSE) -> Cristina
A156: ='Production Plan'!B176 -> B1-02 | B156: =VLOOKUP(A156,'Production Plan'!B:T,14,FALSE) -> Cristina
A157: ='Production Plan'!B177 -> B1-03 | B157: =VLOOKUP(A157,'Production Plan'!B:T,14,FALSE) -> Cristina
...

Sheet Risk Management
A1: Req ID | B1: Included | C1: Requirement | D1: Risk Element | E1: Severity | F1: Issue description | G1: Mitigation | H1: Comment | I1: Decision | J1: Decider | K1: Decision date | L1: Conditions for Approval | M1: Reporter
A2: ='Production Plan'!B2 -> 4.1.1. | B2: =VLOOKUP(A2,'Production Plan'!B:U,15,FALSE) -> 0 | C2: =VLOOKUP(A2,'Production Plan'!B:G,5,FALSE) -> Implementeringsplan | D2: Describe | E2: High | F2: Issue as we may risk fines | G2: Buffer in price | I2: Go-ahead - dependent upon mitigation | J2: Name | K2: 46023 | L2: Actions in mitigation must be done.
A3: ='Production Plan'!B3 -> 4.2.1. | B3: =VLOOKUP(A3,'Production Plan'!B:U,15,FALSE) -> 0 | C3: =VLOOKUP(A3,'Production Plan'!B:G,5,FALSE) -> Tidsplan for optioner | D3: Describe | E3: Medium | F3: Big risk of scope creep | G3: Clear statement of work in Clarification phase | I3: Go ahead - attempt to mitigate | J3: Name | K3: 46023 | L3: Attempt to mitigate, but go ahead, even if unsuccessful.
A4: ='Production Plan'!B4 -> 5.1.1.1. | B4: =VLOOKUP(A4,'Production Plan'!B:U,15,FALSE) -> 0 | C4: =VLOOKUP(A4,'Production Plan'!B:G,5,FALSE) -> Prøveplan
A5: ='Production Plan'!B5 -> 5.1.2.1. | B5: =VLOOKUP(A5,'Production Plan'!B:U,15,FALSE) -> Tony, Cristian | C5: =VLOOKUP(A5,'Production Plan'!B:G,5,FALSE) -> Uddannelse | D5: Describe | E5: Low | F5: We can be sued | G5: We add a line in the contract. | H5: This is a very unlikely scenario. | I5: Go ahead - disregard risk | J5: Name | K5: 46023 | L5: As it is unlikely - we take the risk.
A6: ='Production Plan'!B6 -> 5.1.3.1. | B6: =VLOOKUP(A6,'Production Plan'!B:U,15,FALSE) -> 0 | C6: =VLOOKUP(A6,'Production Plan'!B:G,5,FALSE) -> Migreringsplan
A7: ='Production Plan'!B7 -> 5.2.1.1. | B7: =VLOOKUP(A7,'Production Plan'!B:U,15,FALSE) -> 0 | C7: =VLOOKUP(A7,'Production Plan'!B:G,5,FALSE) -> Opmærkning af sager og dokumenter | D7: Describe | E7: High | F7: We are unable to meet requirement | G7: We build a new module | H7: Their budget is not big enough for this. | I7: No bid | J7: Name | K7: 46023 | L7: -
A8: ='Production Plan'!B8 -> 5.2.1.2. | B8: =VLOOKUP(A8,'Production Plan'!B:U,15,FALSE) -> 0 | C8: =VLOOKUP(A8,'Production Plan'!B:G,5,FALSE) -> Konfliktløsning
A9: ='Production Plan'!B9 -> 5.2.1.3. | B9: =VLOOKUP(A9,'Production Plan'!B:U,15,FALSE) -> 0 | C9: =VLOOKUP(A9,'Production Plan'!B:G,5,FALSE) -> -
A10: ='Production Plan'!B10 -> 5.2.1.4. | B10: =VLOOKUP(A10,'Production Plan'!B:U,15,FALSE) -> 0 | C10: =VLOOKUP(A10,'Production Plan'!B:G,5,FALSE) -> -
A11: ='Production Plan'!B11 -> 5.2.1.5. | B11: =VLOOKUP(A11,'Production Plan'!B:U,15,FALSE) -> 0 | C11: =VLOOKUP(A11,'Production Plan'!B:G,5,FALSE) -> -
A12: ='Production Plan'!B12 -> 5.2.1.6. | B12: =VLOOKUP(A12,'Production Plan'!B:U,15,FALSE) -> 0 | C12: =VLOOKUP(A12,'Production Plan'!B:G,5,FALSE) -> Understøttelse af Elektronisk Sags- og Dokumenthåndtering
A13: ='Production Plan'!B13 -> 5.2.2.1. | B13: =VLOOKUP(A13,'Production Plan'!B:U,15,FALSE) -> 0 | C13: =VLOOKUP(A13,'Production Plan'!B:G,5,FALSE) -> Ejendomsdata
A14: ='Production Plan'!B14 -> 5.2.3.1. | B14: =VLOOKUP(A14,'Production Plan'!B:U,15,FALSE) -> 0 | C14: =VLOOKUP(A14,'Production Plan'!B:G,5,FALSE) -> -
A15: ='Production Plan'!B15 -> 5.2.3.2. | B15: =VLOOKUP(A15,'Production Plan'!B:U,15,FALSE) -> 0 | C15: =VLOOKUP(A15,'Production Plan'!B:G,5,FALSE) -> -
A16: ='Production Plan'!B16 -> 5.2.3.3. | B16: =VLOOKUP(A16,'Production Plan'!B:U,15,FALSE) -> 0 | C16: =VLOOKUP(A16,'Production Plan'!B:G,5,FALSE) -> -
A17: ='Production Plan'!B17 -> 5.2.3.4. | B17: =VLOOKUP(A17,'Production Plan'!B:U,15,FALSE) -> 0 | C17: =VLOOKUP(A17,'Production Plan'!B:G,5,FALSE) -> -
A18: ='Production Plan'!B18 -> 5.2.3.5. | B18: =VLOOKUP(A18,'Production Plan'!B:U,15,FALSE) -> 0 | C18: =VLOOKUP(A18,'Production Plan'!B:G,5,FALSE) -> Interessent roller
A19: ='Production Plan'!B19 -> 5.2.4.1. | B19: =VLOOKUP(A19,'Production Plan'!B:U,15,FALSE) -> 0 | C19: =VLOOKUP(A19,'Production Plan'!B:G,5,FALSE) -> Sagsopslag og visning
... A22: ='Production Plan'!B22 -> 5.2.5.1. | B22: =VLOOKUP(A22,'Production Plan'!B:U,15,FALSE) -> 0 | C22: =VLOOKUP(A22,'Production Plan'!B:G,5,FALSE) -> GIS visning af sager
A23: ='Production Plan'!B24 -> 5.2.6.1. | B23: =VLOOKUP(A23,'Production Plan'!B:U,15,FALSE) -> 0 | C23: =VLOOKUP(A23,'Production Plan'!B:G,5,FALSE) -> -
A24: ='Production Plan'!B25 -> 5.2.6.2. | B24: =VLOOKUP(A24,'Production Plan'!B:U,15,FALSE) -> 0 | C24: =VLOOKUP(A24,'Production Plan'!B:G,5,FALSE) -> -
A25: ='Production Plan'!B26 -> 5.2.6.3. | B25: =VLOOKUP(A25,'Production Plan'!B:U,15,FALSE) -> 0 | C25: =VLOOKUP(A25,'Production Plan'!B:G,5,FALSE) -> Sags/journalnoter
A26: ='Production Plan'!B27 -> 5.2.6.4. | B26: =VLOOKUP(A26,'Production Plan'!B:U,15,FALSE) -> 0 | C26: =VLOOKUP(A26,'Production Plan'!B:G,5,FALSE) -> Overblik på sagen
A27: ='Production Plan'!B28 -> 5.2.6.5. | B27: =VLOOKUP(A27,'Production Plan'!B:U,15,FALSE) -> 0 | C27: =VLOOKUP(A27,'Production Plan'!B:G,5,FALSE) -> Ansøgninger og anmeldelser på sagen
A28: ='Production Plan'!B29 -> 5.2.6.6. | B28: =VLOOKUP(A28,'Production Plan'!B:U,15,FALSE) -> 0 | C28: =VLOOKUP(A28,'Production Plan'!B:G,5,FALSE) -> Overblik på sagsdokumenter
A29: ='Production Plan'!B30 -> 5.2.7.1. | B29: =VLOOKUP(A29,'Production Plan'!B:U,15,FALSE) -> 0 | C29: =VLOOKUP(A29,'Production Plan'!B:G,5,FALSE) -> Sagsoverblik og adviseringer
A30: ='Production Plan'!B31 -> 5.2.7.2. | B30: =VLOOKUP(A30,'Production Plan'!B:U,15,FALSE) -> 0 | C30: =VLOOKUP(A30,'Production Plan'!B:G,5,FALSE) -> Tilpasset overbliksvisning og sortering
A31: ='Production Plan'!B32 -> 5.2.8.1. | B31: =VLOOKUP(A31,'Production Plan'!B:U,15,FALSE) -> 0 | C31: =VLOOKUP(A31,'Production Plan'!B:G,5,FALSE) -> -
A32: ='Production Plan'!B33 -> 5.2.8.2 | B32: =VLOOKUP(A32,'Production Plan'!B:U,15,FALSE) -> 0 | C32: =VLOOKUP(A32,'Production Plan'!B:G,5,FALSE) -> -
A33: ='Production Plan'!B34 -> 5.2.8.3. | B33: =VLOOKUP(A33,'Production Plan'!B:U,15,FALSE) -> 0 | C33: =VLOOKUP(A33,'Production Plan'!B:G,5,FALSE) -> -
A34: ='Production Plan'!B35 -> 5.2.8.4. | B34: =VLOOKUP(A34,'Production Plan'!B:U,15,FALSE) -> 0 | C34: =VLOOKUP(A34,'Production Plan'!B:G,5,FALSE) -> Sagsstatus
... A43: ='Production Plan'!B44 -> 5.2.8.13. | B43: =VLOOKUP(A43,'Production Plan'!B:U,15,FALSE) -> 0 | C43: =VLOOKUP(A43,'Production Plan'!B:G,5,FALSE) -> -
A44: ='Production Plan'!B48 -> 5.2.9.1. | B44: =VLOOKUP(A44,'Production Plan'!B:U,15,FALSE) -> 0 | C44: =VLOOKUP(A44,'Production Plan'!B:G,5,FALSE) -> -
A45: ='Production Plan'!B49 -> 5.2.9.2. | B45: =VLOOKUP(A45,'Production Plan'!B:U,15,FALSE) -> 0 | C45: =VLOOKUP(A45,'Production Plan'!B:G,5,FALSE) -> -
A46: ='Production Plan'!B50 -> 5.2.9.3. | B46: =VLOOKUP(A46,'Production Plan'!B:U,15,FALSE) -> 0 | C46: =VLOOKUP(A46,'Production Plan'!B:G,5,FALSE) -> -
A47: ='Production Plan'!B51 -> 5.2.9.4. | B47: =VLOOKUP(A47,'Production Plan'!B:U,15,FALSE) -> 0 | C47: =VLOOKUP(A47,'Production Plan'!B:G,5,FALSE) -> -
A48: ='Production Plan'!B52 -> 5.2.9.5. | B48: =VLOOKUP(A48,'Production Plan'!B:U,15,FALSE) -> 0 | C48: =VLOOKUP(A48,'Production Plan'!B:G,5,FALSE) -> -
A49: ='Production Plan'!B53 -> 5.2.9.6. | B49: =VLOOKUP(A49,'Production Plan'!B:U,15,FALSE) -> 0 | C49: =VLOOKUP(A49,'Production Plan'!B:G,5,FALSE) -> -
A50: ='Production Plan'!B54 -> 5.2.9.7. | B50: =VLOOKUP(A50,'Production Plan'!B:U,15,FALSE) -> 0 | C50: =VLOOKUP(A50,'Production Plan'!B:G,5,FALSE) -> -
A51: ='Production Plan'!B55 -> 5.2.10.1. | B51: =VLOOKUP(A51,'Production Plan'!B:U,15,FALSE) -> 0 | C51: =VLOOKUP(A51,'Production Plan'!B:G,5,FALSE) -> Dataafgrænsning af sager
A52: ='Production Plan'!B57 -> 5.2.11.1. | B52: =VLOOKUP(A52,'Production Plan'!B:U,15,FALSE) -> 0 | C52: =VLOOKUP(A52,'Production Plan'!B:G,5,FALSE) -> Sagsbehandlingstid og servicemålstid
A53: ='Production Plan'!B58 -> 5.2.11.2. | B53: =VLOOKUP(A53,'Production Plan'!B:U,15,FALSE) -> 0 | C53: =VLOOKUP(A53,'Production Plan'!B:G,5,FALSE) -> Servicemålstid start/stop
A54: ='Production Plan'!B59 -> 5.2.11.3 | B54: =VLOOKUP(A54,'Production Plan'!B:U,15,FALSE) -> 0 | C54: =VLOOKUP(A54,'Production Plan'!B:G,5,FALSE) -> Sagsbehandlingstid for ikke-BOM sager
A55: ='Production Plan'!B62 -> 5.2.12.1. | B55: =VLOOKUP(A55,'Production Plan'!B:U,15,FALSE) -> 0 | C55: =VLOOKUP(A55,'Production Plan'!B:G,5,FALSE) -> Sagens overblik
A56: ='Production Plan'!B63 -> 5.2.12.2 | B56: =VLOOKUP(A56,'Production Plan'!B:U,15,FALSE) -> 0 | C56: =VLOOKUP(A56,'Production Plan'!B:G,5,FALSE) -> Understøtte sagsflow
A57: ='Production Plan'!B66 -> 5.2.13.1. | B57: =VLOOKUP(A57,'Production Plan'!B:U,15,FALSE) -> Jarle | C57: =VLOOKUP(A57,'Production Plan'!B:G,5,FALSE) -> Sagsoprettelse via standardskabelon
A58: ='Production Plan'!B67 -> 5.2.13.2. | B58: =VLOOKUP(A58,'Production Plan'!B:U,15,FALSE) -> Jarle | C58: =VLOOKUP(A58,'Production Plan'!B:G,5,FALSE) -> Standardsagers procesunderstøttelse
A59: ='Production Plan'!B69 -> 5.2.14.1. | B59: =VLOOKUP(A59,'Production Plan'!B:U,15,FALSE) -> 0 | C59: =VLOOKUP(A59,'Production Plan'!B:G,5,FALSE) -> Advis funktion
A60: ='Production Plan'!B70 -> 5.2.14.2. | B60: =VLOOKUP(A60,'Production Plan'!B:U,15,FALSE) -> 0 | C60: =VLOOKUP(A60,'Production Plan'!B:G,5,FALSE) -> Tilpasning af advis
A61: ='Production Plan'!B72 -> 5.2.15.1. | B61: =VLOOKUP(A61,'Production Plan'!B:U,15,FALSE) -> 0 | C61: =VLOOKUP(A61,'Production Plan'!B:G,5,FALSE) -> Markering af dokumenter til FilArkiv
A62: ='Production Plan'!B73 -> 5.2.15.2. | B62: =VLOOKUP(A62,'Production Plan'!B:U,15,FALSE) -> 0 | C62: =VLOOKUP(A62,'Production Plan'!B:G,5,FALSE) -> Håndtering af navne- og adressebeskyttelse
A63: ='Production Plan'!B74 -> 5.2.15.3. | B63: =VLOOKUP(A63,'Production Plan'!B:U,15,FALSE) -> 0 | C63: =VLOOKUP(A63,'Production Plan'!B:G,5,FALSE) -> Overførsel af sagens data og dokumentation
A64: ='Production Plan'!B75 -> 5.2.15.4. | B64: =VLOOKUP(A64,'Production Plan'!B:U,15,FALSE) -> Merge project | C64: =VLOOKUP(A64,'Production Plan'!B:G,5,FALSE) -> Status på overførsel og fejlhåndtering
A65: ='Production Plan'!B78 -> 5.2.16.1. | B65: =VLOOKUP(A65,'Production Plan'!B:U,15,FALSE) -> 0 | C65: =VLOOKUP(A65,'Production Plan'!B:G,5,FALSE) -> Håndtering af servicemålssager
A66: ='Production Plan'!B79 -> 5.2.16.2. | B66: =VLOOKUP(A66,'Production Plan'!B:U,15,FALSE) -> Bjørn Tore | C66: =VLOOKUP(A66,'Production Plan'!B:G,5,FALSE) -> Data på tværs af servicemålskategorier
A67: ='Production Plan'!B80 -> 5.2.16.3. | B67: =VLOOKUP(A67,'Production Plan'!B:U,15,FALSE) -> 0 | C67: =VLOOKUP(A67,'Production Plan'!B:G,5,FALSE) -> Data på enkelte sager
A68: ='Production Plan'!B82 -> 5.2.17.1. | B68: =VLOOKUP(A68,'Production Plan'!B:U,15,FALSE) -> 0 | C68: =VLOOKUP(A68,'Production Plan'!B:G,5,FALSE) -> Registrering af tid på sager
A69: ='Production Plan'!B83 -> 5.2.17.2. | B69: =VLOOKUP(A69,'Production Plan'!B:U,15,FALSE) -> 0 | C69: =VLOOKUP(A69,'Production Plan'!B:G,5,FALSE) -> Registrering af anden tid
A70: ='Production Plan'!B84 -> 5.2.17.3. | B70: =VLOOKUP(A70,'Production Plan'!B:U,15,FALSE) -> 0 | C70: =VLOOKUP(A70,'Production Plan'!B:G,5,FALSE) -> Visning af tidsregistreringer
A71: ='Production Plan'!B85 -> 5.2.17.4. | B71: =VLOOKUP(A71,'Production Plan'!B:U,15,FALSE) -> 0 | C71: =VLOOKUP(A71,'Production Plan'!B:G,5,FALSE) -> Registreringstyper
A72: ='Production Plan'!B86 -> 5.2.17.5. | B72: =VLOOKUP(A72,'Production Plan'!B:U,15,FALSE) -> 0 | C72: =VLOOKUP(A72,'Production Plan'!B:G,5,FALSE) -> Driftsstyring og ledelsesoverblik
A73: ='Production Plan'!B88 -> 5.2.18.1. | B73: =VLOOKUP(A73,'Production Plan'!B:U,15,FALSE) -> Bjørn tore | C73: =VLOOKUP(A73,'Production Plan'!B:G,5,FALSE) -> Rapportering og dataoverførsel
A74: ='Production Plan'!B90 -> 5.2.19.1. | B74: =VLOOKUP(A74,'Production Plan'!B:U,15,FALSE) -> 0 | C74: =VLOOKUP(A74,'Production Plan'!B:G,5,FALSE) -> Anvendelse af AI og algoritmer
A75: ='Production Plan'!B91 -> 5.3.1.1. | B75: =VLOOKUP(A75,'Production Plan'!B:U,15,FALSE) -> 0 | C75: =VLOOKUP(A75,'Production Plan'!B:G,5,FALSE) -> Autentiske kopier af kommunikation
A76: ='Production Plan'!B92 -> 5.3.1.2. | B76: =VLOOKUP(A76,'Production Plan'!B:U,15,FALSE) -> 0 | C76: =VLOOKUP(A76,'Production Plan'!B:G,5,FALSE) -> PDF/A-formaterne
A77: ='Production Plan'!B93 -> 5.3.1.3. | B77: =VLOOKUP(A77,'Production Plan'!B:U,15,FALSE) -> 0 | C77: =VLOOKUP(A77,'Production Plan'!B:G,5,FALSE) -> Automatisk datering af breve
A78: ='Production Plan'!B94 -> 5.3.1.4. | B78: =VLOOKUP(A78,'Production Plan'!B:U,15,FALSE) -> 0 | C78: =VLOOKUP(A78,'Production Plan'!B:G,5,FALSE) -> Notatpligt
A79: ='Production Plan'!B95 -> 5.3.1.5. | B79: =VLOOKUP(A79,'Production Plan'!B:U,15,FALSE) -> 0 | C79: =VLOOKUP(A79,'Production Plan'!B:G,5,FALSE) -> Understøttelse af aktindsigter
A80: ='Production Plan'!B96 -> 5.3.1.1.1. | B80: =VLOOKUP(A80,'Production Plan'!B:U,15,FALSE) -> 0 | C80: =VLOOKUP(A80,'Production Plan'!B:G,5,FALSE) -> Arkivering til Stadsarkivet
A81: ='Production Plan'!B97 -> 5.3.1.1.2. | B81: =VLOOKUP(A81,'Production Plan'!B:U,15,FALSE) -> 0 | C81: =VLOOKUP(A81,'Production Plan'!B:G,5,FALSE) -> Sletning af bevaringsværdige data
A82: ='Production Plan'!B99 -> 5.3.2.1 | B82: =VLOOKUP(A82,'Production Plan'!B:U,15,FALSE) -> 0 | C82: =VLOOKUP(A82,'Production Plan'!B:G,5,FALSE) -> Hosting og miljøer
A83: ='Production Plan'!B100 -> 5.3.2.2 | B83: =VLOOKUP(A83,'Production Plan'!B:U,15,FALSE) -> 0 | C83: =VLOOKUP(A83,'Production Plan'!B:G,5,FALSE) -> Løst koblet arkitektur
A84: ='Production Plan'!B101 -> 5.3.2.3 | B84: =VLOOKUP(A84,'Production Plan'!B:U,15,FALSE) -> 0 | C84: =VLOOKUP(A84,'Production Plan'!B:G,5,FALSE) -> Segmentering af komponenter
A85: ='Production Plan'!B102 -> 5.3.2.4 | B85: =VLOOKUP(A85,'Production Plan'!B:U,15,FALSE) -> 0 | C85: =VLOOKUP(A85,'Production Plan'!B:G,5,FALSE) -> Adskillelse af data
A86: ='Production Plan'!B103 -> 5.3.2.5 | B86: =VLOOKUP(A86,'Production Plan'!B:U,15,FALSE) -> 0 | C86: =VLOOKUP(A86,'Production Plan'!B:G,5,FALSE) -> Beskyttelse mod angreb
A87: ='Production Plan'!B104 -> 5.3.3.1.1 | B87: =VLOOKUP(A87,'Production Plan'!B:U,15,FALSE) -> 0 | C87: =VLOOKUP(A87,'Production Plan'!B:G,5,FALSE) -> Datakvalitet og -integritet i Systemet
A88: ='Production Plan'!B105 -> 5.3.3.1.2 | B88: =VLOOKUP(A88,'Production Plan'!B:U,15,FALSE) -> 0 | C88: =VLOOKUP(A88,'Production Plan'!B:G,5,FALSE) -> Fejlmeldinger ved dataoverførsel
A89: ='Production Plan'!B106 -> 5.3.3.2.1 | B89: =VLOOKUP(A89,'Production Plan'!B:U,15,FALSE) -> 0 | C89: =VLOOKUP(A89,'Production Plan'!B:G,5,FALSE) -> Systemets begrebsmodel
A90: ='Production Plan'!B107 -> 5.3.4.1 | B90: =VLOOKUP(A90,'Production Plan'!B:U,15,FALSE) -> 0 | C90: =VLOOKUP(A90,'Production Plan'!B:G,5,FALSE) -> Sprog
A91: ='Production Plan'!B108 -> 5.3.4.2 | B91: =VLOOKUP(A91,'Production Plan'!B:U,15,FALSE) -> 0 | C91: =VLOOKUP(A91,'Production Plan'!B:G,5,FALSE) -> Fejltekster og meddelelser
A92: ='Production Plan'!B109 -> 5.3.4.3 | B92: =VLOOKUP(A92,'Production Plan'!B:U,15,FALSE) -> 0 | C92: =VLOOKUP(A92,'Production Plan'!B:G,5,FALSE) -> Stavekontrol
A93: ='Production Plan'!B110 -> 5.3.4.4 | B93: =VLOOKUP(A93,'Production Plan'!B:U,15,FALSE) -> 0 | C93: =VLOOKUP(A93,'Production Plan'!B:G,5,FALSE) -> Danske tegn og specialtegn
... A135: ='Production Plan'!B152 -> 5.3.8.1.5. | B135: =VLOOKUP(A135,'Production Plan'!B:U,15,FALSE) -> 0 | C135: =VLOOKUP(A135,'Production Plan'!B:G,5,FALSE) -> Kvalitet af integrationer
A136: ='Production Plan'!B154 -> 5.3.8.2.1.1. | B136: =VLOOKUP(A136,'Production Plan'!B:U,15,FALSE) -> 0 | C136: =VLOOKUP(A136,'Production Plan'!B:G,5,FALSE) -> Byg og Miljø (BOM)
A137: ='Production Plan'!B156 -> 5.3.8.2.2.1. | B137: =VLOOKUP(A137,'Production Plan'!B:U,15,FALSE) -> 0 | C137: =VLOOKUP(A137,'Production Plan'!B:G,5,FALSE) -> Grunddata
