Workbook

Sheet Production Plan
A1: # | B1: ReqID | C1: Document | D1: Section (Headline) | E1: Requirement title | F1: Requirement | G1: Requirement type | H1: Action | I1: Indgår i officiel krav-count? | J1: Vægt | K1: Round #1 | L1: Responsible | M1: Reviewer | N1: Module | O1: Can we meet the requirement? | P1: Comment | Q1: Commitment needed? | R1: Risk Element? | S1: Cost Driver | T1: Link to answer document | U1: Status (phase) | V1: Status (%) | W1: AI — Generated | X1: AI — Source | Y1: AI — Compliance | Z1: AI — Confidence | AA1: AI — Summary | AB1: AI — Gaps & clarifications | AC1: AI — Evidence | AD1: AI — Next action | AE1: AI — Reviewed by | AF1: AI — Review status | AG1: AI — Run ID
A2: 1 | B2: MK-1 | C2: Bilag 1.b | D2: Generelle krav | E2: Rigsarkivets afleveringsmodeller | F2: ESDH-løsningen skal understøtte Rigsarkivets gældende retningslinjer for anmeldelse og godkendelse af it-systemer fra statslige Myndigheder, jf. Cirkulære om anmeldelse og godkendelse af it-systemer på Retsinformation og gældende regler for generel aflevering af statslige it-systemer, jf. Bekendtgørelse om arkiveringsversioner på Retsinformation. | G2: Mindstekrav | H2: =IF(G2="Evalueringskrav","Answer",(IF(G2="Krav","Check",(IF(G2="Mindstekrav","Verify",""))))) | I2: Ja | L2: Anton | O2: 1. Fully met | U2: Not Started | V2: =IF(U2="Not Started",0%,IF(U2="Started",50%,IF(U2="Ready for review",70%,IF(U2="Reviewed - Content",80%,IF(U2="Reviewed - Format",90%,IF(U2="Done",100%,"")))))) | W2: 2026-07-07 | X2: Cursor / tender-response (batch) | Y2: Met | Z2: Verified | AA2: Verify: Rigsarkivets afleveringsmodeller — vurderet opfyldt (tool: 1. Fully met). | AC2: docs/tender-reference/extracted/KK Tender tool.txt; docs/tender-reference/extracted/Nationalbanken/Bilag 3.i Leverandørens Løsningsbeskrivelse.txt; docs/product/RFP_Leverandørens_svar_utdrag.txt | AD2: Anton: Confirm verify-tekst; opdatér review status efter tjek. | AF2: Draft | AG2: uim-esdh-full-2026-07-07
A3: 2 | B3: MK-2 | C3: Bilag 1.b | D3: Generelle krav | E3: Sprog | F3: ESDH-løsningen skal understøtte dansk og engelsk. | G3: Mindstekrav | H3: =IF(G3="Evalueringskrav","Answer",(IF(G3="Krav","Check",(IF(G3="Mindstekrav","Verify",""))))) | I3: Ja | L3: Anton | O3: 1. Fully met | U3: Not Started | V3: =IF(U3="Not Started",0%,IF(U3="Started",50%,IF(U3="Ready for review",70%,IF(U3="Reviewed - Content",80%,IF(U3="Reviewed - Format",90%,IF(U3="Done",100%,"")))))) | W3: 2026-07-07 | X3: Cursor / tender-response (batch) | Y3: Met | Z3: Verified | AA3: Verify: Sprog — vurderet opfyldt (tool: 1. Fully met). | AC3: docs/tender-reference/extracted/Nationalbanken/Bilag 3.i Leverandørens Løsningsbeskrivelse.txt; docs/tender-reference/extracted/HSØ/02.00-Tietoevry-SSA-L-Bilag 2-Leverandørens beskrivelse av Tjenesten.txt; docs/tender-reference/extracted/KK Tender tool.txt | AD3: Anton: Confirm verify-tekst; opdatér review status efter tjek. | AF3: Draft | AG3: uim-esdh-full-2026-07-07
A4: 3 | B4: MK-3 | C4: Bilag 1.b | D4: Generelle krav | E4: Datamodel | F4: ESDH-løsningen skal understøtte en Datamodel med en klar og tydelig beskrivelse af felterne i både frontend og backend. | G4: Mindstekrav | H4: =IF(G4="Evalueringskrav","Answer",(IF(G4="Krav","Check",(IF(G4="Mindstekrav","Verify",""))))) | I4: Ja | L4: Anton | O4: 1. Fully met | U4: Not Started | V4: =IF(U4="Not Started",0%,IF(U4="Started",50%,IF(U4="Ready for review",70%,IF(U4="Reviewed - Content",80%,IF(U4="Reviewed - Format",90%,IF(U4="Done",100%,"")))))) | W4: 2026-07-07 | X4: Cursor / tender-response (batch) | Y4: Met | Z4: Verified | AA4: Verify: Datamodel — vurderet opfyldt (tool: 1. Fully met). | AC4: docs/tender-reference/extracted/KK Tender tool.txt; docs/product/RFP_Leverandørens_svar_utdrag.txt; docs/tender-reference/extracted/HSØ/02.00-Tietoevry-SSA-L-Bilag 2-Leverandørens beskrivelse av Tjenesten.txt | AD4: Anton: Confirm verify-tekst; opdatér review status efter tjek. | AF4: Draft | AG4: uim-esdh-full-2026-07-07
A5: 4 | B5: MK-4 | C5: Bilag 1.b | D5: Generelle krav | E5: GDPR – Ret til indsigt i egne personoplysninger | F5: ESDH-løsningen skal understøtte fremsøgning, sammenstilling og udlevering af personoplysninger om den registrerede i overensstemmelse med GDPR-artikel 15. ESDH-løsningen skal ligeledes understøtte behandling af anmodninger fremsat af en lovlig repræsentant for den registrerede, herunder forældremyndighed eller værgemål. Udleveringen skal kunne leveres i et almindelig læsbart format og skal kunne fremsendes til den registrerede via Digital Post, sikker e-mail og fjernprint. | G5: Mindstekrav | H5: =IF(G5="Evalueringskrav","Answer",(IF(G5="Krav","Check",(IF(G5="Mindstekrav","Verify",""))))) | I5: Ja | L5: Anton | O5: 1. Fully met | U5: Not Started | V5: =IF(U5="Not Started",0%,IF(U5="Started",50%,IF(U5="Ready for review",70%,IF(U5="Reviewed - Content",80%,IF(U5="Reviewed - Format",90%,IF(U5="Done",100%,"")))))) | W5: 2026-07-07 | X5: Cursor / tender-response (batch) | Y5: Met | Z5: Verified | AA5: Verify: GDPR – Ret til indsigt i egne personoplysninger — vurderet opfyldt (tool: 1. Fully met). | AC5: docs/tender-reference/extracted/KK Tender tool.txt; docs/tender-reference/extracted/Nationalbanken/Bilag 3.i Leverandørens Løsningsbeskrivelse.txt; docs/tender-reference/extracted/Nationalbanken/Underbilag 6B - Testplan og Leverandørens prøveprincipper, metoder og -værktøjer (1).txt | AD5: Anton: Confirm verify-tekst; opdatér review status efter tjek. | AF5: Draft | AG5: uim-esdh-full-2026-07-07
A6: 5 | B6: MK-5 | C6: Bilag 1.b | D6: Generelle krav | E6: Anmodninger fra registrerede | F6: ESDH-løsningen skal understøtte håndtering af indsigts-, slette- og berigtigelsesanmodninger fra de registrerede i Løsningen. | G6: Mindstekrav | H6: =IF(G6="Evalueringskrav","Answer",(IF(G6="Krav","Check",(IF(G6="Mindstekrav","Verify",""))))) | I6: Ja | L6: Anton | O6: 1. Fully met | U6: Not Started | V6: =IF(U6="Not Started",0%,IF(U6="Started",50%,IF(U6="Ready for review",70%,IF(U6="Reviewed - Content",80%,IF(U6="Reviewed - Format",90%,IF(U6="Done",100%,"")))))) | W6: 2026-07-07 | X6: Cursor / tender-response (batch) | Y6: Met | Z6: Verified | AA6: Verify: Anmodninger fra registrerede — vurderet opfyldt (tool: 1. Fully met). | AC6: docs/tender-reference/extracted/Nationalbanken/Bilag 3.i Leverandørens Løsningsbeskrivelse.txt; docs/tender-reference/extracted/KK Tender tool.txt; docs/tender-reference/extracted/Nationalbanken/Bilag 1.i Leverandørens Løsningsbeskrivelse.txt | AD6: Anton: Confirm verify-tekst; opdatér review status efter tjek. | AF6: Draft | AG6: uim-esdh-full-2026-07-07
A7: 6 | B7: MK-6 | C7: Bilag 1.b | D7: Generelle krav | E7: Håndtering af sletteregler | F7: ESDH-løsningen skal understøtte håndtering af sletteregler, herunder bevaringskoder, for både midlertidig og permanent sletning. ESDH-løsningen skal understøtte, at sletning alene kan foretages af Brugere med de nødvendige rettigheder, herunder at rettigheder til permanent sletning og midlertidig sletning kan adskilles. Sletteregler skal kunne anvendes på alle Entiteter i Løsningen. | G7: Mindstekrav | H7: =IF(G7="Evalueringskrav","Answer",(IF(G7="Krav","Check",(IF(G7="Mindstekrav","Verify",""))))) | I7: Ja | L7: Morten | O7: 3. Not able to meet | P7: ADN: "Sletteregler for alle entiteter", kan vi sige at vi har det på kontakter? | U7: Not Started | V7: =IF(U7="Not Started",0%,IF(U7="Started",50%,IF(U7="Ready for review",70%,IF(U7="Reviewed - Content",80%,IF(U7="Reviewed - Format",90%,IF(U7="Done",100%,"")))))) | W7: 2026-07-07 | X7: Cursor / tender-response | Y7: Partial | Z7: Verified (sag/dokument/fil); Lead (alle Entiteter) | AA7: Sletteregler og bevaringskoder for sag, dokument og fil; midlertidig vs. permanent sletning med adskilte rettigheder (disposal/purge, skjul permanent sletning for sagsbehandlere). Jf. MK-7 og MK-117. | AB7: «Alle Entiteter» er uafklaret: kontakter har sletning (MK-62) men ikke samme sletteregel-model; øvrige entitetstyper ikke dokumenteret. Tool-rating stadig 3. Not able to meet — afstem internt før opdatering af kolonne O. | AC7: HSØ Bilag 2 kassasjon; Ratatoskr Retention (Disposal), Disposal, Purge, File; MK-7, MK-117, MK-14; MK-62 (ikke dækning for MK-6) | AD7: Q&A: præcisér hvad Ordregiver mener med «alle Entiteter». Koordinér med Anton (MK-7/MK-117/MK-14). Opdatér ikke kolonne O før review. | AF7: Draft | AG7: uim-mk6-2026-07-07
A8: 7 | B8: MK-7 | C8: Bilag 1.b | D8: Generelle krav | E8: Opsætning af slettepolitikker | F8: ESDH-løsningen skal understøtte, at Kunden selv uden Leverdørens involvering kan konfigurere slettepolitikker i Løsningens administrationsmodul. | G8: Mindstekrav | H8: =IF(G8="Evalueringskrav","Answer",(IF(G8="Krav","Check",(IF(G8="Mindstekrav","Verify",""))))) | I8: Ja | L8: Anton | O8: 1. Fully met | U8: Not Started | V8: =IF(U8="Not Started",0%,IF(U8="Started",50%,IF(U8="Ready for review",70%,IF(U8="Reviewed - Content",80%,IF(U8="Reviewed - Format",90%,IF(U8="Done",100%,"")))))) | W8: 2026-07-07 | X8: Cursor / tender-response (batch) | Y8: Met | Z8: Verified | AA8: Verify: Opsætning af slettepolitikker — vurderet opfyldt (tool: 1. Fully met). | AC8: docs/tender-reference/extracted/KUM-SLKS/Bilag 3 - Kravspecifikation.txt; docs/tender-reference/extracted/Nationalbanken/Bilag 3.i Leverandørens Løsningsbeskrivelse.txt; docs/tender-reference/extracted/KUM-SLKS/Bilag 1 - Tidsplan.txt | AD8: Anton: Confirm verify-tekst; opdatér review status efter tjek. | AF8: Draft | AG8: uim-esdh-full-2026-07-07
A9: 8 | B9: MK-8 | C9: Bilag 1.b | D9: Generelle krav | E9: Klassifikationskoder | F9: ESDH-løsningen skal understøtte, at klassifikationskoder kan oprettes af Administrator, hvortil Kunden valgfrit kan bestemme hvilke klassifikationskoder Løsningen skal indeholde. | G9: Mindstekrav | H9: =IF(G9="Evalueringskrav","Answer",(IF(G9="Krav","Check",(IF(G9="Mindstekrav","Verify",""))))) | I9: Ja | L9: Anton | O9: 1. Fully met | U9: Not Started | V9: =IF(U9="Not Started",0%,IF(U9="Started",50%,IF(U9="Ready for review",70%,IF(U9="Reviewed - Content",80%,IF(U9="Reviewed - Format",90%,IF(U9="Done",100%,"")))))) | W9: 2026-07-07 | X9: Cursor / tender-response (batch) | Y9: Met | Z9: Verified | AA9: Verify: Klassifikationskoder — vurderet opfyldt (tool: 1. Fully met). | AC9: docs/tender-reference/extracted/Nationalbanken/Bilag 3.i Leverandørens Løsningsbeskrivelse.txt; docs/tender-reference/extracted/KK Tender tool.txt; docs/tender-reference/extracted/KUM-SLKS/Bilag 3 - Kravspecifikation.txt | AD9: Anton: Confirm verify-tekst; opdatér review status efter tjek. | AF9: Draft | AG9: uim-esdh-full-2026-07-07
A10: 9 | B10: MK-9 | C10: Bilag 1.b | D10: Generelle krav | E10: Deling af Entiteter | F10: ESDH-løsningen skal understøtte, at Entiteter kan deles mellem Brugere, såfremt adgangene tillader dette. | G10: Mindstekrav | H10: =IF(G10="Evalueringskrav","Answer",(IF(G10="Krav","Check",(IF(G10="Mindstekrav","Verify",""))))) | I10: Ja | L10: Anton | O10: 1. Fully met | U10: Not Started | V10: =IF(U10="Not Started",0%,IF(U10="Started",50%,IF(U10="Ready for review",70%,IF(U10="Reviewed - Content",80%,IF(U10="Reviewed - Format",90%,IF(U10="Done",100%,"")))))) | W10: 2026-07-07 | X10: Cursor / tender-response (batch) | Y10: Met | Z10: Verified | AA10: Verify: Deling af Entiteter — vurderet opfyldt (tool: 1. Fully met). | AC10: docs/tender-reference/extracted/Nationalbanken/Bilag 3.i Leverandørens Løsningsbeskrivelse.txt; docs/tender-reference/extracted/KK Tender tool.txt; docs/tender-reference/extracted/KUM-SLKS/Bilag 3 - Kravspecifikation.txt | AD10: Anton: Confirm verify-tekst; opdatér review status efter tjek. | AF10: Draft | AG10: uim-esdh-full-2026-07-07
A11: 10 | B11: MK-10 | C11: Bilag 1.b | D11: Generelle krav | E11: Journalplan | F11: ESDH-løsningen skal understøtte en klassisk journalplan eller facetteret journalplan i minimum tre niveauer og emneordsfelter. | G11: Mindstekrav | H11: =IF(G11="Evalueringskrav","Answer",(IF(G11="Krav","Check",(IF(G11="Mindstekrav","Verify",""))))) | I11: Ja | L11: Anton | O11: 1. Fully met | U11: Not Started | V11: =IF(U11="Not Started",0%,IF(U11="Started",50%,IF(U11="Ready for review",70%,IF(U11="Reviewed - Content",80%,IF(U11="Reviewed - Format",90%,IF(U11="Done",100%,"")))))) | W11: 2026-07-07 | X11: Cursor / tender-response (batch) | Y11: Met | Z11: Verified | AA11: Verify: Journalplan — vurderet opfyldt (tool: 1. Fully met). | AC11: docs/tender-reference/extracted/KK Tender tool.txt; docs/tender-reference/extracted/Nationalbanken/Bilag 3.i Leverandørens Løsningsbeskrivelse.txt; docs/tender-reference/extracted/KUM-SLKS/Bilag 1 - Tidsplan.txt | AD11: Anton: Confirm verify-tekst; opdatér review status efter tjek. | AF11: Draft | AG11: uim-esdh-full-2026-07-07
A12: 11 | B12: MK-11 | C12: Bilag 1.b | D12: Generelle krav | E12: Oprettelse af brevskabeloner | F12: ESDH-løsningen skal understøtte oprettelse af breve baseret på Kundens brevskabeloner i Dynamic Template. | G12: Mindstekrav | H12: =IF(G12="Evalueringskrav","Answer",(IF(G12="Krav","Check",(IF(G12="Mindstekrav","Verify",""))))) | I12: Ja | L12: Anton | N12: Template Connect | O12: 1. Fully met | U12: Not Started | V12: =IF(U12="Not Started",0%,IF(U12="Started",50%,IF(U12="Ready for review",70%,IF(U12="Reviewed - Content",80%,IF(U12="Reviewed - Format",90%,IF(U12="Done",100%,"")))))) | W12: 2026-07-07 | X12: Cursor / tender-response (batch) | Y12: Met | Z12: Verified | AA12: Verify: Oprettelse af brevskabeloner — vurderet opfyldt (tool: 1. Fully met). | AC12: docs/tender-reference/extracted/KK Tender tool.txt; docs/tender-reference/extracted/Nationalbanken/Bilag 3.i Leverandørens Løsningsbeskrivelse.txt; docs/tender-reference/extracted/HSØ/02.00-Tietoevry-SSA-L-Bilag 2-Leverandørens beskrivelse av Tjenesten.txt | AD12: Anton: Confirm verify-tekst; opdatér review status efter tjek. | AF12: Draft | AG12: uim-esdh-full-2026-07-07
A13: 12 | B13: K-1 | C13: Bilag 1.b | D13: Generelle krav | E13: Fejlmeddelelser med handlingsanvisninger | F13: ESDH-løsningen skal understøtte, at fejlmeddelelser i ESDH-løsningen inkluderer handlingsanvisning. | G13: Krav | H13: =IF(G13="Evalueringskrav","Answer",(IF(G13="Krav","Check",(IF(G13="Mindstekrav","Verify",""))))) | I13: Ja | L13: Torben | O13: 1. Fully met | P13: ADN: We tend to say yes to this requirement - but it comes with a risc, especially if customer uses same External partner in the implementation project | R13: Yes | U13: Not Started | V13: =IF(U13="Not Started",0%,IF(U13="Started",50%,IF(U13="Ready for review",70%,IF(U13="Reviewed - Content",80%,IF(U13="Reviewed - Format",90%,IF(U13="Done",100%,"")))))) | W13: 2026-07-07 | X13: Cursor / tender-response (batch) | Y13: Met | Z13: Lead | AA13: Check: Fejlmeddelelser med handlingsanvisninger — vurderet opfyldt (tool: 1. Fully met). | AB13: ADN: We tend to say yes to this requirement - but it comes with a risc, especially if customer uses same External partner in the implementation project | AC13: docs/tender-reference/extracted/KK Tender tool.txt; docs/product/RFP_Leverandørens_svar_utdrag.txt; docs/tender-reference/extracted/HSØ/02.00-Tietoevry-SSA-L-Bilag 2-Leverandørens beskrivelse av Tjenesten.txt | AD13: Torben: Confirm verify-tekst; opdatér review status efter tjek. | AF13: Draft | AG13: uim-esdh-full-2026-07-07
A14: 13 | B14: MK-12 | C14: Bilag 1.b | D14: Sager | E14: Oprettelse af Sager | F14: ESDH-løsningen skal understøtte oprettelse og registrering af sager. | G14: Mindstekrav | H14: =IF(G14="Evalueringskrav","Answer",(IF(G14="Krav","Check",(IF(G14="Mindstekrav","Verify",""))))) | I14: Ja | L14: Anton | O14: 1. Fully met | U14: Not Started | V14: =IF(U14="Not Started",0%,IF(U14="Started",50%,IF(U14="Ready for review",70%,IF(U14="Reviewed - Content",80%,IF(U14="Reviewed - Format",90%,IF(U14="Done",100%,"")))))) | W14: 2026-07-07 | X14: Cursor / tender-response (batch) | Y14: Met | Z14: Verified | AA14: Verify: Oprettelse af Sager — vurderet opfyldt (tool: 1. Fully met). | AC14: docs/tender-reference/extracted/KK Tender tool.txt; docs/tender-reference/extracted/KUM-SLKS/Bilag 3 - 11.8 - Kravspecifikation - Processtyring (1).txt; docs/tender-reference/extracted/KUM-SLKS/Bilag 3 - Kravspecifikation.txt | AD14: Anton: Confirm verify-tekst; opdatér review status efter tjek. | AF14: Draft | AG14: uim-esdh-full-2026-07-07
A15: 14 | B15: MK-13 | C15: Bilag 1.b | D15: Sager | E15: Ændring af sager | F15: ESDH-løsningen skal understøtte ændring af sagens metadata. | G15: Mindstekrav | H15: =IF(G15="Evalueringskrav","Answer",(IF(G15="Krav","Check",(IF(G15="Mindstekrav","Verify",""))))) | I15: Ja | L15: Anton | O15: 1. Fully met | U15: Not Started | V15: =IF(U15="Not Started",0%,IF(U15="Started",50%,IF(U15="Ready for review",70%,IF(U15="Reviewed - Content",80%,IF(U15="Reviewed - Format",90%,IF(U15="Done",100%,"")))))) | W15: 2026-07-07 | X15: Cursor / tender-response (batch) | Y15: Met | Z15: Verified | AA15: Verify: Ændring af sager — vurderet opfyldt (tool: 1. Fully met). | AC15: docs/tender-reference/extracted/KK Tender tool.txt; docs/tender-reference/extracted/KUM-SLKS/Bilag 3 - Kravspecifikation.txt; docs/tender-reference/extracted/Nationalbanken/Bilag 3.i Leverandørens Løsningsbeskrivelse.txt | AD15: Anton: Confirm verify-tekst; opdatér review status efter tjek. | AF15: Draft | AG15: uim-esdh-full-2026-07-07
A16: 15 | B16: MK-14 | C16: Bilag 1.b | D16: Sager | E16: Sletning af sager | F16: ESDH-løsningen skal understøtte både midlertidig og permanent sletning af sager. | G16: Mindstekrav | H16: =IF(G16="Evalueringskrav","Answer",(IF(G16="Krav","Check",(IF(G16="Mindstekrav","Verify",""))))) | I16: Ja | L16: Anton | O16: 1. Fully met | U16: Not Started | V16: =IF(U16="Not Started",0%,IF(U16="Started",50%,IF(U16="Ready for review",70%,IF(U16="Reviewed - Content",80%,IF(U16="Reviewed - Format",90%,IF(U16="Done",100%,"")))))) | W16: 2026-07-07 | X16: Cursor / tender-response (batch) | Y16: Met | Z16: Verified | AA16: Verify: Sletning af sager — vurderet opfyldt (tool: 1. Fully met). | AC16: docs/tender-reference/extracted/KK Tender tool.txt; docs/tender-reference/extracted/Nationalbanken/Bilag 3.i Leverandørens Løsningsbeskrivelse.txt; docs/product/RFP_Leverandørens_svar_utdrag.txt | AD16: Anton: Confirm verify-tekst; opdatér review status efter tjek. | AF16: Draft | AG16: uim-esdh-full-2026-07-07
A17: 16 | B17: MK-15 | C17: Bilag 1.b | D17: Sager | E17: Status | F17: ESDH-løsningen skal understøtte arbejdet med statusser på en sag, f.eks. 'Passiv', 'Under behandling' og 'Lukket' / 'Afsluttet'. ESDH-løsningen skal understøtte, at Kunden selv kan oprette og vedligeholde statuskoder. | G17: Mindstekrav | H17: =IF(G17="Evalueringskrav","Answer",(IF(G17="Krav","Check",(IF(G17="Mindstekrav","Verify",""))))) | I17: Ja | L17: Anton | O17: 1. Fully met | U17: Not Started | V17: =IF(U17="Not Started",0%,IF(U17="Started",50%,IF(U17="Ready for review",70%,IF(U17="Reviewed - Content",80%,IF(U17="Reviewed - Format",90%,IF(U17="Done",100%,"")))))) | W17: 2026-07-07 | X17: Cursor / tender-response (batch) | Y17: Met | Z17: Verified | AA17: Verify: Status — vurderet opfyldt (tool: 1. Fully met). | AC17: docs/tender-reference/extracted/Nationalbanken/Bilag 3.i Leverandørens Løsningsbeskrivelse.txt; docs/tender-reference/extracted/KK Tender tool.txt; docs/tender-reference/extracted/KUM-SLKS/Bilag 3 - Kravspecifikation.txt | AD17: Anton: Confirm verify-tekst; opdatér review status efter tjek. | AF17: Draft | AG17: uim-esdh-full-2026-07-07
A18: 17 | B18: MK-16 | C18: Bilag 1.b | D18: Sager | E18: Sagsnummer | F18: ESDH-løsningen skal understøtte, at hver sag tildeles et unikt sagsnummer automatisk ved oprettelse. | G18: Mindstekrav | H18: =IF(G18="Evalueringskrav","Answer",(IF(G18="Krav","Check",(IF(G18="Mindstekrav","Verify",""))))) | I18: Ja | L18: Anton | O18: 1. Fully met | U18: Not Started | V18: =IF(U18="Not Started",0%,IF(U18="Started",50%,IF(U18="Ready for review",70%,IF(U18="Reviewed - Content",80%,IF(U18="Reviewed - Format",90%,IF(U18="Done",100%,"")))))) | W18: 2026-07-07 | X18: Cursor / tender-response (batch) | Y18: Met | Z18: Verified | AA18: Verify: Sagsnummer — vurderet opfyldt (tool: 1. Fully met). | AC18: docs/tender-reference/extracted/Nationalbanken/Bilag 3.i Leverandørens Løsningsbeskrivelse.txt; docs/tender-reference/extracted/KK Tender tool.txt; docs/tender-reference/extracted/KUM-SLKS/Bilag 3 - Kravspecifikation.txt | AD18: Anton: Confirm verify-tekst; opdatér review status efter tjek. | AF18: Draft | AG18: uim-esdh-full-2026-07-07
A19: 18 | B19: MK-17 | C19: Bilag 1.b | D19: Sager | E19: Ændring af sagstyper | F19: ESDH-løsningen skal understøtte, at en Bruger kan ændre sagstype på sager. | G19: Mindstekrav | H19: =IF(G19="Evalueringskrav","Answer",(IF(G19="Krav","Check",(IF(G19="Mindstekrav","Verify",""))))) | I19: Ja | L19: Anton | O19: 1. Fully met | U19: Not Started | V19: =IF(U19="Not Started",0%,IF(U19="Started",50%,IF(U19="Ready for review",70%,IF(U19="Reviewed - Content",80%,IF(U19="Reviewed - Format",90%,IF(U19="Done",100%,"")))))) | W19: 2026-07-07 | X19: Cursor / tender-response (batch) | Y19: Met | Z19: Verified | AA19: Verify: Ændring af sagstyper — vurderet opfyldt (tool: 1. Fully met). | AC19: docs/tender-reference/extracted/KK Tender tool.txt; docs/tender-reference/extracted/KUM-SLKS/Bilag 3 - Kravspecifikation.txt; docs/tender-reference/extracted/Nationalbanken/Bilag 3.i Leverandørens Løsningsbeskrivelse.txt | AD19: Anton: Confirm verify-tekst; opdatér review status efter tjek. | AF19: Draft | AG19: uim-esdh-full-2026-07-07
A20: 19 | B20: MK-18 | C20: Bilag 1.b | D20: Sager | E20: Sagens frister | F20: ESDH-løsningen skal understøtte, at der kan indsættes, rettes og fjernes frister på alle sagstyper. Fristen skal som minimum bestå af en fristtype, fristdato og fristansvarlig. | G20: Mindstekrav | H20: =IF(G20="Evalueringskrav","Answer",(IF(G20="Krav","Check",(IF(G20="Mindstekrav","Verify",""))))) | I20: Ja | L20: Anton | O20: 1. Fully met | P20: ADN:Configure field called "Fristtype" | U20: Not Started | V20: =IF(U20="Not Started",0%,IF(U20="Started",50%,IF(U20="Ready for review",70%,IF(U20="Reviewed - Content",80%,IF(U20="Reviewed - Format",90%,IF(U20="Done",100%,"")))))) | W20: 2026-07-07 | X20: Cursor / tender-response (batch) | Y20: Met | Z20: Verified | AA20: Verify: Sagens frister — vurderet opfyldt (tool: 1. Fully met). | AB20: ADN:Configure field called "Fristtype" | AC20: docs/tender-reference/extracted/Nationalbanken/Bilag 3.i Leverandørens Løsningsbeskrivelse.txt; docs/tender-reference/extracted/KUM-SLKS/Bilag 3 - Kravspecifikation.txt; docs/tender-reference/extracted/KK Tender tool.txt | AD20: Anton: Confirm verify-tekst; opdatér review status efter tjek. | AF20: Draft | AG20: uim-esdh-full-2026-07-07
A21: 20 | B21: MK-19 | C21: Bilag 1.b | D21: Sager | E21: Afdelingsspecifikke frister | F21: ESDH-løsningen skal understøtte, at Brugere kan indsætte, rette og fjerne én eller flere afdelingsspecifikke frister på sager. | G21: Mindstekrav | H21: =IF(G21="Evalueringskrav","Answer",(IF(G21="Krav","Check",(IF(G21="Mindstekrav","Verify",""))))) | I21: Ja | L21: Anton | O21: 1. Fully met | U21: Not Started | V21: =IF(U21="Not Started",0%,IF(U21="Started",50%,IF(U21="Ready for review",70%,IF(U21="Reviewed - Content",80%,IF(U21="Reviewed - Format",90%,IF(U21="Done",100%,"")))))) | W21: 2026-07-07 | X21: Cursor / tender-response (batch) | Y21: Met | Z21: Verified | AA21: Verify: Afdelingsspecifikke frister — vurderet opfyldt (tool: 1. Fully met). | AC21: docs/tender-reference/extracted/KUM-SLKS/Bilag 3 - Kravspecifikation.txt; docs/tender-reference/extracted/Nationalbanken/Bilag 3.i Leverandørens Løsningsbeskrivelse.txt; docs/tender-reference/extracted/KK Tender tool.txt | AD21: Anton: Confirm verify-tekst; opdatér review status efter tjek. | AF21: Draft | AG21: uim-esdh-full-2026-07-07
A22: 21 | B22: MK-20 | C22: Bilag 1.b | D22: Sager | E22: Samlesager | F22: ESDH-løsningen skal understøtte oprettelse af samlesager. Det skal være muligt for Brugeren at tilknytte enkle sager til samlesager. | G22: Mindstekrav | H22: =IF(G22="Evalueringskrav","Answer",(IF(G22="Krav","Check",(IF(G22="Mindstekrav","Verify",""))))) | I22: Ja | L22: Anton | O22: 1. Fully met | U22: Not Started | V22: =IF(U22="Not Started",0%,IF(U22="Started",50%,IF(U22="Ready for review",70%,IF(U22="Reviewed - Content",80%,IF(U22="Reviewed - Format",90%,IF(U22="Done",100%,"")))))) | W22: 2026-07-07 | X22: Cursor / tender-response (batch) | Y22: Met | Z22: Verified | AA22: Verify: Samlesager — vurderet opfyldt (tool: 1. Fully met). | AC22: docs/tender-reference/extracted/Nationalbanken/Bilag 3.i Leverandørens Løsningsbeskrivelse.txt; docs/tender-reference/extracted/KK Tender tool.txt; docs/tender-reference/extracted/KUM-SLKS/Bilag 3 - 11.8 - Kravspecifikation - Processtyring (1).txt | AD22: Anton: Confirm verify-tekst; opdatér review status efter tjek. | AF22: Draft | AG22: uim-esdh-full-2026-07-07
A23: 22 | B23: MK-21 | C23: Bilag 1.b | D23: Sager | E23: Oprettelse af hierarkisk samling | F23: ESDH-løsningen skal understøtte oprettelsesfunktion til organisering og hierarkisk visning af samling af relaterede sager. | G23: Mindstekrav | H23: =IF(G23="Evalueringskrav","Answer",(IF(G23="Krav","Check",(IF(G23="Mindstekrav","Verify",""))))) | I23: Ja | L23: Eva | O23: 1. Fully met | P23: ADN: Im unsure what they mean with this requirement. - is this "Træstrukturen"? | U23: Not Started | V23: =IF(U23="Not Started",0%,IF(U23="Started",50%,IF(U23="Ready for review",70%,IF(U23="Reviewed - Content",80%,IF(U23="Reviewed - Format",90%,IF(U23="Done",100%,"")))))) | W23: 2026-07-07 | X23: Cursor / tender-response (batch) | Y23: Met | Z23: Verified | AA23: Verify: Oprettelse af hierarkisk samling — vurderet opfyldt (tool: 1. Fully met). | AB23: ADN: Im unsure what they mean with this requirement. - is this "Træstrukturen"? | AC23: docs/tender-reference/extracted/Nationalbanken/Bilag 3.i Leverandørens Løsningsbeskrivelse.txt; docs/tender-reference/extracted/KK Tender tool.txt; docs/tender-reference/extracted/KUM-SLKS/Bilag 3 - Kravspecifikation.txt | AD23: Eva: Confirm verify-tekst; opdatér review status efter tjek. | AF23: Draft | AG23: uim-esdh-full-2026-07-07
A24: 23 | B24: MK-22 | C24: Bilag 1.b | D24: Sager | E24: Referencer | F24: ESDH-løsningen skal understøtte oprettelse af referencer mellem sager ved at etablere links mellem sager. Det skal fremgå tydeligt af den enkelte sag, at den er relateret til en anden. | G24: Mindstekrav | H24: =IF(G24="Evalueringskrav","Answer",(IF(G24="Krav","Check",(IF(G24="Mindstekrav","Verify",""))))) | I24: Ja | L24: Anton | O24: 1. Fully met | U24: Not Started | V24: =IF(U24="Not Started",0%,IF(U24="Started",50%,IF(U24="Ready for review",70%,IF(U24="Reviewed - Content",80%,IF(U24="Reviewed - Format",90%,IF(U24="Done",100%,"")))))) | W24: 2026-07-07 | X24: Cursor / tender-response (batch) | Y24: Met | Z24: Verified | AA24: Verify: Referencer — vurderet opfyldt (tool: 1. Fully met). | AC24: docs/tender-reference/extracted/KK Tender tool.txt; docs/tender-reference/extracted/Nationalbanken/Bilag 3.i Leverandørens Løsningsbeskrivelse.txt; docs/tender-reference/extracted/KUM-SLKS/Bilag 3 - Kravspecifikation.txt | AD24: Anton: Confirm verify-tekst; opdatér review status efter tjek. | AF24: Draft | AG24: uim-esdh-full-2026-07-07
A25: 24 | B25: MK-23 | C25: Bilag 1.b | D25: Sager | E25: Fremvisning af parter | F25: ESDH-løsningen skal understøtte, at sagens parter kan vises enten i sagens overbliksbillede eller i en dedikeret fane. | G25: Mindstekrav | H25: =IF(G25="Evalueringskrav","Answer",(IF(G25="Krav","Check",(IF(G25="Mindstekrav","Verify",""))))) | I25: Ja | L25: Anton | O25: 1. Fully met | U25: Not Started | V25: =IF(U25="Not Started",0%,IF(U25="Started",50%,IF(U25="Ready for review",70%,IF(U25="Reviewed - Content",80%,IF(U25="Reviewed - Format",90%,IF(U25="Done",100%,"")))))) | W25: 2026-07-07 | X25: Cursor / tender-response (batch) | Y25: Met | Z25: Verified | AA25: Verify: Fremvisning af parter — vurderet opfyldt (tool: 1. Fully met). | AC25: docs/tender-reference/extracted/Nationalbanken/Bilag 3.i Leverandørens Løsningsbeskrivelse.txt; docs/tender-reference/extracted/KUM-SLKS/Bilag 3 - Kravspecifikation.txt; docs/tender-reference/extracted/KK Tender tool.txt | AD25: Anton: Confirm verify-tekst; opdatér review status efter tjek. | AF25: Draft | AG25: uim-esdh-full-2026-07-07
A26: 25 | B26: MK-24 | C26: Bilag 1.b | D26: Sager | E26: Partsrolle | F26: ESDH-løsningen skal understøtte, at en kontakt kan tilknyttes til en sag og at kontakten kan have en konkret partsrolle på sagen. | G26: Mindstekrav | H26: =IF(G26="Evalueringskrav","Answer",(IF(G26="Krav","Check",(IF(G26="Mindstekrav","Verify",""))))) | I26: Ja | L26: Anton | O26: 1. Fully met | U26: Not Started | V26: =IF(U26="Not Started",0%,IF(U26="Started",50%,IF(U26="Ready for review",70%,IF(U26="Reviewed - Content",80%,IF(U26="Reviewed - Format",90%,IF(U26="Done",100%,"")))))) | W26: 2026-07-07 | X26: Cursor / tender-response (batch) | Y26: Met | Z26: Verified | AA26: Verify: Partsrolle — vurderet opfyldt (tool: 1. Fully met). | AC26: docs/tender-reference/extracted/KUM-SLKS/Bilag 3 - Kravspecifikation.txt; docs/tender-reference/extracted/Nationalbanken/Bilag 3.i Leverandørens Løsningsbeskrivelse.txt; docs/product/RFP_Leverandørens_svar_utdrag.txt | AD26: Anton: Confirm verify-tekst; opdatér review status efter tjek. | AF26: Draft | AG26: uim-esdh-full-2026-07-07
A27: 26 | B27: MK-25 | C27: Bilag 1.b | D27: Sager | E27: Intern overdragelse af sagsansvar | F27: ESDH-løsningen skal understøtte, at en sag kan overdrages/flyttes til en anden sagsbehandler eller et andet team i organisationen. | G27: Mindstekrav | H27: =IF(G27="Evalueringskrav","Answer",(IF(G27="Krav","Check",(IF(G27="Mindstekrav","Verify",""))))) | I27: Ja | L27: Anton | O27: 1. Fully met | U27: Not Started | V27: =IF(U27="Not Started",0%,IF(U27="Started",50%,IF(U27="Ready for review",70%,IF(U27="Reviewed - Content",80%,IF(U27="Reviewed - Format",90%,IF(U27="Done",100%,"")))))) | W27: 2026-07-07 | X27: Cursor / tender-response (batch) | Y27: Met | Z27: Verified | AA27: Verify: Intern overdragelse af sagsansvar — vurderet opfyldt (tool: 1. Fully met). | AC27: docs/tender-reference/extracted/KUM-SLKS/Bilag 3 - Kravspecifikation.txt; docs/product/RFP_Leverandørens_svar_utdrag.txt; docs/tender-reference/extracted/KK Tender tool.txt | AD27: Anton: Confirm verify-tekst; opdatér review status efter tjek. | AF27: Draft | AG27: uim-esdh-full-2026-07-07
A28: 27 | B28: MK-26 | C28: Bilag 1.b | D28: Sager | E28: Genåbning og opdatering af lukkede sager | F28: ESDH-løsningen skal understøtte, at en formelt afsluttet og lukket sag kan genåbnes af en Bruger, hvis der er behov for at opdatere sagsdata. Sager afleveret til Rigsarkivet skal være undtaget, og skal ikke kunne genåbnes efter aflevering. | G28: Mindstekrav | H28: =IF(G28="Evalueringskrav","Answer",(IF(G28="Krav","Check",(IF(G28="Mindstekrav","Verify",""))))) | I28: Ja | L28: Anton | O28: 1. Fully met | P28: ADN: Configure historic cases with closed Matrix | U28: Not Started | V28: =IF(U28="Not Started",0%,IF(U28="Started",50%,IF(U28="Ready for review",70%,IF(U28="Reviewed - Content",80%,IF(U28="Reviewed - Format",90%,IF(U28="Done",100%,"")))))) | W28: 2026-07-07 | X28: Cursor / tender-response (batch) | Y28: Met | Z28: Verified | AA28: Verify: Genåbning og opdatering af lukkede sager — vurderet opfyldt (tool: 1. Fully met). | AB28: ADN: Configure historic cases with closed Matrix | AC28: docs/tender-reference/extracted/Nationalbanken/Bilag 3.i Leverandørens Løsningsbeskrivelse.txt; docs/tender-reference/extracted/KK Tender tool.txt; docs/tender-reference/extracted/KUM-SLKS/Bilag 3 - Kravspecifikation.txt | AD28: Anton: Confirm verify-tekst; opdatér review status efter tjek. | AF28: Draft | AG28: uim-esdh-full-2026-07-07
A29: 28 | B29: MK-27 | C29: Bilag 1.b | D29: Sager | E29: Sagskopi | F29: ESDH-løsningen skal understøtte oprettelse af en sagskopi, hvor den oprindelige sags metadata overføres til sagskopien. I forbindelse med oprettelse af sagskopien skal Brugeren valgfrit kunne vælge om sagens parter, Dokumenter og øvrigt metadata skal overføres til sagskopien. Metadata på begge sager skal kunne redigeres efterfølgende. | G29: Mindstekrav | H29: =IF(G29="Evalueringskrav","Answer",(IF(G29="Krav","Check",(IF(G29="Mindstekrav","Verify",""))))) | I29: Ja | L29: Anton | O29: 1. Fully met | P29: ADN: copy documents is part of eDoc merger, so Yes | U29: Not Started | V29: =IF(U29="Not Started",0%,IF(U29="Started",50%,IF(U29="Ready for review",70%,IF(U29="Reviewed - Content",80%,IF(U29="Reviewed - Format",90%,IF(U29="Done",100%,"")))))) | W29: 2026-07-07 | X29: Cursor / tender-response (batch) | Y29: Met | Z29: Verified | AA29: Verify: Sagskopi — vurderet opfyldt (tool: 1. Fully met). | AB29: ADN: copy documents is part of eDoc merger, so Yes | AC29: docs/tender-reference/extracted/Nationalbanken/Bilag 3.i Leverandørens Løsningsbeskrivelse.txt; docs/tender-reference/extracted/KK Tender tool.txt; docs/tender-reference/extracted/KUM-SLKS/Bilag 3 - Kravspecifikation.txt | AD29: Anton: Confirm verify-tekst; opdatér review status efter tjek. | AF29: Draft | AG29: uim-esdh-full-2026-07-07
A30: 29 | B30: MK-28 | C30: Bilag 1.b | D30: Sager | E30: Noter | F30: ESDH-løsningen skal understøtte, at der kan oprettes noter på sager. Oplysninger om sagsbehandler, dato og klokkeslæt skal fremgå af noten. Alle Brugere med adgang til sagen skal kunne se agere på noten i sagsbehandlingen. | G30: Mindstekrav | H30: =IF(G30="Evalueringskrav","Answer",(IF(G30="Krav","Check",(IF(G30="Mindstekrav","Verify",""))))) | I30: Ja | L30: Anton | O30: 1. Fully met | U30: Not Started | V30: =IF(U30="Not Started",0%,IF(U30="Started",50%,IF(U30="Ready for review",70%,IF(U30="Reviewed - Content",80%,IF(U30="Reviewed - Format",90%,IF(U30="Done",100%,"")))))) | W30: 2026-07-07 | X30: Cursor / tender-response (batch) | Y30: Met | Z30: Verified | AA30: Verify: Noter — vurderet opfyldt (tool: 1. Fully met). | AC30: docs/tender-reference/extracted/Nationalbanken/Bilag 3.i Leverandørens Løsningsbeskrivelse.txt; docs/tender-reference/extracted/KK Tender tool.txt; docs/tender-reference/extracted/KUM-SLKS/Bilag 3 - Kravspecifikation.txt | AD30: Anton: Confirm verify-tekst; opdatér review status efter tjek. | AF30: Draft | AG30: uim-esdh-full-2026-07-07
A31: 30 | B31: MK-29 | C31: Bilag 1.b | D31: Sager | E31: Journalisering | F31: ESDH-løsningen skal understøtte, at Brugere manuelt kan journalisere og gemme Dokumenter, korrespondancer samt interne og eksterne beskeder på sager. | G31: Mindstekrav | H31: =IF(G31="Evalueringskrav","Answer",(IF(G31="Krav","Check",(IF(G31="Mindstekrav","Verify",""))))) | I31: Ja | L31: Anton | O31: 1. Fully met | U31: Not Started | V31: =IF(U31="Not Started",0%,IF(U31="Started",50%,IF(U31="Ready for review",70%,IF(U31="Reviewed - Content",80%,IF(U31="Reviewed - Format",90%,IF(U31="Done",100%,"")))))) | W31: 2026-07-07 | X31: Cursor / tender-response (batch) | Y31: Met | Z31: Verified | AA31: Verify: Journalisering — vurderet opfyldt (tool: 1. Fully met). | AC31: docs/tender-reference/extracted/KK Tender tool.txt; docs/tender-reference/extracted/Nationalbanken/Bilag 3.i Leverandørens Løsningsbeskrivelse.txt; docs/tender-reference/extracted/KUM-SLKS/Bilag 3 - Kravspecifikation.txt | AD31: Anton: Confirm verify-tekst; opdatér review status efter tjek. | AF31: Draft | AG31: uim-esdh-full-2026-07-07
A32: 31 | B32: MK-30 | C32: Bilag 1.b | D32: Sager | E32: Præsentation af hierarkiske samlinger | F32: ESDH-løsningen skal understøtte visning af hierarkiske samlinger af relaterede sager fra søgningslister og visningslister. | G32: Mindstekrav | H32: =IF(G32="Evalueringskrav","Answer",(IF(G32="Krav","Check",(IF(G32="Mindstekrav","Verify",""))))) | I32: Ja | L32: Eva | O32: 3. Not able to meet | P32: ADN: Det er kludret formuleret - men jeg tolker det til, at de fra en søgning på et projekt, skal kunne se relaterede sager i resultatlisterne.. Det er udfordrende | U32: Not Started | V32: =IF(U32="Not Started",0%,IF(U32="Started",50%,IF(U32="Ready for review",70%,IF(U32="Reviewed - Content",80%,IF(U32="Reviewed - Format",90%,IF(U32="Done",100%,"")))))) | W32: 2026-07-07 | X32: Cursor / tender-response (MCP-enriched) | Y32: Not met | Z32: Lead | AA32: Verify: Præsentation af hierarkiske samlinger — gap ift. kravtekst; eskalér commitment eller afklaring. | AB32: ADN: Det er kludret formuleret - men jeg tolker det til, at de fra en søgning på et projekt, skal kunne se relaterede sager i resultatlisterne.. Det er udfordrende | Red flag: Det er kludret formuleret - men jeg tolker det til, at de fra en søgning på et projekt, skal kunne se relaterede sager i resultatlisterne.. Det er udfordrende | AC32: Wiki: EArchive 360°; Setup of Continuous Transfer | AD32: Eva: Commitment/no-bid beslutning; overvej Q&A til ordregiver. | AF32: Draft | AG32: uim-esdh-full-2026-07-07
A33: 32 | B33: MK-31 | C33: Bilag 1.b | D33: Sager | E33: Antal frister | F33: ESDH-løsningen skal understøtte, at en sag kan have flere frister tilknyttet. Fristerne skal vises på en logisk og overskuelig måde i brugergrænsefladen, så Brugeren nemt kan se fristtype, status og tidspunkt for kommende frister. | G33: Mindstekrav | H33: =IF(G33="Evalueringskrav","Answer",(IF(G33="Krav","Check",(IF(G33="Mindstekrav","Verify",""))))) | I33: Ja | L33: Anton | O33: 1. Fully met | U33: Not Started | V33: =IF(U33="Not Started",0%,IF(U33="Started",50%,IF(U33="Ready for review",70%,IF(U33="Reviewed - Content",80%,IF(U33="Reviewed - Format",90%,IF(U33="Done",100%,"")))))) | W33: 2026-07-07 | X33: Cursor / tender-response (batch) | Y33: Met | Z33: Verified | AA33: Verify: Antal frister — vurderet opfyldt (tool: 1. Fully met). | AC33: docs/tender-reference/extracted/Nationalbanken/Bilag 3.i Leverandørens Løsningsbeskrivelse.txt; docs/tender-reference/extracted/KK Tender tool.txt; docs/tender-reference/extracted/KUM-SLKS/Bilag 3 - Kravspecifikation.txt | AD33: Anton: Confirm verify-tekst; opdatér review status efter tjek. | AF33: Draft | AG33: uim-esdh-full-2026-07-07
A34: 33 | B34: MK-32 | C34: Bilag 1.b | D34: Sager | E34: Noter – Journalisering på sag | F34: ESDH-løsningen skal understøtte, at noter kan konverteres til et Dokument med en tilhørende Fil, som kan journaliseres på den tilknyttede sag. | G34: Mindstekrav | H34: =IF(G34="Evalueringskrav","Answer",(IF(G34="Krav","Check",(IF(G34="Mindstekrav","Verify",""))))) | I34: Ja | L34: Anton | O34: 1. Fully met | P34: ADN: Configure Case Note summary functionality | U34: Not Started | V34: =IF(U34="Not Started",0%,IF(U34="Started",50%,IF(U34="Ready for review",70%,IF(U34="Reviewed - Content",80%,IF(U34="Reviewed - Format",90%,IF(U34="Done",100%,"")))))) | W34: 2026-07-07 | X34: Cursor / tender-response (batch) | Y34: Met | Z34: Verified | AA34: Verify: Noter – Journalisering på sag — vurderet opfyldt (tool: 1. Fully met). | AB34: ADN: Configure Case Note summary functionality | AC34: docs/tender-reference/extracted/KK Tender tool.txt; docs/tender-reference/extracted/KUM-SLKS/Bilag 3 - Kravspecifikation.txt; docs/tender-reference/extracted/Nationalbanken/Bilag 3.i Leverandørens Løsningsbeskrivelse.txt | AD34: Anton: Confirm verify-tekst; opdatér review status efter tjek. | AF34: Draft | AG34: uim-esdh-full-2026-07-07
A35: 34 | B35: MK-33 | C35: Bilag 1.b | D35: Dokumenter | E35: Behandling af Dokumenter | F35: ESDH-løsningen skal understøtte grundlæggende dokumenthåndtering, herunder oprettelse, redigering, versionsstyring og tilknytning af relevante metadata. | G35: Mindstekrav | H35: =IF(G35="Evalueringskrav","Answer",(IF(G35="Krav","Check",(IF(G35="Mindstekrav","Verify",""))))) | I35: Ja | L35: Anton | O35: 1. Fully met | U35: Not Started | V35: =IF(U35="Not Started",0%,IF(U35="Started",50%,IF(U35="Ready for review",70%,IF(U35="Reviewed - Content",80%,IF(U35="Reviewed - Format",90%,IF(U35="Done",100%,"")))))) | W35: 2026-07-07 | X35: Cursor / tender-response (batch) | Y35: Met | Z35: Verified | AA35: Verify: Behandling af Dokumenter — vurderet opfyldt (tool: 1. Fully met). | AC35: docs/tender-reference/extracted/Nationalbanken/Bilag 3.i Leverandørens Løsningsbeskrivelse.txt; docs/tender-reference/extracted/KK Tender tool.txt; docs/tender-reference/extracted/KUM-SLKS/Bilag 3 - Kravspecifikation.txt | AD35: Anton: Confirm verify-tekst; opdatér review status efter tjek. | AF35: Draft | AG35: uim-esdh-full-2026-07-07
A36: 35 | B36: MK-34 | C36: Bilag 1.b | D36: Dokumenter | E36: Oprettelse af felter | F36: ESDH-løsningen skal understøtte, at felter kan oprettes og relateres til Dokumenter af Kunden. | G36: Mindstekrav | H36: =IF(G36="Evalueringskrav","Answer",(IF(G36="Krav","Check",(IF(G36="Mindstekrav","Verify",""))))) | I36: Ja | L36: Anton | O36: 1. Fully met | U36: Not Started | V36: =IF(U36="Not Started",0%,IF(U36="Started",50%,IF(U36="Ready for review",70%,IF(U36="Reviewed - Content",80%,IF(U36="Reviewed - Format",90%,IF(U36="Done",100%,"")))))) | W36: 2026-07-07 | X36: Cursor / tender-response (batch) | Y36: Met | Z36: Verified | AA36: Verify: Oprettelse af felter — vurderet opfyldt (tool: 1. Fully met). | AC36: docs/tender-reference/extracted/KUM-SLKS/Bilag 3 - Kravspecifikation.txt; docs/tender-reference/extracted/KK Tender tool.txt; docs/tender-reference/extracted/KUM-SLKS/Bilag 3 - 11.8 - Kravspecifikation - Processtyring (1).txt | AD36: Anton: Confirm verify-tekst; opdatér review status efter tjek. | AF36: Draft | AG36: uim-esdh-full-2026-07-07
A37: 36 | B37: MK-35 | C37: Bilag 1.b | D37: Dokumenter | E37: Unikt ID | F37: ESDH-løsningen skal understøtte, at alle Dokumenter, Filer, Hoveddokumenter og Bilag har hver deres unikke ID, som skal være synligt i brugergrænsefladen. | G37: Mindstekrav | H37: =IF(G37="Evalueringskrav","Answer",(IF(G37="Krav","Check",(IF(G37="Mindstekrav","Verify",""))))) | I37: Ja | L37: Anton | O37: 1. Fully met | P37: ADN: Hvornår er noget ”synligt i brugergrænsefladen”… vi har recno på filer, men de kræver ”vis egenskaber” for at være synlige. Tjek definitionsbilag for ordet "brugergrænsefladen" Maksimeret visning - ny visning | U37: Not Started | V37: =IF(U37="Not Started",0%,IF(U37="Started",50%,IF(U37="Ready for review",70%,IF(U37="Reviewed - Content",80%,IF(U37="Reviewed - Format",90%,IF(U37="Done",100%,"")))))) | W37: 2026-07-07 | X37: Cursor / tender-response (MCP-enriched) | Y37: Met | Z37: Lead | AA37: Verify: Unikt ID — vurderet opfyldt (tool: 1. Fully met). | AB37: ADN: Hvornår er noget ”synligt i brugergrænsefladen”… vi har recno på filer, men de kræver ”vis egenskaber” for at være synlige. Tjek definitionsbilag for ordet "brugergrænsefladen" Maksimeret visning - ny visning | Red flag: Hvornår er noget ”synligt i brugergrænsefladen”… vi har recno på filer, men de kræver ”vis egenskaber” for at være synlige. | AC37: Wiki: 360° AutoSaver - Technical documentation; Process Engine - Manual | AD37: Anton: Confirm verify-tekst; opdatér review status efter tjek. | AF37: Draft | AG37: uim-esdh-full-2026-07-07
A38: 37 | B38: MK-36 | C38: Bilag 1.b | D38: Dokumenter | E38: Relation mellem sag og Dokument | F38: ESDH-løsningen skal understøtte en obligatorisk relation mellem sag og Dokument. | G38: Mindstekrav | H38: =IF(G38="Evalueringskrav","Answer",(IF(G38="Krav","Check",(IF(G38="Mindstekrav","Verify",""))))) | I38: Ja | L38: Anton | O38: 1. Fully met | U38: Not Started | V38: =IF(U38="Not Started",0%,IF(U38="Started",50%,IF(U38="Ready for review",70%,IF(U38="Reviewed - Content",80%,IF(U38="Reviewed - Format",90%,IF(U38="Done",100%,"")))))) | W38: 2026-07-07 | X38: Cursor / tender-response (batch) | Y38: Met | Z38: Verified | AA38: Verify: Relation mellem sag og Dokument — vurderet opfyldt (tool: 1. Fully met). | AC38: docs/tender-reference/extracted/KK Tender tool.txt; docs/tender-reference/extracted/KUM-SLKS/Bilag 3 - Kravspecifikation.txt; docs/tender-reference/extracted/Nationalbanken/Bilag 3.i Leverandørens Løsningsbeskrivelse.txt | AD38: Anton: Confirm verify-tekst; opdatér review status efter tjek. | AF38: Draft | AG38: uim-esdh-full-2026-07-07
A39: 38 | B39: MK-37 | C39: Bilag 1.b | D39: Dokumenter | E39: Bilag | F39: ESDH-løsningen skal understøtte, at et Hoveddokument kan have et eller flere Bilag. | G39: Mindstekrav | H39: =IF(G39="Evalueringskrav","Answer",(IF(G39="Krav","Check",(IF(G39="Mindstekrav","Verify",""))))) | I39: Ja | L39: Anton | O39: 1. Fully met | U39: Not Started | V39: =IF(U39="Not Started",0%,IF(U39="Started",50%,IF(U39="Ready for review",70%,IF(U39="Reviewed - Content",80%,IF(U39="Reviewed - Format",90%,IF(U39="Done",100%,"")))))) | W39: 2026-07-07 | X39: Cursor / tender-response (batch) | Y39: Met | Z39: Verified | AA39: Verify: Bilag — vurderet opfyldt (tool: 1. Fully met). | AC39: docs/product/RFP_Leverandørens_svar_utdrag.txt; docs/tender-reference/extracted/KUM-SLKS/Bilag 3 - Kravspecifikation.txt; docs/tender-reference/extracted/NND/02.01-Tieto-Bilag 2-Vedlegg-Leverandørens utfyllende svar til kravtabell.txt | AD39: Anton: Confirm verify-tekst; opdatér review status efter tjek. | AF39: Draft | AG39: uim-esdh-full-2026-07-07
A40: 39 | B40: MK-38 | C40: Bilag 1.b | D40: Dokumenter | E40: Valg af Hoveddokument og Bilag | F40: ESDH-løsningen skal understøtte, at Brugeren kan vælge, hvilken Fil der skal være Hoveddokument, og hvilke Filer der skal tilknyttes som Bilag. | G40: Mindstekrav | H40: =IF(G40="Evalueringskrav","Answer",(IF(G40="Krav","Check",(IF(G40="Mindstekrav","Verify",""))))) | I40: Ja | L40: Anton | O40: 1. Fully met | U40: Not Started | V40: =IF(U40="Not Started",0%,IF(U40="Started",50%,IF(U40="Ready for review",70%,IF(U40="Reviewed - Content",80%,IF(U40="Reviewed - Format",90%,IF(U40="Done",100%,"")))))) | W40: 2026-07-07 | X40: Cursor / tender-response (batch) | Y40: Met | Z40: Verified | AA40: Verify: Valg af Hoveddokument og Bilag — vurderet opfyldt (tool: 1. Fully met). | AC40: docs/tender-reference/extracted/KUM-SLKS/Bilag 3 - Kravspecifikation.txt; docs/tender-reference/extracted/Nationalbanken/Bilag 3.i Leverandørens Løsningsbeskrivelse.txt; docs/product/RFP_Leverandørens_svar_utdrag.txt | AD40: Anton: Confirm verify-tekst; opdatér review status efter tjek. | AF40: Draft | AG40: uim-esdh-full-2026-07-07
A41: 40 | B41: MK-39 | C41: Bilag 1.b | D41: Dokumenter | E41: Dokumentets kontakter | F41: ESDH-løsningen skal understøtte, at et indgående eller udgående Dokument kan tilknyttes en kontakt som henholdsvis afsender eller modtager på Dokumentet. | G41: Mindstekrav | H41: =IF(G41="Evalueringskrav","Answer",(IF(G41="Krav","Check",(IF(G41="Mindstekrav","Verify",""))))) | I41: Ja | L41: Anton | O41: 1. Fully met | U41: Not Started | V41: =IF(U41="Not Started",0%,IF(U41="Started",50%,IF(U41="Ready for review",70%,IF(U41="Reviewed - Content",80%,IF(U41="Reviewed - Format",90%,IF(U41="Done",100%,"")))))) | W41: 2026-07-07 | X41: Cursor / tender-response (batch) | Y41: Met | Z41: Verified | AA41: Verify: Dokumentets kontakter — vurderet opfyldt (tool: 1. Fully met). | AC41: docs/tender-reference/extracted/Nationalbanken/Bilag 3.i Leverandørens Løsningsbeskrivelse.txt; docs/tender-reference/extracted/KUM-SLKS/Bilag 3 - Kravspecifikation.txt; docs/tender-reference/extracted/KK Tender tool.txt | AD41: Anton: Confirm verify-tekst; opdatér review status efter tjek. | AF41: Draft | AG41: uim-esdh-full-2026-07-07
A42: 41 | B42: MK-40 | C42: Bilag 1.b | D42: Dokumenter | E42: Versionsstyring | F42: ESDH-løsningen skal understøtte versionsstyring af Filer, så hver version af en Fil kan identificeres. Det skal som udgangspunkt kun være den seneste version, der kan åbnes i redigerbar tilstand. | G42: Mindstekrav | H42: =IF(G42="Evalueringskrav","Answer",(IF(G42="Krav","Check",(IF(G42="Mindstekrav","Verify",""))))) | I42: Ja | L42: Anton | O42: 1. Fully met | U42: Not Started | V42: =IF(U42="Not Started",0%,IF(U42="Started",50%,IF(U42="Ready for review",70%,IF(U42="Reviewed - Content",80%,IF(U42="Reviewed - Format",90%,IF(U42="Done",100%,"")))))) | W42: 2026-07-07 | X42: Cursor / tender-response (batch) | Y42: Met | Z42: Verified | AA42: Verify: Versionsstyring — vurderet opfyldt (tool: 1. Fully met). | AC42: docs/tender-reference/extracted/KK Tender tool.txt; docs/tender-reference/extracted/Nationalbanken/Bilag 3.i Leverandørens Løsningsbeskrivelse.txt; docs/tender-reference/extracted/KUM-SLKS/Bilag 3 - Kravspecifikation.txt | AD42: Anton: Confirm verify-tekst; opdatér review status efter tjek. | AF42: Draft | AG42: uim-esdh-full-2026-07-07
A43: 42 | B43: MK-41 | C43: Bilag 1.b | D43: Dokumenter | E43: Genskabelse af tidligere filversion | F43: ESDH-løsningen skal understøtte, at Brugere kan genskabe en tidligere version af en Fil, så den overskriver den nyeste version. Begge versioner skal bevares i versionshistorikken. | G43: Mindstekrav | H43: =IF(G43="Evalueringskrav","Answer",(IF(G43="Krav","Check",(IF(G43="Mindstekrav","Verify",""))))) | I43: Ja | L43: Anton | O43: 1. Fully met | U43: Not Started | V43: =IF(U43="Not Started",0%,IF(U43="Started",50%,IF(U43="Ready for review",70%,IF(U43="Reviewed - Content",80%,IF(U43="Reviewed - Format",90%,IF(U43="Done",100%,"")))))) | W43: 2026-07-07 | X43: Cursor / tender-response (batch) | Y43: Met | Z43: Verified | AA43: Verify: Genskabelse af tidligere filversion — vurderet opfyldt (tool: 1. Fully met). | AC43: docs/tender-reference/extracted/Nationalbanken/Bilag 3.i Leverandørens Løsningsbeskrivelse.txt; docs/tender-reference/extracted/KK Tender tool.txt; docs/tender-reference/extracted/KUM-SLKS/Bilag 3 - Kravspecifikation.txt | AD43: Anton: Confirm verify-tekst; opdatér review status efter tjek. | AF43: Draft | AG43: uim-esdh-full-2026-07-07
A44: 43 | B44: MK-42 | C44: Bilag 1.b | D44: Dokumenter | E44: Låsning af filversioner ved journalisering | F44: ESDH-løsningen skal understøtte, at et journaliseret Dokuments tidligere filversioner er tilgængelige i Løsningen. | G44: Mindstekrav | H44: =IF(G44="Evalueringskrav","Answer",(IF(G44="Krav","Check",(IF(G44="Mindstekrav","Verify",""))))) | I44: Ja | L44: Anton | O44: 1. Fully met | U44: Not Started | V44: =IF(U44="Not Started",0%,IF(U44="Started",50%,IF(U44="Ready for review",70%,IF(U44="Reviewed - Content",80%,IF(U44="Reviewed - Format",90%,IF(U44="Done",100%,"")))))) | W44: 2026-07-07 | X44: Cursor / tender-response (batch) | Y44: Met | Z44: Verified | AA44: Verify: Låsning af filversioner ved journalisering — vurderet opfyldt (tool: 1. Fully met). | AC44: docs/tender-reference/extracted/KK Tender tool.txt; docs/tender-reference/extracted/KUM-SLKS/Bilag 3 - Kravspecifikation.txt; docs/tender-reference/extracted/Nationalbanken/Bilag 3.i Leverandørens Løsningsbeskrivelse.txt | AD44: Anton: Confirm verify-tekst; opdatér review status efter tjek. | AF44: Draft | AG44: uim-esdh-full-2026-07-07
A45: 44 | B45: MK-43 | C45: Bilag 1.b | D45: Dokumenter | E45: Kopi af Dokument | F45: ESDH-løsningen skal understøtte, at der kan oprettes en kopi af et eksisterende Dokument. Dokumentets tilknyttede Filer, Bilag, metadata og tilknyttede parter skal overføres til det nye Dokument. | G45: Mindstekrav | H45: =IF(G45="Evalueringskrav","Answer",(IF(G45="Krav","Check",(IF(G45="Mindstekrav","Verify",""))))) | I45: Ja | L45: Anton | O45: 1. Fully met | U45: Not Started | V45: =IF(U45="Not Started",0%,IF(U45="Started",50%,IF(U45="Ready for review",70%,IF(U45="Reviewed - Content",80%,IF(U45="Reviewed - Format",90%,IF(U45="Done",100%,"")))))) | W45: 2026-07-07 | X45: Cursor / tender-response (batch) | Y45: Met | Z45: Verified | AA45: Verify: Kopi af Dokument — vurderet opfyldt (tool: 1. Fully met). | AC45: docs/tender-reference/extracted/Nationalbanken/Bilag 3.i Leverandørens Løsningsbeskrivelse.txt; docs/product/RFP_Leverandørens_svar_utdrag.txt; docs/tender-reference/extracted/HSØ/02.00-Tietoevry-SSA-L-Bilag 2-Leverandørens beskrivelse av Tjenesten.txt | AD45: Anton: Confirm verify-tekst; opdatér review status efter tjek. | AF45: Draft | AG45: uim-esdh-full-2026-07-07
A46: 45 | B46: MK-44 | C46: Bilag 1.b | D46: Dokumenter | E46: Omjournalisering af Dokumenter mellem sager | F46: ESDH-løsningen skal understøtte, at Dokumenter med tilknyttede Filer kan omjournaliseres fra én sag til en anden, og at det fremgår af den oprindelige sag, hvilken sag Dokumentet er omjournaliseret til. | G46: Mindstekrav | H46: =IF(G46="Evalueringskrav","Answer",(IF(G46="Krav","Check",(IF(G46="Mindstekrav","Verify",""))))) | I46: Ja | L46: Anton | O46: 1. Fully met | U46: Not Started | V46: =IF(U46="Not Started",0%,IF(U46="Started",50%,IF(U46="Ready for review",70%,IF(U46="Reviewed - Content",80%,IF(U46="Reviewed - Format",90%,IF(U46="Done",100%,"")))))) | W46: 2026-07-07 | X46: Cursor / tender-response (batch) | Y46: Met | Z46: Verified | AA46: Verify: Omjournalisering af Dokumenter mellem sager — vurderet opfyldt (tool: 1. Fully met). | AC46: docs/tender-reference/extracted/KK Tender tool.txt; docs/tender-reference/extracted/KUM-SLKS/Bilag 3 - Kravspecifikation.txt; docs/tender-reference/extracted/Nationalbanken/Bilag 3.i Leverandørens Løsningsbeskrivelse.txt | AD46: Anton: Confirm verify-tekst; opdatér review status efter tjek. | AF46: Draft | AG46: uim-esdh-full-2026-07-07
A47: 46 | B47: MK-45 | C47: Bilag 1.b | D47: Dokumenter | E47: Beskyttelse af journaliserede Dokumenter | F47: ESDH-løsningen skal understøtte, at journaliserede Dokumenter ikke kan slettes af Brugere uden rettigheder. De skal håndteres i overensstemmelse med Løsningens slette- og bevaringsregler. | G47: Mindstekrav | H47: =IF(G47="Evalueringskrav","Answer",(IF(G47="Krav","Check",(IF(G47="Mindstekrav","Verify",""))))) | I47: Ja | L47: Anton | O47: 1. Fully met | U47: Not Started | V47: =IF(U47="Not Started",0%,IF(U47="Started",50%,IF(U47="Ready for review",70%,IF(U47="Reviewed - Content",80%,IF(U47="Reviewed - Format",90%,IF(U47="Done",100%,"")))))) | W47: 2026-07-07 | X47: Cursor / tender-response (batch) | Y47: Met | Z47: Verified | AA47: Verify: Beskyttelse af journaliserede Dokumenter — vurderet opfyldt (tool: 1. Fully met). | AC47: docs/tender-reference/extracted/KK Tender tool.txt; docs/tender-reference/extracted/Nationalbanken/Bilag 3.i Leverandørens Løsningsbeskrivelse.txt; docs/tender-reference/extracted/HSØ/02.00-Tietoevry-SSA-L-Bilag 2-Leverandørens beskrivelse av Tjenesten.txt | AD47: Anton: Confirm verify-tekst; opdatér review status efter tjek. | AF47: Draft | AG47: uim-esdh-full-2026-07-07
A48: 47 | B48: MK-46 | C48: Bilag 1.b | D48: Dokumenter | E48: Noter | F48: ESDH-løsningen skal understøtte, at der kan oprettes noter på Dokumenter. Oplysninger om sagsbehandler, dato og klokkeslæt skal fremgå af noten. Alle Brugere med adgang til Dokumentet skal kunne se agere på noten i sagsbehandlingen. | G48: Mindstekrav | H48: =IF(G48="Evalueringskrav","Answer",(IF(G48="Krav","Check",(IF(G48="Mindstekrav","Verify",""))))) | I48: Ja | L48: Anton | O48: 1. Fully met | U48: Not Started | V48: =IF(U48="Not Started",0%,IF(U48="Started",50%,IF(U48="Ready for review",70%,IF(U48="Reviewed - Content",80%,IF(U48="Reviewed - Format",90%,IF(U48="Done",100%,"")))))) | W48: 2026-07-07 | X48: Cursor / tender-response (batch) | Y48: Met | Z48: Verified | AA48: Verify: Noter — vurderet opfyldt (tool: 1. Fully met). | AC48: docs/tender-reference/extracted/Nationalbanken/Bilag 3.i Leverandørens Løsningsbeskrivelse.txt; docs/tender-reference/extracted/KK Tender tool.txt; docs/tender-reference/extracted/KUM-SLKS/Bilag 3 - Kravspecifikation.txt | AD48: Anton: Confirm verify-tekst; opdatér review status efter tjek. | AF48: Draft | AG48: uim-esdh-full-2026-07-07
A49: 48 | B49: MK-47 | C49: Bilag 1.b | D49: Dokumenter | E49: Dokumentets frister | F49: ESDH-løsningen skal understøtte, at der kan indsættes, rettes og fjernes frister på Dokumenter. Fristen skal som minimum bestå af en fristtype, fristdato og fristansvarlig. | G49: Mindstekrav | H49: =IF(G49="Evalueringskrav","Answer",(IF(G49="Krav","Check",(IF(G49="Mindstekrav","Verify",""))))) | I49: Ja | L49: Anton | O49: 1. Fully met | U49: Not Started | V49: =IF(U49="Not Started",0%,IF(U49="Started",50%,IF(U49="Ready for review",70%,IF(U49="Reviewed - Content",80%,IF(U49="Reviewed - Format",90%,IF(U49="Done",100%,"")))))) | W49: 2026-07-07 | X49: Cursor / tender-response (batch) | Y49: Met | Z49: Verified | AA49: Verify: Dokumentets frister — vurderet opfyldt (tool: 1. Fully met). | AC49: docs/tender-reference/extracted/Nationalbanken/Bilag 3.i Leverandørens Løsningsbeskrivelse.txt; docs/tender-reference/extracted/NND/02.01-Tieto-Bilag 2-Vedlegg-Leverandørens utfyllende svar til kravtabell.txt; docs/product/RFP_Leverandørens_svar_utdrag.txt | AD49: Anton: Confirm verify-tekst; opdatér review status efter tjek. | AF49: Draft | AG49: uim-esdh-full-2026-07-07
A50: 49 | B50: MK-48 | C50: Bilag 1.b | D50: Dokumenter | E50: Afdelingsspecifikke frister | F50: ESDH-løsningen skal understøtte, at Brugere kan indsætte, rette og fjerne én eller flere afdelingsspecifikke frister på Dokumenter. | G50: Mindstekrav | H50: =IF(G50="Evalueringskrav","Answer",(IF(G50="Krav","Check",(IF(G50="Mindstekrav","Verify",""))))) | I50: Ja | L50: Anton | O50: 1. Fully met | U50: Not Started | V50: =IF(U50="Not Started",0%,IF(U50="Started",50%,IF(U50="Ready for review",70%,IF(U50="Reviewed - Content",80%,IF(U50="Reviewed - Format",90%,IF(U50="Done",100%,"")))))) | W50: 2026-07-07 | X50: Cursor / tender-response (batch) | Y50: Met | Z50: Verified | AA50: Verify: Afdelingsspecifikke frister — vurderet opfyldt (tool: 1. Fully met). | AC50: docs/tender-reference/extracted/KUM-SLKS/Bilag 3 - Kravspecifikation.txt; docs/tender-reference/extracted/Nationalbanken/Bilag 3.i Leverandørens Løsningsbeskrivelse.txt; docs/tender-reference/extracted/KK Tender tool.txt | AD50: Anton: Confirm verify-tekst; opdatér review status efter tjek. | AF50: Draft | AG50: uim-esdh-full-2026-07-07
A51: 50 | B51: MK-49 | C51: Bilag 1.b | D51: Dokumenter | E51: Integreret viewer | F51: ESDH-løsningen skal understøtte en integreret dokumentviewer i brugergrænsefladen. Løsningen skal understøtte forhåndsvisning af Dokumenter fra sager, søgninger og listevisninger. ESDH-løsningen skal understøtte, at Brugeren får præsenteret Dokumentets tekst/indhold direkte i Løsningen. | G51: Mindstekrav | H51: =IF(G51="Evalueringskrav","Answer",(IF(G51="Krav","Check",(IF(G51="Mindstekrav","Verify",""))))) | I51: Ja | L51: Eva | N51: Fileviewer | O51: 1. Fully met | P51: ADN: ”Direkte” er problematisk, hvis det forbyder os fra et nyt vindue. | U51: Not Started | V51: =IF(U51="Not Started",0%,IF(U51="Started",50%,IF(U51="Ready for review",70%,IF(U51="Reviewed - Content",80%,IF(U51="Reviewed - Format",90%,IF(U51="Done",100%,"")))))) | W51: 2026-07-07 | X51: Cursor / tender-response (MCP-enriched) | Y51: Met | Z51: Verified | AA51: Verify: Integreret viewer — vurderet opfyldt (tool: 1. Fully met). | AB51: ADN: ”Direkte” er problematisk, hvis det forbyder os fra et nyt vindue. | Red flag: ”Direkte” er problematisk, hvis det forbyder os fra et nyt vindue. | AC51: Ratatoskr: 360° File Viewer (incl Prizm) (release); File (admin-en) | Wiki: Overview of PDF functionality in 360; 6.0 release information | AD51: Eva: Confirm verify-tekst; opdatér review status efter tjek. | AF51: Draft | AG51: uim-esdh-full-2026-07-07
A52: 51 | B52: MK-50 | C52: Bilag 1.b | D52: Dokumenter | E52: Navigation og scrolling i dokumentlister | F52: ESDH-løsningen skal understøtte, at Brugeren kan navigere og scrolle i dokument- og fillistevisninger, og at forhåndsvisningen automatisk opdateres og viser det Dokument/Fil, som Brugeren har navigeret til. | G52: Mindstekrav | H52: =IF(G52="Evalueringskrav","Answer",(IF(G52="Krav","Check",(IF(G52="Mindstekrav","Verify",""))))) | I52: Ja | L52: Hans | O52: 3. Not able to meet | P52: ADN Vores forhåndsvisning ”opdateres ikke automatisk”. Kræver aktivt klik på det dokument/fil der ønskes forhåndsvist. "Navigeret til," kan det tolkes til at brugeren foretager et aktivt klik? ADN: ask question | U52: Not Started | V52: =IF(U52="Not Started",0%,IF(U52="Started",50%,IF(U52="Ready for review",70%,IF(U52="Reviewed - Content",80%,IF(U52="Reviewed - Format",90%,IF(U52="Done",100%,"")))))) | W52: 2026-07-07 | X52: Cursor / tender-response (MCP-enriched) | Y52: Not met | Z52: Lead | AA52: Verify: Navigation og scrolling i dokumentlister — gap ift. kravtekst; eskalér commitment eller afklaring. | AB52: ADN Vores forhåndsvisning ”opdateres ikke automatisk”. Kræver aktivt klik på det dokument/fil der ønskes forhåndsvist. "Navigeret til," kan det tolkes til at brugeren foretager et aktivt klik? ADN: ask question | Red flag: Vores forhåndsvisning ”opdateres ikke automatisk”. Kræver aktivt klik på det dokument/fil der ønskes forhåndsvist. | AC52: Wiki: 6.5 release information | AD52: Hans: Commitment/no-bid beslutning; overvej Q&A til ordregiver. | AF52: Draft | AG52: uim-esdh-full-2026-07-07
A53: 52 | B53: MK-51 | C53: Bilag 1.b | D53: Dokumenter | E53: Konvertering til PDF | F53: ESDH-løsningen skal understøtte, at alle Dokumenter automatisk kan blive konverteret til PDF-format, med undtagelse af medie- og eksekverbare filer. | G53: Mindstekrav | H53: =IF(G53="Evalueringskrav","Answer",(IF(G53="Krav","Check",(IF(G53="Mindstekrav","Verify",""))))) | I53: Ja | L53: Anton | O53: 1. Fully met | P53: ADN: "Kan blive" kræver ikke at vi faktisk gør det | U53: Not Started | V53: =IF(U53="Not Started",0%,IF(U53="Started",50%,IF(U53="Ready for review",70%,IF(U53="Reviewed - Content",80%,IF(U53="Reviewed - Format",90%,IF(U53="Done",100%,"")))))) | W53: 2026-07-07 | X53: Cursor / tender-response (batch) | Y53: Met | Z53: Verified | AA53: Verify: Konvertering til PDF — vurderet opfyldt (tool: 1. Fully met). | AB53: ADN: "Kan blive" kræver ikke at vi faktisk gør det | AC53: docs/tender-reference/extracted/KK Tender tool.txt; docs/tender-reference/extracted/Nationalbanken/Underbilag 6B - Testplan og Leverandørens prøveprincipper, metoder og -værktøjer (1).txt; docs/tender-reference/extracted/HSØ/02.00-Tietoevry-SSA-L-Bilag 2-Leverandørens beskrivelse av Tjenesten.txt | AD53: Anton: Confirm verify-tekst; opdatér review status efter tjek. | AF53: Draft | AG53: uim-esdh-full-2026-07-07
A54: 53 | B54: MK-52 | C54: Bilag 1.b | D54: Dokumenter | E54: Filtyper | F54: ESDH-løsningen skal understøtte, at alle filtyper må gemmes i ESDH-løsningen. | G54: Mindstekrav | H54: =IF(G54="Evalueringskrav","Answer",(IF(G54="Krav","Check",(IF(G54="Mindstekrav","Verify",""))))) | I54: Ja | L54: Anton | O54: 1. Fully met | U54: Not Started | V54: =IF(U54="Not Started",0%,IF(U54="Started",50%,IF(U54="Ready for review",70%,IF(U54="Reviewed - Content",80%,IF(U54="Reviewed - Format",90%,IF(U54="Done",100%,"")))))) | W54: 2026-07-07 | X54: Cursor / tender-response (batch) | Y54: Met | Z54: Verified | AA54: Verify: Filtyper — vurderet opfyldt (tool: 1. Fully met). | AC54: docs/tender-reference/extracted/KK Tender tool.txt; docs/tender-reference/extracted/Nationalbanken/Bilag 3.i Leverandørens Løsningsbeskrivelse.txt; docs/tender-reference/extracted/HSØ/02.00-Tietoevry-SSA-L-Bilag 2-Leverandørens beskrivelse av Tjenesten.txt | AD54: Anton: Confirm verify-tekst; opdatér review status efter tjek. | AF54: Draft | AG54: uim-esdh-full-2026-07-07
A55: 54 | B55: K-2 | C55: Bilag 1.b | D55: Dokumenter | E55: Dokumenttilføjelse via træk-og-slip | F55: ESDH-løsningen skal understøtte, at Brugere kan trække og slippe Dokumenter direkte fra e-mailklienter og stifinder til relevante sager. | G55: Krav | H55: =IF(G55="Evalueringskrav","Answer",(IF(G55="Krav","Check",(IF(G55="Mindstekrav","Verify",""))))) | I55: Ja | L55: Anton | O55: 1. Fully met | U55: Not Started | V55: =IF(U55="Not Started",0%,IF(U55="Started",50%,IF(U55="Ready for review",70%,IF(U55="Reviewed - Content",80%,IF(U55="Reviewed - Format",90%,IF(U55="Done",100%,"")))))) | W55: 2026-07-07 | X55: Cursor / tender-response (batch) | Y55: Met | Z55: Verified | AA55: Check: Dokumenttilføjelse via træk-og-slip — vurderet opfyldt (tool: 1. Fully met). | AC55: docs/tender-reference/extracted/Nationalbanken/Bilag 3.i Leverandørens Løsningsbeskrivelse.txt; docs/tender-reference/extracted/KK Tender tool.txt; docs/tender-reference/extracted/KUM-SLKS/Bilag 3 - Kravspecifikation.txt | AD55: Anton: Confirm verify-tekst; opdatér review status efter tjek. | AF55: Draft | AG55: uim-esdh-full-2026-07-07
A56: 55 | B56: K-3 | C56: Bilag 1.b | D56: Dokumenter | E56: Liste over Dokumenter, der ikke kan PDF-konverteres | F56: ESDH-løsningen skal understøtte, at der i ESDH-løsningen kan præsenteres en standardliste over alle Dokumenter, hvor konverteringen til PDF-format er mislykket. | G56: Krav | H56: =IF(G56="Evalueringskrav","Answer",(IF(G56="Krav","Check",(IF(G56="Mindstekrav","Verify",""))))) | I56: Ja | L56: Anton | O56: 1. Fully met | U56: Not Started | V56: =IF(U56="Not Started",0%,IF(U56="Started",50%,IF(U56="Ready for review",70%,IF(U56="Reviewed - Content",80%,IF(U56="Reviewed - Format",90%,IF(U56="Done",100%,"")))))) | W56: 2026-07-07 | X56: Cursor / tender-response (batch) | Y56: Met | Z56: Verified | AA56: Check: Liste over Dokumenter, der ikke kan PDF-konverteres — vurderet opfyldt (tool: 1. Fully met). | AC56: docs/tender-reference/extracted/Nationalbanken/Underbilag 6B - Testplan og Leverandørens prøveprincipper, metoder og -værktøjer (1).txt; docs/tender-reference/extracted/KK Tender tool.txt; docs/tender-reference/extracted/NND/02.01-Tieto-Bilag 2-Vedlegg-Leverandørens utfyllende svar til kravtabell.txt | AD56: Anton: Confirm verify-tekst; opdatér review status efter tjek. | AF56: Draft | AG56: uim-esdh-full-2026-07-07
A57: 56 | B57: MK-53 | C57: Bilag 1.b | D57: Kontakter | E57: Oprettelse af kontakter | F57: ESDH-løsningen skal understøtte oprettelse af kontakter med metadata i et kontaktregister. | G57: Mindstekrav | H57: =IF(G57="Evalueringskrav","Answer",(IF(G57="Krav","Check",(IF(G57="Mindstekrav","Verify",""))))) | I57: Ja | L57: Anton | O57: 1. Fully met | U57: Not Started | V57: =IF(U57="Not Started",0%,IF(U57="Started",50%,IF(U57="Ready for review",70%,IF(U57="Reviewed - Content",80%,IF(U57="Reviewed - Format",90%,IF(U57="Done",100%,"")))))) | W57: 2026-07-07 | X57: Cursor / tender-response (batch) | Y57: Met | Z57: Verified | AA57: Verify: Oprettelse af kontakter — vurderet opfyldt (tool: 1. Fully met). | AC57: docs/tender-reference/extracted/Nationalbanken/Bilag 3.i Leverandørens Løsningsbeskrivelse.txt; docs/product/RFP_Leverandørens_svar_utdrag.txt; docs/tender-reference/extracted/HSØ/02.00-Tietoevry-SSA-L-Bilag 2-Leverandørens beskrivelse av Tjenesten.txt | AD57: Anton: Confirm verify-tekst; opdatér review status efter tjek. | AF57: Draft | AG57: uim-esdh-full-2026-07-07
A58: 57 | B58: MK-54 | C58: Bilag 1.b | D58: Kontakter | E58: Kontakttyper | F58: ESDH-løsningen skal understøtte oprettelse af nye kontakttyper. | G58: Mindstekrav | H58: =IF(G58="Evalueringskrav","Answer",(IF(G58="Krav","Check",(IF(G58="Mindstekrav","Verify",""))))) | I58: Ja | L58: Anton | O58: 1. Fully met | P58: ADN: In KUM - we said yes to this, with the idea that we configure a field on contacts called "Contact Type" to live up to this. Only thing with this approach, is we need to find a word for our enterprises, contact persons and private persons besides "Types" to sell this in a clarification phase. (We could call them contact-archives to align with document archive?) | R58: Yes | U58: Not Started | V58: =IF(U58="Not Started",0%,IF(U58="Started",50%,IF(U58="Ready for review",70%,IF(U58="Reviewed - Content",80%,IF(U58="Reviewed - Format",90%,IF(U58="Done",100%,"")))))) | W58: 2026-07-07 | X58: Cursor / tender-response (batch) | Y58: Met | Z58: Lead | AA58: Verify: Kontakttyper — vurderet opfyldt (tool: 1. Fully met). | AB58: ADN: In KUM - we said yes to this, with the idea that we configure a field on contacts called "Contact Type" to live up to this. Only thing with this approach, is we need to find a word for our enterprises, contact persons and private persons besides "Types" to sell this in a clarification phase. (We could call them contact-archives to align with document archive?) | AC58: docs/tender-reference/extracted/Nationalbanken/Bilag 3.i Leverandørens Løsningsbeskrivelse.txt; docs/product/RFP_Leverandørens_svar_utdrag.txt; docs/tender-reference/extracted/HSØ/02.00-Tietoevry-SSA-L-Bilag 2-Leverandørens beskrivelse av Tjenesten.txt | AD58: Anton: Confirm verify-tekst; opdatér review status efter tjek. | AF58: Draft | AG58: uim-esdh-full-2026-07-07
A59: 58 | B59: MK-55 | C59: Bilag 1.b | D59: Kontakter | E59: Redigering af kontakter | F59: ESDH-løsningen skal understøtte redigering af metadata på kontakter, såfremt at Brugeren har rettighed hertil. | G59: Mindstekrav | H59: =IF(G59="Evalueringskrav","Answer",(IF(G59="Krav","Check",(IF(G59="Mindstekrav","Verify",""))))) | I59: Ja | L59: Anton | O59: 1. Fully met | U59: Not Started | V59: =IF(U59="Not Started",0%,IF(U59="Started",50%,IF(U59="Ready for review",70%,IF(U59="Reviewed - Content",80%,IF(U59="Reviewed - Format",90%,IF(U59="Done",100%,"")))))) | W59: 2026-07-07 | X59: Cursor / tender-response (batch) | Y59: Met | Z59: Verified | AA59: Verify: Redigering af kontakter — vurderet opfyldt (tool: 1. Fully met). | AC59: docs/tender-reference/extracted/KK Tender tool.txt; docs/tender-reference/extracted/KUM-SLKS/Bilag 3 - Kravspecifikation.txt; docs/tender-reference/extracted/Nationalbanken/Bilag 3.i Leverandørens Løsningsbeskrivelse.txt | AD59: Anton: Confirm verify-tekst; opdatér review status efter tjek. | AF59: Draft | AG59: uim-esdh-full-2026-07-07
A60: 59 | B60: MK-56 | C60: Bilag 1.b | D60: Kontakter | E60: Automatisk dubletkontrol i kontakt-registeret | F60: ESDH-løsningen skal understøtte, at en Bruger ikke kan oprette en kontakt, hvis kontaktens unikke ID allerede findes i kontaktregisteret. | G60: Mindstekrav | H60: =IF(G60="Evalueringskrav","Answer",(IF(G60="Krav","Check",(IF(G60="Mindstekrav","Verify",""))))) | I60: Ja | L60: Morten | O60: 2. Partly met | P60: ADN: Vi advarer, men vi forbyder ikke. CPR/CVR er ikke så unikt at det ikke kan duplikeres. ADN: Enten med udvidet duplikat-kontrol eller BRE der forbyder det. | Q60: Yes | U60: Not Started | V60: =IF(U60="Not Started",0%,IF(U60="Started",50%,IF(U60="Ready for review",70%,IF(U60="Reviewed - Content",80%,IF(U60="Reviewed - Format",90%,IF(U60="Done",100%,"")))))) | W60: 2026-07-07 | X60: Cursor / tender-response (MCP-enriched) | Y60: Partial | Z60: Lead | AA60: Verify: Automatisk dubletkontrol i kontakt-registeret — delvist opfyldt; afklar scope og scoring. | AB60: ADN: Vi advarer, men vi forbyder ikke. CPR/CVR er ikke så unikt at det ikke kan duplikeres. ADN: Enten med udvidet duplikat-kontrol eller BRE der forbyder det. | Red flag: Vi advarer, men vi forbyder ikke. CPR/CVR er ikke så unikt at det ikke kan duplikeres. | AC60: Wiki: 360° Contact register cleaning tools; 360° Integration with Enhetsregisteret (BRREG) | AD60: Morten: Afklar delkrav; align tool-rating (O) med AI compliance. | AF60: Draft | AG60: uim-esdh-full-2026-07-07
A61: 60 | B61: MK-57 | C61: Bilag 1.b | D61: Kontakter | E61: Fremsøgning | F61: ESDH-løsningen skal understøtte, at kontakter kan fremsøges via relevante metadata. | G61: Mindstekrav | H61: =IF(G61="Evalueringskrav","Answer",(IF(G61="Krav","Check",(IF(G61="Mindstekrav","Verify",""))))) | I61: Ja | L61: Anton | O61: 1. Fully met | U61: Not Started | V61: =IF(U61="Not Started",0%,IF(U61="Started",50%,IF(U61="Ready for review",70%,IF(U61="Reviewed - Content",80%,IF(U61="Reviewed - Format",90%,IF(U61="Done",100%,"")))))) | W61: 2026-07-07 | X61: Cursor / tender-response (batch) | Y61: Met | Z61: Verified | AA61: Verify: Fremsøgning — vurderet opfyldt (tool: 1. Fully met). | AC61: docs/tender-reference/extracted/Nationalbanken/Bilag 3.i Leverandørens Løsningsbeskrivelse.txt; docs/tender-reference/extracted/KUM-SLKS/Bilag 3 - Kravspecifikation.txt; docs/product/RFP_Leverandørens_svar_utdrag.txt | AD61: Anton: Confirm verify-tekst; opdatér review status efter tjek. | AF61: Draft | AG61: uim-esdh-full-2026-07-07
A62: 61 | B62: MK-58 | C62: Bilag 1.b | D62: Kontakter | E62: Tilknytning af kontakt på sag | F62: ESDH-løsningen skal understøtte, at en Bruger kan oprette en ny kontakt eller søge efter en eksisterende kontakt med henblik på at tilknytte kontakten til alle Entiteter i Løsningen, herunder sager, Dokumenter og Kundeoprettede Entiteter. | G62: Mindstekrav | H62: =IF(G62="Evalueringskrav","Answer",(IF(G62="Krav","Check",(IF(G62="Mindstekrav","Verify",""))))) | I62: Ja | L62: Anton | O62: 1. Fully met | U62: Not Started | V62: =IF(U62="Not Started",0%,IF(U62="Started",50%,IF(U62="Ready for review",70%,IF(U62="Reviewed - Content",80%,IF(U62="Reviewed - Format",90%,IF(U62="Done",100%,"")))))) | W62: 2026-07-07 | X62: Cursor / tender-response (batch) | Y62: Met | Z62: Verified | AA62: Verify: Tilknytning af kontakt på sag — vurderet opfyldt (tool: 1. Fully met). | AC62: docs/tender-reference/extracted/Nationalbanken/Bilag 3.i Leverandørens Løsningsbeskrivelse.txt; docs/tender-reference/extracted/KUM-SLKS/Bilag 3 - Kravspecifikation.txt; docs/product/RFP_Leverandørens_svar_utdrag.txt | AD62: Anton: Confirm verify-tekst; opdatér review status efter tjek. | AF62: Draft | AG62: uim-esdh-full-2026-07-07
A63: 62 | B63: MK-59 | C63: Bilag 1.b | D63: Kontakter | E63: Automatisk opdatering | F63: ESDH-løsningen skal understøtte, at kontakter automatisk kan opdateres via f.eks. integration til CPR, CVR eller lignende register på relevante metadata. Det skal ske som automatiske batch-kørsler, der med faste intervaller sikrer, at eksisterende metadata i systemet altid er ajourførte. | G63: Mindstekrav | H63: =IF(G63="Evalueringskrav","Answer",(IF(G63="Krav","Check",(IF(G63="Mindstekrav","Verify",""))))) | I63: Ja | L63: Anton | O63: 1. Fully met | U63: Not Started | V63: =IF(U63="Not Started",0%,IF(U63="Started",50%,IF(U63="Ready for review",70%,IF(U63="Reviewed - Content",80%,IF(U63="Reviewed - Format",90%,IF(U63="Done",100%,"")))))) | W63: 2026-07-07 | X63: Cursor / tender-response (batch) | Y63: Met | Z63: Verified | AA63: Verify: Automatisk opdatering — vurderet opfyldt (tool: 1. Fully met). | AC63: docs/tender-reference/extracted/Nationalbanken/Bilag 3.i Leverandørens Løsningsbeskrivelse.txt; docs/tender-reference/extracted/HSØ/02.00-Tietoevry-SSA-L-Bilag 2-Leverandørens beskrivelse av Tjenesten.txt; docs/tender-reference/extracted/KK Tender tool.txt | AD63: Anton: Confirm verify-tekst; opdatér review status efter tjek. | AF63: Draft | AG63: uim-esdh-full-2026-07-07
A64: 63 | B64: MK-60 | C64: Bilag 1.b | D64: Kontakter | E64: Oprettelse og import af kontakt-oplysninger fra CPR | F64: ESDH-løsningen skal understøtte, at Brugeren kan foretage onlineopslag på et specifikt CPR-nr. via ESDH-løsningen og importere dennes stamdata til ESDH-løsningen. Personen skal oprettes eller opdateres i Løsningens kontaktregister. | G64: Mindstekrav | H64: =IF(G64="Evalueringskrav","Answer",(IF(G64="Krav","Check",(IF(G64="Mindstekrav","Verify",""))))) | I64: Ja | L64: Anton | N64: CPR | O64: 1. Fully met | U64: Not Started | V64: =IF(U64="Not Started",0%,IF(U64="Started",50%,IF(U64="Ready for review",70%,IF(U64="Reviewed - Content",80%,IF(U64="Reviewed - Format",90%,IF(U64="Done",100%,"")))))) | W64: 2026-07-07 | X64: Cursor / tender-response (batch) | Y64: Met | Z64: Verified | AA64: Verify: Oprettelse og import af kontakt-oplysninger fra CPR — vurderet opfyldt (tool: 1. Fully met). | AC64: docs/tender-reference/extracted/Nationalbanken/Bilag 3.i Leverandørens Løsningsbeskrivelse.txt; docs/tender-reference/extracted/KK Tender tool.txt; docs/tender-reference/extracted/KUM-SLKS/Bilag 3 - Kravspecifikation.txt | AD64: Anton: Confirm verify-tekst; opdatér review status efter tjek. | AF64: Draft | AG64: uim-esdh-full-2026-07-07
A65: 64 | B65: MK-61 | C65: Bilag 1.b | D65: Kontakter | E65: Oprettelse og import af kontaktoplysninger fra CVR | F65: ESDH-løsningen skal understøtte, at Brugeren kan foretage onlineopslag på et specifikt CVR-nr. via ESDH-løsningen og importere virksomhedens stamdata til ESDH-løsningen. Virksomheden skal oprettes eller opdateres i Løsningens kontaktregister. | G65: Mindstekrav | H65: =IF(G65="Evalueringskrav","Answer",(IF(G65="Krav","Check",(IF(G65="Mindstekrav","Verify",""))))) | I65: Ja | L65: Anton | N65: CVR | O65: 1. Fully met | U65: Not Started | V65: =IF(U65="Not Started",0%,IF(U65="Started",50%,IF(U65="Ready for review",70%,IF(U65="Reviewed - Content",80%,IF(U65="Reviewed - Format",90%,IF(U65="Done",100%,"")))))) | W65: 2026-07-07 | X65: Cursor / tender-response (batch) | Y65: Met | Z65: Verified | AA65: Verify: Oprettelse og import af kontaktoplysninger fra CVR — vurderet opfyldt (tool: 1. Fully met). | AC65: docs/tender-reference/extracted/Nationalbanken/Bilag 3.i Leverandørens Løsningsbeskrivelse.txt; docs/tender-reference/extracted/KK Tender tool.txt; docs/tender-reference/extracted/KUM-SLKS/Bilag 3 - Kravspecifikation.txt | AD65: Anton: Confirm verify-tekst; opdatér review status efter tjek. | AF65: Draft | AG65: uim-esdh-full-2026-07-07
A66: 65 | B66: MK-62 | C66: Bilag 1.b | D66: Kontakter | E66: Sletning af kontakter | F66: ESDH-løsningen skal understøtte sletning af kontakter. Den udførende Bruger skal adviseres, hvis kontakten er tilknyttet sager, Dokumenter eller har reference til anden kontakt. | G66: Mindstekrav | H66: =IF(G66="Evalueringskrav","Answer",(IF(G66="Krav","Check",(IF(G66="Mindstekrav","Verify",""))))) | I66: Ja | L66: Anton | O66: 1. Fully met | U66: Not Started | V66: =IF(U66="Not Started",0%,IF(U66="Started",50%,IF(U66="Ready for review",70%,IF(U66="Reviewed - Content",80%,IF(U66="Reviewed - Format",90%,IF(U66="Done",100%,"")))))) | W66: 2026-07-07 | X66: Cursor / tender-response (batch) | Y66: Met | Z66: Verified | AA66: Verify: Sletning af kontakter — vurderet opfyldt (tool: 1. Fully met). | AC66: docs/tender-reference/extracted/Nationalbanken/Bilag 3.i Leverandørens Løsningsbeskrivelse.txt; docs/tender-reference/extracted/KK Tender tool.txt; docs/product/RFP_Leverandørens_svar_utdrag.txt | AD66: Anton: Confirm verify-tekst; opdatér review status efter tjek. | AF66: Draft | AG66: uim-esdh-full-2026-07-07
A67: 66 | B67: MK-63 | C67: Bilag 1.b | D67: Kontakter | E67: Deaktivering af kontakter | F67: ESDH-løsningen skal understøtte, at en kontakt kan deaktiveres samt, at deaktiveret kontakt ikke kan tilknyttes Entiteter. | G67: Mindstekrav | H67: =IF(G67="Evalueringskrav","Answer",(IF(G67="Krav","Check",(IF(G67="Mindstekrav","Verify",""))))) | I67: Ja | L67: Anton | O67: 1. Fully met | U67: Not Started | V67: =IF(U67="Not Started",0%,IF(U67="Started",50%,IF(U67="Ready for review",70%,IF(U67="Reviewed - Content",80%,IF(U67="Reviewed - Format",90%,IF(U67="Done",100%,"")))))) | W67: 2026-07-07 | X67: Cursor / tender-response (batch) | Y67: Met | Z67: Verified | AA67: Verify: Deaktivering af kontakter — vurderet opfyldt (tool: 1. Fully met). | AC67: docs/product/RFP_Leverandørens_svar_utdrag.txt; docs/tender-reference/extracted/HSØ/02.00-Tietoevry-SSA-L-Bilag 2-Leverandørens beskrivelse av Tjenesten.txt; docs/tender-reference/extracted/NND/02.01-Tieto-Bilag 2-Vedlegg-Leverandørens utfyllende svar til kravtabell.txt | AD67: Anton: Confirm verify-tekst; opdatér review status efter tjek. | AF67: Draft | AG67: uim-esdh-full-2026-07-07
A68: 67 | B68: MK-64 | C68: Bilag 1.b | D68: Kontakter | E68: Deaktiverede kontakter | F68: ESDH-løsningen skal understøtte, at deaktiverede kontakter kan fremsøges i Løsningen. | G68: Mindstekrav | H68: =IF(G68="Evalueringskrav","Answer",(IF(G68="Krav","Check",(IF(G68="Mindstekrav","Verify",""))))) | I68: Ja | L68: Anton | O68: 1. Fully met | U68: Not Started | V68: =IF(U68="Not Started",0%,IF(U68="Started",50%,IF(U68="Ready for review",70%,IF(U68="Reviewed - Content",80%,IF(U68="Reviewed - Format",90%,IF(U68="Done",100%,"")))))) | W68: 2026-07-07 | X68: Cursor / tender-response (batch) | Y68: Met | Z68: Lead | AA68: Verify: Deaktiverede kontakter — vurderet opfyldt (tool: 1. Fully met). | AC68: docs/tender-reference/extracted/KUM-SLKS/Bilag 3 - Kravspecifikation.txt; docs/tender-reference/extracted/Nationalbanken/Bilag 3.i Leverandørens Løsningsbeskrivelse.txt; docs/product/RFP_Leverandørens_svar_utdrag.txt | AD68: Anton: Confirm verify-tekst; opdatér review status efter tjek. | AF68: Draft | AG68: uim-esdh-full-2026-07-07
A69: 68 | B69: EK-1 | C69: Bilag 1.b | D69: Kontakter | E69: Udlændinge-overblik | F69: Kunden har behov for at udstille en udlændinges stamdata i Løsningen. Kunden betragter en udlænding som en kontakttype, som kan tilknyttes til Entiteter i Løsningen. ESDH-løsningen skal understøtte, at Administrator kan konfigurere en Udlændingekontakt via no code administratormodul, der sikrer et fuldt overblik over Udlændingekontakten. Administratoren skal dertil kunne opsætte og konfigurere udlændingeoverblikket i brugergrænsefladen. Overblikket over udlændingen skal indeholde følgende: Sager, hvor udlændingen indgår som part samt hvilken rolle udlændingen har på sagen Afgørelser, som er tilknyttet udlændingen med følgende metadata: Sagsnr. Afgørelsesdato Afgørelsestype Sagsområde f.eks. familiesammenføring Ansvarligt team Ansvarlig sagsbehandler Stamdata på udlændingen herunder: Cpr.nr. Udlændinge nr. Fornavn og efternavn Adresse, postnr. og by Telefon og e-mailadresse Nationalitet Køn Familierelationer (f.eks. barn, forældre, værge) Datoer for ind- og udrejse til/fra Danmark Rejsedokumenter (f.eks. pas og nationalt ID-kort) Dokumenter som udlændingen er tilknyttet, samt hvilken partsrolle udlændingen har på Dokumentet Sager i anden Myndighed herunder: Sagsnr. Sagsområde f.eks. asyl Ansvarligt team Ansvarlig sagsbehandler Afgørelser i anden Myndighed herunder: Sagsnr. Afgørelsesdato Afgørelsestype Sagsområde f.eks. familiesammenføring Ansvarligt team Ansvarlig sagsbehandler Leverandøren skal beskrive, hvordan den tilbudte ESDH-løsning understøtter, at Administrator kan konfigurere en Udlændingekontakt via no code administratormodul. Leverandøren skal gennem konkrete skærmbilleder demonstrere om og hvordan ESDH-løsningen understøtter de stillede krav og møder Kundens behov. Leverandøren skal redegøre for: Hvordan ESDH-løsningen understøtter et udlændingeoverblik Hvordan Brugeren kan navigere i oplysningerne på udlændingeoverblikket Hvordan Administratoren kan oprette og vedligeholde udlændingeoverblikket Evalueringskriterier: Det vægtes positivt, i hvor høj grad Brugeren på en let og intuitiv måde kan navigere i udlændingeoverblikkets data. Det vægtes positivt, i hvor høj grad Administrator kan oprette og vedligeholde udlændingeoverblikket via et administratormodul uden involvering af Leverandør. Det vægtes positivt, i hvor høj grad udlændingeoverblikket indeholder et samlet overblik over udlændingens sager og Afgørelser i egen Myndighed samt overblik over sager og Afgørelser i øvrige Myndigheders sager. Det vægtes positivt, i hvor høj grad Dokumenter udstilles på en let og overskuelig måde på udlændingeoverblikket f.eks. via filtrering. Det vægtes positivt, i hvor høj grad der på udlændingeoverblikket kan noteres flere oplysninger af samme type f.eks. datoer for ind- og udrejse. Det vægtes positivt, i hvor høj grad udlændingeoverblikket opdateres i realtid, når der f.eks. tilføjes nye sager og Afgørelser eller stamdata opdateres i eksterne registre. Det vægtes positivt, i hvor høj grad felter på udlændingeoverblikket kan gøres skrivebeskyttet, så opdatering af felter kun kan ske via eksterne registre. | G69: Evalueringskrav | H69: =IF(G69="Evalueringskrav","Answer",(IF(G69="Krav","Check",(IF(G69="Mindstekrav","Verify",""))))) | I69: Ja | L69: Claus | U69: Not Started | V69: =IF(U69="Not Started",0%,IF(U69="Started",50%,IF(U69="Ready for review",70%,IF(U69="Reviewed - Content",80%,IF(U69="Reviewed - Format",90%,IF(U69="Done",100%,"")))))) | W69: 2026-07-07 | X69: Cursor / tender-response (MCP-enriched) | Y69: Draft needed | Z69: Lead | AA69: Answer: Udlændinge-overblik — informationskrav; udkast bilag/dokumentation mangler. | AB69: Mangler link til svar-bilag i kolonne T. | AC69: No help or wiki match for foreigner contact overview (udlændingeoverblik) | AD69: Claus: Opret/link svar-bilag; draft IK-tekst fra prior art. | AF69: Draft | AG69: uim-esdh-full-2026-07-07
A70: 69 | B70: MK-65 | C70: Bilag 1.b | D70: Søgning | E70: Søgning | F70: ESDH-løsningen skal understøtte, at der kan søges i alle standard- og Kundeoprettede felter. | G70: Mindstekrav | H70: =IF(G70="Evalueringskrav","Answer",(IF(G70="Krav","Check",(IF(G70="Mindstekrav","Verify",""))))) | I70: Ja | L70: Claus | O70: 1. Fully met | P70: ADN: Search "in all fields" comes with a risc, especially if any external consultant is still involved from the customer side. | R70: Yes | U70: Not Started | V70: =IF(U70="Not Started",0%,IF(U70="Started",50%,IF(U70="Ready for review",70%,IF(U70="Reviewed - Content",80%,IF(U70="Reviewed - Format",90%,IF(U70="Done",100%,"")))))) | W70: 2026-07-07 | X70: Cursor / tender-response (batch) | Y70: Met | Z70: Verified | AA70: Verify: Søgning — vurderet opfyldt (tool: 1. Fully met). | AB70: ADN: Search "in all fields" comes with a risc, especially if any external consultant is still involved from the customer side. | AC70: docs/tender-reference/extracted/KK Tender tool.txt; docs/tender-reference/extracted/KUM-SLKS/Bilag 3 - Kravspecifikation.txt; docs/tender-reference/extracted/Nationalbanken/Bilag 3.i Leverandørens Løsningsbeskrivelse.txt | AD70: Claus: Confirm verify-tekst; opdatér review status efter tjek. | AF70: Draft | AG70: uim-esdh-full-2026-07-07
A71: 70 | B71: MK-66 | C71: Bilag 1.b | D71: Søgning | E71: Søgning på flere felter på samme tid | F71: ESDH-løsningen skal understøtte, at der kan søges på alle standard- og Kundeoprettede felter på samme tid i ESDH-løsningen. | G71: Mindstekrav | H71: =IF(G71="Evalueringskrav","Answer",(IF(G71="Krav","Check",(IF(G71="Mindstekrav","Verify",""))))) | I71: Ja | L71: Claus | N71: Management Reporting API | O71: 2. Partly met | P71: ADN: Det her krav er formuleret uden logiske begræsninger mellem entiteter, hvilke tikke giver mening. Det kan vi ikke understøtte. Does this require you should be able to search for all case and document, and contact-related fields, in 1 joint search?? CHM: Requirement doesnt say where it should be performed. Could it be solved by management reporting api? Querry builder might also be a way to look - but we havent decided on a specific solution yet. | Q71: Yes | R71: Yes | U71: Not Started | V71: =IF(U71="Not Started",0%,IF(U71="Started",50%,IF(U71="Ready for review",70%,IF(U71="Reviewed - Content",80%,IF(U71="Reviewed - Format",90%,IF(U71="Done",100%,"")))))) | W71: 2026-07-07 | X71: Cursor / tender-response (MCP-enriched) | Y71: Partial | Z71: Lead | AA71: Verify: Søgning på flere felter på samme tid — delvist opfyldt; afklar scope og scoring. | AB71: ADN: Det her krav er formuleret uden logiske begræsninger mellem entiteter, hvilke tikke giver mening. Det kan vi ikke understøtte. Does this require you should be able to search for all case and document, and contact-related fields, in 1 joint search?? CHM: Requirement doesnt say where it should be performed. Could it be solved by management reporting api? Querry builder might also be a way to look - but we havent decided on a specific solution yet. | Red flag: Det her krav er formuleret uden logiske begræsninger mellem entiteter, hvilke tikke giver mening. Det kan vi ikke understøtte. | AC71: Ratatoskr: Search and Result lists (admin-en); Advanced search (admin-en); 360° Search Assistant (admin-en) | Wiki: 6.8 release information; Feature Toggles 2025-2026 | AD71: Claus: Afklar delkrav; align tool-rating (O) med AI compliance. | AF71: Draft | AG71: uim-esdh-full-2026-07-07
A72: 71 | B72: MK-67 | C72: Bilag 1.b | D72: Søgning | E72: Søgning på filindhold | F72: ESDH-løsningen skal understøtte søgning i indholdet af Filer. | G72: Mindstekrav | H72: =IF(G72="Evalueringskrav","Answer",(IF(G72="Krav","Check",(IF(G72="Mindstekrav","Verify",""))))) | I72: Ja | L72: Anton | O72: 1. Fully met | U72: Not Started | V72: =IF(U72="Not Started",0%,IF(U72="Started",50%,IF(U72="Ready for review",70%,IF(U72="Reviewed - Content",80%,IF(U72="Reviewed - Format",90%,IF(U72="Done",100%,"")))))) | W72: 2026-07-07 | X72: Cursor / tender-response (batch) | Y72: Met | Z72: Verified | AA72: Verify: Søgning på filindhold — vurderet opfyldt (tool: 1. Fully met). | AC72: docs/tender-reference/extracted/Nationalbanken/Bilag 3.i Leverandørens Løsningsbeskrivelse.txt; docs/tender-reference/extracted/KK Tender tool.txt; docs/tender-reference/extracted/KUM-SLKS/Bilag 3 - Kravspecifikation.txt | AD72: Anton: Confirm verify-tekst; opdatér review status efter tjek. | AF72: Draft | AG72: uim-esdh-full-2026-07-07
A73: 72 | B73: MK-68 | C73: Bilag 1.b | D73: Søgning | E73: Trunkering i avanceret søgning | F73: ESDH-løsningen skal understøtte, at Brugeren kan anvende trunkering, hvis der ønskes søgning på begyndelsen eller slutningen af et ord. | G73: Mindstekrav | H73: =IF(G73="Evalueringskrav","Answer",(IF(G73="Krav","Check",(IF(G73="Mindstekrav","Verify",""))))) | I73: Ja | L73: Anton | O73: 1. Fully met | P73: ADN Det her lugter af at være målrettet os givet titlen, fordi de ved vi ikke kan i den avancerede søgning - men kravteksten indeholder det ikke, "Avanceret søg" og derfor bør vi være OK med kravet. | U73: Not Started | V73: =IF(U73="Not Started",0%,IF(U73="Started",50%,IF(U73="Ready for review",70%,IF(U73="Reviewed - Content",80%,IF(U73="Reviewed - Format",90%,IF(U73="Done",100%,"")))))) | W73: 2026-07-07 | X73: Cursor / tender-response (MCP-enriched) | Y73: Met | Z73: Lead | AA73: Verify: Trunkering i avanceret søgning — vurderet opfyldt (tool: 1. Fully met). | AB73: ADN Det her lugter af at være målrettet os givet titlen, fordi de ved vi ikke kan i den avancerede søgning - men kravteksten indeholder det ikke, "Avanceret søg" og derfor bør vi være OK med kravet. | Red flag: Det her lugter af at være givet titlen her, fordi de ved vi ikke kan i den avancerede søgning - men kravteksten indeholder det ikke, og derfor bør vi være OK med kravet | AC73: Ratatoskr: Advanced search (admin-en) | Wiki: Build log hotfix packages | AD73: Anton: Confirm verify-tekst; opdatér review status efter tjek. | AF73: Draft | AG73: uim-esdh-full-2026-07-07
A74: 73 | B74: MK-69 | C74: Bilag 1.b | D74: Søgning | E74: Gemte søgninger | F74: ESDH-løsningen skal understøtte, at søgninger kan gemmes i Løsningen og deles af Brugere. | G74: Mindstekrav | H74: =IF(G74="Evalueringskrav","Answer",(IF(G74="Krav","Check",(IF(G74="Mindstekrav","Verify",""))))) | I74: Ja | L74: Anton | O74: 1. Fully met | P74: ADN: Configure Share saved search Toggle | U74: Not Started | V74: =IF(U74="Not Started",0%,IF(U74="Started",50%,IF(U74="Ready for review",70%,IF(U74="Reviewed - Content",80%,IF(U74="Reviewed - Format",90%,IF(U74="Done",100%,"")))))) | W74: 2026-07-07 | X74: Cursor / tender-response (batch) | Y74: Met | Z74: Verified | AA74: Verify: Gemte søgninger — vurderet opfyldt (tool: 1. Fully met). | AB74: ADN: Configure Share saved search Toggle | AC74: docs/tender-reference/extracted/KK Tender tool.txt; docs/tender-reference/extracted/KUM-SLKS/Bilag 3 - Kravspecifikation.txt; docs/tender-reference/extracted/Nationalbanken/Bilag 3.i Leverandørens Løsningsbeskrivelse.txt | AD74: Anton: Confirm verify-tekst; opdatér review status efter tjek. | AF74: Draft | AG74: uim-esdh-full-2026-07-07
A75: 74 | B75: MK-70 | C75: Bilag 1.b | D75: Søgning | E75: Søgeresultater | F75: ESDH-løsningen skal understøtte, at alle felter kan vises i søgeresultaternes visningslister. | G75: Mindstekrav | H75: =IF(G75="Evalueringskrav","Answer",(IF(G75="Krav","Check",(IF(G75="Mindstekrav","Verify",""))))) | I75: Ja | L75: Claus | O75: 2. Partly met | P75: ADN: ”Alle felter” - godt nok afgrænset til søgeresultater, men stadig en stor risc, fra en ondsindet kunde. Vi må spørge willy | R75: Yes | U75: Not Started | V75: =IF(U75="Not Started",0%,IF(U75="Started",50%,IF(U75="Ready for review",70%,IF(U75="Reviewed - Content",80%,IF(U75="Reviewed - Format",90%,IF(U75="Done",100%,"")))))) | W75: 2026-07-07 | X75: Cursor / tender-response (MCP-enriched) | Y75: Partial | Z75: Lead | AA75: Verify: Søgeresultater — delvist opfyldt; afklar scope og scoring. | AB75: ADN: ”Alle felter” - godt nok afgrænset til søgeresultater, men stadig en stor risc, fra en ondsindet kunde. Vi må spørge willy | Red flag: ”Alle felter” - godt nok afgrænset til søgeresultater, men stadig en stor risc, fra en ondsindet kunde. | AC75: Ratatoskr: Search and Result lists (admin-en) | Wiki: CIM - How to create Reports | AD75: Claus: Afklar delkrav; align tool-rating (O) med AI compliance. | AF75: Draft | AG75: uim-esdh-full-2026-07-07
A76: 75 | B76: MK-71 | C76: Bilag 1.b | D76: Søgning | E76: Søgning i dropdown-felter ved registrering | F76: ESDH-løsningen skal understøtte, at der kan søges på værdier i alle dropdown-felter. | G76: Mindstekrav | H76: =IF(G76="Evalueringskrav","Answer",(IF(G76="Krav","Check",(IF(G76="Mindstekrav","Verify",""))))) | I76: Ja | L76: Anton | O76: 1. Fully met | P76: ADN: Requirement contains the word "All" but i cant come up with anywhere, where we dont support this. | R76: Yes | U76: Not Started | V76: =IF(U76="Not Started",0%,IF(U76="Started",50%,IF(U76="Ready for review",70%,IF(U76="Reviewed - Content",80%,IF(U76="Reviewed - Format",90%,IF(U76="Done",100%,"")))))) | W76: 2026-07-07 | X76: Cursor / tender-response (batch) | Y76: Met | Z76: Verified | AA76: Verify: Søgning i dropdown-felter ved registrering — vurderet opfyldt (tool: 1. Fully met). | AB76: ADN: Requirement contains the word "All" but i cant come up with anywhere, where we dont support this. | AC76: docs/tender-reference/extracted/KUM-SLKS/Bilag 3 - Kravspecifikation.txt; docs/tender-reference/extracted/Nationalbanken/Bilag 3.i Leverandørens Løsningsbeskrivelse.txt; docs/tender-reference/extracted/KK Tender tool.txt | AD76: Anton: Confirm verify-tekst; opdatér review status efter tjek. | AF76: Draft | AG76: uim-esdh-full-2026-07-07
A77: 76 | B77: MK-72 | C77: Bilag 1.b | D77: Søgning | E77: Søgning på alle niveauer i journalplan | F77: ESDH-løsningen skal understøtte, at der kan søges på alle niveauer i journalplanen. | G77: Mindstekrav | H77: =IF(G77="Evalueringskrav","Answer",(IF(G77="Krav","Check",(IF(G77="Mindstekrav","Verify",""))))) | I77: Ja | L77: Anton | O77: 1. Fully met | P77: ADN: We got the commitment on KUM | U77: Not Started | V77: =IF(U77="Not Started",0%,IF(U77="Started",50%,IF(U77="Ready for review",70%,IF(U77="Reviewed - Content",80%,IF(U77="Reviewed - Format",90%,IF(U77="Done",100%,"")))))) | W77: 2026-07-07 | X77: Cursor / tender-response (batch) | Y77: Met | Z77: Verified | AA77: Verify: Søgning på alle niveauer i journalplan — vurderet opfyldt (tool: 1. Fully met). | AB77: ADN: We got the commitment on KUM | AC77: docs/tender-reference/extracted/KUM-SLKS/Bilag 3 - Kravspecifikation.txt; docs/tender-reference/extracted/Nationalbanken/Bilag 3.i Leverandørens Løsningsbeskrivelse.txt; docs/tender-reference/extracted/KK Tender tool.txt | AD77: Anton: Confirm verify-tekst; opdatér review status efter tjek. | AF77: Draft | AG77: uim-esdh-full-2026-07-07
A78: 77 | B78: MK-73 | C78: Bilag 1.b | D78: Søgning | E78: Søgning på tværs af Entiteter | F78: ESDH-løsningen skal understøtte, at der kan søges på tværs af Entiteter. | G78: Mindstekrav | H78: =IF(G78="Evalueringskrav","Answer",(IF(G78="Krav","Check",(IF(G78="Mindstekrav","Verify",""))))) | I78: Ja | L78: Anton | O78: 1. Fully met | U78: Not Started | V78: =IF(U78="Not Started",0%,IF(U78="Started",50%,IF(U78="Ready for review",70%,IF(U78="Reviewed - Content",80%,IF(U78="Reviewed - Format",90%,IF(U78="Done",100%,"")))))) | W78: 2026-07-07 | X78: Cursor / tender-response (batch) | Y78: Met | Z78: Verified | AA78: Verify: Søgning på tværs af Entiteter — vurderet opfyldt (tool: 1. Fully met). | AC78: docs/tender-reference/extracted/Nationalbanken/Bilag 3.i Leverandørens Løsningsbeskrivelse.txt; docs/tender-reference/extracted/KK Tender tool.txt; docs/tender-reference/extracted/KUM-SLKS/Bilag 3 - Kravspecifikation.txt | AD78: Anton: Confirm verify-tekst; opdatér review status efter tjek. | AF78: Draft | AG78: uim-esdh-full-2026-07-07
A79: 78 | B79: MK-74 | C79: Bilag 1.b | D79: Søgning | E79: Søgebilleder - Entiteter | F79: ESDH-løsningen skal understøtte, at Kunden kan opsætte og konfigurere søgebilleder for alle Løsningens standard- og Kundeoprettede Entiteter. | G79: Mindstekrav | H79: =IF(G79="Evalueringskrav","Answer",(IF(G79="Krav","Check",(IF(G79="Mindstekrav","Verify",""))))) | I79: Ja | L79: Claus | O79: 2. Partly met | P79: ADN: Det understøtter vi ikke. COuld we argue, that it doesnt state it should remember these configurations, and therefore we live up to it? | U79: Not Started | V79: =IF(U79="Not Started",0%,IF(U79="Started",50%,IF(U79="Ready for review",70%,IF(U79="Reviewed - Content",80%,IF(U79="Reviewed - Format",90%,IF(U79="Done",100%,"")))))) | W79: 2026-07-07 | X79: Cursor / tender-response (MCP-enriched) | Y79: Partial | Z79: Lead | AA79: Verify: Søgebilleder - Entiteter — delvist opfyldt; afklar scope og scoring. | AB79: ADN: Det understøtter vi ikke. COuld we argue, that it doesnt state it should remember these configurations, and therefore we live up to it? | Red flag: Det understøtter vi ikke. | AC79: Ratatoskr: Advanced search (admin-en); Search and Result lists (admin-en) | Wiki: 5.11 release information | AD79: Claus: Afklar delkrav; align tool-rating (O) med AI compliance. | AF79: Draft | AG79: uim-esdh-full-2026-07-07
A80: 79 | B80: MK-75 | C80: Bilag 1.b | D80: Søgning | E80: Søgebilleder - Felter | F80: ESDH-løsningen skal understøtte, at Kunden selv kan definere og konfigurere, hvilke standard- og Kundeoprettede felter søgebilledet skal indeholde. | G80: Mindstekrav | H80: =IF(G80="Evalueringskrav","Answer",(IF(G80="Krav","Check",(IF(G80="Mindstekrav","Verify",""))))) | I80: Ja | L80: Claus | O80: 2. Partly met | P80: ADN: Det understøtter vi ikke. COuld we argue, that it doesnt state it should remember these configurations, and therefore we live up to it? | U80: Not Started | V80: =IF(U80="Not Started",0%,IF(U80="Started",50%,IF(U80="Ready for review",70%,IF(U80="Reviewed - Content",80%,IF(U80="Reviewed - Format",90%,IF(U80="Done",100%,"")))))) | W80: 2026-07-07 | X80: Cursor / tender-response (MCP-enriched) | Y80: Partial | Z80: Lead | AA80: Verify: Søgebilleder - Felter — delvist opfyldt; afklar scope og scoring. | AB80: ADN: Det understøtter vi ikke. COuld we argue, that it doesnt state it should remember these configurations, and therefore we live up to it? | Red flag: Det understøtter vi ikke | AC80: Ratatoskr: Advanced search (admin-en) | Wiki: Build log hotfix packages | AD80: Claus: Afklar delkrav; align tool-rating (O) med AI compliance. | AF80: Draft | AG80: uim-esdh-full-2026-07-07
A81: 80 | B81: K-4 | C81: Bilag 1.b | D81: Søgning | E81: Søgeoperatorer | F81: ESDH-løsningen skal understøtte, at Brugere kan anvende følgende søgeoperatorer ved fritekstsøgning og søgning i strukturerede felter: ”Og”, ”Eller” og ”Ikke”-søgning Større end / mindre end (f.eks. ved dato- eller talfelter) Indeholder Lig med (præcis match) | G81: Krav | H81: =IF(G81="Evalueringskrav","Answer",(IF(G81="Krav","Check",(IF(G81="Mindstekrav","Verify",""))))) | I81: Ja | L81: Anton | O81: 1. Fully met | P81: ADN: We support this in a combination of global search and advanced search - it isnt specified to be in 1 place. | U81: Not Started | V81: =IF(U81="Not Started",0%,IF(U81="Started",50%,IF(U81="Ready for review",70%,IF(U81="Reviewed - Content",80%,IF(U81="Reviewed - Format",90%,IF(U81="Done",100%,"")))))) | W81: 2026-07-07 | X81: Cursor / tender-response (batch) | Y81: Met | Z81: Verified | AA81: Check: Søgeoperatorer — vurderet opfyldt (tool: 1. Fully met). | AB81: ADN: We support this in a combination of global search and advanced search - it isnt specified to be in 1 place. | AC81: docs/tender-reference/extracted/Nationalbanken/Bilag 3.i Leverandørens Løsningsbeskrivelse.txt; docs/tender-reference/extracted/KK Tender tool.txt; docs/tender-reference/extracted/KUM-SLKS/Bilag 3 - Kravspecifikation.txt | AD81: Anton: Confirm verify-tekst; opdatér review status efter tjek. | AF81: Draft | AG81: uim-esdh-full-2026-07-07
A82: 81 | B82: K-5 | C82: Bilag 1.b | D82: Søgning | E82: Abonnementer | F82: ESDH-løsningen skal understøtte, at Brugere kan abonnere på søgninger. | G82: Krav | H82: =IF(G82="Evalueringskrav","Answer",(IF(G82="Krav","Check",(IF(G82="Mindstekrav","Verify",""))))) | I82: Ja | L82: Anton | O82: 1. Fully met | U82: Not Started | V82: =IF(U82="Not Started",0%,IF(U82="Started",50%,IF(U82="Ready for review",70%,IF(U82="Reviewed - Content",80%,IF(U82="Reviewed - Format",90%,IF(U82="Done",100%,"")))))) | W82: 2026-07-07 | X82: Cursor / tender-response (batch) | Y82: Met | Z82: Lead | AA82: Check: Abonnementer — vurderet opfyldt (tool: 1. Fully met). | AC82: docs/tender-reference/extracted/KK Tender tool.txt; docs/tender-reference/extracted/KUM-SLKS/Bilag 3 - Kravspecifikation.txt; docs/tender-reference/extracted/Nationalbanken/Bilag 3.i Leverandørens Løsningsbeskrivelse.txt | AD82: Anton: Confirm verify-tekst; opdatér review status efter tjek. | AF82: Draft | AG82: uim-esdh-full-2026-07-07
A83: 82 | B83: K-6 | C83: Bilag 1.b | D83: Søgning | E83: Eksport af søgning | F83: ESDH-løsningen skal understøtte eksport af det komplette søgeresultat fra brugergrænsefladen til regnearksprogram anvendt af Kundens, men må dog ikke overstige regnearksprogrammets maksimum rækkekapacitet. | G83: Krav | H83: =IF(G83="Evalueringskrav","Answer",(IF(G83="Krav","Check",(IF(G83="Mindstekrav","Verify",""))))) | I83: Ja | L83: Claus | O83: 2. Partly met | P83: ADN: This means we must support pretty much "unlimited export to Excel" | R83: Yes | U83: Not Started | V83: =IF(U83="Not Started",0%,IF(U83="Started",50%,IF(U83="Ready for review",70%,IF(U83="Reviewed - Content",80%,IF(U83="Reviewed - Format",90%,IF(U83="Done",100%,"")))))) | W83: 2026-07-07 | X83: Cursor / tender-response (MCP-enriched) | Y83: Partial | Z83: Verified | AA83: Check: Eksport af søgning — delvist opfyldt; afklar scope og scoring. | AB83: ADN: This means we must support pretty much "unlimited export to Excel" | AC83: Wiki: 360° settings - internal reference | AD83: Claus: Afklar delkrav; align tool-rating (O) med AI compliance. | AF83: Draft | AG83: uim-esdh-full-2026-07-07
A84: 83 | B84: EK-2 | C84: Bilag 1.b | D84: Dashboards | E84: Dashboards | F84: ESDH-løsningen skal understøtte realtidsbaserede dashboards, der giver Kundens Brugere et hurtigt og overskueligt overblik over relevante data i ESDH-løsningen. Dashboard i ESDH-løsningen skal understøtte visualiseringer og udtræk af statistiske data til brug for konkret sagsbehandling, Myndighedsarbejde, ledelsestilsyn og politiske beslutninger. Leverandøren skal beskrive, hvordan den tilbudte ESDH-løsning understøtter realtidsbaserede dashboards. Leverandøren skal gennem konkrete skærmbilleder demonstrere om og hvordan ESDH-løsningen understøtter de stillede krav og møder Kundens behov. Leverandøren skal redegøre for: Hvordan ESDH-løsningen understøtter, at Administrator og Bruger kan oprette egne realtidsbaserede dashboards til sags- og driftsstyring Hvordan ESDH-løsningen understøtter visning af både individuelle og afdelingsspecifikke frister med farver eller ikoner, når en frist for eksempel nærmer sig udløb Hvilke visualiseringer som ESDH-løsningen understøtter Hvordan ESDH-løsningen understøtter effektiv og brugervenlig navigation til underliggende detaljer fra dashboards Hvordan ESDH-løsningen understøtter dashboards på Dokument og kontaktniveau Hvordan dashboards på en let og intuitiv måde kan oprettes og vedligeholdes af Administrator Hvordan dashboards på en let og intuitiv måde kan deles på organisatorisk niveau samt brugerniveau Evalueringskriterier: Det vægtes positivt, i hvor høj grad Brugere og Administratorer kan personalisere og konfigurere dashboards efter individuelle og organisatoriske behov, samt at disse kan deles på en intuitiv og brugervenlig måde. Det vægtes positivt, i hvor høj grad dashboard-visninger kan tilpasses forskellige brugerroller, medarbejderniveauer og organisatorisk opdeling. Det vægtes positivt, i hvor høj grad dashboards kan udstilles på forskellige visuelle måder herunder, at der er mulighed for at konfigurere kolonner i visningen samt, at data kan eksporteres i relevante formater. Det vægtes positivt, i hvor høj grad ESDH-løsningens dashboards kan udstille resultater i dashboard-widgets. Det vægtes positivt, i hvor høj grad dashboards kan tilpasses med en grafisk udstilling, der indeholder: Listevisninger Søjlediagrammer Cirkeldiagrammer Tællere Det vægtes positivt, i hvor høj grad data og søgeresultater, der udstilles på dashboards, opdateres automatisk i realtid uden behov for manuel opdatering (refresh). Det vægtes positivt, i hvor høj grad en Administrator kan udrulle dashboads til organisationen, afdelinger, teams og Brugere, som styres centralt. | G84: Evalueringskrav | H84: =IF(G84="Evalueringskrav","Answer",(IF(G84="Krav","Check",(IF(G84="Mindstekrav","Verify",""))))) | I84: Ja | L84: Torben | U84: Not Started | V84: =IF(U84="Not Started",0%,IF(U84="Started",50%,IF(U84="Ready for review",70%,IF(U84="Reviewed - Content",80%,IF(U84="Reviewed - Format",90%,IF(U84="Done",100%,"")))))) | W84: 2026-07-07 | X84: Cursor / tender-response (MCP-enriched) | Y84: Draft needed | Z84: Lead | AA84: Answer: Dashboards — informationskrav; udkast bilag/dokumentation mangler. | AB84: Mangler link til svar-bilag i kolonne T. | AC84: Wiki: Build log hotfix packages | AD84: Torben: Opret/link svar-bilag; draft IK-tekst fra prior art. | AF84: Draft | AG84: uim-esdh-full-2026-07-07
A85: 84 | B85: MK-76 | C85: Bilag 1.b | D85: Brugergrænsefladen | E85: Browser-baseret brugergrænseflade | F85: ESDH-løsningen skal understøtte afvikling i en af nedenstående standardbrowsere uden løsnings-specifikt plugin: Microsoft Edge Google Chrome | G85: Mindstekrav | H85: =IF(G85="Evalueringskrav","Answer",(IF(G85="Krav","Check",(IF(G85="Mindstekrav","Verify",""))))) | I85: Ja | L85: Anton | O85: 1. Fully met | P85: ADN: Påvirker ikke os - men det her krav er et godt eksempel på en Kunde der beskriver en løsning frem for et behov. Hvorfor skal det være browserbaseret? AOP: Meget standard i udbud. Baggrunden er, at det anses som værende fremtiden og lettere for kunden at administrere selv. | U85: Not Started | V85: =IF(U85="Not Started",0%,IF(U85="Started",50%,IF(U85="Ready for review",70%,IF(U85="Reviewed - Content",80%,IF(U85="Reviewed - Format",90%,IF(U85="Done",100%,"")))))) | W85: 2026-07-07 | X85: Cursor / tender-response (MCP-enriched) | Y85: Met | Z85: Verified | AA85: Verify: Browser-baseret brugergrænseflade — vurderet opfyldt (tool: 1. Fully met). | AB85: ADN: Påvirker ikke os - men det her krav er et godt eksempel på en Kunde der beskriver en løsning frem for et behov. Hvorfor skal det være browserbaseret? AOP: Meget standard i udbud. Baggrunden er, at det anses som værende fremtiden og lettere for kunden at administrere selv. | Red flag: Påvirker ikke os - men det her krav er et godt eksempel på en Kunde der beskriver en løsning frem for et behov. Hvorfor skal det være browserbaseret? | AC85: Wiki: Frontend guidelines for modern web applications; BSP design goals and technical changes | AD85: Anton: Confirm verify-tekst; opdatér review status efter tjek. | AF85: Draft | AG85: uim-esdh-full-2026-07-07
A86: 85 | B86: MK-77 | C86: Bilag 1.b | D86: Brugergrænsefladen | E86: Visning af store mængder | F86: ESDH-løsningen skal understøtte, at alle listevisninger fra standard og Kundeoprettede Entiteter eller i søgningsresultater ikke har begrænsning i antal resultater. Resultaterne kan opdeles på flere sider jf. arkitekturmønsteret pagination (processen med at opdele store mængder indhold, data eller søgeresultater i mindre, overskuelige bidder). | G86: Mindstekrav | H86: =IF(G86="Evalueringskrav","Answer",(IF(G86="Krav","Check",(IF(G86="Mindstekrav","Verify",""))))) | I86: Ja | L86: Claus | O86: 3. Not able to meet | P86: ADN: Issue - ”Alle” og ”ingen begrænsning” i samme sætning.. | R86: Yes | U86: Not Started | V86: =IF(U86="Not Started",0%,IF(U86="Started",50%,IF(U86="Ready for review",70%,IF(U86="Reviewed - Content",80%,IF(U86="Reviewed - Format",90%,IF(U86="Done",100%,"")))))) | W86: 2026-07-07 | X86: Cursor / tender-response (MCP-enriched) | Y86: Not met | Z86: Lead | AA86: Verify: Visning af store mængder — gap ift. kravtekst; eskalér commitment eller afklaring. | AB86: ADN: Issue - ”Alle” og ”ingen begrænsning” i samme sætning.. | Red flag: Issue - ”Alle” og ”ingen begrænsning” i samme sætning.. | AC86: Ratatoskr: Search and Result lists (admin-en) | Wiki: 5.14 release information | AD86: Claus: Commitment/no-bid beslutning; overvej Q&A til ordregiver. | AF86: Draft | AG86: uim-esdh-full-2026-07-07
A87: 86 | B87: MK-78 | C87: Bilag 1.b | D87: Brugergrænsefladen | E87: Genvejstaster | F87: ESDH-løsningen skal understøtte brugen af genvejstaster, funktionstaster eller tastekombinationer. Genvejstaster skal være dokumenteret i hjælpefunktionen. | G87: Mindstekrav | H87: =IF(G87="Evalueringskrav","Answer",(IF(G87="Krav","Check",(IF(G87="Mindstekrav","Verify",""))))) | I87: Ja | L87: Anton | O87: 1. Fully met | P87: ADN: Det her bevæger vi os væk fra, fordi det ikke er særligt WCAG-compliant. MEN - vi skal bemærke de ikke definere det skal gælde alt, eller hvad man skal kunne, så hvis vi har en genvejstast ét sted i løsningen, kan vi principielt sige ja til dette krav. Vi understøtter brugen af "Tab" og "Enter" - vi skal bare sikre os det står i onlinehjælpen. | U87: Not Started | V87: =IF(U87="Not Started",0%,IF(U87="Started",50%,IF(U87="Ready for review",70%,IF(U87="Reviewed - Content",80%,IF(U87="Reviewed - Format",90%,IF(U87="Done",100%,"")))))) | W87: 2026-07-07 | X87: Cursor / tender-response (MCP-enriched) | Y87: Met | Z87: Lead | AA87: Verify: Genvejstaster — vurderet opfyldt (tool: 1. Fully met). | AB87: ADN: Det her bevæger vi os væk fra, fordi det ikke er særligt WCAG-compliant. MEN - vi skal bemærke de ikke definere det skal gælde alt, eller hvad man skal kunne, så hvis vi har en genvejstast ét sted i løsningen, kan vi principielt sige ja til dette krav. Vi understøtter brugen af "Tab" og "Enter" - vi skal bare sikre os det står i onlinehjælpen. | Red flag: Det her bevæger vi os væk fra, fordi det ikke er særligt WCAG-compliant. MEN - vi skal bemærke de ikke definere det skal gælde alt, eller hvad man skal kunne, så hvis vi har en genvejstast ét sted i løsningen, kan vi principielt sige ja til dette krav. | AC87: No keyboard shortcut documentation in help or wiki | AD87: Anton: Confirm verify-tekst; opdatér review status efter tjek. | AF87: Draft | AG87: uim-esdh-full-2026-07-07
A88: 87 | B88: MK-79 | C88: Bilag 1.b | D88: Brugergrænsefladen | E88: Obligatoriske felter | F88: ESDH-løsningen skal understøtte en tydelig marker af obligatoriske felter i forbindelse med oprettelse eller redigering af Entiteter. | G88: Mindstekrav | H88: =IF(G88="Evalueringskrav","Answer",(IF(G88="Krav","Check",(IF(G88="Mindstekrav","Verify",""))))) | I88: Ja | L88: Anton | O88: 1. Fully met | U88: Not Started | V88: =IF(U88="Not Started",0%,IF(U88="Started",50%,IF(U88="Ready for review",70%,IF(U88="Reviewed - Content",80%,IF(U88="Reviewed - Format",90%,IF(U88="Done",100%,"")))))) | W88: 2026-07-07 | X88: Cursor / tender-response (batch) | Y88: Met | Z88: Verified | AA88: Verify: Obligatoriske felter — vurderet opfyldt (tool: 1. Fully met). | AC88: docs/tender-reference/extracted/Nationalbanken/Bilag 3.i Leverandørens Løsningsbeskrivelse.txt; docs/product/RFP_Leverandørens_svar_utdrag.txt; docs/tender-reference/extracted/HSØ/02.00-Tietoevry-SSA-L-Bilag 2-Leverandørens beskrivelse av Tjenesten.txt | AD88: Anton: Confirm verify-tekst; opdatér review status efter tjek. | AF88: Draft | AG88: uim-esdh-full-2026-07-07
A89: 88 | B89: MK-80 | C89: Bilag 1.b | D89: Brugergrænsefladen | E89: Masseændring | F89: ESDH-løsningen skal understøtte, at en Bruger via brugergrænsefladen kan foretage masseændringer af tilknyttede standard- og Kundeoprettede felter på sager, Dokumenter, kontakter og Kundeoprettede Entiteter. | G89: Mindstekrav | H89: =IF(G89="Evalueringskrav","Answer",(IF(G89="Krav","Check",(IF(G89="Mindstekrav","Verify",""))))) | I89: Ja | L89: Torben | O89: 3. Not able to meet | P89: ADN: Vi skal bemærke de ikke bruger ordet ”Alle” i denne sætning - meeeen.. Vi har det slet ikke for Kontakter, projekter, ejendomme og aktiviteter, og vi har det ingen steder for kundeoprettede felter. (De specificere heller ikke at det skal være på alle kundeoprettede entiteter) Måske vi kan bruge det til noget. | Q89: Yes | U89: Not Started | V89: =IF(U89="Not Started",0%,IF(U89="Started",50%,IF(U89="Ready for review",70%,IF(U89="Reviewed - Content",80%,IF(U89="Reviewed - Format",90%,IF(U89="Done",100%,"")))))) | W89: 2026-07-07 | X89: Cursor / tender-response (MCP-enriched) | Y89: Not met | Z89: Lead | AA89: Verify: Masseændring — gap ift. kravtekst; eskalér commitment eller afklaring. | AB89: ADN: Vi skal bemærke de ikke bruger ordet ”Alle” i denne sætning - meeeen.. Vi har det slet ikke for Kontakter, projekter, ejendomme og aktiviteter, og vi har det ingen steder for kundeoprettede felter. (De specificere heller ikke at det skal være på alle kundeoprettede entiteter) Måske vi kan bruge det til noget. | Red flag: Vi skal bemærke de ikke bruger ordet ”Alle” i denne sætning - meeeen.. Vi har det slet ikke for Kontakter, projekter, ejendomme og aktiviteter, og vi har det ingen steder for kundeoprettede felter. (De specificere heller ikke at det skal være på alle kundeoprettede entiteter) Måske vi kan bruge det til noget. | AC89: Wiki: 5.14 release information; 6.0 release information | AD89: Torben: Commitment/no-bid beslutning; overvej Q&A til ordregiver. | AF89: Draft | AG89: uim-esdh-full-2026-07-07
A90: 89 | B90: MK-81 | C90: Bilag 1.b | D90: Brugergrænsefladen | E90: Visuel visning på Dokument metadata | F90: ESDH-løsningen skal understøtte en visuel adskillelse af indgående og udgående Dokumenter, f.eks. via opmærkning. | G90: Mindstekrav | H90: =IF(G90="Evalueringskrav","Answer",(IF(G90="Krav","Check",(IF(G90="Mindstekrav","Verify",""))))) | I90: Ja | L90: Anton | O90: 1. Fully met | P90: ADN: Hvornår er noget ”Visuelt adskilt”? - er det nok at der står ”Indgående” og/eller ”Udgående”? hos os står der "Dokument ind", eller "dokument ud" - det er vel visuelt adskildt.. Jeg kan se at der ikke står det samme? | U90: Not Started | V90: =IF(U90="Not Started",0%,IF(U90="Started",50%,IF(U90="Ready for review",70%,IF(U90="Reviewed - Content",80%,IF(U90="Reviewed - Format",90%,IF(U90="Done",100%,"")))))) | W90: 2026-07-07 | X90: Cursor / tender-response (MCP-enriched) | Y90: Met | Z90: Lead | AA90: Verify: Visuel visning på Dokument metadata — vurderet opfyldt (tool: 1. Fully met). | AB90: ADN: Hvornår er noget ”Visuelt adskilt”? - er det nok at der står ”Indgående” og/eller ”Udgående”? hos os står der "Dokument ind", eller "dokument ud" - det er vel visuelt adskildt.. Jeg kan se at der ikke står det samme? | Red flag: Hvornår er noget ”Visuelt adskilt”? - er det nok at der står ”Indgående” og/eller ”Udgående”? | AC90: Wiki: 6.8 release information; EDoc Documentation for Support | AD90: Anton: Confirm verify-tekst; opdatér review status efter tjek. | AF90: Draft | AG90: uim-esdh-full-2026-07-07
A91: 90 | B91: MK-82 | C91: Bilag 1.b | D91: Brugergrænsefladen | E91: Markering af obligatoriske felter | F91: ESDH-løsningen skal understøtte en tydelig markering af, om felter er obligatoriske. Det skal være gældende for Løsningens standard- og Kundeoprettede felter. | G91: Mindstekrav | H91: =IF(G91="Evalueringskrav","Answer",(IF(G91="Krav","Check",(IF(G91="Mindstekrav","Verify",""))))) | I91: Ja | L91: Anton | O91: 1. Fully met | U91: Not Started | V91: =IF(U91="Not Started",0%,IF(U91="Started",50%,IF(U91="Ready for review",70%,IF(U91="Reviewed - Content",80%,IF(U91="Reviewed - Format",90%,IF(U91="Done",100%,"")))))) | W91: 2026-07-07 | X91: Cursor / tender-response (batch) | Y91: Met | Z91: Verified | AA91: Verify: Markering af obligatoriske felter — vurderet opfyldt (tool: 1. Fully met). | AC91: docs/tender-reference/extracted/KK Tender tool.txt; docs/tender-reference/extracted/KUM-SLKS/Bilag 3 - Kravspecifikation.txt; docs/tender-reference/extracted/Nationalbanken/Bilag 3.i Leverandørens Løsningsbeskrivelse.txt | AD91: Anton: Confirm verify-tekst; opdatér review status efter tjek. | AF91: Draft | AG91: uim-esdh-full-2026-07-07
A92: 91 | B92: MK-83 | C92: Bilag 1.b | D92: Brugergrænsefladen | E92: Kolonnevisninger - Standard | F92: ESDH-løsningen skal understøtte at Kunden kan tilvælge og fravælge kolonnevisninger på sager, Dokumenter, kontakt-billeder. | G92: Mindstekrav | H92: =IF(G92="Evalueringskrav","Answer",(IF(G92="Krav","Check",(IF(G92="Mindstekrav","Verify",""))))) | I92: Ja | L92: Torben | O92: 3. Not able to meet | P92: ADN Det understøtter vi ikke - jeg tænker de mener kolonner inde i webparts på vores overbliksbilleder. | U92: Not Started | V92: =IF(U92="Not Started",0%,IF(U92="Started",50%,IF(U92="Ready for review",70%,IF(U92="Reviewed - Content",80%,IF(U92="Reviewed - Format",90%,IF(U92="Done",100%,"")))))) | W92: 2026-07-07 | X92: Cursor / tender-response (MCP-enriched) | Y92: Not met | Z92: Lead | AA92: Verify: Kolonnevisninger - Standard — gap ift. kravtekst; eskalér commitment eller afklaring. | AB92: ADN Det understøtter vi ikke - jeg tænker de mener kolonner inde i webparts på vores overbliksbilleder. | Red flag: Det understøtter vi ikke - jeg tænker de mener kolonner inde i webparts på vores overbliksbilleder. | AC92: Wiki: 360° Version 5 changes in detail views and wizards | AD92: Torben: Commitment/no-bid beslutning; overvej Q&A til ordregiver. | AF92: Draft | AG92: uim-esdh-full-2026-07-07
A93: 92 | B93: MK-84 | C93: Bilag 1.b | D93: Brugergrænsefladen | E93: Kolonnevisninger - Kundeoprettede | F93: ESDH-løsningen skal understøtte, at Kunden kan tilvælge og fravælge kolonnevisninger på Kundeoprettede Entiteter. | G93: Mindstekrav | H93: =IF(G93="Evalueringskrav","Answer",(IF(G93="Krav","Check",(IF(G93="Mindstekrav","Verify",""))))) | I93: Ja | L93: Torben | O93: 3. Not able to meet | P93: ADN: Det understøtter vi ikke - jeg tænker de mener kolonner inde i webparts på vores overbliksbilleder. | U93: Not Started | V93: =IF(U93="Not Started",0%,IF(U93="Started",50%,IF(U93="Ready for review",70%,IF(U93="Reviewed - Content",80%,IF(U93="Reviewed - Format",90%,IF(U93="Done",100%,"")))))) | W93: 2026-07-07 | X93: Cursor / tender-response (MCP-enriched) | Y93: Not met | Z93: Lead | AA93: Verify: Kolonnevisninger - Kundeoprettede — gap ift. kravtekst; eskalér commitment eller afklaring. | AB93: ADN: Det understøtter vi ikke - jeg tænker de mener kolonner inde i webparts på vores overbliksbilleder. | Red flag: Det understøtter vi ikke - jeg tænker de mener kolonner inde i webparts på vores overbliksbilleder. | AC93: Wiki: 360° Version 5 changes in detail views and wizards | AD93: Torben: Commitment/no-bid beslutning; overvej Q&A til ordregiver. | AF93: Draft | AG93: uim-esdh-full-2026-07-07
A94: 93 | B94: MK-85 | C94: Bilag 1.b | D94: Brugergrænsefladen | E94: Kundeoprettede felter på kolonnevisning | F94: ESDH-løsningen skal understøtte, at Kundeoprettede felter skal kunne anvendes i kolonnevisningerne på standard Entiteter og Kundeoprettede Entiteter. | G94: Mindstekrav | H94: =IF(G94="Evalueringskrav","Answer",(IF(G94="Krav","Check",(IF(G94="Mindstekrav","Verify",""))))) | I94: Ja | L94: Torben | O94: 3. Not able to meet | P94: ADN: Det understøtter vi ikke - jeg tænker de mener kolonner inde i webparts på vores overbliksbilleder.Vi gemmer ikke sorteringer og filtreringer | U94: Not Started | V94: =IF(U94="Not Started",0%,IF(U94="Started",50%,IF(U94="Ready for review",70%,IF(U94="Reviewed - Content",80%,IF(U94="Reviewed - Format",90%,IF(U94="Done",100%,"")))))) | W94: 2026-07-07 | X94: Cursor / tender-response (MCP-enriched) | Y94: Not met | Z94: Lead | AA94: Verify: Kundeoprettede felter på kolonnevisning — gap ift. kravtekst; eskalér commitment eller afklaring. | AB94: ADN: Det understøtter vi ikke - jeg tænker de mener kolonner inde i webparts på vores overbliksbilleder.Vi gemmer ikke sorteringer og filtreringer | Red flag: Det understøtter vi ikke - jeg tænker de mener kolonner inde i webparts på vores overbliksbilleder. | AC94: Ratatoskr: Custom fields (admin-en) | Wiki: Build log hotfix packages; 6.0 release information | AD94: Torben: Commitment/no-bid beslutning; overvej Q&A til ordregiver. | AF94: Draft | AG94: uim-esdh-full-2026-07-07
A95: 94 | B95: MK-86 | C95: Bilag 1.b | D95: Brugergrænsefladen | E95: Filtrering og sortering på kolonnevisninger | F95: ESDH-løsningen skal understøtte filtrering og sortering på kolonnevisninger. Brugerens valgte indstillinger skal kunne gemmes som standardvisning for Brugeren. | G95: Mindstekrav | H95: =IF(G95="Evalueringskrav","Answer",(IF(G95="Krav","Check",(IF(G95="Mindstekrav","Verify",""))))) | I95: Ja | L95: Torben | O95: 3. Not able to meet | P95: ADN: Det understøtter vi ikke - jeg tænker de mener kolonner inde i webparts på vores overbliksbilleder.Vi gemmer ikke sorteringer og filtreringer | U95: Not Started | V95: =IF(U95="Not Started",0%,IF(U95="Started",50%,IF(U95="Ready for review",70%,IF(U95="Reviewed - Content",80%,IF(U95="Reviewed - Format",90%,IF(U95="Done",100%,"")))))) | W95: 2026-07-07 | X95: Cursor / tender-response (MCP-enriched) | Y95: Not met | Z95: Lead | AA95: Verify: Filtrering og sortering på kolonnevisninger — gap ift. kravtekst; eskalér commitment eller afklaring. | AB95: ADN: Det understøtter vi ikke - jeg tænker de mener kolonner inde i webparts på vores overbliksbilleder.Vi gemmer ikke sorteringer og filtreringer | Red flag: Det understøtter vi ikke - jeg tænker de mener kolonner inde i webparts på vores overbliksbilleder.Vi gemmer ikke sorteringer og filtreringer | AC95: Wiki: Build log hotfix packages; 5.9 release information | AD95: Torben: Commitment/no-bid beslutning; overvej Q&A til ordregiver. | AF95: Draft | AG95: uim-esdh-full-2026-07-07
A96: 95 | B96: MK-87 | C96: Bilag 1.b | D96: Brugergrænsefladen | E96: Faner og widgets | F96: ESDH-løsningen skal understøtte, at Kunden kan opsætte Kundeoprettede faner/widgets på både standard- og Kundeoprettede Entiteter. | G96: Mindstekrav | H96: =IF(G96="Evalueringskrav","Answer",(IF(G96="Krav","Check",(IF(G96="Mindstekrav","Verify",""))))) | I96: Ja | L96: Torben | O96: 3. Not able to meet | P96: ADN: ”kundeoprettede faner” på overbliksbilleder kræver en voldsomt udvidelse af FFUI Overbliksbilleder | U96: Not Started | V96: =IF(U96="Not Started",0%,IF(U96="Started",50%,IF(U96="Ready for review",70%,IF(U96="Reviewed - Content",80%,IF(U96="Reviewed - Format",90%,IF(U96="Done",100%,"")))))) | W96: 2026-07-07 | X96: Cursor / tender-response (MCP-enriched) | Y96: Not met | Z96: Lead | AA96: Verify: Faner og widgets — gap ift. kravtekst; eskalér commitment eller afklaring. | AB96: ADN: ”kundeoprettede faner” på overbliksbilleder kræver en voldsomt udvidelse af FFUI Overbliksbilleder | Red flag: ”kundeoprettede faner” på overbliksbilleder kræver en voldsomt udvidelse af FFUI Overbliksbilleder | AC96: No custom tabs/widgets on entity overviews documentation | AD96: Torben: Commitment/no-bid beslutning; overvej Q&A til ordregiver. | AF96: Draft | AG96: uim-esdh-full-2026-07-07
A97: 96 | B97: MK-88 | C97: Bilag 1.b | D97: Brugergrænsefladen | E97: Fleksibilitet | F97: ESDH-løsningen skal understøtte, at Kunden har fuld fleksibilitet til vælge, hvor Kundeoprettede Entiteter og Kundeoprettede felter vises i brugergrænsefladen. | G97: Mindstekrav | H97: =IF(G97="Evalueringskrav","Answer",(IF(G97="Krav","Check",(IF(G97="Mindstekrav","Verify",""))))) | I97: Ja | L97: Torben | O97: 3. Not able to meet | P97: ADN: Hvis vi nu tolker det her til webparten "brugerdefinerede felter" og webparten: "Ejendomme", "Projekter" og "Aktiviteter" - så kan kunden jo godt på sags- og dokumentoversigter bestemme hvor disse vises. Vi har det dog ikke på kontaktoverblik. | U97: Not Started | V97: =IF(U97="Not Started",0%,IF(U97="Started",50%,IF(U97="Ready for review",70%,IF(U97="Reviewed - Content",80%,IF(U97="Reviewed - Format",90%,IF(U97="Done",100%,"")))))) | W97: 2026-07-07 | X97: Cursor / tender-response (MCP-enriched) | Y97: Not met | Z97: Lead | AA97: Verify: Fleksibilitet — gap ift. kravtekst; eskalér commitment eller afklaring. | AB97: ADN: Hvis vi nu tolker det her til webparten "brugerdefinerede felter" og webparten: "Ejendomme", "Projekter" og "Aktiviteter" - så kan kunden jo godt på sags- og dokumentoversigter bestemme hvor disse vises. Vi har det dog ikke på kontaktoverblik. | Red flag: Understøttes ikke | AC97: Wiki: Flexibility initiatives; Full-Flex UI entity creation | AD97: Torben: Commitment/no-bid beslutning; overvej Q&A til ordregiver. | AF97: Draft | AG97: uim-esdh-full-2026-07-07
A98: 97 | B98: K-7 | C98: Bilag 1.b | D98: Brugergrænsefladen | E98: Relationer skal være navigerbare | F98: Løsningen skal understøtte, at relationer mellem standardentiteter og Kundens egne oprettede Entiteter er aktive og navigerbare i brugergrænsefladen. Det skal være muligt for Brugeren at klikke på en reference til en relateret Entitet og blive ledt direkte til den pågældende Entitets indhold, metadata og tilknyttede relationer. Eksempelvis skal en Bruger, der står på en sag, kunne vælge et relateret Dokument og blive ledt direkte til Dokumentet og dets metadata. Hvis Dokumentet er tilknyttet en kontakt, f.eks. en Udlænding, skal Brugeren tilsvarende kunne klikke på kontakten og blive ledt til kontaktens stamdata, metadata og relaterede sager, Dokumenter eller øvrige relevante Entiteter. | G98: Krav | H98: =IF(G98="Evalueringskrav","Answer",(IF(G98="Krav","Check",(IF(G98="Mindstekrav","Verify",""))))) | I98: Ja | L98: Anton | O98: 1. Fully met | U98: Not Started | V98: =IF(U98="Not Started",0%,IF(U98="Started",50%,IF(U98="Ready for review",70%,IF(U98="Reviewed - Content",80%,IF(U98="Reviewed - Format",90%,IF(U98="Done",100%,"")))))) | W98: 2026-07-07 | X98: Cursor / tender-response (batch) | Y98: Met | Z98: Verified | AA98: Check: Relationer skal være navigerbare — vurderet opfyldt (tool: 1. Fully met). | AC98: docs/tender-reference/extracted/Nationalbanken/Bilag 3.i Leverandørens Løsningsbeskrivelse.txt; docs/tender-reference/extracted/KK Tender tool.txt; docs/tender-reference/extracted/KUM-SLKS/Bilag 3 - Kravspecifikation.txt | AD98: Anton: Confirm verify-tekst; opdatér review status efter tjek. | AF98: Draft | AG98: uim-esdh-full-2026-07-07
A99: 98 | B99: EK-3 | C99: Bilag 1.b | D99: Brugergrænsefladen | E99: Bruger-grænseflade | F99: I forbindelse med Kundens daglige anvendelse af ESDH-løsningen er det væsentligt, at brugergrænsefladen kan tilpasses den enkelte Brugers og organisationens behov, herunder ved tilpasning, filtrering og sortering af faner/widgets, felter og kolonner. Leverandøren skal beskrive, hvordan den tilbudte ESDH-løsning understøtter tilpasning af brugergrænsefladen. Leverandøren skal gennem konkrete skærmbilleder demonstrere om og hvordan ESDH-løsningen understøtter de stillede krav og møder Kundens behov. Leverandøren skal redegøre for: Hvordan ESDH-løsningen giver Brugeren hurtig og overskuelig adgang til relevante oplysninger i forbindelse med sagsbehandling Hvordan Brugeren kan personalisere brugergrænsefladen f.eks. via tilpasning af kolonner på alle Entiteter og søgebilleder Hvordan Brugeren kan personalisere visningsbilleder via filtrering og sortering Hvilke muligheder Administratoren har for at tilpasse udstillingen af data på sager, Dokumenter og kontakter Hvordan Administratoren kan tilpasse søgebilleder og resultatlister Hvordan Administratoren kan konfigurere og udrulle opsætning til hele organisationen samt udvalgte teams og medarbejdere Evalueringskriterier: Det vægtes positivt, i hvor høj grad Brugeren kan personalisere brugergrænsefladen til egne behov f.eks. tilpasning af kolonner i alle visningsbilleder. Det vægtes positivt, i hvor høj grad Administratoren kan tilpasse brugergrænsefladen på alle Entiteter, visningsbilleder, resultatlister og søgebilleder f.eks. tilpasning af kolonner, filtreringer og placering af felter. Det vægtes positivt, i hvor høj grad Administratoren kan udrulle opsætninger og tilpasninger på flere organisatoriske niveauer samt at Administratoren kan begrænse muligheden for bruger-personalisering af den udrullede opsætning. Det vægtes positivt, i hvor høj grad Administratoren kan tilføje og fjerne både standardfelter og Kundeoprettede felter fra alle Entiteters visnings- og søgebilleder. | G99: Evalueringskrav | H99: =IF(G99="Evalueringskrav","Answer",(IF(G99="Krav","Check",(IF(G99="Mindstekrav","Verify",""))))) | I99: Ja | L99: Claus | U99: Not Started | V99: =IF(U99="Not Started",0%,IF(U99="Started",50%,IF(U99="Ready for review",70%,IF(U99="Reviewed - Content",80%,IF(U99="Reviewed - Format",90%,IF(U99="Done",100%,"")))))) | W99: 2026-07-07 | X99: Cursor / tender-response (MCP-enriched) | Y99: Draft needed | Z99: Lead | AA99: Answer: Bruger-grænseflade — informationskrav; udkast bilag/dokumentation mangler. | AB99: Mangler link til svar-bilag i kolonne T. | AC99: Wiki: Full-Flex UI entity creation; Flexibility initiatives | AD99: Claus: Opret/link svar-bilag; draft IK-tekst fra prior art. | AF99: Draft | AG99: uim-esdh-full-2026-07-07
A100: 99 | B100: MK-89 | C100: Bilag 1.b | D100: Aktindsigt | E100: Oprettelse og behandling af aktindsigter | F100: ESDH-løsningen skal understøtte oprettelse og behandling af aktindsigter som sagstyper i ESDH-løsningen i henhold til både Forvaltningsloven og Offentlighedsloven. | G100: Mindstekrav | H100: =IF(G100="Evalueringskrav","Answer",(IF(G100="Krav","Check",(IF(G100="Mindstekrav","Verify",""))))) | I100: Ja | L100: Anton | O100: 1. Fully met | U100: Not Started | V100: =IF(U100="Not Started",0%,IF(U100="Started",50%,IF(U100="Ready for review",70%,IF(U100="Reviewed - Content",80%,IF(U100="Reviewed - Format",90%,IF(U100="Done",100%,"")))))) | W100: 2026-07-07 | X100: Cursor / tender-response (batch) | Y100: Met | Z100: Verified | AA100: Verify: Oprettelse og behandling af aktindsigter — vurderet opfyldt (tool: 1. Fully met). | AC100: docs/tender-reference/extracted/KK Tender tool.txt; docs/tender-reference/extracted/Nationalbanken/Bilag 3.i Leverandørens Løsningsbeskrivelse.txt; docs/tender-reference/extracted/KUM-SLKS/Bilag 3 - Kravspecifikation.txt | AD100: Anton: Confirm verify-tekst; opdatér review status efter tjek. | AF100: Draft | AG100: uim-esdh-full-2026-07-07
...

Sheet Red flags
A1: Krav nr. | B1: Kravtekst | C1: Kommentar
A2: MK-30 | B2: MK-30 | C2: Det er kludret formuleret - men jeg tolker det til, at de fra en søgning på et projekt, skal kunne se relaterede sager i resultatlisterne.. Det er udfordrende
A3: MK-35 | B3: ESDH-løsningen skal understøtte, at alle Dokumenter, Filer, Hoveddokumenter og Bilag har hver deres unikke ID, som skal være synligt i brugergrænsefladen. | C3: Hvornår er noget ”synligt i brugergrænsefladen”… vi har recno på filer, men de kræver ”vis egenskaber” for at være synlige.
A4: MK-49 | B4: ESDH-løsningen skal understøtte en integreret dokumentviewer i brugergrænsefladen. Løsningen skal understøtte forhåndsvisning af Dokumenter fra sager, søgninger og listevisninger. ESDH-løsningen skal understøtte, at Brugeren får præsenteret Dokumentets tekst/indhold direkte i Løsningen. | C4: ”Direkte” er problematisk, hvis det forbyder os fra et nyt vindue.
A5: MK-50 | B5: ESDH-løsningen skal understøtte, at Brugeren kan navigere og scrolle i dokument- og fillistevisninger, og at forhåndsvisningen automatisk opdateres og viser det Dokument/Fil, som Brugeren har navigeret til. | C5: Vores forhåndsvisning ”opdateres ikke automatisk”. Kræver aktivt klik på det dokument/fil der ønskes forhåndsvist.
A6: MK-56 | B6: ESDH-løsningen skal understøtte, at en Bruger ikke kan oprette en kontakt, hvis kontaktens unikke ID allerede findes i kontaktregisteret. | C6: Vi advarer, men vi forbyder ikke. CPR/CVR er ikke så unikt at det ikke kan duplikeres.
A7: MK-66 | B7: ESDH-løsningen skal understøtte, at der kan søges på alle standard- og Kundeoprettede felter på samme tid i ESDH-løsningen. | C7: Det her krav er formuleret uden logiske begræsninger mellem entiteter, hvilke tikke giver mening. Det kan vi ikke understøtte.
A8: MK-68 | B8: Trunkering i avanceret søgning | C8: Det her lugter af at være givet titlen her, fordi de ved vi ikke kan i den avancerede søgning - men kravteksten indeholder det ikke, og derfor bør vi være OK med kravet
A9: MK-70 | B9: ESDH-løsningen skal understøtte, at alle felter kan vises i søgeresultaternes visningslister. | C9: ”Alle felter” - godt nok afgrænset til søgeresultater, men stadig en stor risc, fra en ondsindet kunde.
A10: MK-74 | B10: ESDH-løsningen skal understøtte, at Kunden kan opsætte og konfigurere søgebilleder for alle Løsningens standard- og Kundeoprettede Entiteter. | C10: Det understøtter vi ikke.
A11: MK-75 | B11: ESDH-løsningen skal understøtte, at Kunden selv kan definere og konfigurere, hvilke standard- og Kundeoprettede felter søgebilledet skal indeholde. | C11: Det understøtter vi ikke
A12: MK-76 | B12: MK-76 | C12: Påvirker ikke os - men det her krav er et godt eksempel på en Kunde der beskriver en løsning frem for et behov. Hvorfor skal det være browserbaseret?
... A53: Fordeling af krav | B53: I udbudsmaterialet findes der følgende fordeling af krav: - ca. 217 krav (83 %) er klassificeret som Mindstekrav, - ca. 33 krav (13 %) er klassificeret som Krav, - kun ca. 12 krav (4 %) er klassificeret som Evalueringskrav. | C53: Tommelfingerreglen for offentlige udbud er, at kun omkring 10% af et udbuds totale antal krav bør være mindstekrav.

Sheet Q&A
A1: # | B1: Relates to requirement ID | C1: Sender | D1: Question | E1: Sent Date | F1: Answer | G1: Received Date | H1: Comment
A2: 1 | B2: Leveringskontrakten: Punkt 16.1 (Forsinkelse) Punkt 16.3 (Bod) Punkt 16.4 (Erstatning) Bilag 1.h Servicemål (SLA-bod) Bilag 5 CSR (CSR-bod) Bilag 6 Trepartsaftale (bod ved mangelfuld rapportering til SKI) | C2: Tieto | D2: Leveringskontrakten fastsætter et bod-system med følgende elementer: (1) Dagbod på 0,1% af evalueringsteknisk pris (minimum DKK 1.500/dag) fra dag 31 af forsinkelse, (2) Supplerende bodspoint ved SLA-overtrædelser værdsatte til leverandørens timepris, (3) Maksimalt bod på 10% af evalueringsteknisk pris. Bod kan modregnes direkte i vederlaget. Den samlede bod-risiko kan dermed udgøre væsentligt af projektets fortjeneste. Leverandøren finder, at de samlede bodsbestemmelser i Leveringskontrakten og de tilhørende bilag er væsentligt mere vidtgående end det, der almindeligvis ses i markedet for tilsvarende offentlige it-kontrakter. Kontrakten indeholder blandt andet bod ved implementeringsforsinkelse, bod ved mangler, særskilte bodsbestemmelser for servicemål, CSR-relaterede bodsbestemmelser samt bodsbestemmelser i trepartsaftalen med SKI. Efter tilbudsgivers opfattelse medfører dette et uforholdsmæssigt højt risikoniveau, idet flere bodsregimer kan finde anvendelse parallelt for samme kontraktforhold. Den samlede regulering fremstår derfor ikke markedskonform og understøtter efter tilbudsgivers vurdering ikke et balanceret kontraktforhold, hvor begge parter har et fælles incitament til at løse udfordringer i samarbejde. Som bestemmelserne er udformet, kan de eksempelvis føre til situationer, hvor: samme hændelse udløser flere samtidige bodskrav efter forskellige bilag, mindre eller kortvarige afvigelser med begrænset forretningsmæssig betydning kan udløse betydelige økonomiske sanktioner, bod kan påløbe, selv om leverandøren arbejder aktivt og loyalt på at afhjælpe forholdet, kunden får et økonomisk incitament til at lade bod fortsætte frem for hurtigt at samarbejde om en praktisk løsning, fordi kontrakten ikke i tilstrækkelig grad understøtter afhjælpning før sanktionering. Vil Kunden derfor overveje at justere bodsbestemmelserne, så de samlet set bliver mere proportionale og markedskonforme, eksempelvis ved at: begrænse muligheden for kumulation af bod, reducere bodsniveauerne, indføre en rimelig afhjælpningsperiode før bod pålægges, fastsætte et samlet loft for bod på tværs af kontrakten og bilagene. En sådan justering vil efter tilbudsgivers vurdering skabe et mere balanceret kontraktgrundlag, hvor sanktioner fortsat kan anvendes ved væsentlig misligholdelse, men hvor kontrakten i højere grad understøtter et samarbejde om hurtig afhjælpning og en succesfuld leverance. Det kombinerede bod-system (dagbod + bodspoint) udgør en betydelig finansiel risiko uden tydelige årsagssammenhænge til kundens tab. En 10% maksimalbod kan være højere end projektets nettoresultat. Hvis leverandøren ikke kan påtage sig sådan risiko uden væsentlig prisforhøjelse, eller hvis risikoen vurderes som uacceptabel, kan dette påvirke antallet og kvaliteten af tilbud. Kun meget store leverandører med høj risiko-tolerance kan være villige til at byde under disse betingelser. | H2: Afventer - efter ferien
A3: 2 | B3: Bilag 1 Kundens opgavebeskrivelse Punkt 2.2 Support og vedligeholdelse Punkt 2.3 Implementering Punkt 3 Eksisterende it-miljø Punkt 4 Tidsplan Bilag 1.c Kundens eksisterende it-landskab Bilag 1.g Samarbejde under Leveringskontrakten Bilag 1.h Servicemål Bilag 1.l Statens IT's driftsmodeller | C3: Tieto | D3: Leverandøren implementerer ESDH-systemet, men Statens IT (SIT) driver og supporterer det i produktionsmiljø efter Go-Live. Ansvarsgrænsen mellem disse to roller er ikke præcist defineret. Det er uklart: Hvem er ansvarlig hvis SIT's infrastruktur fejler? Hvem betaler hvis SIT ikke leverer promised ressourcer (CPU-kapacitet, lagring, backup)? Kan leverandøren blive pålagt bod for SLA-overtrædelser der skyldes SIT's manglende drift-ressourcer?  Kan I præcisere grænserne for ansvar mellem leverandørens implementering og SIT's drift? Specifikt: (1) Hvis systemet ikke opnår den fastsatte tilgængelighed eller performance på grund af utilstrækkelig infrastruktur fra SIT, hvem betaler? (2) Hvad er proceduren hvis SIT kan ikke levere promised drift-ressourcer? (3) Er der SLA'er for SIT's drift, og hvordan håndteres overtrædelser af disse SLA'er? Baggrund for spørgsmål: Hvis leverandøren kan blive pålagt bod for SLAovertrædelser der skyldes SIT's drift-mangler, betyder det, at leverandøren kan straffes økonomisk for fejl som ligger uden for deres kontrol. Dette øger risikoen betydeligt og kan være uacceptabelt for leverandøren. Manglende klarhed omkring ansvarsgrænserne kan føre til tvister og påvirke leverandørens vilje til at acceptere SLA'er. | H3: Afventer - efter ferien
A4: 4 | B4: Bilag 1.b Krav til standardsoftware Samtlige MK, K og EK Bilag 1.e Krav til IT- og informationssikkerhed Samtlige MK og K Opfordringsskrivelsen Afsnit om evaluering Afsnit om konditionsmæssighed | C4: Tieto | D4: I udbudsmaterialet findes der følgende fordeling af krav: - ca. 217 krav (83 %) er klassificeret som Mindstekrav, - ca. 33 krav (13 %) er klassificeret som Krav, - kun ca. 12 krav (4 %) er klassificeret som Evalueringskrav. Det betyder, at langt hovedparten af kravene er ufravigelige Mindstekrav, som tilbudsgiver skal opfylde, mens kun en meget begrænset del af kravene giver mulighed for, at Ordregiver kan evaluere forskellige løsningsforslag og deres kvalitet. Tommelfingerreglen for offentlige udbud er, at kun omkring 10% af et udbuds totale antal krav bør være mindstekrav. Efter vores opfattelse indebærer en så høj andel af detaljerede Mindstekrav en risiko for, at konkurrencen begrænses unødigt, idet leverandørerne kun i begrænset omfang får mulighed for at konkurrere på forskellige standardfunktionaliteter, arkitekturvalg og løsningsmetoder. Dette gælder særligt, når Mindstekravene omfatter detaljerede krav til funktionalitet, brugergrænseflade og systemarkitektur frem for de bagvedliggende forretningsmæssige behov. Ordregiver bedes derfor oplyse: Hvilke overvejelser ligger til grund for, at ca. 83 % af kravene er udformet som Mindstekrav? Har Ordregiver vurderet, om alle disse krav er nødvendige som ufravigelige Mindstekrav, eller om en del af kravene kunne være udformet som Krav eller Evalueringskrav, således at forskellige standardløsninger kunne konkurrere på deres respektive styrker? Hvordan har Ordregiver sikret, at kravspecifikationen er udformet i overensstemmelse med udbudslovens § 42 om tekniske specifikationer, således at kravene ikke i praksis favoriserer bestemte produkter eller leverandører, men giver alle relevante standardløsninger mulighed for at konkurrere på lige vilkår? Hvordan har Ordregiver vurderet, at den valgte kravstruktur er forenelig med udbudslovens § 2 om ligebehandling og proportionalitet, når langt størstedelen af kravene er gjort til ufravigelige Mindstekrav? Baggrunden for spørgsmålene er, at en kravspecifikation med en meget høj andel af detaljerede Mindstekrav kan medføre, at konkurrencen i praksis begrænses til standardløsninger, som allerede er indrettet efter netop disse krav. Leverandører, der kan opfylde Ordregivers behov gennem andre standardfunktionaliteter eller en anden systemarkitektur, kan dermed få vanskeligere ved at konkurrere, selv om løsningen opfylder de bagvedliggende forretningsmæssige behov. Ordregiver bedes derfor redegøre for, hvilke konkrete vurderinger der er foretaget for at sikre, at kravspecifikationen ikke begrænser konkurrencen mere end nødvendigt, og at de opstillede Mindstekrav er proportionale og objektivt nødvendige for at opfylde Ordregivers behov. | H4: Afventer - efter ferien
A5: 5 | B5: Opfordringsskrivelsen Afsnit 3 Skriftlige spørgsmål Tidsplanen for spørgsmål og svar Tilbudsfrister | C5: Tieto | D5: Ordregiver har anført, at tilbudsgiverne i perioden fra den 10. juli 2026 til den 2. august 2026 ikke kan forvente at modtage svar på indsendte spørgsmål. Udbudsmaterialet er omfattende og indeholder et betydeligt antal detaljerede tekniske, kontraktuelle og sikkerhedsmæssige krav. For at kunne udarbejde et kvalificeret og konkurrencedygtigt tilbud er tilbudsgiverne afhængige af løbende afklaring af spørgsmål til udbudsmaterialet. Ordregiver bedes derfor redegøre for, hvordan det er vurderet, at den lange periode uden mulighed for afklaring giver tilbudsgiverne tilstrækkelige muligheder for at udarbejde et fuldt oplyst og konkurrencedygtigt tilbud på lige vilkår. Har Ordregiver overvejet enten: at besvare spørgsmål løbende i ferieperioden, at forlænge tilbudsfristen tilsvarende, eller at forlænge fristen for indsendelse af spørgsmål, således at tilbudsgiverne reelt har mulighed for at få afklaret væsentlige forhold i udbudsmaterialet inden tilbudsafgivelsen? | H5: Afventer - efter ferien
A6: 6 | B6: Bilag 1 Kundens opgavebeskrivelse Punkt 2.3 Implementering Punkt 4 Tidsplan Bilag 1.g Samarbejde under Leveringskontrakten Kapitel 3 Samarbejdsorganisation i implementeringsfasen Punkt 3.5 Projektledelse | C6: Tieto | D6: Udbudsmaterialet beskriver, at implementeringen skal gennemføres i et tæt samarbejde mellem Ordregiver og Leverandøren, og at begge parter har væsentlige roller i projektets gennemførelse. Ordregiver bedes derfor oplyse, hvem der forventes at varetage projektlederrollen på Ordregivers side under implementeringsfasen. Er det Ordregivers forventning, at projektledelsen varetages af interne medarbejdere, eller forventes projektledelsen helt eller delvist varetaget af en ekstern rådgiver? Såfremt Ordregiver forventer at anvende en ekstern rådgiver, bedes Ordregiver oplyse, om denne vil være den samme rådgiver, som har bistået Ordregiver med udarbejdelsen af udbudsmaterialet og den forudgående anskaffelsesproces. Baggrunden for spørgsmålet er, at projektorganisationen, projektledelsens rolle og graden af kontinuitet mellem udbudsfasen og implementeringsfasen har væsentlig betydning for implementeringsrisikoen, governance, beslutningsprocesser og samarbejdsmodellen. Disse forhold indgår direkte i tilbudsgivernes vurdering af risiko og dermed i prissætningen af implementeringsopgaven. En afklaring vil derfor bidrage til en mere ensartet risikovurdering og prissætning blandt tilbudsgiverne. | H6: Afventer - efter ferien
A7: 7 | B7: Bilag 1 Kundens opgavebeskrivelse Punkt 4.1 Faser i tidsplanen Punkt 4.2 Nedbrydning af faserne Aktiviteten "Kontraktunderskrivelse" Leveringskontrakten Punkt 13 Varighed | C7: Tieto | D7: Det fremgår af Bilag 1, at afklaringsfasen omfatter en række aktiviteter, herunder planlægning, afklaringer, projektopstart, miljøopsætning og etablering af testmiljø, og at afklaringsfasen afsluttes med "Kontraktunderskrivelse". Tilbudsgiver forstår dette således, at den endelige kontrakt først underskrives efter gennemførelsen af afklaringsfasen. Er denne forståelse korrekt? Såfremt dette er tilfældet, bedes Ordregiver redegøre for: Hvilket kontraktgrundlag regulerer Parternes rettigheder og forpligtelser under afklaringsfasen. Hvordan Ordregiver har vurderet denne model i forhold til almindelig udbuds- og kontraktpraksis, hvor kontrakten typisk indgås forud for projektets opstart. Hvilke konsekvenser det har, hvis Parterne ikke kan opnå enighed om de forhold, der afklares i afklaringsfasen, herunder om Ordregiver i så fald kan vælge ikke at underskrive kontrakten, selv om leverandøren er blevet tildelt kontrakten efter gennemført udbud. | H7: Afventer - efter ferien
A8: 8 | B8: Option 5 – Databasedrift hos Statens IT Bilag 1 Kundens opgavebeskrivelse Punkt 7 Optioner Option 5 Databasedrift hos Statens IT Bilag 1.i Vederlag og betalingsplan Prissætning af optioner Bilag 1.l Statens IT's driftsmodeller Bilag 1.h Servicemål (hvis optionen aktiveres) | C8: Tieto | D8: Det fremgår af Option 5, at Ordregiver ønsker mulighed for at overdrage ansvaret for drift og vedligeholdelse af ESDH-løsningens database (middleware) til Leverandøren i Ordregivers miljø hos Statens IT. Ordregiver bedes oplyse, om Statens IT har bekræftet, at den beskrevne driftsmodel er teknisk, kontraktuelt og driftsmæssigt mulig inden for Statens IT's gældende driftsmodeller og rammevilkår. Såfremt dette er tilfældet, bedes Ordregiver oplyse, om den nødvendige afklaring og accept fra Statens IT allerede foreligger, eller om dette først skal ske i forbindelse med en eventuel aktivering af optionen. Baggrunden for spørgsmålet er, at optionens gennemførlighed afhænger af Statens IT's rammer og godkendelser. En afklaring er derfor nødvendig for, at tilbudsgiverne kan foretage en retvisende risikovurdering og prissætning af optionen på et ensartet grundlag.
A9: 9 | B9: Erklæring om Ruslands-forordningen. | C9: Tieto | D9: Leverandøren gør opmærksom på, at der mangler en Erklæring om Ruslands-forordningen. Vil det være muligt for Ordregiver at uploade denne?
A10: 10 | B10: Bilag 1.f | C10: Anton | D10: Det fremgår af Bilag 1.f, pkt. 12.1 og 12.2, at Driftsprøven først kan påbegyndes, når den fulde løsning er klar, herunder når både Proces- og regelstyringskomponenten samt Integrationsplatformen har gennemført og bestået deres respektive overtagelsesprøver. Samtidig fremgår det af Leveringskontrakten, at Ordregiver har adgang til at gøre misligholdelsesbeføjelser gældende ved væsentlige forsinkelser, herunder hvis leveringen overskrider de kontraktuelle frister. Ordregiver bedes derfor oplyse, hvordan denne afhængighed håndteres, hvis Proces- og regelstyringskomponenten og/eller Integrationsplatformen leveres af en anden leverandør, og en forsinkelse hos denne leverandør medfører, at Driftsprøven for ESDH-løsningen ikke kan påbegyndes eller afsluttes rettidigt. Bekræfter Ordregiver, at Leverandøren ikke kan ifalde bod, misligholdelsesansvar eller risikere ophævelse som følge af forsinkelser, der udelukkende skyldes manglende levering eller godkendelse af disse øvrige komponenter?
A11: 11 | B11: Bilag 1.f | C11: Tieto | D11: Det fremgår af Leveringskontrakten samt Bilag 1.d, at ESDH-løsningen udgør den første af tre komponenter i Ordregivers målarkitektur, og at den endelige Driftsprøve for ESDH-løsningen forudsætter, at både Proces- og regelstyringskomponenten samt Integrationsplatformen er implementeret og har bestået deres respektive overtagelsesprøver. Ordregiver bedes redegøre for, hvordan den valgte opdeling af anskaffelsen er vurderet i forhold til udbudslovens § 2 om ligebehandling, gennemsigtighed og proportionalitet, når den kontraktuelle godkendelse af ESDH-løsningen er direkte afhængig af leverancer, der ikke er omfattet af nærværende udbud. Ordregiver bedes samtidig oplyse, hvilke overvejelser der ligger til grund for, at de tre indbyrdes afhængige komponenter udbydes separat, herunder hvordan Ordregiver har sikret en klar ansvarsfordeling og en rimelig risikofordeling mellem de enkelte leverandører. | H11: Afventer
A12: 12 | B12: Bilag 1.b | C12: Anton | D12: MK 189 er selvmodsigende: Ved afslutningen af hypercare-perioden skal Leverandøren udarbejde en rapport, der beskriver status og håndtering af samtlige registrerede fejl. Rapporten skal senest overleveres til Kunden ved afslutning af hypercare. Hvornår skal Leverandøren påbegynde udarbejdelsen, og hvornår skal den afleveres til kunden?
A13: 13 | B13: Bilag 1.b | C13: Hans | D13: Ordregiver bedes præcisere, hvordan kravet om, at "Brugeren kan navigere og scrolle i dokument- og fillistevisninger, og at forhåndsvisningen automatisk opdateres og viser det Dokument/Fil, som Brugeren har navigeret til", skal forstås. Er det Ordregivers forventning, at forhåndsvisningen løbende skal skifte i takt med, at Brugeren scroller gennem listen, eller er kravet opfyldt, når forhåndsvisningen automatisk opdateres, efter at Brugeren har navigeret til og valgt et andet dokument eller en anden fil? Baggrunden for spørgsmålet er, at de to fortolkninger medfører forskellige krav til brugergrænsefladens adfærd, og en præcisering vil sikre en ensartet vurdering af tilbuddene.
A14: 14
A15: 15
A16: 16
A17: 17
A18: 18
A19: 19
A20: 20

Sheet Timeline
A1: Meeting | B1: Date
A2: Tender material published | B2: Fri 03. Jul | C2: done
A3: Material and requests sent to stakeholders | B3: Fri 03. Jul | C3: done
A4: Kick-off meeting | B4: Mon 06. Jul | C4: done
A5: Initial Solution Review | B5: Tue 07. Jul | C5: done
A6: Initial guiding price meeting | B6: Tue 07. Jul | C6: done
A7: Initial Legal review | B7: Tue 07. Jul | C7: done | E7: 10. juli til 2. august kan vi ikke forvente at få svar fra kunden.
A8: Initial SLA and servicegoal review | B8: Tue 07. Jul | C8: done
A9: DG1 | B9: Tue 07. Jul | C9: done
A10: Holidays
A11: Legal review | B11: Wed 05. Aug | C11: done
A12: Final SLA and servicegoals review | B12: Wed 05. Aug | C12: done
A13: Finance review | B13: Fri 07. Aug
A14: Product commitments | B14: Mon 10. Aug | C14: skal muligvis flyttes
A15: Send material for DG2 L2 and L1 | B15: Mon 10. Aug at 9
A16: DG2 L2 and L1 | B16: Tue 11. Aug at 9
A17: Deadline for spørgsmål | B17: fre 14. august
A18: Send material for DG2 L0 | B18: Mon 17. Aug before 11
A19: DG2 L0 | B19: Tue 18. Aug at 11
A20: Close for Edits | B20: Tue 24. Aug kl. 12
A21: Hand-in | B21: Wed 26. Aug at 12

Sheet Status
C8: Total numer of Requirements | D8: =COUNTIF('Production Plan'!B:B,"<>")-1
E11: Round 1
E12: # of requirements | F12: %
C13: Not Started | E13: =COUNTIF('Production Plan'!U:U,Status!$C$13) | F13: =E13/$D$8
C14: Started | E14: =COUNTIF('Production Plan'!U:U,Status!C14) | F14: =E14/$D$8
C15: Ready for review | E15: =COUNTIF('Production Plan'!U:U,Status!C15) | F15: =E15/$D$8
C16: Reviewed - Content | E16: =COUNTIF('Production Plan'!U:U,Status!C16) | F16: =E16/$D$8
C17: Reviewed - Format | E17: =COUNTIF('Production Plan'!U:U,Status!C17) | F17: =E17/$D$8
C18: Done | E18: =COUNTIF('Production Plan'!U:U,Status!C18) | F18: =E18/$D$8
C19: Total | E19: =SUM(E13:E18) | F19: =SUM(F13:F18)
C20: Missing | E20: =$D$8-E19 | F20: =100%-F19
E27: Round 1
C28: Responsible | E28: # of Requirements | F28: %
C29: Anton | E29: =COUNTIF('Production Plan'!L:L,C29) | F29: =E29/$D$8
C30: Anita | E30: =COUNTIF('Production Plan'!L:L,C30) | F30: =E30/$D$8
C31: Hans | E31: =COUNTIF('Production Plan'!L:L,C31) | F31: =E31/$D$8
C32: Claus | E32: =COUNTIF('Production Plan'!L:L,C32) | F32: =E32/$D$8
C33: Torben | E33: =COUNTIF('Production Plan'!L:L,C33) | F33: =E33/$D$8
C34: Cristina | E34: =COUNTIF('Production Plan'!L:L,C34) | F34: =E34/$D$8
C35: Johan | E35: =COUNTIF('Production Plan'!L:L,C35) | F35: =E35/$D$8
C36: Mandip | E36: =COUNTIF('Production Plan'!L:L,C36) | F36: =E36/$D$8
C37: CloudOps | E37: =COUNTIF('Production Plan'!L:L,C37) | F37: =E37/$D$8
C38: Kaare | E38: =COUNTIF('Production Plan'!L:L,C38) | F38: =E38/$D$8
C39: Morten | E39: =COUNTIF('Production Plan'!L:L,C39) | F39: =E39/$D$8
C40: Total | E40: =SUM(E29:E39) | F40: =SUM(F29:F39)
C41: Missing | E41: =$D$8-E40 | F41: =100%-F40

Sheet Commitment
A1: Req ID | B1: Included | C1: Requirement | D1: Non-standard element | E1: Effect if not included | F1: Issue description | G1: Committer | H1: Comitted date | I1: Conditions for commitment | J1: Comment
A2: ='Production Plan'!B2 | B2: =VLOOKUP(A2,'Production Plan'!B:Q,14,FALSE) | C2: =VLOOKUP(A2,'Production Plan'!B:F,5,FALSE) | D2: Describe | E2: Disqualification/Non-conditional | F2: Issue as we don't have this solution | G2: Name | H2: 46023 | I2: Conditional upon winning.
A3: ='Production Plan'!B3 | B3: =VLOOKUP(A3,'Production Plan'!B:Q,14,FALSE)
A4: ='Production Plan'!B4 | B4: =VLOOKUP(A4,'Production Plan'!B:Q,14,FALSE)
A5: ='Production Plan'!B5 | B5: =VLOOKUP(A5,'Production Plan'!B:Q,14,FALSE)
A6: ='Production Plan'!B6 | B6: =VLOOKUP(A6,'Production Plan'!B:Q,14,FALSE)
A7: ='Production Plan'!B7 | B7: =VLOOKUP(A7,'Production Plan'!B:Q,14,FALSE)
A8: ='Production Plan'!B8 | B8: =VLOOKUP(A8,'Production Plan'!B:Q,14,FALSE)
A9: ='Production Plan'!B9 | B9: =VLOOKUP(A9,'Production Plan'!B:Q,14,FALSE)
A10: ='Production Plan'!B10 | B10: =VLOOKUP(A10,'Production Plan'!B:Q,14,FALSE)
A11: ='Production Plan'!B11 | B11: =VLOOKUP(A11,'Production Plan'!B:Q,14,FALSE)
A12: ='Production Plan'!B12 | B12: =VLOOKUP(A12,'Production Plan'!B:Q,14,FALSE)
A13: ='Production Plan'!B13 | B13: =VLOOKUP(A13,'Production Plan'!B:Q,14,FALSE)
A14: ='Production Plan'!B14 | B14: =VLOOKUP(A14,'Production Plan'!B:Q,14,FALSE)
... A322: ='Production Plan'!B322 | B322: =VLOOKUP(A322,'Production Plan'!B:Q,14,FALSE)
A323: ='Production Plan'!#REF! | B323: =VLOOKUP(A323,'Production Plan'!B:Q,14,FALSE)
A324: ='Production Plan'!B323 | B324: =VLOOKUP(A324,'Production Plan'!B:Q,14,FALSE)
A325: ='Production Plan'!B324 | B325: =VLOOKUP(A325,'Production Plan'!B:Q,14,FALSE)
A326: ='Production Plan'!B325 | B326: =VLOOKUP(A326,'Production Plan'!B:Q,14,FALSE)
A327: ='Production Plan'!B326 | B327: =VLOOKUP(A327,'Production Plan'!B:Q,14,FALSE)
A328: ='Production Plan'!B327 | B328: =VLOOKUP(A328,'Production Plan'!B:Q,14,FALSE)
A329: ='Production Plan'!B328 | B329: =VLOOKUP(A329,'Production Plan'!B:Q,14,FALSE)
A330: ='Production Plan'!B329 | B330: =VLOOKUP(A330,'Production Plan'!B:Q,14,FALSE)
A331: ='Production Plan'!B330 | B331: =VLOOKUP(A331,'Production Plan'!B:Q,14,FALSE)
A332: ='Production Plan'!B331 | B332: =VLOOKUP(A332,'Production Plan'!B:Q,14,FALSE)
A333: ='Production Plan'!B332 | B333: =VLOOKUP(A333,'Production Plan'!B:Q,14,FALSE)
A334: ='Production Plan'!B333 | B334: =VLOOKUP(A334,'Production Plan'!B:Q,14,FALSE)
A335: ='Production Plan'!B334 | B335: =VLOOKUP(A335,'Production Plan'!B:Q,14,FALSE)
... A358: ='Production Plan'!B357 | B358: =VLOOKUP(A358,'Production Plan'!B:Q,14,FALSE)
A359: ='Production Plan'!#REF! | B359: =VLOOKUP(A359,'Production Plan'!B:Q,14,FALSE)
A360: ='Production Plan'!#REF! | B360: =VLOOKUP(A360,'Production Plan'!B:Q,14,FALSE)
A361: ='Production Plan'!#REF! | B361: =VLOOKUP(A361,'Production Plan'!B:Q,14,FALSE)
A362: ='Production Plan'!#REF! | B362: =VLOOKUP(A362,'Production Plan'!B:Q,14,FALSE)
A363: ='Production Plan'!#REF! | B363: =VLOOKUP(A363,'Production Plan'!B:Q,14,FALSE)
A364: ='Production Plan'!#REF! | B364: =VLOOKUP(A364,'Production Plan'!B:Q,14,FALSE)
A365: ='Production Plan'!#REF! | B365: =VLOOKUP(A365,'Production Plan'!B:Q,14,FALSE)
A366: ='Production Plan'!#REF! | B366: =VLOOKUP(A366,'Production Plan'!B:Q,14,FALSE)
A367: ='Production Plan'!#REF! | B367: =VLOOKUP(A367,'Production Plan'!B:Q,14,FALSE)
A368: ='Production Plan'!#REF! | B368: =VLOOKUP(A368,'Production Plan'!B:Q,14,FALSE)
A369: ='Production Plan'!#REF! | B369: =VLOOKUP(A369,'Production Plan'!B:Q,14,FALSE)
A370: ='Production Plan'!B358 | B370: =VLOOKUP(A370,'Production Plan'!B:Q,14,FALSE)
A371: ='Production Plan'!B359 | B371: =VLOOKUP(A371,'Production Plan'!B:Q,14,FALSE)
A372: ='Production Plan'!B360 | B372: =VLOOKUP(A372,'Production Plan'!B:Q,14,FALSE)
A373: ='Production Plan'!B361 | B373: =VLOOKUP(A373,'Production Plan'!B:Q,14,FALSE)
A374: ='Production Plan'!B362 | B374: =VLOOKUP(A374,'Production Plan'!B:Q,14,FALSE)
A375: ='Production Plan'!B363 | B375: =VLOOKUP(A375,'Production Plan'!B:Q,14,FALSE)
A376: ='Production Plan'!B364 | B376: =VLOOKUP(A376,'Production Plan'!B:Q,14,FALSE)
A377: ='Production Plan'!B365 | B377: =VLOOKUP(A377,'Production Plan'!B:Q,14,FALSE)
A378: ='Production Plan'!B366 | B378: =VLOOKUP(A378,'Production Plan'!B:Q,14,FALSE)
A379: ='Production Plan'!B367 | B379: =VLOOKUP(A379,'Production Plan'!B:Q,14,FALSE)
A380: ='Production Plan'!B368 | B380: =VLOOKUP(A380,'Production Plan'!B:Q,14,FALSE)
A381: ='Production Plan'!B369 | B381: =VLOOKUP(A381,'Production Plan'!B:Q,14,FALSE)
... A1000: ='Production Plan'!B988 | B1000: =VLOOKUP(A1000,'Production Plan'!B:Q,14,FALSE)

Sheet Risk Management
A1: Req ID | B1: Included | C1: Requirement | D1: Risk Element | E1: Severity | F1: Issue description | G1: Mitigation | H1: Comment | I1: Decision | J1: Decider | K1: Decision date | L1: Conditions for Approval | M1: Reporter
A2: ='Production Plan'!B2 | B2: =VLOOKUP(A2,'Production Plan'!B:R,15,FALSE) | C2: =VLOOKUP(A2,'Production Plan'!B:F,5,FALSE) | D2: Describe | E2: High | F2: Issue as we may risk fines | G2: Buffer in price | I2: Go-ahead - dependent upon mitigation | J2: Name | K2: 46023 | L2: Actions in mitigation must be done.
A3: ='Production Plan'!B3 | B3: =VLOOKUP(A3,'Production Plan'!B:R,15,FALSE) | C3: =VLOOKUP(A3,'Production Plan'!B:F,5,FALSE) | D3: Describe | E3: Medium | F3: Big risk of scope creep | G3: Clear statement of work in Clarification phase | I3: Go ahead - attempt to mitigate | J3: Name | K3: 46023 | L3: Attempt to mitigate, but go ahead, even if unsuccessful.
A4: ='Production Plan'!B4 | B4: =VLOOKUP(A4,'Production Plan'!B:R,15,FALSE) | C4: =VLOOKUP(A4,'Production Plan'!B:F,5,FALSE)
A5: ='Production Plan'!B5 | B5: =VLOOKUP(A5,'Production Plan'!B:R,15,FALSE) | C5: =VLOOKUP(A5,'Production Plan'!B:F,5,FALSE) | D5: Describe | E5: Low | F5: We can be sued | G5: We add a line in the contract. | H5: This is a very unlikely scenario. | I5: Go ahead - disregard risk | J5: Name | K5: 46023 | L5: As it is unlikely - we take the risk.
A6: ='Production Plan'!B6 | B6: =VLOOKUP(A6,'Production Plan'!B:R,15,FALSE) | C6: =VLOOKUP(A6,'Production Plan'!B:F,5,FALSE)
A7: ='Production Plan'!B7 | B7: =VLOOKUP(A7,'Production Plan'!B:R,15,FALSE) | C7: =VLOOKUP(A7,'Production Plan'!B:F,5,FALSE) | D7: Describe | E7: High | F7: We are unable to meet requirement | G7: We build a new module | H7: Their budget is not big enough for this. | I7: No bid | J7: Name | K7: 46023 | L7: -
A8: ='Production Plan'!B8 | B8: =VLOOKUP(A8,'Production Plan'!B:R,15,FALSE) | C8: =VLOOKUP(A8,'Production Plan'!B:F,5,FALSE)
A9: ='Production Plan'!B9 | B9: =VLOOKUP(A9,'Production Plan'!B:R,15,FALSE) | C9: =VLOOKUP(A9,'Production Plan'!B:F,5,FALSE)
A10: ='Production Plan'!B10 | B10: =VLOOKUP(A10,'Production Plan'!B:R,15,FALSE) | C10: =VLOOKUP(A10,'Production Plan'!B:F,5,FALSE)
A11: ='Production Plan'!B11 | B11: =VLOOKUP(A11,'Production Plan'!B:R,15,FALSE) | C11: =VLOOKUP(A11,'Production Plan'!B:F,5,FALSE)
A12: ='Production Plan'!B12 | B12: =VLOOKUP(A12,'Production Plan'!B:R,15,FALSE) | C12: =VLOOKUP(A12,'Production Plan'!B:F,5,FALSE)
A13: ='Production Plan'!B13 | B13: =VLOOKUP(A13,'Production Plan'!B:R,15,FALSE) | C13: =VLOOKUP(A13,'Production Plan'!B:F,5,FALSE)
A14: ='Production Plan'!B14 | B14: =VLOOKUP(A14,'Production Plan'!B:R,15,FALSE) | C14: =VLOOKUP(A14,'Production Plan'!B:F,5,FALSE)
A15: ='Production Plan'!B15 | B15: =VLOOKUP(A15,'Production Plan'!B:R,15,FALSE) | C15: =VLOOKUP(A15,'Production Plan'!B:F,5,FALSE)
A16: ='Production Plan'!B16 | B16: =VLOOKUP(A16,'Production Plan'!B:R,15,FALSE) | C16: =VLOOKUP(A16,'Production Plan'!B:F,5,FALSE)
A17: ='Production Plan'!B17 | B17: =VLOOKUP(A17,'Production Plan'!B:R,15,FALSE) | C17: =VLOOKUP(A17,'Production Plan'!B:F,5,FALSE)
A18: ='Production Plan'!B18 | B18: =VLOOKUP(A18,'Production Plan'!B:R,15,FALSE) | C18: =VLOOKUP(A18,'Production Plan'!B:F,5,FALSE)
A19: ='Production Plan'!B19 | B19: =VLOOKUP(A19,'Production Plan'!B:R,15,FALSE) | C19: =VLOOKUP(A19,'Production Plan'!B:F,5,FALSE)
... A322: ='Production Plan'!B322 | B322: =VLOOKUP(A322,'Production Plan'!B:R,15,FALSE) | C322: =VLOOKUP(A322,'Production Plan'!B:F,5,FALSE)
A323: ='Production Plan'!#REF! | B323: =VLOOKUP(A323,'Production Plan'!B:R,15,FALSE) | C323: =VLOOKUP(A323,'Production Plan'!B:F,5,FALSE)
A324: ='Production Plan'!B323 | B324: =VLOOKUP(A324,'Production Plan'!B:R,15,FALSE) | C324: =VLOOKUP(A324,'Production Plan'!B:F,5,FALSE)
A325: ='Production Plan'!B324 | B325: =VLOOKUP(A325,'Production Plan'!B:R,15,FALSE) | C325: =VLOOKUP(A325,'Production Plan'!B:F,5,FALSE)
A326: ='Production Plan'!B325 | B326: =VLOOKUP(A326,'Production Plan'!B:R,15,FALSE) | C326: =VLOOKUP(A326,'Production Plan'!B:F,5,FALSE)
A327: ='Production Plan'!B326 | B327: =VLOOKUP(A327,'Production Plan'!B:R,15,FALSE) | C327: =VLOOKUP(A327,'Production Plan'!B:F,5,FALSE)
A328: ='Production Plan'!B327 | B328: =VLOOKUP(A328,'Production Plan'!B:R,15,FALSE) | C328: =VLOOKUP(A328,'Production Plan'!B:F,5,FALSE)
A329: ='Production Plan'!B328 | B329: =VLOOKUP(A329,'Production Plan'!B:R,15,FALSE) | C329: =VLOOKUP(A329,'Production Plan'!B:F,5,FALSE)
A330: ='Production Plan'!B329 | B330: =VLOOKUP(A330,'Production Plan'!B:R,15,FALSE) | C330: =VLOOKUP(A330,'Production Plan'!B:F,5,FALSE)
A331: ='Production Plan'!B330 | B331: =VLOOKUP(A331,'Production Plan'!B:R,15,FALSE) | C331: =VLOOKUP(A331,'Production Plan'!B:F,5,FALSE)
A332: ='Production Plan'!B331 | B332: =VLOOKUP(A332,'Production Plan'!B:R,15,FALSE) | C332: =VLOOKUP(A332,'Production Plan'!B:F,5,FALSE)
A333: ='Production Plan'!B332 | B333: =VLOOKUP(A333,'Production Plan'!B:R,15,FALSE) | C333: =VLOOKUP(A333,'Production Plan'!B:F,5,FALSE)
A334: ='Production Plan'!B333 | B334: =VLOOKUP(A334,'Production Plan'!B:R,15,FALSE) | C334: =VLOOKUP(A334,'Production Plan'!B:F,5,FALSE)
A335: ='Production Plan'!B334 | B335: =VLOOKUP(A335,'Production Plan'!B:R,15,FALSE) | C335: =VLOOKUP(A335,'Production Plan'!B:F,5,FALSE)
... A358: ='Production Plan'!B357 | B358: =VLOOKUP(A358,'Production Plan'!B:R,15,FALSE) | C358: =VLOOKUP(A358,'Production Plan'!B:F,5,FALSE)
A359: ='Production Plan'!#REF! | B359: =VLOOKUP(A359,'Production Plan'!B:R,15,FALSE) | C359: =VLOOKUP(A359,'Production Plan'!B:F,5,FALSE)
A360: ='Production Plan'!#REF! | B360: =VLOOKUP(A360,'Production Plan'!B:R,15,FALSE) | C360: =VLOOKUP(A360,'Production Plan'!B:F,5,FALSE)
A361: ='Production Plan'!#REF! | B361: =VLOOKUP(A361,'Production Plan'!B:R,15,FALSE) | C361: =VLOOKUP(A361,'Production Plan'!B:F,5,FALSE)
A362: ='Production Plan'!#REF! | B362: =VLOOKUP(A362,'Production Plan'!B:R,15,FALSE) | C362: =VLOOKUP(A362,'Production Plan'!B:F,5,FALSE)
A363: ='Production Plan'!#REF! | B363: =VLOOKUP(A363,'Production Plan'!B:R,15,FALSE) | C363: =VLOOKUP(A363,'Production Plan'!B:F,5,FALSE)
A364: ='Production Plan'!#REF! | B364: =VLOOKUP(A364,'Production Plan'!B:R,15,FALSE) | C364: =VLOOKUP(A364,'Production Plan'!B:F,5,FALSE)
A365: ='Production Plan'!#REF! | B365: =VLOOKUP(A365,'Production Plan'!B:R,15,FALSE) | C365: =VLOOKUP(A365,'Production Plan'!B:F,5,FALSE)
A366: ='Production Plan'!#REF! | B366: =VLOOKUP(A366,'Production Plan'!B:R,15,FALSE) | C366: =VLOOKUP(A366,'Production Plan'!B:F,5,FALSE)
A367: ='Production Plan'!#REF! | B367: =VLOOKUP(A367,'Production Plan'!B:R,15,FALSE) | C367: =VLOOKUP(A367,'Production Plan'!B:F,5,FALSE)
A368: ='Production Plan'!#REF! | B368: =VLOOKUP(A368,'Production Plan'!B:R,15,FALSE) | C368: =VLOOKUP(A368,'Production Plan'!B:F,5,FALSE)
A369: ='Production Plan'!#REF! | B369: =VLOOKUP(A369,'Production Plan'!B:R,15,FALSE) | C369: =VLOOKUP(A369,'Production Plan'!B:F,5,FALSE)
A370: ='Production Plan'!B358 | B370: =VLOOKUP(A370,'Production Plan'!B:R,15,FALSE) | C370: =VLOOKUP(A370,'Production Plan'!B:F,5,FALSE)
A371: ='Production Plan'!B359 | B371: =VLOOKUP(A371,'Production Plan'!B:R,15,FALSE) | C371: =VLOOKUP(A371,'Production Plan'!B:F,5,FALSE)
A372: ='Production Plan'!B360 | B372: =VLOOKUP(A372,'Production Plan'!B:R,15,FALSE) | C372: =VLOOKUP(A372,'Production Plan'!B:F,5,FALSE)
A373: ='Production Plan'!B361 | B373: =VLOOKUP(A373,'Production Plan'!B:R,15,FALSE) | C373: =VLOOKUP(A373,'Production Plan'!B:F,5,FALSE)
A374: ='Production Plan'!B362 | B374: =VLOOKUP(A374,'Production Plan'!B:R,15,FALSE) | C374: =VLOOKUP(A374,'Production Plan'!B:F,5,FALSE)
A375: ='Production Plan'!B363 | B375: =VLOOKUP(A375,'Production Plan'!B:R,15,FALSE) | C375: =VLOOKUP(A375,'Production Plan'!B:F,5,FALSE)
A376: ='Production Plan'!B364 | B376: =VLOOKUP(A376,'Production Plan'!B:R,15,FALSE) | C376: =VLOOKUP(A376,'Production Plan'!B:F,5,FALSE)
A377: ='Production Plan'!B365 | B377: =VLOOKUP(A377,'Production Plan'!B:R,15,FALSE) | C377: =VLOOKUP(A377,'Production Plan'!B:F,5,FALSE)
A378: ='Production Plan'!B366 | B378: =VLOOKUP(A378,'Production Plan'!B:R,15,FALSE) | C378: =VLOOKUP(A378,'Production Plan'!B:F,5,FALSE)
A379: ='Production Plan'!B367 | B379: =VLOOKUP(A379,'Production Plan'!B:R,15,FALSE) | C379: =VLOOKUP(A379,'Production Plan'!B:F,5,FALSE)
A380: ='Production Plan'!B368 | B380: =VLOOKUP(A380,'Production Plan'!B:R,15,FALSE) | C380: =VLOOKUP(A380,'Production Plan'!B:F,5,FALSE)
A381: ='Production Plan'!B369 | B381: =VLOOKUP(A381,'Production Plan'!B:R,15,FALSE) | C381: =VLOOKUP(A381,'Production Plan'!B:F,5,FALSE)
... A453: ='Production Plan'!B441 | B453: =VLOOKUP(A453,'Production Plan'!B:R,15,FALSE) | C453: =VLOOKUP(A453,'Production Plan'!B:F,5,FALSE)

Sheet Cost Drivers
A1: Req ID | B1: Included | C1: Requirement | D1: Reason for increased cost | E1: Severity | F1: Estimated increase in cost | G1: Estimator | H1: Estimation date | I1: Included in pricing
A2: ='Production Plan'!B2 | B2: =VLOOKUP(A2,'Production Plan'!B:S,16,FALSE) | C2: =VLOOKUP(A2,'Production Plan'!B:F,5,FALSE) | D2: Describe | E2: Low | F2: Estimation - DKK or EUR value and/or ressource use. | G2: Name | H2: 46023 | I2: Yes
A3: ='Production Plan'!B3 | B3: =VLOOKUP(A3,'Production Plan'!B:S,16,FALSE) | C3: =VLOOKUP(A3,'Production Plan'!B:F,5,FALSE) | D3: Describe | E3: Medium | F3: Estimation - DKK or EUR value and/or ressource use. | G3: Name | H3: 46023 | I3: Yes
A4: ='Production Plan'!B4 | B4: =VLOOKUP(A4,'Production Plan'!B:S,16,FALSE) | C4: =VLOOKUP(A4,'Production Plan'!B:F,5,FALSE)
A5: ='Production Plan'!B5 | B5: =VLOOKUP(A5,'Production Plan'!B:S,16,FALSE) | C5: =VLOOKUP(A5,'Production Plan'!B:F,5,FALSE)
A6: ='Production Plan'!B6 | B6: =VLOOKUP(A6,'Production Plan'!B:S,16,FALSE) | C6: =VLOOKUP(A6,'Production Plan'!B:F,5,FALSE)
A7: ='Production Plan'!B7 | B7: =VLOOKUP(A7,'Production Plan'!B:S,16,FALSE) | C7: =VLOOKUP(A7,'Production Plan'!B:F,5,FALSE) | D7: Describe | E7: High | F7: Estimation - DKK or EUR value and/or ressource use. | G7: Name | H7: 46023 | I7: Yes
A8: ='Production Plan'!B8 | B8: =VLOOKUP(A8,'Production Plan'!B:S,16,FALSE) | C8: =VLOOKUP(A8,'Production Plan'!B:F,5,FALSE)
A9: ='Production Plan'!B9 | B9: =VLOOKUP(A9,'Production Plan'!B:S,16,FALSE) | C9: =VLOOKUP(A9,'Production Plan'!B:F,5,FALSE)
A10: ='Production Plan'!B10 | B10: =VLOOKUP(A10,'Production Plan'!B:S,16,FALSE) | C10: =VLOOKUP(A10,'Production Plan'!B:F,5,FALSE)
A11: ='Production Plan'!B11 | B11: =VLOOKUP(A11,'Production Plan'!B:S,16,FALSE) | C11: =VLOOKUP(A11,'Production Plan'!B:F,5,FALSE)
A12: ='Production Plan'!B12 | B12: =VLOOKUP(A12,'Production Plan'!B:S,16,FALSE) | C12: =VLOOKUP(A12,'Production Plan'!B:F,5,FALSE)
A13: ='Production Plan'!B13 | B13: =VLOOKUP(A13,'Production Plan'!B:S,16,FALSE) | C13: =VLOOKUP(A13,'Production Plan'!B:F,5,FALSE)
A14: ='Production Plan'!B14 | B14: =VLOOKUP(A14,'Production Plan'!B:S,16,FALSE) | C14: =VLOOKUP(A14,'Production Plan'!B:F,5,FALSE)
A15: ='Production Plan'!B15 | B15: =VLOOKUP(A15,'Production Plan'!B:S,16,FALSE) | C15: =VLOOKUP(A15,'Production Plan'!B:F,5,FALSE)
A16: ='Production Plan'!B16 | B16: =VLOOKUP(A16,'Production Plan'!B:S,16,FALSE) | C16: =VLOOKUP(A16,'Production Plan'!B:F,5,FALSE)
A17: ='Production Plan'!B17 | B17: =VLOOKUP(A17,'Production Plan'!B:S,16,FALSE) | C17: =VLOOKUP(A17,'Production Plan'!B:F,5,FALSE)
A18: ='Production Plan'!B18 | B18: =VLOOKUP(A18,'Production Plan'!B:S,16,FALSE) | C18: =VLOOKUP(A18,'Production Plan'!B:F,5,FALSE)
A19: ='Production Plan'!B19 | B19: =VLOOKUP(A19,'Production Plan'!B:S,16,FALSE) | C19: =VLOOKUP(A19,'Production Plan'!B:F,5,FALSE)
... A322: ='Production Plan'!B322 | B322: =VLOOKUP(A322,'Production Plan'!B:S,16,FALSE) | C322: =VLOOKUP(A322,'Production Plan'!B:F,5,FALSE)
A323: ='Production Plan'!#REF! | B323: =VLOOKUP(A323,'Production Plan'!B:S,16,FALSE) | C323: =VLOOKUP(A323,'Production Plan'!B:F,5,FALSE)
A324: ='Production Plan'!B323 | B324: =VLOOKUP(A324,'Production Plan'!B:S,16,FALSE) | C324: =VLOOKUP(A324,'Production Plan'!B:F,5,FALSE)
A325: ='Production Plan'!B324 | B325: =VLOOKUP(A325,'Production Plan'!B:S,16,FALSE) | C325: =VLOOKUP(A325,'Production Plan'!B:F,5,FALSE)
A326: ='Production Plan'!B325 | B326: =VLOOKUP(A326,'Production Plan'!B:S,16,FALSE) | C326: =VLOOKUP(A326,'Production Plan'!B:F,5,FALSE)
A327: ='Production Plan'!B326 | B327: =VLOOKUP(A327,'Production Plan'!B:S,16,FALSE) | C327: =VLOOKUP(A327,'Production Plan'!B:F,5,FALSE)
A328: ='Production Plan'!B327 | B328: =VLOOKUP(A328,'Production Plan'!B:S,16,FALSE) | C328: =VLOOKUP(A328,'Production Plan'!B:F,5,FALSE)
A329: ='Production Plan'!B328 | B329: =VLOOKUP(A329,'Production Plan'!B:S,16,FALSE) | C329: =VLOOKUP(A329,'Production Plan'!B:F,5,FALSE)
A330: ='Production Plan'!B329 | B330: =VLOOKUP(A330,'Production Plan'!B:S,16,FALSE) | C330: =VLOOKUP(A330,'Production Plan'!B:F,5,FALSE)
A331: ='Production Plan'!B330 | B331: =VLOOKUP(A331,'Production Plan'!B:S,16,FALSE) | C331: =VLOOKUP(A331,'Production Plan'!B:F,5,FALSE)
A332: ='Production Plan'!B331 | B332: =VLOOKUP(A332,'Production Plan'!B:S,16,FALSE) | C332: =VLOOKUP(A332,'Production Plan'!B:F,5,FALSE)
A333: ='Production Plan'!B332 | B333: =VLOOKUP(A333,'Production Plan'!B:S,16,FALSE) | C333: =VLOOKUP(A333,'Production Plan'!B:F,5,FALSE)
A334: ='Production Plan'!B333 | B334: =VLOOKUP(A334,'Production Plan'!B:S,16,FALSE) | C334: =VLOOKUP(A334,'Production Plan'!B:F,5,FALSE)
A335: ='Production Plan'!B334 | B335: =VLOOKUP(A335,'Production Plan'!B:S,16,FALSE) | C335: =VLOOKUP(A335,'Production Plan'!B:F,5,FALSE)
... A358: ='Production Plan'!B357 | B358: =VLOOKUP(A358,'Production Plan'!B:S,16,FALSE) | C358: =VLOOKUP(A358,'Production Plan'!B:F,5,FALSE)
A359: ='Production Plan'!#REF! | B359: =VLOOKUP(A359,'Production Plan'!B:S,16,FALSE) | C359: =VLOOKUP(A359,'Production Plan'!B:F,5,FALSE)
A360: ='Production Plan'!#REF! | B360: =VLOOKUP(A360,'Production Plan'!B:S,16,FALSE) | C360: =VLOOKUP(A360,'Production Plan'!B:F,5,FALSE)
A361: ='Production Plan'!#REF! | B361: =VLOOKUP(A361,'Production Plan'!B:S,16,FALSE) | C361: =VLOOKUP(A361,'Production Plan'!B:F,5,FALSE)
A362: ='Production Plan'!#REF! | B362: =VLOOKUP(A362,'Production Plan'!B:S,16,FALSE) | C362: =VLOOKUP(A362,'Production Plan'!B:F,5,FALSE)
A363: ='Production Plan'!#REF! | B363: =VLOOKUP(A363,'Production Plan'!B:S,16,FALSE) | C363: =VLOOKUP(A363,'Production Plan'!B:F,5,FALSE)
A364: ='Production Plan'!#REF! | B364: =VLOOKUP(A364,'Production Plan'!B:S,16,FALSE) | C364: =VLOOKUP(A364,'Production Plan'!B:F,5,FALSE)
A365: ='Production Plan'!#REF! | B365: =VLOOKUP(A365,'Production Plan'!B:S,16,FALSE) | C365: =VLOOKUP(A365,'Production Plan'!B:F,5,FALSE)
A366: ='Production Plan'!#REF! | B366: =VLOOKUP(A366,'Production Plan'!B:S,16,FALSE) | C366: =VLOOKUP(A366,'Production Plan'!B:F,5,FALSE)
A367: ='Production Plan'!#REF! | B367: =VLOOKUP(A367,'Production Plan'!B:S,16,FALSE) | C367: =VLOOKUP(A367,'Production Plan'!B:F,5,FALSE)
A368: ='Production Plan'!#REF! | B368: =VLOOKUP(A368,'Production Plan'!B:S,16,FALSE) | C368: =VLOOKUP(A368,'Production Plan'!B:F,5,FALSE)
A369: ='Production Plan'!#REF! | B369: =VLOOKUP(A369,'Production Plan'!B:S,16,FALSE) | C369: =VLOOKUP(A369,'Production Plan'!B:F,5,FALSE)
A370: ='Production Plan'!B358 | B370: =VLOOKUP(A370,'Production Plan'!B:S,16,FALSE) | C370: =VLOOKUP(A370,'Production Plan'!B:F,5,FALSE)
A371: ='Production Plan'!B359 | B371: =VLOOKUP(A371,'Production Plan'!B:S,16,FALSE) | C371: =VLOOKUP(A371,'Production Plan'!B:F,5,FALSE)
A372: ='Production Plan'!B360 | B372: =VLOOKUP(A372,'Production Plan'!B:S,16,FALSE) | C372: =VLOOKUP(A372,'Production Plan'!B:F,5,FALSE)
A373: ='Production Plan'!B361 | B373: =VLOOKUP(A373,'Production Plan'!B:S,16,FALSE) | C373: =VLOOKUP(A373,'Production Plan'!B:F,5,FALSE)
A374: ='Production Plan'!B362 | B374: =VLOOKUP(A374,'Production Plan'!B:S,16,FALSE) | C374: =VLOOKUP(A374,'Production Plan'!B:F,5,FALSE)
A375: ='Production Plan'!B363 | B375: =VLOOKUP(A375,'Production Plan'!B:S,16,FALSE) | C375: =VLOOKUP(A375,'Production Plan'!B:F,5,FALSE)
A376: ='Production Plan'!B364 | B376: =VLOOKUP(A376,'Production Plan'!B:S,16,FALSE) | C376: =VLOOKUP(A376,'Production Plan'!B:F,5,FALSE)
A377: ='Production Plan'!B365 | B377: =VLOOKUP(A377,'Production Plan'!B:S,16,FALSE) | C377: =VLOOKUP(A377,'Production Plan'!B:F,5,FALSE)
A378: ='Production Plan'!B366 | B378: =VLOOKUP(A378,'Production Plan'!B:S,16,FALSE) | C378: =VLOOKUP(A378,'Production Plan'!B:F,5,FALSE)
A379: ='Production Plan'!B367 | B379: =VLOOKUP(A379,'Production Plan'!B:S,16,FALSE) | C379: =VLOOKUP(A379,'Production Plan'!B:F,5,FALSE)
A380: ='Production Plan'!B368 | B380: =VLOOKUP(A380,'Production Plan'!B:S,16,FALSE) | C380: =VLOOKUP(A380,'Production Plan'!B:F,5,FALSE)
A381: ='Production Plan'!B369 | B381: =VLOOKUP(A381,'Production Plan'!B:S,16,FALSE) | C381: =VLOOKUP(A381,'Production Plan'!B:F,5,FALSE)
... A1078: ='Production Plan'!B1066 | B1078: =VLOOKUP(A1078,'Production Plan'!B:S,16,FALSE) | C1078: =VLOOKUP(A1078,'Production Plan'!B:F,5,FALSE)

Sheet Pricing
B4: Link to Price Model:
B5: Modules total price:
B7: Estimates for delivery:

Sheet Evalueringshieraki
B1: max point | C1: krav
A2: Implementering/installa-tion og/eller konfigura-tion | B2: 40 | C2: • EK-1 – Udlændingeoverblik • EK-3 – Brugergrænseflade • EK-5 – Administratormodul • EK-6 – Datamodel • EK-7 – Konfiguration af brugergrænseflade • EK-8 – Afgørelsesmodul
A3: funktionalitet | B3: 40 | C3: EK-2 – Dashboards • EK-4 – Aktindsigt • EK-9 – Organisatoriske rolle/rettigheder • EK-10 – Brugerrettet logning og sagsgang i brugergrænsefladen • EK-11 – Outlook integration til journalisering • EK-12 – ESDH Standard API
A4: brugsvilkår | B4: 20 | C4: K-Krav i Bilag 1.b Krav til standardsoftware og Bilag 1.e Krav til IT- og informationssikkerhed
B7: 10 point for k-krav ja, 1 point for k-krav nej

Sheet AI — Legend
A1: Field | B1: Description
A2: Purpose | B2: AI-generated draft compliance input. Not official bid text until reviewed.
A3: Editable columns | B3: W–AG on Production Plan only. Columns A–V are human/tool fields.
A4: Promotion | B4: Copy accepted values to O/P manually after setting Review status = Accepted.
A5: Regeneration | B5: Re-running the script overwrites AI columns for matched ReqID rows only.
A6: Disambiguation | B6: Use document (Bilag) in draft JSON when ReqID appears on multiple rows.
