Workbook

Sheet Production Plan
A1: # | B1: ReqID | C1: Document | D1: Section (Headline) | E1: Requirement title | F1: Requirement | G1: Requirement type | H1: Action | I1: Indgår i officiel krav-count? | J1: Vægt | K1: Round #1 | L1: Responsible | M1: Reviewer | N1: Module | O1: Can we meet the requirement? | P1: Comment | Q1: PFR-nr. | R1: Commitment needed? | S1: Risk Element? | T1: Cost Driver | U1: Link to answer document | V1: Status (phase) | W1: Status (%) | X1: AI — Generated | Y1: AI — Source | Z1: AI — Compliance | AA1: AI — Confidence | AB1: AI — Summary | AC1: AI — Gaps & clarifications | AD1: AI — Evidence | AE1: AI — Next action | AF1: AI — Reviewed by | AG1: AI — Review status | AH1: AI — Run ID
A2: 1 | B2: MK-1 | C2: Bilag 1.b | D2: Generelle krav | E2: Rigsarkivets afleveringsmodeller | F2: ESDH-løsningen skal understøtte Rigsarkivets gældende retningslinjer for anmeldelse og godkendelse af it-systemer fra statslige Myndigheder, jf. Cirkulære om anmeldelse og godkendelse af it-systemer på Retsinformation og gældende regler for generel aflevering af statslige it-systemer, jf. Bekendtgørelse om arkiveringsversioner på Retsinformation. | G2: Mindstekrav | H2: =IF(G2="Evalueringskrav","Answer",(IF(G2="Krav","Check",(IF(G2="Mindstekrav","Verify",""))))) -> Verify | I2: Ja | L2: Anton | O2: 1. Fully met | V2: Reviewed - Content | W2: =IF(V2="Not Started",0%,IF(V2="Started",50%,IF(V2="Ready for review",70%,IF(V2="Reviewed - Content",80%,IF(V2="Reviewed - Format",90%,IF(V2="Done",100%,"")))))) -> 0.8 | X2: 2026-07-07 | Y2: Cursor / tender-response (batch) | Z2: Met | AA2: Verified | AB2: Verify: Rigsarkivets afleveringsmodeller — vurderet opfyldt (tool: 1. Fully met). | AD2: docs/tender-reference/extracted/KK Tender tool.txt; docs/tender-reference/extracted/Nationalbanken/Bilag 3.i Leverandørens Løsningsbeskrivelse.txt; docs/product/RFP_Leverandørens_svar_utdrag.txt | AE2: Anton: Confirm verify-tekst; opdatér review status efter tjek. | AG2: Draft | AH2: uim-esdh-full-2026-07-07
A3: 2 | B3: MK-2 | C3: Bilag 1.b | D3: Generelle krav | E3: Sprog | F3: ESDH-løsningen skal understøtte dansk og engelsk. | G3: Mindstekrav | H3: =IF(G3="Evalueringskrav","Answer",(IF(G3="Krav","Check",(IF(G3="Mindstekrav","Verify",""))))) -> Verify | I3: Ja | L3: Anton | O3: 1. Fully met | V3: Reviewed - Content | W3: =IF(V3="Not Started",0%,IF(V3="Started",50%,IF(V3="Ready for review",70%,IF(V3="Reviewed - Content",80%,IF(V3="Reviewed - Format",90%,IF(V3="Done",100%,"")))))) -> 0.8 | X3: 2026-07-07 | Y3: Cursor / tender-response (batch) | Z3: Met | AA3: Verified | AB3: Verify: Sprog — vurderet opfyldt (tool: 1. Fully met). | AD3: docs/tender-reference/extracted/Nationalbanken/Bilag 3.i Leverandørens Løsningsbeskrivelse.txt; docs/tender-reference/extracted/HSØ/02.00-Tietoevry-SSA-L-Bilag 2-Leverandørens beskrivelse av Tjenesten.txt; docs/tender-reference/extracted/KK Tender tool.txt | AE3: Anton: Confirm verify-tekst; opdatér review status efter tjek. | AG3: Draft | AH3: uim-esdh-full-2026-07-07
A4: 3 | B4: MK-3 | C4: Bilag 1.b | D4: Generelle krav | E4: Datamodel | F4: ESDH-løsningen skal understøtte en Datamodel med en klar og tydelig beskrivelse af felterne i både frontend og backend. | G4: Mindstekrav | H4: =IF(G4="Evalueringskrav","Answer",(IF(G4="Krav","Check",(IF(G4="Mindstekrav","Verify",""))))) -> Verify | I4: Ja | L4: Anton | O4: 1. Fully met | V4: Reviewed - Content | W4: =IF(V4="Not Started",0%,IF(V4="Started",50%,IF(V4="Ready for review",70%,IF(V4="Reviewed - Content",80%,IF(V4="Reviewed - Format",90%,IF(V4="Done",100%,"")))))) -> 0.8 | X4: 2026-07-07 | Y4: Cursor / tender-response (batch) | Z4: Met | AA4: Verified | AB4: Verify: Datamodel — vurderet opfyldt (tool: 1. Fully met). | AD4: docs/tender-reference/extracted/KK Tender tool.txt; docs/product/RFP_Leverandørens_svar_utdrag.txt; docs/tender-reference/extracted/HSØ/02.00-Tietoevry-SSA-L-Bilag 2-Leverandørens beskrivelse av Tjenesten.txt | AE4: Anton: Confirm verify-tekst; opdatér review status efter tjek. | AG4: Draft | AH4: uim-esdh-full-2026-07-07
A5: 4 | B5: MK-4 | C5: Bilag 1.b | D5: Generelle krav | E5: GDPR – Ret til indsigt i egne personoplysninger | F5: ESDH-løsningen skal understøtte fremsøgning, sammenstilling og udlevering af personoplysninger om den registrerede i overensstemmelse med GDPR-artikel 15. ESDH-løsningen skal ligeledes understøtte behandling af anmodninger fremsat af en lovlig repræsentant for den registrerede, herunder forældremyndighed eller værgemål. Udleveringen skal kunne leveres i et almindelig læsbart format og skal kunne fremsendes til den registrerede via Digital Post, sikker e-mail og fjernprint. | G5: Mindstekrav | H5: =IF(G5="Evalueringskrav","Answer",(IF(G5="Krav","Check",(IF(G5="Mindstekrav","Verify",""))))) -> Verify | I5: Ja | L5: Anton | O5: 1. Fully met | V5: Reviewed - Content | W5: =IF(V5="Not Started",0%,IF(V5="Started",50%,IF(V5="Ready for review",70%,IF(V5="Reviewed - Content",80%,IF(V5="Reviewed - Format",90%,IF(V5="Done",100%,"")))))) -> 0.8 | X5: 2026-07-07 | Y5: Cursor / tender-response (batch) | Z5: Met | AA5: Verified | AB5: Verify: GDPR – Ret til indsigt i egne personoplysninger — vurderet opfyldt (tool: 1. Fully met). | AD5: docs/tender-reference/extracted/KK Tender tool.txt; docs/tender-reference/extracted/Nationalbanken/Bilag 3.i Leverandørens Løsningsbeskrivelse.txt; docs/tender-reference/extracted/Nationalbanken/Underbilag 6B - Testplan og Leverandørens prøveprincipper, metoder og -værktøjer (1).txt | AE5: Anton: Confirm verify-tekst; opdatér review status efter tjek. | AG5: Draft | AH5: uim-esdh-full-2026-07-07
A6: 5 | B6: MK-5 | C6: Bilag 1.b | D6: Generelle krav | E6: Anmodninger fra registrerede | F6: ESDH-løsningen skal understøtte håndtering af indsigts-, slette- og berigtigelsesanmodninger fra de registrerede i Løsningen. | G6: Mindstekrav | H6: =IF(G6="Evalueringskrav","Answer",(IF(G6="Krav","Check",(IF(G6="Mindstekrav","Verify",""))))) -> Verify | I6: Ja | L6: Anton | O6: 1. Fully met | V6: Reviewed - Content | W6: =IF(V6="Not Started",0%,IF(V6="Started",50%,IF(V6="Ready for review",70%,IF(V6="Reviewed - Content",80%,IF(V6="Reviewed - Format",90%,IF(V6="Done",100%,"")))))) -> 0.8 | X6: 2026-07-07 | Y6: Cursor / tender-response (batch) | Z6: Met | AA6: Verified | AB6: Verify: Anmodninger fra registrerede — vurderet opfyldt (tool: 1. Fully met). | AD6: docs/tender-reference/extracted/Nationalbanken/Bilag 3.i Leverandørens Løsningsbeskrivelse.txt; docs/tender-reference/extracted/KK Tender tool.txt; docs/tender-reference/extracted/Nationalbanken/Bilag 1.i Leverandørens Løsningsbeskrivelse.txt | AE6: Anton: Confirm verify-tekst; opdatér review status efter tjek. | AG6: Draft | AH6: uim-esdh-full-2026-07-07
A7: 6 | B7: MK-6 | C7: Bilag 1.b | D7: Generelle krav | E7: Håndtering af sletteregler | F7: ESDH-løsningen skal understøtte håndtering af sletteregler, herunder bevaringskoder, for både midlertidig og permanent sletning. ESDH-løsningen skal understøtte, at sletning alene kan foretages af Brugere med de nødvendige rettigheder, herunder at rettigheder til permanent sletning og midlertidig sletning kan adskilles. Sletteregler skal kunne anvendes på alle Entiteter i Løsningen. | G7: Mindstekrav | H7: =IF(G7="Evalueringskrav","Answer",(IF(G7="Krav","Check",(IF(G7="Mindstekrav","Verify",""))))) -> Verify | I7: Ja | L7: Morten | O7: 3. Not able to meet | P7: ADN: "Sletteregler for alle entiteter", kan vi sige at vi har det på kontakter? | Q7: 433881 | R7: Yes | V7: Not Started | W7: =IF(V7="Not Started",0%,IF(V7="Started",50%,IF(V7="Ready for review",70%,IF(V7="Reviewed - Content",80%,IF(V7="Reviewed - Format",90%,IF(V7="Done",100%,"")))))) -> 0 | X7: 2026-07-07 | Y7: Cursor / tender-response | Z7: Partial | AA7: Verified (sag/dokument/fil); Lead (alle Entiteter) | AB7: Sletteregler og bevaringskoder for sag, dokument og fil; midlertidig vs. permanent sletning med adskilte rettigheder (disposal/purge, skjul permanent sletning for sagsbehandlere). Jf. MK-7 og MK-117. | AC7: «Alle Entiteter» er uafklaret: kontakter har sletning (MK-62) men ikke samme sletteregel-model; øvrige entitetstyper ikke dokumenteret. Tool-rating stadig 3. Not able to meet — afstem internt før opdatering af kolonne O. | AD7: HSØ Bilag 2 kassasjon; Ratatoskr Retention (Disposal), Disposal, Purge, File; MK-7, MK-117, MK-14; MK-62 (ikke dækning for MK-6) | AE7: Q&A: præcisér hvad Ordregiver mener med «alle Entiteter». Koordinér med Anton (MK-7/MK-117/MK-14). Opdatér ikke kolonne O før review. | AG7: Draft | AH7: uim-mk6-2026-07-07
A8: 7 | B8: MK-7 | C8: Bilag 1.b | D8: Generelle krav | E8: Opsætning af slettepolitikker | F8: ESDH-løsningen skal understøtte, at Kunden selv uden Leverdørens involvering kan konfigurere slettepolitikker i Løsningens administrationsmodul. | G8: Mindstekrav | H8: =IF(G8="Evalueringskrav","Answer",(IF(G8="Krav","Check",(IF(G8="Mindstekrav","Verify",""))))) -> Verify | I8: Ja | L8: Anton | O8: 1. Fully met | V8: Reviewed - Content | W8: =IF(V8="Not Started",0%,IF(V8="Started",50%,IF(V8="Ready for review",70%,IF(V8="Reviewed - Content",80%,IF(V8="Reviewed - Format",90%,IF(V8="Done",100%,"")))))) -> 0.8 | X8: 2026-07-07 | Y8: Cursor / tender-response (batch) | Z8: Met | AA8: Verified | AB8: Verify: Opsætning af slettepolitikker — vurderet opfyldt (tool: 1. Fully met). | AD8: docs/tender-reference/extracted/KUM-SLKS/Bilag 3 - Kravspecifikation.txt; docs/tender-reference/extracted/Nationalbanken/Bilag 3.i Leverandørens Løsningsbeskrivelse.txt; docs/tender-reference/extracted/KUM-SLKS/Bilag 1 - Tidsplan.txt | AE8: Anton: Confirm verify-tekst; opdatér review status efter tjek. | AG8: Draft | AH8: uim-esdh-full-2026-07-07
A9: 8 | B9: MK-8 | C9: Bilag 1.b | D9: Generelle krav | E9: Klassifikationskoder | F9: ESDH-løsningen skal understøtte, at klassifikationskoder kan oprettes af Administrator, hvortil Kunden valgfrit kan bestemme hvilke klassifikationskoder Løsningen skal indeholde. | G9: Mindstekrav | H9: =IF(G9="Evalueringskrav","Answer",(IF(G9="Krav","Check",(IF(G9="Mindstekrav","Verify",""))))) -> Verify | I9: Ja | L9: Anton | O9: 1. Fully met | V9: Reviewed - Content | W9: =IF(V9="Not Started",0%,IF(V9="Started",50%,IF(V9="Ready for review",70%,IF(V9="Reviewed - Content",80%,IF(V9="Reviewed - Format",90%,IF(V9="Done",100%,"")))))) -> 0.8 | X9: 2026-07-07 | Y9: Cursor / tender-response (batch) | Z9: Met | AA9: Verified | AB9: Verify: Klassifikationskoder — vurderet opfyldt (tool: 1. Fully met). | AD9: docs/tender-reference/extracted/Nationalbanken/Bilag 3.i Leverandørens Løsningsbeskrivelse.txt; docs/tender-reference/extracted/KK Tender tool.txt; docs/tender-reference/extracted/KUM-SLKS/Bilag 3 - Kravspecifikation.txt | AE9: Anton: Confirm verify-tekst; opdatér review status efter tjek. | AG9: Draft | AH9: uim-esdh-full-2026-07-07
A10: 9 | B10: MK-9 | C10: Bilag 1.b | D10: Generelle krav | E10: Deling af Entiteter | F10: ESDH-løsningen skal understøtte, at Entiteter kan deles mellem Brugere, såfremt adgangene tillader dette. | G10: Mindstekrav | H10: =IF(G10="Evalueringskrav","Answer",(IF(G10="Krav","Check",(IF(G10="Mindstekrav","Verify",""))))) -> Verify | I10: Ja | L10: Anton | O10: 1. Fully met | V10: Reviewed - Content | W10: =IF(V10="Not Started",0%,IF(V10="Started",50%,IF(V10="Ready for review",70%,IF(V10="Reviewed - Content",80%,IF(V10="Reviewed - Format",90%,IF(V10="Done",100%,"")))))) -> 0.8 | X10: 2026-07-07 | Y10: Cursor / tender-response (batch) | Z10: Met | AA10: Verified | AB10: Verify: Deling af Entiteter — vurderet opfyldt (tool: 1. Fully met). | AD10: docs/tender-reference/extracted/Nationalbanken/Bilag 3.i Leverandørens Løsningsbeskrivelse.txt; docs/tender-reference/extracted/KK Tender tool.txt; docs/tender-reference/extracted/KUM-SLKS/Bilag 3 - Kravspecifikation.txt | AE10: Anton: Confirm verify-tekst; opdatér review status efter tjek. | AG10: Draft | AH10: uim-esdh-full-2026-07-07
A11: 10 | B11: MK-10 | C11: Bilag 1.b | D11: Generelle krav | E11: Journalplan | F11: ESDH-løsningen skal understøtte en klassisk journalplan eller facetteret journalplan i minimum tre niveauer og emneordsfelter. | G11: Mindstekrav | H11: =IF(G11="Evalueringskrav","Answer",(IF(G11="Krav","Check",(IF(G11="Mindstekrav","Verify",""))))) -> Verify | I11: Ja | L11: Anton | O11: 1. Fully met | V11: Reviewed - Content | W11: =IF(V11="Not Started",0%,IF(V11="Started",50%,IF(V11="Ready for review",70%,IF(V11="Reviewed - Content",80%,IF(V11="Reviewed - Format",90%,IF(V11="Done",100%,"")))))) -> 0.8 | X11: 2026-07-07 | Y11: Cursor / tender-response (batch) | Z11: Met | AA11: Verified | AB11: Verify: Journalplan — vurderet opfyldt (tool: 1. Fully met). | AD11: docs/tender-reference/extracted/KK Tender tool.txt; docs/tender-reference/extracted/Nationalbanken/Bilag 3.i Leverandørens Løsningsbeskrivelse.txt; docs/tender-reference/extracted/KUM-SLKS/Bilag 1 - Tidsplan.txt | AE11: Anton: Confirm verify-tekst; opdatér review status efter tjek. | AG11: Draft | AH11: uim-esdh-full-2026-07-07
A12: 11 | B12: MK-11 | C12: Bilag 1.b | D12: Generelle krav | E12: Oprettelse af brevskabeloner | F12: ESDH-løsningen skal understøtte oprettelse af breve baseret på Kundens brevskabeloner i Dynamic Template. | G12: Mindstekrav | H12: =IF(G12="Evalueringskrav","Answer",(IF(G12="Krav","Check",(IF(G12="Mindstekrav","Verify",""))))) -> Verify | I12: Ja | L12: Anton | N12: Template Connect | O12: 1. Fully met | V12: Reviewed - Content | W12: =IF(V12="Not Started",0%,IF(V12="Started",50%,IF(V12="Ready for review",70%,IF(V12="Reviewed - Content",80%,IF(V12="Reviewed - Format",90%,IF(V12="Done",100%,"")))))) -> 0.8 | X12: 2026-07-07 | Y12: Cursor / tender-response (batch) | Z12: Met | AA12: Verified | AB12: Verify: Oprettelse af brevskabeloner — vurderet opfyldt (tool: 1. Fully met). | AD12: docs/tender-reference/extracted/KK Tender tool.txt; docs/tender-reference/extracted/Nationalbanken/Bilag 3.i Leverandørens Løsningsbeskrivelse.txt; docs/tender-reference/extracted/HSØ/02.00-Tietoevry-SSA-L-Bilag 2-Leverandørens beskrivelse av Tjenesten.txt | AE12: Anton: Confirm verify-tekst; opdatér review status efter tjek. | AG12: Draft | AH12: uim-esdh-full-2026-07-07
A13: 12 | B13: K-1 | C13: Bilag 1.b | D13: Generelle krav | E13: Fejlmeddelelser med handlingsanvisninger | F13: ESDH-løsningen skal understøtte, at fejlmeddelelser i ESDH-løsningen inkluderer handlingsanvisning. | G13: Krav | H13: =IF(G13="Evalueringskrav","Answer",(IF(G13="Krav","Check",(IF(G13="Mindstekrav","Verify",""))))) -> Check | I13: Ja | L13: Torben | O13: 1. Fully met | P13: ADN: We tend to say yes to this requirement - but it comes with a risc, especially if customer uses same External partner in the implementation project | S13: Yes | V13: Ready for review | W13: =IF(V13="Not Started",0%,IF(V13="Started",50%,IF(V13="Ready for review",70%,IF(V13="Reviewed - Content",80%,IF(V13="Reviewed - Format",90%,IF(V13="Done",100%,"")))))) -> 0.7 | X13: 2026-07-07 | Y13: Cursor / tender-response (batch) | Z13: Met | AA13: Lead | AB13: Check: Fejlmeddelelser med handlingsanvisninger — vurderet opfyldt (tool: 1. Fully met). | AC13: ADN: We tend to say yes to this requirement - but it comes with a risc, especially if customer uses same External partner in the implementation project | AD13: docs/tender-reference/extracted/KK Tender tool.txt; docs/product/RFP_Leverandørens_svar_utdrag.txt; docs/tender-reference/extracted/HSØ/02.00-Tietoevry-SSA-L-Bilag 2-Leverandørens beskrivelse av Tjenesten.txt | AE13: Torben: Confirm verify-tekst; opdatér review status efter tjek. | AG13: Draft | AH13: uim-esdh-full-2026-07-07
A14: 13 | B14: MK-12 | C14: Bilag 1.b | D14: Sager | E14: Oprettelse af Sager | F14: ESDH-løsningen skal understøtte oprettelse og registrering af sager. | G14: Mindstekrav | H14: =IF(G14="Evalueringskrav","Answer",(IF(G14="Krav","Check",(IF(G14="Mindstekrav","Verify",""))))) -> Verify | I14: Ja | L14: Anton | O14: 1. Fully met | V14: Reviewed - Content | W14: =IF(V14="Not Started",0%,IF(V14="Started",50%,IF(V14="Ready for review",70%,IF(V14="Reviewed - Content",80%,IF(V14="Reviewed - Format",90%,IF(V14="Done",100%,"")))))) -> 0.8 | X14: 2026-07-07 | Y14: Cursor / tender-response (batch) | Z14: Met | AA14: Verified | AB14: Verify: Oprettelse af Sager — vurderet opfyldt (tool: 1. Fully met). | AD14: docs/tender-reference/extracted/KK Tender tool.txt; docs/tender-reference/extracted/KUM-SLKS/Bilag 3 - 11.8 - Kravspecifikation - Processtyring (1).txt; docs/tender-reference/extracted/KUM-SLKS/Bilag 3 - Kravspecifikation.txt | AE14: Anton: Confirm verify-tekst; opdatér review status efter tjek. | AG14: Draft | AH14: uim-esdh-full-2026-07-07
A15: 14 | B15: MK-13 | C15: Bilag 1.b | D15: Sager | E15: Ændring af sager | F15: ESDH-løsningen skal understøtte ændring af sagens metadata. | G15: Mindstekrav | H15: =IF(G15="Evalueringskrav","Answer",(IF(G15="Krav","Check",(IF(G15="Mindstekrav","Verify",""))))) -> Verify | I15: Ja | L15: Anton | O15: 1. Fully met | V15: Reviewed - Content | W15: =IF(V15="Not Started",0%,IF(V15="Started",50%,IF(V15="Ready for review",70%,IF(V15="Reviewed - Content",80%,IF(V15="Reviewed - Format",90%,IF(V15="Done",100%,"")))))) -> 0.8 | X15: 2026-07-07 | Y15: Cursor / tender-response (batch) | Z15: Met | AA15: Verified | AB15: Verify: Ændring af sager — vurderet opfyldt (tool: 1. Fully met). | AD15: docs/tender-reference/extracted/KK Tender tool.txt; docs/tender-reference/extracted/KUM-SLKS/Bilag 3 - Kravspecifikation.txt; docs/tender-reference/extracted/Nationalbanken/Bilag 3.i Leverandørens Løsningsbeskrivelse.txt | AE15: Anton: Confirm verify-tekst; opdatér review status efter tjek. | AG15: Draft | AH15: uim-esdh-full-2026-07-07
A16: 15 | B16: MK-14 | C16: Bilag 1.b | D16: Sager | E16: Sletning af sager | F16: ESDH-løsningen skal understøtte både midlertidig og permanent sletning af sager. | G16: Mindstekrav | H16: =IF(G16="Evalueringskrav","Answer",(IF(G16="Krav","Check",(IF(G16="Mindstekrav","Verify",""))))) -> Verify | I16: Ja | L16: Anton | O16: 1. Fully met | V16: Reviewed - Content | W16: =IF(V16="Not Started",0%,IF(V16="Started",50%,IF(V16="Ready for review",70%,IF(V16="Reviewed - Content",80%,IF(V16="Reviewed - Format",90%,IF(V16="Done",100%,"")))))) -> 0.8 | X16: 2026-07-07 | Y16: Cursor / tender-response (batch) | Z16: Met | AA16: Verified | AB16: Verify: Sletning af sager — vurderet opfyldt (tool: 1. Fully met). | AD16: docs/tender-reference/extracted/KK Tender tool.txt; docs/tender-reference/extracted/Nationalbanken/Bilag 3.i Leverandørens Løsningsbeskrivelse.txt; docs/product/RFP_Leverandørens_svar_utdrag.txt | AE16: Anton: Confirm verify-tekst; opdatér review status efter tjek. | AG16: Draft | AH16: uim-esdh-full-2026-07-07
A17: 16 | B17: MK-15 | C17: Bilag 1.b | D17: Sager | E17: Status | F17: ESDH-løsningen skal understøtte arbejdet med statusser på en sag, f.eks. 'Passiv', 'Under behandling' og 'Lukket' / 'Afsluttet'. ESDH-løsningen skal understøtte, at Kunden selv kan oprette og vedligeholde statuskoder. | G17: Mindstekrav | H17: =IF(G17="Evalueringskrav","Answer",(IF(G17="Krav","Check",(IF(G17="Mindstekrav","Verify",""))))) -> Verify | I17: Ja | L17: Anton | O17: 1. Fully met | V17: Reviewed - Content | W17: =IF(V17="Not Started",0%,IF(V17="Started",50%,IF(V17="Ready for review",70%,IF(V17="Reviewed - Content",80%,IF(V17="Reviewed - Format",90%,IF(V17="Done",100%,"")))))) -> 0.8 | X17: 2026-07-07 | Y17: Cursor / tender-response (batch) | Z17: Met | AA17: Verified | AB17: Verify: Status — vurderet opfyldt (tool: 1. Fully met). | AD17: docs/tender-reference/extracted/Nationalbanken/Bilag 3.i Leverandørens Løsningsbeskrivelse.txt; docs/tender-reference/extracted/KK Tender tool.txt; docs/tender-reference/extracted/KUM-SLKS/Bilag 3 - Kravspecifikation.txt | AE17: Anton: Confirm verify-tekst; opdatér review status efter tjek. | AG17: Draft | AH17: uim-esdh-full-2026-07-07
A18: 17 | B18: MK-16 | C18: Bilag 1.b | D18: Sager | E18: Sagsnummer | F18: ESDH-løsningen skal understøtte, at hver sag tildeles et unikt sagsnummer automatisk ved oprettelse. | G18: Mindstekrav | H18: =IF(G18="Evalueringskrav","Answer",(IF(G18="Krav","Check",(IF(G18="Mindstekrav","Verify",""))))) -> Verify | I18: Ja | L18: Anton | O18: 1. Fully met | V18: Reviewed - Content | W18: =IF(V18="Not Started",0%,IF(V18="Started",50%,IF(V18="Ready for review",70%,IF(V18="Reviewed - Content",80%,IF(V18="Reviewed - Format",90%,IF(V18="Done",100%,"")))))) -> 0.8 | X18: 2026-07-07 | Y18: Cursor / tender-response (batch) | Z18: Met | AA18: Verified | AB18: Verify: Sagsnummer — vurderet opfyldt (tool: 1. Fully met). | AD18: docs/tender-reference/extracted/Nationalbanken/Bilag 3.i Leverandørens Løsningsbeskrivelse.txt; docs/tender-reference/extracted/KK Tender tool.txt; docs/tender-reference/extracted/KUM-SLKS/Bilag 3 - Kravspecifikation.txt | AE18: Anton: Confirm verify-tekst; opdatér review status efter tjek. | AG18: Draft | AH18: uim-esdh-full-2026-07-07
A19: 18 | B19: MK-17 | C19: Bilag 1.b | D19: Sager | E19: Ændring af sagstyper | F19: ESDH-løsningen skal understøtte, at en Bruger kan ændre sagstype på sager. | G19: Mindstekrav | H19: =IF(G19="Evalueringskrav","Answer",(IF(G19="Krav","Check",(IF(G19="Mindstekrav","Verify",""))))) -> Verify | I19: Ja | L19: Anton | O19: 1. Fully met | V19: Reviewed - Content | W19: =IF(V19="Not Started",0%,IF(V19="Started",50%,IF(V19="Ready for review",70%,IF(V19="Reviewed - Content",80%,IF(V19="Reviewed - Format",90%,IF(V19="Done",100%,"")))))) -> 0.8 | X19: 2026-07-07 | Y19: Cursor / tender-response (batch) | Z19: Met | AA19: Verified | AB19: Verify: Ændring af sagstyper — vurderet opfyldt (tool: 1. Fully met). | AD19: docs/tender-reference/extracted/KK Tender tool.txt; docs/tender-reference/extracted/KUM-SLKS/Bilag 3 - Kravspecifikation.txt; docs/tender-reference/extracted/Nationalbanken/Bilag 3.i Leverandørens Løsningsbeskrivelse.txt | AE19: Anton: Confirm verify-tekst; opdatér review status efter tjek. | AG19: Draft | AH19: uim-esdh-full-2026-07-07
A20: 19 | B20: MK-18 | C20: Bilag 1.b | D20: Sager | E20: Sagens frister | F20: ESDH-løsningen skal understøtte, at der kan indsættes, rettes og fjernes frister på alle sagstyper. Fristen skal som minimum bestå af en fristtype, fristdato og fristansvarlig. | G20: Mindstekrav | H20: =IF(G20="Evalueringskrav","Answer",(IF(G20="Krav","Check",(IF(G20="Mindstekrav","Verify",""))))) -> Verify | I20: Ja | L20: Anton | O20: 1. Fully met | P20: ADN:Configure field called "Fristtype" | V20: Reviewed - Content | W20: =IF(V20="Not Started",0%,IF(V20="Started",50%,IF(V20="Ready for review",70%,IF(V20="Reviewed - Content",80%,IF(V20="Reviewed - Format",90%,IF(V20="Done",100%,"")))))) -> 0.8 | X20: 2026-07-07 | Y20: Cursor / tender-response (batch) | Z20: Met | AA20: Verified | AB20: Verify: Sagens frister — vurderet opfyldt (tool: 1. Fully met). | AC20: ADN:Configure field called "Fristtype" | AD20: docs/tender-reference/extracted/Nationalbanken/Bilag 3.i Leverandørens Løsningsbeskrivelse.txt; docs/tender-reference/extracted/KUM-SLKS/Bilag 3 - Kravspecifikation.txt; docs/tender-reference/extracted/KK Tender tool.txt | AE20: Anton: Confirm verify-tekst; opdatér review status efter tjek. | AG20: Draft | AH20: uim-esdh-full-2026-07-07
A21: 20 | B21: MK-19 | C21: Bilag 1.b | D21: Sager | E21: Afdelingsspecifikke frister | F21: ESDH-løsningen skal understøtte, at Brugere kan indsætte, rette og fjerne én eller flere afdelingsspecifikke frister på sager. | G21: Mindstekrav | H21: =IF(G21="Evalueringskrav","Answer",(IF(G21="Krav","Check",(IF(G21="Mindstekrav","Verify",""))))) -> Verify | I21: Ja | L21: Anton | O21: 1. Fully met | V21: Reviewed - Content | W21: =IF(V21="Not Started",0%,IF(V21="Started",50%,IF(V21="Ready for review",70%,IF(V21="Reviewed - Content",80%,IF(V21="Reviewed - Format",90%,IF(V21="Done",100%,"")))))) -> 0.8 | X21: 2026-07-07 | Y21: Cursor / tender-response (batch) | Z21: Met | AA21: Verified | AB21: Verify: Afdelingsspecifikke frister — vurderet opfyldt (tool: 1. Fully met). | AD21: docs/tender-reference/extracted/KUM-SLKS/Bilag 3 - Kravspecifikation.txt; docs/tender-reference/extracted/Nationalbanken/Bilag 3.i Leverandørens Løsningsbeskrivelse.txt; docs/tender-reference/extracted/KK Tender tool.txt | AE21: Anton: Confirm verify-tekst; opdatér review status efter tjek. | AG21: Draft | AH21: uim-esdh-full-2026-07-07
A22: 21 | B22: MK-20 | C22: Bilag 1.b | D22: Sager | E22: Samlesager | F22: ESDH-løsningen skal understøtte oprettelse af samlesager. Det skal være muligt for Brugeren at tilknytte enkle sager til samlesager. | G22: Mindstekrav | H22: =IF(G22="Evalueringskrav","Answer",(IF(G22="Krav","Check",(IF(G22="Mindstekrav","Verify",""))))) -> Verify | I22: Ja | L22: Anton | O22: 1. Fully met | V22: Reviewed - Content | W22: =IF(V22="Not Started",0%,IF(V22="Started",50%,IF(V22="Ready for review",70%,IF(V22="Reviewed - Content",80%,IF(V22="Reviewed - Format",90%,IF(V22="Done",100%,"")))))) -> 0.8 | X22: 2026-07-07 | Y22: Cursor / tender-response (batch) | Z22: Met | AA22: Verified | AB22: Verify: Samlesager — vurderet opfyldt (tool: 1. Fully met). | AD22: docs/tender-reference/extracted/Nationalbanken/Bilag 3.i Leverandørens Løsningsbeskrivelse.txt; docs/tender-reference/extracted/KK Tender tool.txt; docs/tender-reference/extracted/KUM-SLKS/Bilag 3 - 11.8 - Kravspecifikation - Processtyring (1).txt | AE22: Anton: Confirm verify-tekst; opdatér review status efter tjek. | AG22: Draft | AH22: uim-esdh-full-2026-07-07
A23: 22 | B23: MK-21 | C23: Bilag 1.b | D23: Sager | E23: Oprettelse af hierarkisk samling | F23: ESDH-løsningen skal understøtte oprettelsesfunktion til organisering og hierarkisk visning af samling af relaterede sager. | G23: Mindstekrav | H23: =IF(G23="Evalueringskrav","Answer",(IF(G23="Krav","Check",(IF(G23="Mindstekrav","Verify",""))))) -> Verify | I23: Ja | L23: Eva | O23: 1. Fully met | P23: ADN: Im unsure what they mean with this requirement. - is this "Træstrukturen"? | V23: Ready for review | W23: =IF(V23="Not Started",0%,IF(V23="Started",50%,IF(V23="Ready for review",70%,IF(V23="Reviewed - Content",80%,IF(V23="Reviewed - Format",90%,IF(V23="Done",100%,"")))))) -> 0.7 | X23: 2026-07-07 | Y23: Cursor / tender-response (batch) | Z23: Met | AA23: Verified | AB23: Verify: Oprettelse af hierarkisk samling — vurderet opfyldt (tool: 1. Fully met). | AC23: ADN: Im unsure what they mean with this requirement. - is this "Træstrukturen"? | AD23: docs/tender-reference/extracted/Nationalbanken/Bilag 3.i Leverandørens Løsningsbeskrivelse.txt; docs/tender-reference/extracted/KK Tender tool.txt; docs/tender-reference/extracted/KUM-SLKS/Bilag 3 - Kravspecifikation.txt | AE23: Eva: Confirm verify-tekst; opdatér review status efter tjek. | AG23: Draft | AH23: uim-esdh-full-2026-07-07
A24: 23 | B24: MK-22 | C24: Bilag 1.b | D24: Sager | E24: Referencer | F24: ESDH-løsningen skal understøtte oprettelse af referencer mellem sager ved at etablere links mellem sager. Det skal fremgå tydeligt af den enkelte sag, at den er relateret til en anden. | G24: Mindstekrav | H24: =IF(G24="Evalueringskrav","Answer",(IF(G24="Krav","Check",(IF(G24="Mindstekrav","Verify",""))))) -> Verify | I24: Ja | L24: Anton | O24: 1. Fully met | V24: Reviewed - Content | W24: =IF(V24="Not Started",0%,IF(V24="Started",50%,IF(V24="Ready for review",70%,IF(V24="Reviewed - Content",80%,IF(V24="Reviewed - Format",90%,IF(V24="Done",100%,"")))))) -> 0.8 | X24: 2026-07-07 | Y24: Cursor / tender-response (batch) | Z24: Met | AA24: Verified | AB24: Verify: Referencer — vurderet opfyldt (tool: 1. Fully met). | AD24: docs/tender-reference/extracted/KK Tender tool.txt; docs/tender-reference/extracted/Nationalbanken/Bilag 3.i Leverandørens Løsningsbeskrivelse.txt; docs/tender-reference/extracted/KUM-SLKS/Bilag 3 - Kravspecifikation.txt | AE24: Anton: Confirm verify-tekst; opdatér review status efter tjek. | AG24: Draft | AH24: uim-esdh-full-2026-07-07
A25: 24 | B25: MK-23 | C25: Bilag 1.b | D25: Sager | E25: Fremvisning af parter | F25: ESDH-løsningen skal understøtte, at sagens parter kan vises enten i sagens overbliksbillede eller i en dedikeret fane. | G25: Mindstekrav | H25: =IF(G25="Evalueringskrav","Answer",(IF(G25="Krav","Check",(IF(G25="Mindstekrav","Verify",""))))) -> Verify | I25: Ja | L25: Anton | O25: 1. Fully met | V25: Reviewed - Content | W25: =IF(V25="Not Started",0%,IF(V25="Started",50%,IF(V25="Ready for review",70%,IF(V25="Reviewed - Content",80%,IF(V25="Reviewed - Format",90%,IF(V25="Done",100%,"")))))) -> 0.8 | X25: 2026-07-07 | Y25: Cursor / tender-response (batch) | Z25: Met | AA25: Verified | AB25: Verify: Fremvisning af parter — vurderet opfyldt (tool: 1. Fully met). | AD25: docs/tender-reference/extracted/Nationalbanken/Bilag 3.i Leverandørens Løsningsbeskrivelse.txt; docs/tender-reference/extracted/KUM-SLKS/Bilag 3 - Kravspecifikation.txt; docs/tender-reference/extracted/KK Tender tool.txt | AE25: Anton: Confirm verify-tekst; opdatér review status efter tjek. | AG25: Draft | AH25: uim-esdh-full-2026-07-07
A26: 25 | B26: MK-24 | C26: Bilag 1.b | D26: Sager | E26: Partsrolle | F26: ESDH-løsningen skal understøtte, at en kontakt kan tilknyttes til en sag og at kontakten kan have en konkret partsrolle på sagen. | G26: Mindstekrav | H26: =IF(G26="Evalueringskrav","Answer",(IF(G26="Krav","Check",(IF(G26="Mindstekrav","Verify",""))))) -> Verify | I26: Ja | L26: Anton | O26: 1. Fully met | V26: Reviewed - Content | W26: =IF(V26="Not Started",0%,IF(V26="Started",50%,IF(V26="Ready for review",70%,IF(V26="Reviewed - Content",80%,IF(V26="Reviewed - Format",90%,IF(V26="Done",100%,"")))))) -> 0.8 | X26: 2026-07-07 | Y26: Cursor / tender-response (batch) | Z26: Met | AA26: Verified | AB26: Verify: Partsrolle — vurderet opfyldt (tool: 1. Fully met). | AD26: docs/tender-reference/extracted/KUM-SLKS/Bilag 3 - Kravspecifikation.txt; docs/tender-reference/extracted/Nationalbanken/Bilag 3.i Leverandørens Løsningsbeskrivelse.txt; docs/product/RFP_Leverandørens_svar_utdrag.txt | AE26: Anton: Confirm verify-tekst; opdatér review status efter tjek. | AG26: Draft | AH26: uim-esdh-full-2026-07-07
A27: 26 | B27: MK-25 | C27: Bilag 1.b | D27: Sager | E27: Intern overdragelse af sagsansvar | F27: ESDH-løsningen skal understøtte, at en sag kan overdrages/flyttes til en anden sagsbehandler eller et andet team i organisationen. | G27: Mindstekrav | H27: =IF(G27="Evalueringskrav","Answer",(IF(G27="Krav","Check",(IF(G27="Mindstekrav","Verify",""))))) -> Verify | I27: Ja | L27: Anton | O27: 1. Fully met | V27: Reviewed - Content | W27: =IF(V27="Not Started",0%,IF(V27="Started",50%,IF(V27="Ready for review",70%,IF(V27="Reviewed - Content",80%,IF(V27="Reviewed - Format",90%,IF(V27="Done",100%,"")))))) -> 0.8 | X27: 2026-07-07 | Y27: Cursor / tender-response (batch) | Z27: Met | AA27: Verified | AB27: Verify: Intern overdragelse af sagsansvar — vurderet opfyldt (tool: 1. Fully met). | AD27: docs/tender-reference/extracted/KUM-SLKS/Bilag 3 - Kravspecifikation.txt; docs/product/RFP_Leverandørens_svar_utdrag.txt; docs/tender-reference/extracted/KK Tender tool.txt | AE27: Anton: Confirm verify-tekst; opdatér review status efter tjek. | AG27: Draft | AH27: uim-esdh-full-2026-07-07
A28: 27 | B28: MK-26 | C28: Bilag 1.b | D28: Sager | E28: Genåbning og opdatering af lukkede sager | F28: ESDH-løsningen skal understøtte, at en formelt afsluttet og lukket sag kan genåbnes af en Bruger, hvis der er behov for at opdatere sagsdata. Sager afleveret til Rigsarkivet skal være undtaget, og skal ikke kunne genåbnes efter aflevering. | G28: Mindstekrav | H28: =IF(G28="Evalueringskrav","Answer",(IF(G28="Krav","Check",(IF(G28="Mindstekrav","Verify",""))))) -> Verify | I28: Ja | L28: Anton | O28: 1. Fully met | P28: ADN: Configure historic cases with closed Matrix | V28: Reviewed - Content | W28: =IF(V28="Not Started",0%,IF(V28="Started",50%,IF(V28="Ready for review",70%,IF(V28="Reviewed - Content",80%,IF(V28="Reviewed - Format",90%,IF(V28="Done",100%,"")))))) -> 0.8 | X28: 2026-07-07 | Y28: Cursor / tender-response (batch) | Z28: Met | AA28: Verified | AB28: Verify: Genåbning og opdatering af lukkede sager — vurderet opfyldt (tool: 1. Fully met). | AC28: ADN: Configure historic cases with closed Matrix | AD28: docs/tender-reference/extracted/Nationalbanken/Bilag 3.i Leverandørens Løsningsbeskrivelse.txt; docs/tender-reference/extracted/KK Tender tool.txt; docs/tender-reference/extracted/KUM-SLKS/Bilag 3 - Kravspecifikation.txt | AE28: Anton: Confirm verify-tekst; opdatér review status efter tjek. | AG28: Draft | AH28: uim-esdh-full-2026-07-07
A29: 28 | B29: MK-27 | C29: Bilag 1.b | D29: Sager | E29: Sagskopi | F29: ESDH-løsningen skal understøtte oprettelse af en sagskopi, hvor den oprindelige sags metadata overføres til sagskopien. I forbindelse med oprettelse af sagskopien skal Brugeren valgfrit kunne vælge om sagens parter, Dokumenter og øvrigt metadata skal overføres til sagskopien. Metadata på begge sager skal kunne redigeres efterfølgende. | G29: Mindstekrav | H29: =IF(G29="Evalueringskrav","Answer",(IF(G29="Krav","Check",(IF(G29="Mindstekrav","Verify",""))))) -> Verify | I29: Ja | L29: Anton | O29: 1. Fully met | P29: ADN: copy documents is part of eDoc merger, so Yes | V29: Reviewed - Content | W29: =IF(V29="Not Started",0%,IF(V29="Started",50%,IF(V29="Ready for review",70%,IF(V29="Reviewed - Content",80%,IF(V29="Reviewed - Format",90%,IF(V29="Done",100%,"")))))) -> 0.8 | X29: 2026-07-07 | Y29: Cursor / tender-response (batch) | Z29: Met | AA29: Verified | AB29: Verify: Sagskopi — vurderet opfyldt (tool: 1. Fully met). | AC29: ADN: copy documents is part of eDoc merger, so Yes | AD29: docs/tender-reference/extracted/Nationalbanken/Bilag 3.i Leverandørens Løsningsbeskrivelse.txt; docs/tender-reference/extracted/KK Tender tool.txt; docs/tender-reference/extracted/KUM-SLKS/Bilag 3 - Kravspecifikation.txt | AE29: Anton: Confirm verify-tekst; opdatér review status efter tjek. | AG29: Draft | AH29: uim-esdh-full-2026-07-07
A30: 29 | B30: MK-28 | C30: Bilag 1.b | D30: Sager | E30: Noter | F30: ESDH-løsningen skal understøtte, at der kan oprettes noter på sager. Oplysninger om sagsbehandler, dato og klokkeslæt skal fremgå af noten. Alle Brugere med adgang til sagen skal kunne se agere på noten i sagsbehandlingen. | G30: Mindstekrav | H30: =IF(G30="Evalueringskrav","Answer",(IF(G30="Krav","Check",(IF(G30="Mindstekrav","Verify",""))))) -> Verify | I30: Ja | L30: Anton | O30: 1. Fully met | V30: Reviewed - Content | W30: =IF(V30="Not Started",0%,IF(V30="Started",50%,IF(V30="Ready for review",70%,IF(V30="Reviewed - Content",80%,IF(V30="Reviewed - Format",90%,IF(V30="Done",100%,"")))))) -> 0.8 | X30: 2026-07-07 | Y30: Cursor / tender-response (batch) | Z30: Met | AA30: Verified | AB30: Verify: Noter — vurderet opfyldt (tool: 1. Fully met). | AD30: docs/tender-reference/extracted/Nationalbanken/Bilag 3.i Leverandørens Løsningsbeskrivelse.txt; docs/tender-reference/extracted/KK Tender tool.txt; docs/tender-reference/extracted/KUM-SLKS/Bilag 3 - Kravspecifikation.txt | AE30: Anton: Confirm verify-tekst; opdatér review status efter tjek. | AG30: Draft | AH30: uim-esdh-full-2026-07-07
A31: 30 | B31: MK-29 | C31: Bilag 1.b | D31: Sager | E31: Journalisering | F31: ESDH-løsningen skal understøtte, at Brugere manuelt kan journalisere og gemme Dokumenter, korrespondancer samt interne og eksterne beskeder på sager. | G31: Mindstekrav | H31: =IF(G31="Evalueringskrav","Answer",(IF(G31="Krav","Check",(IF(G31="Mindstekrav","Verify",""))))) -> Verify | I31: Ja | L31: Anton | O31: 1. Fully met | V31: Reviewed - Content | W31: =IF(V31="Not Started",0%,IF(V31="Started",50%,IF(V31="Ready for review",70%,IF(V31="Reviewed - Content",80%,IF(V31="Reviewed - Format",90%,IF(V31="Done",100%,"")))))) -> 0.8 | X31: 2026-07-07 | Y31: Cursor / tender-response (batch) | Z31: Met | AA31: Verified | AB31: Verify: Journalisering — vurderet opfyldt (tool: 1. Fully met). | AD31: docs/tender-reference/extracted/KK Tender tool.txt; docs/tender-reference/extracted/Nationalbanken/Bilag 3.i Leverandørens Løsningsbeskrivelse.txt; docs/tender-reference/extracted/KUM-SLKS/Bilag 3 - Kravspecifikation.txt | AE31: Anton: Confirm verify-tekst; opdatér review status efter tjek. | AG31: Draft | AH31: uim-esdh-full-2026-07-07
A32: 31 | B32: MK-30 | C32: Bilag 1.b | D32: Sager | E32: Præsentation af hierarkiske samlinger | F32: ESDH-løsningen skal understøtte visning af hierarkiske samlinger af relaterede sager fra søgningslister og visningslister. | G32: Mindstekrav | H32: =IF(G32="Evalueringskrav","Answer",(IF(G32="Krav","Check",(IF(G32="Mindstekrav","Verify",""))))) -> Verify | I32: Ja | L32: Eva | O32: 3. Not able to meet | P32: ADN: Det er kludret formuleret - men jeg tolker det til, at de fra en søgning på et projekt, skal kunne se relaterede sager i resultatlisterne.. Det er udfordrende | Q32: 433877 | R32: Yes | V32: Not Started | W32: =IF(V32="Not Started",0%,IF(V32="Started",50%,IF(V32="Ready for review",70%,IF(V32="Reviewed - Content",80%,IF(V32="Reviewed - Format",90%,IF(V32="Done",100%,"")))))) -> 0 | X32: 2026-07-07 | Y32: Cursor / tender-response (MCP-enriched) | Z32: Not met | AA32: Lead | AB32: Verify: Præsentation af hierarkiske samlinger — gap ift. kravtekst; eskalér commitment eller afklaring. | AC32: ADN: Det er kludret formuleret - men jeg tolker det til, at de fra en søgning på et projekt, skal kunne se relaterede sager i resultatlisterne.. Det er udfordrende | Red flag: Det er kludret formuleret - men jeg tolker det til, at de fra en søgning på et projekt, skal kunne se relaterede sager i resultatlisterne.. Det er udfordrende | AD32: Wiki: EArchive 360°; Setup of Continuous Transfer | AE32: Eva: Commitment/no-bid beslutning; overvej Q&A til ordregiver. | AG32: Draft | AH32: uim-esdh-full-2026-07-07
A33: 32 | B33: MK-31 | C33: Bilag 1.b | D33: Sager | E33: Antal frister | F33: ESDH-løsningen skal understøtte, at en sag kan have flere frister tilknyttet. Fristerne skal vises på en logisk og overskuelig måde i brugergrænsefladen, så Brugeren nemt kan se fristtype, status og tidspunkt for kommende frister. | G33: Mindstekrav | H33: =IF(G33="Evalueringskrav","Answer",(IF(G33="Krav","Check",(IF(G33="Mindstekrav","Verify",""))))) -> Verify | I33: Ja | L33: Anton | O33: 1. Fully met | V33: Reviewed - Content | W33: =IF(V33="Not Started",0%,IF(V33="Started",50%,IF(V33="Ready for review",70%,IF(V33="Reviewed - Content",80%,IF(V33="Reviewed - Format",90%,IF(V33="Done",100%,"")))))) -> 0.8 | X33: 2026-07-07 | Y33: Cursor / tender-response (batch) | Z33: Met | AA33: Verified | AB33: Verify: Antal frister — vurderet opfyldt (tool: 1. Fully met). | AD33: docs/tender-reference/extracted/Nationalbanken/Bilag 3.i Leverandørens Løsningsbeskrivelse.txt; docs/tender-reference/extracted/KK Tender tool.txt; docs/tender-reference/extracted/KUM-SLKS/Bilag 3 - Kravspecifikation.txt | AE33: Anton: Confirm verify-tekst; opdatér review status efter tjek. | AG33: Draft | AH33: uim-esdh-full-2026-07-07
A34: 33 | B34: MK-32 | C34: Bilag 1.b | D34: Sager | E34: Noter – Journalisering på sag | F34: ESDH-løsningen skal understøtte, at noter kan konverteres til et Dokument med en tilhørende Fil, som kan journaliseres på den tilknyttede sag. | G34: Mindstekrav | H34: =IF(G34="Evalueringskrav","Answer",(IF(G34="Krav","Check",(IF(G34="Mindstekrav","Verify",""))))) -> Verify | I34: Ja | L34: Anton | O34: 1. Fully met | P34: ADN: Configure Case Note summary functionality | V34: Reviewed - Content | W34: =IF(V34="Not Started",0%,IF(V34="Started",50%,IF(V34="Ready for review",70%,IF(V34="Reviewed - Content",80%,IF(V34="Reviewed - Format",90%,IF(V34="Done",100%,"")))))) -> 0.8 | X34: 2026-07-07 | Y34: Cursor / tender-response (batch) | Z34: Met | AA34: Verified | AB34: Verify: Noter – Journalisering på sag — vurderet opfyldt (tool: 1. Fully met). | AC34: ADN: Configure Case Note summary functionality | AD34: docs/tender-reference/extracted/KK Tender tool.txt; docs/tender-reference/extracted/KUM-SLKS/Bilag 3 - Kravspecifikation.txt; docs/tender-reference/extracted/Nationalbanken/Bilag 3.i Leverandørens Løsningsbeskrivelse.txt | AE34: Anton: Confirm verify-tekst; opdatér review status efter tjek. | AG34: Draft | AH34: uim-esdh-full-2026-07-07
A35: 34 | B35: MK-33 | C35: Bilag 1.b | D35: Dokumenter | E35: Behandling af Dokumenter | F35: ESDH-løsningen skal understøtte grundlæggende dokumenthåndtering, herunder oprettelse, redigering, versionsstyring og tilknytning af relevante metadata. | G35: Mindstekrav | H35: =IF(G35="Evalueringskrav","Answer",(IF(G35="Krav","Check",(IF(G35="Mindstekrav","Verify",""))))) -> Verify | I35: Ja | L35: Anton | O35: 1. Fully met | V35: Reviewed - Content | W35: =IF(V35="Not Started",0%,IF(V35="Started",50%,IF(V35="Ready for review",70%,IF(V35="Reviewed - Content",80%,IF(V35="Reviewed - Format",90%,IF(V35="Done",100%,"")))))) -> 0.8 | X35: 2026-07-07 | Y35: Cursor / tender-response (batch) | Z35: Met | AA35: Verified | AB35: Verify: Behandling af Dokumenter — vurderet opfyldt (tool: 1. Fully met). | AD35: docs/tender-reference/extracted/Nationalbanken/Bilag 3.i Leverandørens Løsningsbeskrivelse.txt; docs/tender-reference/extracted/KK Tender tool.txt; docs/tender-reference/extracted/KUM-SLKS/Bilag 3 - Kravspecifikation.txt | AE35: Anton: Confirm verify-tekst; opdatér review status efter tjek. | AG35: Draft | AH35: uim-esdh-full-2026-07-07
A36: 35 | B36: MK-34 | C36: Bilag 1.b | D36: Dokumenter | E36: Oprettelse af felter | F36: ESDH-løsningen skal understøtte, at felter kan oprettes og relateres til Dokumenter af Kunden. | G36: Mindstekrav | H36: =IF(G36="Evalueringskrav","Answer",(IF(G36="Krav","Check",(IF(G36="Mindstekrav","Verify",""))))) -> Verify | I36: Ja | L36: Anton | O36: 1. Fully met | V36: Reviewed - Content | W36: =IF(V36="Not Started",0%,IF(V36="Started",50%,IF(V36="Ready for review",70%,IF(V36="Reviewed - Content",80%,IF(V36="Reviewed - Format",90%,IF(V36="Done",100%,"")))))) -> 0.8 | X36: 2026-07-07 | Y36: Cursor / tender-response (batch) | Z36: Met | AA36: Verified | AB36: Verify: Oprettelse af felter — vurderet opfyldt (tool: 1. Fully met). | AD36: docs/tender-reference/extracted/KUM-SLKS/Bilag 3 - Kravspecifikation.txt; docs/tender-reference/extracted/KK Tender tool.txt; docs/tender-reference/extracted/KUM-SLKS/Bilag 3 - 11.8 - Kravspecifikation - Processtyring (1).txt | AE36: Anton: Confirm verify-tekst; opdatér review status efter tjek. | AG36: Draft | AH36: uim-esdh-full-2026-07-07
A37: 36 | B37: MK-35 | C37: Bilag 1.b | D37: Dokumenter | E37: Unikt ID | F37: ESDH-løsningen skal understøtte, at alle Dokumenter, Filer, Hoveddokumenter og Bilag har hver deres unikke ID, som skal være synligt i brugergrænsefladen. | G37: Mindstekrav | H37: =IF(G37="Evalueringskrav","Answer",(IF(G37="Krav","Check",(IF(G37="Mindstekrav","Verify",""))))) -> Verify | I37: Ja | L37: Anton | O37: 1. Fully met | P37: ADN: Hvornår er noget ”synligt i brugergrænsefladen”… vi har recno på filer, men de kræver ”vis egenskaber” for at være synlige. Tjek definitionsbilag for ordet "brugergrænsefladen" Maksimeret visning - ny visning | V37: Reviewed - Content | W37: =IF(V37="Not Started",0%,IF(V37="Started",50%,IF(V37="Ready for review",70%,IF(V37="Reviewed - Content",80%,IF(V37="Reviewed - Format",90%,IF(V37="Done",100%,"")))))) -> 0.8 | X37: 2026-07-07 | Y37: Cursor / tender-response (MCP-enriched) | Z37: Met | AA37: Lead | AB37: Verify: Unikt ID — vurderet opfyldt (tool: 1. Fully met). | AC37: ADN: Hvornår er noget ”synligt i brugergrænsefladen”… vi har recno på filer, men de kræver ”vis egenskaber” for at være synlige. Tjek definitionsbilag for ordet "brugergrænsefladen" Maksimeret visning - ny visning | Red flag: Hvornår er noget ”synligt i brugergrænsefladen”… vi har recno på filer, men de kræver ”vis egenskaber” for at være synlige. | AD37: Wiki: 360° AutoSaver - Technical documentation; Process Engine - Manual | AE37: Anton: Confirm verify-tekst; opdatér review status efter tjek. | AG37: Draft | AH37: uim-esdh-full-2026-07-07
A38: 37 | B38: MK-36 | C38: Bilag 1.b | D38: Dokumenter | E38: Relation mellem sag og Dokument | F38: ESDH-løsningen skal understøtte en obligatorisk relation mellem sag og Dokument. | G38: Mindstekrav | H38: =IF(G38="Evalueringskrav","Answer",(IF(G38="Krav","Check",(IF(G38="Mindstekrav","Verify",""))))) -> Verify | I38: Ja | L38: Anton | O38: 1. Fully met | V38: Reviewed - Content | W38: =IF(V38="Not Started",0%,IF(V38="Started",50%,IF(V38="Ready for review",70%,IF(V38="Reviewed - Content",80%,IF(V38="Reviewed - Format",90%,IF(V38="Done",100%,"")))))) -> 0.8 | X38: 2026-07-07 | Y38: Cursor / tender-response (batch) | Z38: Met | AA38: Verified | AB38: Verify: Relation mellem sag og Dokument — vurderet opfyldt (tool: 1. Fully met). | AD38: docs/tender-reference/extracted/KK Tender tool.txt; docs/tender-reference/extracted/KUM-SLKS/Bilag 3 - Kravspecifikation.txt; docs/tender-reference/extracted/Nationalbanken/Bilag 3.i Leverandørens Løsningsbeskrivelse.txt | AE38: Anton: Confirm verify-tekst; opdatér review status efter tjek. | AG38: Draft | AH38: uim-esdh-full-2026-07-07
A39: 38 | B39: MK-37 | C39: Bilag 1.b | D39: Dokumenter | E39: Bilag | F39: ESDH-løsningen skal understøtte, at et Hoveddokument kan have et eller flere Bilag. | G39: Mindstekrav | H39: =IF(G39="Evalueringskrav","Answer",(IF(G39="Krav","Check",(IF(G39="Mindstekrav","Verify",""))))) -> Verify | I39: Ja | L39: Anton | O39: 1. Fully met | V39: Reviewed - Content | W39: =IF(V39="Not Started",0%,IF(V39="Started",50%,IF(V39="Ready for review",70%,IF(V39="Reviewed - Content",80%,IF(V39="Reviewed - Format",90%,IF(V39="Done",100%,"")))))) -> 0.8 | X39: 2026-07-07 | Y39: Cursor / tender-response (batch) | Z39: Met | AA39: Verified | AB39: Verify: Bilag — vurderet opfyldt (tool: 1. Fully met). | AD39: docs/product/RFP_Leverandørens_svar_utdrag.txt; docs/tender-reference/extracted/KUM-SLKS/Bilag 3 - Kravspecifikation.txt; docs/tender-reference/extracted/NND/02.01-Tieto-Bilag 2-Vedlegg-Leverandørens utfyllende svar til kravtabell.txt | AE39: Anton: Confirm verify-tekst; opdatér review status efter tjek. | AG39: Draft | AH39: uim-esdh-full-2026-07-07
A40: 39 | B40: MK-38 | C40: Bilag 1.b | D40: Dokumenter | E40: Valg af Hoveddokument og Bilag | F40: ESDH-løsningen skal understøtte, at Brugeren kan vælge, hvilken Fil der skal være Hoveddokument, og hvilke Filer der skal tilknyttes som Bilag. | G40: Mindstekrav | H40: =IF(G40="Evalueringskrav","Answer",(IF(G40="Krav","Check",(IF(G40="Mindstekrav","Verify",""))))) -> Verify | I40: Ja | L40: Anton | O40: 1. Fully met | V40: Reviewed - Content | W40: =IF(V40="Not Started",0%,IF(V40="Started",50%,IF(V40="Ready for review",70%,IF(V40="Reviewed - Content",80%,IF(V40="Reviewed - Format",90%,IF(V40="Done",100%,"")))))) -> 0.8 | X40: 2026-07-07 | Y40: Cursor / tender-response (batch) | Z40: Met | AA40: Verified | AB40: Verify: Valg af Hoveddokument og Bilag — vurderet opfyldt (tool: 1. Fully met). | AD40: docs/tender-reference/extracted/KUM-SLKS/Bilag 3 - Kravspecifikation.txt; docs/tender-reference/extracted/Nationalbanken/Bilag 3.i Leverandørens Løsningsbeskrivelse.txt; docs/product/RFP_Leverandørens_svar_utdrag.txt | AE40: Anton: Confirm verify-tekst; opdatér review status efter tjek. | AG40: Draft | AH40: uim-esdh-full-2026-07-07
A41: 40 | B41: MK-39 | C41: Bilag 1.b | D41: Dokumenter | E41: Dokumentets kontakter | F41: ESDH-løsningen skal understøtte, at et indgående eller udgående Dokument kan tilknyttes en kontakt som henholdsvis afsender eller modtager på Dokumentet. | G41: Mindstekrav | H41: =IF(G41="Evalueringskrav","Answer",(IF(G41="Krav","Check",(IF(G41="Mindstekrav","Verify",""))))) -> Verify | I41: Ja | L41: Anton | O41: 1. Fully met | V41: Reviewed - Content | W41: =IF(V41="Not Started",0%,IF(V41="Started",50%,IF(V41="Ready for review",70%,IF(V41="Reviewed - Content",80%,IF(V41="Reviewed - Format",90%,IF(V41="Done",100%,"")))))) -> 0.8 | X41: 2026-07-07 | Y41: Cursor / tender-response (batch) | Z41: Met | AA41: Verified | AB41: Verify: Dokumentets kontakter — vurderet opfyldt (tool: 1. Fully met). | AD41: docs/tender-reference/extracted/Nationalbanken/Bilag 3.i Leverandørens Løsningsbeskrivelse.txt; docs/tender-reference/extracted/KUM-SLKS/Bilag 3 - Kravspecifikation.txt; docs/tender-reference/extracted/KK Tender tool.txt | AE41: Anton: Confirm verify-tekst; opdatér review status efter tjek. | AG41: Draft | AH41: uim-esdh-full-2026-07-07
A42: 41 | B42: MK-40 | C42: Bilag 1.b | D42: Dokumenter | E42: Versionsstyring | F42: ESDH-løsningen skal understøtte versionsstyring af Filer, så hver version af en Fil kan identificeres. Det skal som udgangspunkt kun være den seneste version, der kan åbnes i redigerbar tilstand. | G42: Mindstekrav | H42: =IF(G42="Evalueringskrav","Answer",(IF(G42="Krav","Check",(IF(G42="Mindstekrav","Verify",""))))) -> Verify | I42: Ja | L42: Anton | O42: 1. Fully met | V42: Reviewed - Content | W42: =IF(V42="Not Started",0%,IF(V42="Started",50%,IF(V42="Ready for review",70%,IF(V42="Reviewed - Content",80%,IF(V42="Reviewed - Format",90%,IF(V42="Done",100%,"")))))) -> 0.8 | X42: 2026-07-07 | Y42: Cursor / tender-response (batch) | Z42: Met | AA42: Verified | AB42: Verify: Versionsstyring — vurderet opfyldt (tool: 1. Fully met). | AD42: docs/tender-reference/extracted/KK Tender tool.txt; docs/tender-reference/extracted/Nationalbanken/Bilag 3.i Leverandørens Løsningsbeskrivelse.txt; docs/tender-reference/extracted/KUM-SLKS/Bilag 3 - Kravspecifikation.txt | AE42: Anton: Confirm verify-tekst; opdatér review status efter tjek. | AG42: Draft | AH42: uim-esdh-full-2026-07-07
A43: 42 | B43: MK-41 | C43: Bilag 1.b | D43: Dokumenter | E43: Genskabelse af tidligere filversion | F43: ESDH-løsningen skal understøtte, at Brugere kan genskabe en tidligere version af en Fil, så den overskriver den nyeste version. Begge versioner skal bevares i versionshistorikken. | G43: Mindstekrav | H43: =IF(G43="Evalueringskrav","Answer",(IF(G43="Krav","Check",(IF(G43="Mindstekrav","Verify",""))))) -> Verify | I43: Ja | L43: Anton | O43: 1. Fully met | V43: Reviewed - Content | W43: =IF(V43="Not Started",0%,IF(V43="Started",50%,IF(V43="Ready for review",70%,IF(V43="Reviewed - Content",80%,IF(V43="Reviewed - Format",90%,IF(V43="Done",100%,"")))))) -> 0.8 | X43: 2026-07-07 | Y43: Cursor / tender-response (batch) | Z43: Met | AA43: Verified | AB43: Verify: Genskabelse af tidligere filversion — vurderet opfyldt (tool: 1. Fully met). | AD43: docs/tender-reference/extracted/Nationalbanken/Bilag 3.i Leverandørens Løsningsbeskrivelse.txt; docs/tender-reference/extracted/KK Tender tool.txt; docs/tender-reference/extracted/KUM-SLKS/Bilag 3 - Kravspecifikation.txt | AE43: Anton: Confirm verify-tekst; opdatér review status efter tjek. | AG43: Draft | AH43: uim-esdh-full-2026-07-07
A44: 43 | B44: MK-42 | C44: Bilag 1.b | D44: Dokumenter | E44: Låsning af filversioner ved journalisering | F44: ESDH-løsningen skal understøtte, at et journaliseret Dokuments tidligere filversioner er tilgængelige i Løsningen. | G44: Mindstekrav | H44: =IF(G44="Evalueringskrav","Answer",(IF(G44="Krav","Check",(IF(G44="Mindstekrav","Verify",""))))) -> Verify | I44: Ja | L44: Anton | O44: 1. Fully met | V44: Reviewed - Content | W44: =IF(V44="Not Started",0%,IF(V44="Started",50%,IF(V44="Ready for review",70%,IF(V44="Reviewed - Content",80%,IF(V44="Reviewed - Format",90%,IF(V44="Done",100%,"")))))) -> 0.8 | X44: 2026-07-07 | Y44: Cursor / tender-response (batch) | Z44: Met | AA44: Verified | AB44: Verify: Låsning af filversioner ved journalisering — vurderet opfyldt (tool: 1. Fully met). | AD44: docs/tender-reference/extracted/KK Tender tool.txt; docs/tender-reference/extracted/KUM-SLKS/Bilag 3 - Kravspecifikation.txt; docs/tender-reference/extracted/Nationalbanken/Bilag 3.i Leverandørens Løsningsbeskrivelse.txt | AE44: Anton: Confirm verify-tekst; opdatér review status efter tjek. | AG44: Draft | AH44: uim-esdh-full-2026-07-07
A45: 44 | B45: MK-43 | C45: Bilag 1.b | D45: Dokumenter | E45: Kopi af Dokument | F45: ESDH-løsningen skal understøtte, at der kan oprettes en kopi af et eksisterende Dokument. Dokumentets tilknyttede Filer, Bilag, metadata og tilknyttede parter skal overføres til det nye Dokument. | G45: Mindstekrav | H45: =IF(G45="Evalueringskrav","Answer",(IF(G45="Krav","Check",(IF(G45="Mindstekrav","Verify",""))))) -> Verify | I45: Ja | L45: Anton | O45: 1. Fully met | V45: Reviewed - Content | W45: =IF(V45="Not Started",0%,IF(V45="Started",50%,IF(V45="Ready for review",70%,IF(V45="Reviewed - Content",80%,IF(V45="Reviewed - Format",90%,IF(V45="Done",100%,"")))))) -> 0.8 | X45: 2026-07-07 | Y45: Cursor / tender-response (batch) | Z45: Met | AA45: Verified | AB45: Verify: Kopi af Dokument — vurderet opfyldt (tool: 1. Fully met). | AD45: docs/tender-reference/extracted/Nationalbanken/Bilag 3.i Leverandørens Løsningsbeskrivelse.txt; docs/product/RFP_Leverandørens_svar_utdrag.txt; docs/tender-reference/extracted/HSØ/02.00-Tietoevry-SSA-L-Bilag 2-Leverandørens beskrivelse av Tjenesten.txt | AE45: Anton: Confirm verify-tekst; opdatér review status efter tjek. | AG45: Draft | AH45: uim-esdh-full-2026-07-07
A46: 45 | B46: MK-44 | C46: Bilag 1.b | D46: Dokumenter | E46: Omjournalisering af Dokumenter mellem sager | F46: ESDH-løsningen skal understøtte, at Dokumenter med tilknyttede Filer kan omjournaliseres fra én sag til en anden, og at det fremgår af den oprindelige sag, hvilken sag Dokumentet er omjournaliseret til. | G46: Mindstekrav | H46: =IF(G46="Evalueringskrav","Answer",(IF(G46="Krav","Check",(IF(G46="Mindstekrav","Verify",""))))) -> Verify | I46: Ja | L46: Anton | O46: 1. Fully met | V46: Reviewed - Content | W46: =IF(V46="Not Started",0%,IF(V46="Started",50%,IF(V46="Ready for review",70%,IF(V46="Reviewed - Content",80%,IF(V46="Reviewed - Format",90%,IF(V46="Done",100%,"")))))) -> 0.8 | X46: 2026-07-07 | Y46: Cursor / tender-response (batch) | Z46: Met | AA46: Verified | AB46: Verify: Omjournalisering af Dokumenter mellem sager — vurderet opfyldt (tool: 1. Fully met). | AD46: docs/tender-reference/extracted/KK Tender tool.txt; docs/tender-reference/extracted/KUM-SLKS/Bilag 3 - Kravspecifikation.txt; docs/tender-reference/extracted/Nationalbanken/Bilag 3.i Leverandørens Løsningsbeskrivelse.txt | AE46: Anton: Confirm verify-tekst; opdatér review status efter tjek. | AG46: Draft | AH46: uim-esdh-full-2026-07-07
A47: 46 | B47: MK-45 | C47: Bilag 1.b | D47: Dokumenter | E47: Beskyttelse af journaliserede Dokumenter | F47: ESDH-løsningen skal understøtte, at journaliserede Dokumenter ikke kan slettes af Brugere uden rettigheder. De skal håndteres i overensstemmelse med Løsningens slette- og bevaringsregler. | G47: Mindstekrav | H47: =IF(G47="Evalueringskrav","Answer",(IF(G47="Krav","Check",(IF(G47="Mindstekrav","Verify",""))))) -> Verify | I47: Ja | L47: Anton | O47: 1. Fully met | V47: Reviewed - Content | W47: =IF(V47="Not Started",0%,IF(V47="Started",50%,IF(V47="Ready for review",70%,IF(V47="Reviewed - Content",80%,IF(V47="Reviewed - Format",90%,IF(V47="Done",100%,"")))))) -> 0.8 | X47: 2026-07-07 | Y47: Cursor / tender-response (batch) | Z47: Met | AA47: Verified | AB47: Verify: Beskyttelse af journaliserede Dokumenter — vurderet opfyldt (tool: 1. Fully met). | AD47: docs/tender-reference/extracted/KK Tender tool.txt; docs/tender-reference/extracted/Nationalbanken/Bilag 3.i Leverandørens Løsningsbeskrivelse.txt; docs/tender-reference/extracted/HSØ/02.00-Tietoevry-SSA-L-Bilag 2-Leverandørens beskrivelse av Tjenesten.txt | AE47: Anton: Confirm verify-tekst; opdatér review status efter tjek. | AG47: Draft | AH47: uim-esdh-full-2026-07-07
A48: 47 | B48: MK-46 | C48: Bilag 1.b | D48: Dokumenter | E48: Noter | F48: ESDH-løsningen skal understøtte, at der kan oprettes noter på Dokumenter. Oplysninger om sagsbehandler, dato og klokkeslæt skal fremgå af noten. Alle Brugere med adgang til Dokumentet skal kunne se agere på noten i sagsbehandlingen. | G48: Mindstekrav | H48: =IF(G48="Evalueringskrav","Answer",(IF(G48="Krav","Check",(IF(G48="Mindstekrav","Verify",""))))) -> Verify | I48: Ja | L48: Anton | O48: 1. Fully met | V48: Reviewed - Content | W48: =IF(V48="Not Started",0%,IF(V48="Started",50%,IF(V48="Ready for review",70%,IF(V48="Reviewed - Content",80%,IF(V48="Reviewed - Format",90%,IF(V48="Done",100%,"")))))) -> 0.8 | X48: 2026-07-07 | Y48: Cursor / tender-response (batch) | Z48: Met | AA48: Verified | AB48: Verify: Noter — vurderet opfyldt (tool: 1. Fully met). | AD48: docs/tender-reference/extracted/Nationalbanken/Bilag 3.i Leverandørens Løsningsbeskrivelse.txt; docs/tender-reference/extracted/KK Tender tool.txt; docs/tender-reference/extracted/KUM-SLKS/Bilag 3 - Kravspecifikation.txt | AE48: Anton: Confirm verify-tekst; opdatér review status efter tjek. | AG48: Draft | AH48: uim-esdh-full-2026-07-07
A49: 48 | B49: MK-47 | C49: Bilag 1.b | D49: Dokumenter | E49: Dokumentets frister | F49: ESDH-løsningen skal understøtte, at der kan indsættes, rettes og fjernes frister på Dokumenter. Fristen skal som minimum bestå af en fristtype, fristdato og fristansvarlig. | G49: Mindstekrav | H49: =IF(G49="Evalueringskrav","Answer",(IF(G49="Krav","Check",(IF(G49="Mindstekrav","Verify",""))))) -> Verify | I49: Ja | L49: Anton | O49: 1. Fully met | V49: Reviewed - Content | W49: =IF(V49="Not Started",0%,IF(V49="Started",50%,IF(V49="Ready for review",70%,IF(V49="Reviewed - Content",80%,IF(V49="Reviewed - Format",90%,IF(V49="Done",100%,"")))))) -> 0.8 | X49: 2026-07-07 | Y49: Cursor / tender-response (batch) | Z49: Met | AA49: Verified | AB49: Verify: Dokumentets frister — vurderet opfyldt (tool: 1. Fully met). | AD49: docs/tender-reference/extracted/Nationalbanken/Bilag 3.i Leverandørens Løsningsbeskrivelse.txt; docs/tender-reference/extracted/NND/02.01-Tieto-Bilag 2-Vedlegg-Leverandørens utfyllende svar til kravtabell.txt; docs/product/RFP_Leverandørens_svar_utdrag.txt | AE49: Anton: Confirm verify-tekst; opdatér review status efter tjek. | AG49: Draft | AH49: uim-esdh-full-2026-07-07
A50: 49 | B50: MK-48 | C50: Bilag 1.b | D50: Dokumenter | E50: Afdelingsspecifikke frister | F50: ESDH-løsningen skal understøtte, at Brugere kan indsætte, rette og fjerne én eller flere afdelingsspecifikke frister på Dokumenter. | G50: Mindstekrav | H50: =IF(G50="Evalueringskrav","Answer",(IF(G50="Krav","Check",(IF(G50="Mindstekrav","Verify",""))))) -> Verify | I50: Ja | L50: Anton | O50: 1. Fully met | V50: Reviewed - Content | W50: =IF(V50="Not Started",0%,IF(V50="Started",50%,IF(V50="Ready for review",70%,IF(V50="Reviewed - Content",80%,IF(V50="Reviewed - Format",90%,IF(V50="Done",100%,"")))))) -> 0.8 | X50: 2026-07-07 | Y50: Cursor / tender-response (batch) | Z50: Met | AA50: Verified | AB50: Verify: Afdelingsspecifikke frister — vurderet opfyldt (tool: 1. Fully met). | AD50: docs/tender-reference/extracted/KUM-SLKS/Bilag 3 - Kravspecifikation.txt; docs/tender-reference/extracted/Nationalbanken/Bilag 3.i Leverandørens Løsningsbeskrivelse.txt; docs/tender-reference/extracted/KK Tender tool.txt | AE50: Anton: Confirm verify-tekst; opdatér review status efter tjek. | AG50: Draft | AH50: uim-esdh-full-2026-07-07
A51: 50 | B51: MK-49 | C51: Bilag 1.b | D51: Dokumenter | E51: Integreret viewer | F51: ESDH-løsningen skal understøtte en integreret dokumentviewer i brugergrænsefladen. Løsningen skal understøtte forhåndsvisning af Dokumenter fra sager, søgninger og listevisninger. ESDH-løsningen skal understøtte, at Brugeren får præsenteret Dokumentets tekst/indhold direkte i Løsningen. | G51: Mindstekrav | H51: =IF(G51="Evalueringskrav","Answer",(IF(G51="Krav","Check",(IF(G51="Mindstekrav","Verify",""))))) -> Verify | I51: Ja | L51: Eva | N51: Fileviewer | O51: 1. Fully met | P51: ADN: ”Direkte” er problematisk, hvis det forbyder os fra et nyt vindue. | V51: Ready for review | W51: =IF(V51="Not Started",0%,IF(V51="Started",50%,IF(V51="Ready for review",70%,IF(V51="Reviewed - Content",80%,IF(V51="Reviewed - Format",90%,IF(V51="Done",100%,"")))))) -> 0.7 | X51: 2026-07-07 | Y51: Cursor / tender-response (MCP-enriched) | Z51: Met | AA51: Verified | AB51: Verify: Integreret viewer — vurderet opfyldt (tool: 1. Fully met). | AC51: ADN: ”Direkte” er problematisk, hvis det forbyder os fra et nyt vindue. | Red flag: ”Direkte” er problematisk, hvis det forbyder os fra et nyt vindue. | AD51: Ratatoskr: 360° File Viewer (incl Prizm) (release); File (admin-en) | Wiki: Overview of PDF functionality in 360; 6.0 release information | AE51: Eva: Confirm verify-tekst; opdatér review status efter tjek. | AG51: Draft | AH51: uim-esdh-full-2026-07-07
A52: 51 | B52: MK-50 | C52: Bilag 1.b | D52: Dokumenter | E52: Navigation og scrolling i dokumentlister | F52: ESDH-løsningen skal understøtte, at Brugeren kan navigere og scrolle i dokument- og fillistevisninger, og at forhåndsvisningen automatisk opdateres og viser det Dokument/Fil, som Brugeren har navigeret til. | G52: Mindstekrav | H52: =IF(G52="Evalueringskrav","Answer",(IF(G52="Krav","Check",(IF(G52="Mindstekrav","Verify",""))))) -> Verify | I52: Ja | L52: Hans | O52: 3. Not able to meet | P52: ADN Vores forhåndsvisning ”opdateres ikke automatisk”. Kræver aktivt klik på det dokument/fil der ønskes forhåndsvist. "Navigeret til," kan det tolkes til at brugeren foretager et aktivt klik? ADN: ask question AOP: Discuss in status meeting. Vi kan læse det "dumt" og se det som at man skal kunne scolle og så navigere ved at trykke - dette kan vi - medfører risk. AOP: Vi aftalte at tage risk. | T52: Yes | V52: Started | W52: =IF(V52="Not Started",0%,IF(V52="Started",50%,IF(V52="Ready for review",70%,IF(V52="Reviewed - Content",80%,IF(V52="Reviewed - Format",90%,IF(V52="Done",100%,"")))))) -> 0.5 | X52: 2026-07-07 | Y52: Cursor / tender-response (MCP-enriched) | Z52: Not met | AA52: Lead | AB52: Verify: Navigation og scrolling i dokumentlister — gap ift. kravtekst; eskalér commitment eller afklaring. | AC52: ADN Vores forhåndsvisning ”opdateres ikke automatisk”. Kræver aktivt klik på det dokument/fil der ønskes forhåndsvist. "Navigeret til," kan det tolkes til at brugeren foretager et aktivt klik? ADN: ask question | Red flag: Vores forhåndsvisning ”opdateres ikke automatisk”. Kræver aktivt klik på det dokument/fil der ønskes forhåndsvist. | AD52: Wiki: 6.5 release information | AE52: Hans: Commitment/no-bid beslutning; overvej Q&A til ordregiver. | AG52: Draft | AH52: uim-esdh-full-2026-07-07
A53: 52 | B53: MK-51 | C53: Bilag 1.b | D53: Dokumenter | E53: Konvertering til PDF | F53: ESDH-løsningen skal understøtte, at alle Dokumenter automatisk kan blive konverteret til PDF-format, med undtagelse af medie- og eksekverbare filer. | G53: Mindstekrav | H53: =IF(G53="Evalueringskrav","Answer",(IF(G53="Krav","Check",(IF(G53="Mindstekrav","Verify",""))))) -> Verify | I53: Ja | L53: Anton | O53: 1. Fully met | P53: ADN: "Kan blive" kræver ikke at vi faktisk gør det | V53: Reviewed - Content | W53: =IF(V53="Not Started",0%,IF(V53="Started",50%,IF(V53="Ready for review",70%,IF(V53="Reviewed - Content",80%,IF(V53="Reviewed - Format",90%,IF(V53="Done",100%,"")))))) -> 0.8 | X53: 2026-07-07 | Y53: Cursor / tender-response (batch) | Z53: Met | AA53: Verified | AB53: Verify: Konvertering til PDF — vurderet opfyldt (tool: 1. Fully met). | AC53: ADN: "Kan blive" kræver ikke at vi faktisk gør det | AD53: docs/tender-reference/extracted/KK Tender tool.txt; docs/tender-reference/extracted/Nationalbanken/Underbilag 6B - Testplan og Leverandørens prøveprincipper, metoder og -værktøjer (1).txt; docs/tender-reference/extracted/HSØ/02.00-Tietoevry-SSA-L-Bilag 2-Leverandørens beskrivelse av Tjenesten.txt | AE53: Anton: Confirm verify-tekst; opdatér review status efter tjek. | AG53: Draft | AH53: uim-esdh-full-2026-07-07
A54: 53 | B54: MK-52 | C54: Bilag 1.b | D54: Dokumenter | E54: Filtyper | F54: ESDH-løsningen skal understøtte, at alle filtyper må gemmes i ESDH-løsningen. | G54: Mindstekrav | H54: =IF(G54="Evalueringskrav","Answer",(IF(G54="Krav","Check",(IF(G54="Mindstekrav","Verify",""))))) -> Verify | I54: Ja | L54: Anton | O54: 1. Fully met | V54: Reviewed - Content | W54: =IF(V54="Not Started",0%,IF(V54="Started",50%,IF(V54="Ready for review",70%,IF(V54="Reviewed - Content",80%,IF(V54="Reviewed - Format",90%,IF(V54="Done",100%,"")))))) -> 0.8 | X54: 2026-07-07 | Y54: Cursor / tender-response (batch) | Z54: Met | AA54: Verified | AB54: Verify: Filtyper — vurderet opfyldt (tool: 1. Fully met). | AD54: docs/tender-reference/extracted/KK Tender tool.txt; docs/tender-reference/extracted/Nationalbanken/Bilag 3.i Leverandørens Løsningsbeskrivelse.txt; docs/tender-reference/extracted/HSØ/02.00-Tietoevry-SSA-L-Bilag 2-Leverandørens beskrivelse av Tjenesten.txt | AE54: Anton: Confirm verify-tekst; opdatér review status efter tjek. | AG54: Draft | AH54: uim-esdh-full-2026-07-07
A55: 54 | B55: K-2 | C55: Bilag 1.b | D55: Dokumenter | E55: Dokumenttilføjelse via træk-og-slip | F55: ESDH-løsningen skal understøtte, at Brugere kan trække og slippe Dokumenter direkte fra e-mailklienter og stifinder til relevante sager. | G55: Krav | H55: =IF(G55="Evalueringskrav","Answer",(IF(G55="Krav","Check",(IF(G55="Mindstekrav","Verify",""))))) -> Check | I55: Ja | L55: Anton | O55: 1. Fully met | V55: Reviewed - Content | W55: =IF(V55="Not Started",0%,IF(V55="Started",50%,IF(V55="Ready for review",70%,IF(V55="Reviewed - Content",80%,IF(V55="Reviewed - Format",90%,IF(V55="Done",100%,"")))))) -> 0.8 | X55: 2026-07-07 | Y55: Cursor / tender-response (batch) | Z55: Met | AA55: Verified | AB55: Check: Dokumenttilføjelse via træk-og-slip — vurderet opfyldt (tool: 1. Fully met). | AD55: docs/tender-reference/extracted/Nationalbanken/Bilag 3.i Leverandørens Løsningsbeskrivelse.txt; docs/tender-reference/extracted/KK Tender tool.txt; docs/tender-reference/extracted/KUM-SLKS/Bilag 3 - Kravspecifikation.txt | AE55: Anton: Confirm verify-tekst; opdatér review status efter tjek. | AG55: Draft | AH55: uim-esdh-full-2026-07-07
A56: 55 | B56: K-3 | C56: Bilag 1.b | D56: Dokumenter | E56: Liste over Dokumenter, der ikke kan PDF-konverteres | F56: ESDH-løsningen skal understøtte, at der i ESDH-løsningen kan præsenteres en standardliste over alle Dokumenter, hvor konverteringen til PDF-format er mislykket. | G56: Krav | H56: =IF(G56="Evalueringskrav","Answer",(IF(G56="Krav","Check",(IF(G56="Mindstekrav","Verify",""))))) -> Check | I56: Ja | L56: Anton | O56: 1. Fully met | V56: Reviewed - Content | W56: =IF(V56="Not Started",0%,IF(V56="Started",50%,IF(V56="Ready for review",70%,IF(V56="Reviewed - Content",80%,IF(V56="Reviewed - Format",90%,IF(V56="Done",100%,"")))))) -> 0.8 | X56: 2026-07-07 | Y56: Cursor / tender-response (batch) | Z56: Met | AA56: Verified | AB56: Check: Liste over Dokumenter, der ikke kan PDF-konverteres — vurderet opfyldt (tool: 1. Fully met). | AD56: docs/tender-reference/extracted/Nationalbanken/Underbilag 6B - Testplan og Leverandørens prøveprincipper, metoder og -værktøjer (1).txt; docs/tender-reference/extracted/KK Tender tool.txt; docs/tender-reference/extracted/NND/02.01-Tieto-Bilag 2-Vedlegg-Leverandørens utfyllende svar til kravtabell.txt | AE56: Anton: Confirm verify-tekst; opdatér review status efter tjek. | AG56: Draft | AH56: uim-esdh-full-2026-07-07
A57: 56 | B57: MK-53 | C57: Bilag 1.b | D57: Kontakter | E57: Oprettelse af kontakter | F57: ESDH-løsningen skal understøtte oprettelse af kontakter med metadata i et kontaktregister. | G57: Mindstekrav | H57: =IF(G57="Evalueringskrav","Answer",(IF(G57="Krav","Check",(IF(G57="Mindstekrav","Verify",""))))) -> Verify | I57: Ja | L57: Anton | O57: 1. Fully met | V57: Reviewed - Content | W57: =IF(V57="Not Started",0%,IF(V57="Started",50%,IF(V57="Ready for review",70%,IF(V57="Reviewed - Content",80%,IF(V57="Reviewed - Format",90%,IF(V57="Done",100%,"")))))) -> 0.8 | X57: 2026-07-07 | Y57: Cursor / tender-response (batch) | Z57: Met | AA57: Verified | AB57: Verify: Oprettelse af kontakter — vurderet opfyldt (tool: 1. Fully met). | AD57: docs/tender-reference/extracted/Nationalbanken/Bilag 3.i Leverandørens Løsningsbeskrivelse.txt; docs/product/RFP_Leverandørens_svar_utdrag.txt; docs/tender-reference/extracted/HSØ/02.00-Tietoevry-SSA-L-Bilag 2-Leverandørens beskrivelse av Tjenesten.txt | AE57: Anton: Confirm verify-tekst; opdatér review status efter tjek. | AG57: Draft | AH57: uim-esdh-full-2026-07-07
A58: 57 | B58: MK-54 | C58: Bilag 1.b | D58: Kontakter | E58: Kontakttyper | F58: ESDH-løsningen skal understøtte oprettelse af nye kontakttyper. | G58: Mindstekrav | H58: =IF(G58="Evalueringskrav","Answer",(IF(G58="Krav","Check",(IF(G58="Mindstekrav","Verify",""))))) -> Verify | I58: Ja | L58: Anton | O58: 1. Fully met | P58: ADN: In KUM - we said yes to this, with the idea that we configure a field on contacts called "Contact Type" to live up to this. Only thing with this approach, is we need to find a word for our enterprises, contact persons and private persons besides "Types" to sell this in a clarification phase. (We could call them contact-archives to align with document archive?) | S58: Yes | V58: Reviewed - Content | W58: =IF(V58="Not Started",0%,IF(V58="Started",50%,IF(V58="Ready for review",70%,IF(V58="Reviewed - Content",80%,IF(V58="Reviewed - Format",90%,IF(V58="Done",100%,"")))))) -> 0.8 | X58: 2026-07-07 | Y58: Cursor / tender-response (batch) | Z58: Met | AA58: Lead | AB58: Verify: Kontakttyper — vurderet opfyldt (tool: 1. Fully met). | AC58: ADN: In KUM - we said yes to this, with the idea that we configure a field on contacts called "Contact Type" to live up to this. Only thing with this approach, is we need to find a word for our enterprises, contact persons and private persons besides "Types" to sell this in a clarification phase. (We could call them contact-archives to align with document archive?) | AD58: docs/tender-reference/extracted/Nationalbanken/Bilag 3.i Leverandørens Løsningsbeskrivelse.txt; docs/product/RFP_Leverandørens_svar_utdrag.txt; docs/tender-reference/extracted/HSØ/02.00-Tietoevry-SSA-L-Bilag 2-Leverandørens beskrivelse av Tjenesten.txt | AE58: Anton: Confirm verify-tekst; opdatér review status efter tjek. | AG58: Draft | AH58: uim-esdh-full-2026-07-07
A59: 58 | B59: MK-55 | C59: Bilag 1.b | D59: Kontakter | E59: Redigering af kontakter | F59: ESDH-løsningen skal understøtte redigering af metadata på kontakter, såfremt at Brugeren har rettighed hertil. | G59: Mindstekrav | H59: =IF(G59="Evalueringskrav","Answer",(IF(G59="Krav","Check",(IF(G59="Mindstekrav","Verify",""))))) -> Verify | I59: Ja | L59: Anton | O59: 1. Fully met | V59: Reviewed - Content | W59: =IF(V59="Not Started",0%,IF(V59="Started",50%,IF(V59="Ready for review",70%,IF(V59="Reviewed - Content",80%,IF(V59="Reviewed - Format",90%,IF(V59="Done",100%,"")))))) -> 0.8 | X59: 2026-07-07 | Y59: Cursor / tender-response (batch) | Z59: Met | AA59: Verified | AB59: Verify: Redigering af kontakter — vurderet opfyldt (tool: 1. Fully met). | AD59: docs/tender-reference/extracted/KK Tender tool.txt; docs/tender-reference/extracted/KUM-SLKS/Bilag 3 - Kravspecifikation.txt; docs/tender-reference/extracted/Nationalbanken/Bilag 3.i Leverandørens Løsningsbeskrivelse.txt | AE59: Anton: Confirm verify-tekst; opdatér review status efter tjek. | AG59: Draft | AH59: uim-esdh-full-2026-07-07
A60: 59 | B60: MK-56 | C60: Bilag 1.b | D60: Kontakter | E60: Automatisk dubletkontrol i kontakt-registeret | F60: ESDH-løsningen skal understøtte, at en Bruger ikke kan oprette en kontakt, hvis kontaktens unikke ID allerede findes i kontaktregisteret. | G60: Mindstekrav | H60: =IF(G60="Evalueringskrav","Answer",(IF(G60="Krav","Check",(IF(G60="Mindstekrav","Verify",""))))) -> Verify | I60: Ja | L60: Morten | O60: 2. Partly met | P60: ADN: Vi advarer, men vi forbyder ikke. CPR/CVR er ikke så unikt at det ikke kan duplikeres. ADN: Enten med udvidet duplikat-kontrol eller BRE der forbyder det. | Q60: 433880 | R60: Yes | V60: Not Started | W60: =IF(V60="Not Started",0%,IF(V60="Started",50%,IF(V60="Ready for review",70%,IF(V60="Reviewed - Content",80%,IF(V60="Reviewed - Format",90%,IF(V60="Done",100%,"")))))) -> 0 | X60: 2026-07-07 | Y60: Cursor / tender-response (MCP-enriched) | Z60: Partial | AA60: Lead | AB60: Verify: Automatisk dubletkontrol i kontakt-registeret — delvist opfyldt; afklar scope og scoring. | AC60: ADN: Vi advarer, men vi forbyder ikke. CPR/CVR er ikke så unikt at det ikke kan duplikeres. ADN: Enten med udvidet duplikat-kontrol eller BRE der forbyder det. | Red flag: Vi advarer, men vi forbyder ikke. CPR/CVR er ikke så unikt at det ikke kan duplikeres. | AD60: Wiki: 360° Contact register cleaning tools; 360° Integration with Enhetsregisteret (BRREG) | AE60: Morten: Afklar delkrav; align tool-rating (O) med AI compliance. | AG60: Draft | AH60: uim-esdh-full-2026-07-07
A61: 60 | B61: MK-57 | C61: Bilag 1.b | D61: Kontakter | E61: Fremsøgning | F61: ESDH-løsningen skal understøtte, at kontakter kan fremsøges via relevante metadata. | G61: Mindstekrav | H61: =IF(G61="Evalueringskrav","Answer",(IF(G61="Krav","Check",(IF(G61="Mindstekrav","Verify",""))))) -> Verify | I61: Ja | L61: Anton | O61: 1. Fully met | V61: Reviewed - Content | W61: =IF(V61="Not Started",0%,IF(V61="Started",50%,IF(V61="Ready for review",70%,IF(V61="Reviewed - Content",80%,IF(V61="Reviewed - Format",90%,IF(V61="Done",100%,"")))))) -> 0.8 | X61: 2026-07-07 | Y61: Cursor / tender-response (batch) | Z61: Met | AA61: Verified | AB61: Verify: Fremsøgning — vurderet opfyldt (tool: 1. Fully met). | AD61: docs/tender-reference/extracted/Nationalbanken/Bilag 3.i Leverandørens Løsningsbeskrivelse.txt; docs/tender-reference/extracted/KUM-SLKS/Bilag 3 - Kravspecifikation.txt; docs/product/RFP_Leverandørens_svar_utdrag.txt | AE61: Anton: Confirm verify-tekst; opdatér review status efter tjek. | AG61: Draft | AH61: uim-esdh-full-2026-07-07
A62: 61 | B62: MK-58 | C62: Bilag 1.b | D62: Kontakter | E62: Tilknytning af kontakt på sag | F62: ESDH-løsningen skal understøtte, at en Bruger kan oprette en ny kontakt eller søge efter en eksisterende kontakt med henblik på at tilknytte kontakten til alle Entiteter i Løsningen, herunder sager, Dokumenter og Kundeoprettede Entiteter. | G62: Mindstekrav | H62: =IF(G62="Evalueringskrav","Answer",(IF(G62="Krav","Check",(IF(G62="Mindstekrav","Verify",""))))) -> Verify | I62: Ja | L62: Anton | O62: 1. Fully met | V62: Reviewed - Content | W62: =IF(V62="Not Started",0%,IF(V62="Started",50%,IF(V62="Ready for review",70%,IF(V62="Reviewed - Content",80%,IF(V62="Reviewed - Format",90%,IF(V62="Done",100%,"")))))) -> 0.8 | X62: 2026-07-07 | Y62: Cursor / tender-response (batch) | Z62: Met | AA62: Verified | AB62: Verify: Tilknytning af kontakt på sag — vurderet opfyldt (tool: 1. Fully met). | AD62: docs/tender-reference/extracted/Nationalbanken/Bilag 3.i Leverandørens Løsningsbeskrivelse.txt; docs/tender-reference/extracted/KUM-SLKS/Bilag 3 - Kravspecifikation.txt; docs/product/RFP_Leverandørens_svar_utdrag.txt | AE62: Anton: Confirm verify-tekst; opdatér review status efter tjek. | AG62: Draft | AH62: uim-esdh-full-2026-07-07
A63: 62 | B63: MK-59 | C63: Bilag 1.b | D63: Kontakter | E63: Automatisk opdatering | F63: ESDH-løsningen skal understøtte, at kontakter automatisk kan opdateres via f.eks. integration til CPR, CVR eller lignende register på relevante metadata. Det skal ske som automatiske batch-kørsler, der med faste intervaller sikrer, at eksisterende metadata i systemet altid er ajourførte. | G63: Mindstekrav | H63: =IF(G63="Evalueringskrav","Answer",(IF(G63="Krav","Check",(IF(G63="Mindstekrav","Verify",""))))) -> Verify | I63: Ja | L63: Anton | O63: 1. Fully met | V63: Reviewed - Content | W63: =IF(V63="Not Started",0%,IF(V63="Started",50%,IF(V63="Ready for review",70%,IF(V63="Reviewed - Content",80%,IF(V63="Reviewed - Format",90%,IF(V63="Done",100%,"")))))) -> 0.8 | X63: 2026-07-07 | Y63: Cursor / tender-response (batch) | Z63: Met | AA63: Verified | AB63: Verify: Automatisk opdatering — vurderet opfyldt (tool: 1. Fully met). | AD63: docs/tender-reference/extracted/Nationalbanken/Bilag 3.i Leverandørens Løsningsbeskrivelse.txt; docs/tender-reference/extracted/HSØ/02.00-Tietoevry-SSA-L-Bilag 2-Leverandørens beskrivelse av Tjenesten.txt; docs/tender-reference/extracted/KK Tender tool.txt | AE63: Anton: Confirm verify-tekst; opdatér review status efter tjek. | AG63: Draft | AH63: uim-esdh-full-2026-07-07
A64: 63 | B64: MK-60 | C64: Bilag 1.b | D64: Kontakter | E64: Oprettelse og import af kontakt-oplysninger fra CPR | F64: ESDH-løsningen skal understøtte, at Brugeren kan foretage onlineopslag på et specifikt CPR-nr. via ESDH-løsningen og importere dennes stamdata til ESDH-løsningen. Personen skal oprettes eller opdateres i Løsningens kontaktregister. | G64: Mindstekrav | H64: =IF(G64="Evalueringskrav","Answer",(IF(G64="Krav","Check",(IF(G64="Mindstekrav","Verify",""))))) -> Verify | I64: Ja | L64: Anton | N64: CPR | O64: 1. Fully met | V64: Reviewed - Content | W64: =IF(V64="Not Started",0%,IF(V64="Started",50%,IF(V64="Ready for review",70%,IF(V64="Reviewed - Content",80%,IF(V64="Reviewed - Format",90%,IF(V64="Done",100%,"")))))) -> 0.8 | X64: 2026-07-07 | Y64: Cursor / tender-response (batch) | Z64: Met | AA64: Verified | AB64: Verify: Oprettelse og import af kontakt-oplysninger fra CPR — vurderet opfyldt (tool: 1. Fully met). | AD64: docs/tender-reference/extracted/Nationalbanken/Bilag 3.i Leverandørens Løsningsbeskrivelse.txt; docs/tender-reference/extracted/KK Tender tool.txt; docs/tender-reference/extracted/KUM-SLKS/Bilag 3 - Kravspecifikation.txt | AE64: Anton: Confirm verify-tekst; opdatér review status efter tjek. | AG64: Draft | AH64: uim-esdh-full-2026-07-07
A65: 64 | B65: MK-61 | C65: Bilag 1.b | D65: Kontakter | E65: Oprettelse og import af kontaktoplysninger fra CVR | F65: ESDH-løsningen skal understøtte, at Brugeren kan foretage onlineopslag på et specifikt CVR-nr. via ESDH-løsningen og importere virksomhedens stamdata til ESDH-løsningen. Virksomheden skal oprettes eller opdateres i Løsningens kontaktregister. | G65: Mindstekrav | H65: =IF(G65="Evalueringskrav","Answer",(IF(G65="Krav","Check",(IF(G65="Mindstekrav","Verify",""))))) -> Verify | I65: Ja | L65: Anton | N65: CVR | O65: 1. Fully met | V65: Reviewed - Content | W65: =IF(V65="Not Started",0%,IF(V65="Started",50%,IF(V65="Ready for review",70%,IF(V65="Reviewed - Content",80%,IF(V65="Reviewed - Format",90%,IF(V65="Done",100%,"")))))) -> 0.8 | X65: 2026-07-07 | Y65: Cursor / tender-response (batch) | Z65: Met | AA65: Verified | AB65: Verify: Oprettelse og import af kontaktoplysninger fra CVR — vurderet opfyldt (tool: 1. Fully met). | AD65: docs/tender-reference/extracted/Nationalbanken/Bilag 3.i Leverandørens Løsningsbeskrivelse.txt; docs/tender-reference/extracted/KK Tender tool.txt; docs/tender-reference/extracted/KUM-SLKS/Bilag 3 - Kravspecifikation.txt | AE65: Anton: Confirm verify-tekst; opdatér review status efter tjek. | AG65: Draft | AH65: uim-esdh-full-2026-07-07
A66: 65 | B66: MK-62 | C66: Bilag 1.b | D66: Kontakter | E66: Sletning af kontakter | F66: ESDH-løsningen skal understøtte sletning af kontakter. Den udførende Bruger skal adviseres, hvis kontakten er tilknyttet sager, Dokumenter eller har reference til anden kontakt. | G66: Mindstekrav | H66: =IF(G66="Evalueringskrav","Answer",(IF(G66="Krav","Check",(IF(G66="Mindstekrav","Verify",""))))) -> Verify | I66: Ja | L66: Anton | O66: 1. Fully met | V66: Reviewed - Content | W66: =IF(V66="Not Started",0%,IF(V66="Started",50%,IF(V66="Ready for review",70%,IF(V66="Reviewed - Content",80%,IF(V66="Reviewed - Format",90%,IF(V66="Done",100%,"")))))) -> 0.8 | X66: 2026-07-07 | Y66: Cursor / tender-response (batch) | Z66: Met | AA66: Verified | AB66: Verify: Sletning af kontakter — vurderet opfyldt (tool: 1. Fully met). | AD66: docs/tender-reference/extracted/Nationalbanken/Bilag 3.i Leverandørens Løsningsbeskrivelse.txt; docs/tender-reference/extracted/KK Tender tool.txt; docs/product/RFP_Leverandørens_svar_utdrag.txt | AE66: Anton: Confirm verify-tekst; opdatér review status efter tjek. | AG66: Draft | AH66: uim-esdh-full-2026-07-07
A67: 66 | B67: MK-63 | C67: Bilag 1.b | D67: Kontakter | E67: Deaktivering af kontakter | F67: ESDH-løsningen skal understøtte, at en kontakt kan deaktiveres samt, at deaktiveret kontakt ikke kan tilknyttes Entiteter. | G67: Mindstekrav | H67: =IF(G67="Evalueringskrav","Answer",(IF(G67="Krav","Check",(IF(G67="Mindstekrav","Verify",""))))) -> Verify | I67: Ja | L67: Anton | O67: 1. Fully met | V67: Reviewed - Content | W67: =IF(V67="Not Started",0%,IF(V67="Started",50%,IF(V67="Ready for review",70%,IF(V67="Reviewed - Content",80%,IF(V67="Reviewed - Format",90%,IF(V67="Done",100%,"")))))) -> 0.8 | X67: 2026-07-07 | Y67: Cursor / tender-response (batch) | Z67: Met | AA67: Verified | AB67: Verify: Deaktivering af kontakter — vurderet opfyldt (tool: 1. Fully met). | AD67: docs/product/RFP_Leverandørens_svar_utdrag.txt; docs/tender-reference/extracted/HSØ/02.00-Tietoevry-SSA-L-Bilag 2-Leverandørens beskrivelse av Tjenesten.txt; docs/tender-reference/extracted/NND/02.01-Tieto-Bilag 2-Vedlegg-Leverandørens utfyllende svar til kravtabell.txt | AE67: Anton: Confirm verify-tekst; opdatér review status efter tjek. | AG67: Draft | AH67: uim-esdh-full-2026-07-07
A68: 67 | B68: MK-64 | C68: Bilag 1.b | D68: Kontakter | E68: Deaktiverede kontakter | F68: ESDH-løsningen skal understøtte, at deaktiverede kontakter kan fremsøges i Løsningen. | G68: Mindstekrav | H68: =IF(G68="Evalueringskrav","Answer",(IF(G68="Krav","Check",(IF(G68="Mindstekrav","Verify",""))))) -> Verify | I68: Ja | L68: Anton | O68: 1. Fully met | V68: Reviewed - Content | W68: =IF(V68="Not Started",0%,IF(V68="Started",50%,IF(V68="Ready for review",70%,IF(V68="Reviewed - Content",80%,IF(V68="Reviewed - Format",90%,IF(V68="Done",100%,"")))))) -> 0.8 | X68: 2026-07-07 | Y68: Cursor / tender-response (batch) | Z68: Met | AA68: Lead | AB68: Verify: Deaktiverede kontakter — vurderet opfyldt (tool: 1. Fully met). | AD68: docs/tender-reference/extracted/KUM-SLKS/Bilag 3 - Kravspecifikation.txt; docs/tender-reference/extracted/Nationalbanken/Bilag 3.i Leverandørens Løsningsbeskrivelse.txt; docs/product/RFP_Leverandørens_svar_utdrag.txt | AE68: Anton: Confirm verify-tekst; opdatér review status efter tjek. | AG68: Draft | AH68: uim-esdh-full-2026-07-07
A69: 68 | B69: EK-1 | C69: Bilag 1.b | D69: Kontakter | E69: Udlændinge-overblik | F69: Kunden har behov for at udstille en udlændinges stamdata i Løsningen. Kunden betragter en udlænding som en kontakttype, som kan tilknyttes til Entiteter i Løsningen. ESDH-løsningen skal understøtte, at Administrator kan konfigurere en Udlændingekontakt via no code administratormodul, der sikrer et fuldt overblik over Udlændingekontakten. Administratoren skal dertil kunne opsætte og konfigurere udlændingeoverblikket i brugergrænsefladen. Overblikket over udlændingen skal indeholde følgende: Sager, hvor udlændingen indgår som part samt hvilken rolle udlændingen har på sagen Afgørelser, som er tilknyttet udlændingen med følgende metadata: Sagsnr. Afgørelsesdato Afgørelsestype Sagsområde f.eks. familiesammenføring Ansvarligt team Ansvarlig sagsbehandler Stamdata på udlændingen herunder: Cpr.nr. Udlændinge nr. Fornavn og efternavn Adresse, postnr. og by Telefon og e-mailadresse Nationalitet Køn Familierelationer (f.eks. barn, forældre, værge) Datoer for ind- og udrejse til/fra Danmark Rejsedokumenter (f.eks. pas og nationalt ID-kort) Dokumenter som udlændingen er tilknyttet, samt hvilken partsrolle udlændingen har på Dokumentet Sager i anden Myndighed herunder: Sagsnr. Sagsområde f.eks. asyl Ansvarligt team Ansvarlig sagsbehandler Afgørelser i anden Myndighed herunder: Sagsnr. Afgørelsesdato Afgørelsestype Sagsområde f.eks. familiesammenføring Ansvarligt team Ansvarlig sagsbehandler Leverandøren skal beskrive, hvordan den tilbudte ESDH-løsning understøtter, at Administrator kan konfigurere en Udlændingekontakt via no code administratormodul. Leverandøren skal gennem konkrete skærmbilleder demonstrere om og hvordan ESDH-løsningen understøtter de stillede krav og møder Kundens behov. Leverandøren skal redegøre for: Hvordan ESDH-løsningen understøtter et udlændingeoverblik Hvordan Brugeren kan navigere i oplysningerne på udlændingeoverblikket Hvordan Administratoren kan oprette og vedligeholde udlændingeoverblikket Evalueringskriterier: Det vægtes positivt, i hvor høj grad Brugeren på en let og intuitiv måde kan navigere i udlændingeoverblikkets data. Det vægtes positivt, i hvor høj grad Administrator kan oprette og vedligeholde udlændingeoverblikket via et administratormodul uden involvering af Leverandør. Det vægtes positivt, i hvor høj grad udlændingeoverblikket indeholder et samlet overblik over udlændingens sager og Afgørelser i egen Myndighed samt overblik over sager og Afgørelser i øvrige Myndigheders sager. Det vægtes positivt, i hvor høj grad Dokumenter udstilles på en let og overskuelig måde på udlændingeoverblikket f.eks. via filtrering. Det vægtes positivt, i hvor høj grad der på udlændingeoverblikket kan noteres flere oplysninger af samme type f.eks. datoer for ind- og udrejse. Det vægtes positivt, i hvor høj grad udlændingeoverblikket opdateres i realtid, når der f.eks. tilføjes nye sager og Afgørelser eller stamdata opdateres i eksterne registre. Det vægtes positivt, i hvor høj grad felter på udlændingeoverblikket kan gøres skrivebeskyttet, så opdatering af felter kun kan ske via eksterne registre. | G69: Evalueringskrav | H69: =IF(G69="Evalueringskrav","Answer",(IF(G69="Krav","Check",(IF(G69="Mindstekrav","Verify",""))))) -> Answer | I69: Ja | L69: Claus | Q69: 433895 | R69: Yes | V69: Not Started | W69: =IF(V69="Not Started",0%,IF(V69="Started",50%,IF(V69="Ready for review",70%,IF(V69="Reviewed - Content",80%,IF(V69="Reviewed - Format",90%,IF(V69="Done",100%,"")))))) -> 0 | X69: 2026-07-07 | Y69: Cursor / tender-response (MCP-enriched) | Z69: Draft needed | AA69: Lead | AB69: Answer: Udlændinge-overblik — informationskrav; udkast bilag/dokumentation mangler. | AC69: Mangler link til svar-bilag i kolonne T. | AD69: No help or wiki match for foreigner contact overview (udlændingeoverblik) | AE69: Claus: Opret/link svar-bilag; draft IK-tekst fra prior art. | AG69: Draft | AH69: uim-esdh-full-2026-07-07
A70: 69 | B70: MK-65 | C70: Bilag 1.b | D70: Søgning | E70: Søgning | F70: ESDH-løsningen skal understøtte, at der kan søges i alle standard- og Kundeoprettede felter. | G70: Mindstekrav | H70: =IF(G70="Evalueringskrav","Answer",(IF(G70="Krav","Check",(IF(G70="Mindstekrav","Verify",""))))) -> Verify | I70: Ja | L70: Claus | O70: 1. Fully met | P70: ADN: Search "in all fields" comes with a risc, especially if any external consultant is still involved from the customer side. CHM: Reporting API understøtter søgning i alle felter. Hvis søgningen skal foregå "inde i løsningen", så skal vi have et commitment fra Products. Identisk med MK-66. | R70: Yes | S70: Yes | V70: Started | W70: =IF(V70="Not Started",0%,IF(V70="Started",50%,IF(V70="Ready for review",70%,IF(V70="Reviewed - Content",80%,IF(V70="Reviewed - Format",90%,IF(V70="Done",100%,"")))))) -> 0.5 | X70: 2026-07-07 | Y70: Cursor / tender-response (batch) | Z70: Met | AA70: Verified | AB70: Verify: Søgning — vurderet opfyldt (tool: 1. Fully met). | AC70: ADN: Search "in all fields" comes with a risc, especially if any external consultant is still involved from the customer side. | AD70: docs/tender-reference/extracted/KK Tender tool.txt; docs/tender-reference/extracted/KUM-SLKS/Bilag 3 - Kravspecifikation.txt; docs/tender-reference/extracted/Nationalbanken/Bilag 3.i Leverandørens Løsningsbeskrivelse.txt | AE70: Claus: Confirm verify-tekst; opdatér review status efter tjek. | AG70: Draft | AH70: uim-esdh-full-2026-07-07
A71: 70 | B71: MK-66 | C71: Bilag 1.b | D71: Søgning | E71: Søgning på flere felter på samme tid | F71: ESDH-løsningen skal understøtte, at der kan søges på alle standard- og Kundeoprettede felter på samme tid i ESDH-løsningen. | G71: Mindstekrav | H71: =IF(G71="Evalueringskrav","Answer",(IF(G71="Krav","Check",(IF(G71="Mindstekrav","Verify",""))))) -> Verify | I71: Ja | L71: Claus | N71: Management Reporting API | O71: 2. Partly met | P71: ADN: Det her krav er formuleret uden logiske begræsninger mellem entiteter, hvilke tikke giver mening. Det kan vi ikke understøtte. Does this require you should be able to search for all case and document, and contact-related fields, in 1 joint search?? CHM: Requirement doesnt say where it should be performed. Could it be solved by management reporting api? Querry builder might also be a way to look - but we havent decided on a specific solution yet. | Q71: 433882 | R71: Yes | S71: Yes | V71: Started | W71: =IF(V71="Not Started",0%,IF(V71="Started",50%,IF(V71="Ready for review",70%,IF(V71="Reviewed - Content",80%,IF(V71="Reviewed - Format",90%,IF(V71="Done",100%,"")))))) -> 0.5 | X71: 2026-07-07 | Y71: Cursor / tender-response (MCP-enriched) | Z71: Partial | AA71: Lead | AB71: Verify: Søgning på flere felter på samme tid — delvist opfyldt; afklar scope og scoring. | AC71: ADN: Det her krav er formuleret uden logiske begræsninger mellem entiteter, hvilke tikke giver mening. Det kan vi ikke understøtte. Does this require you should be able to search for all case and document, and contact-related fields, in 1 joint search?? CHM: Requirement doesnt say where it should be performed. Could it be solved by management reporting api? Querry builder might also be a way to look - but we havent decided on a specific solution yet. | Red flag: Det her krav er formuleret uden logiske begræsninger mellem entiteter, hvilke tikke giver mening. Det kan vi ikke understøtte. | AD71: Ratatoskr: Search and Result lists (admin-en); Advanced search (admin-en); 360° Search Assistant (admin-en) | Wiki: 6.8 release information; Feature Toggles 2025-2026 | AE71: Claus: Afklar delkrav; align tool-rating (O) med AI compliance. | AG71: Draft | AH71: uim-esdh-full-2026-07-07
A72: 71 | B72: MK-67 | C72: Bilag 1.b | D72: Søgning | E72: Søgning på filindhold | F72: ESDH-løsningen skal understøtte søgning i indholdet af Filer. | G72: Mindstekrav | H72: =IF(G72="Evalueringskrav","Answer",(IF(G72="Krav","Check",(IF(G72="Mindstekrav","Verify",""))))) -> Verify | I72: Ja | L72: Anton | O72: 1. Fully met | V72: Reviewed - Content | W72: =IF(V72="Not Started",0%,IF(V72="Started",50%,IF(V72="Ready for review",70%,IF(V72="Reviewed - Content",80%,IF(V72="Reviewed - Format",90%,IF(V72="Done",100%,"")))))) -> 0.8 | X72: 2026-07-07 | Y72: Cursor / tender-response (batch) | Z72: Met | AA72: Verified | AB72: Verify: Søgning på filindhold — vurderet opfyldt (tool: 1. Fully met). | AD72: docs/tender-reference/extracted/Nationalbanken/Bilag 3.i Leverandørens Løsningsbeskrivelse.txt; docs/tender-reference/extracted/KK Tender tool.txt; docs/tender-reference/extracted/KUM-SLKS/Bilag 3 - Kravspecifikation.txt | AE72: Anton: Confirm verify-tekst; opdatér review status efter tjek. | AG72: Draft | AH72: uim-esdh-full-2026-07-07
A73: 72 | B73: MK-68 | C73: Bilag 1.b | D73: Søgning | E73: Trunkering i avanceret søgning | F73: ESDH-løsningen skal understøtte, at Brugeren kan anvende trunkering, hvis der ønskes søgning på begyndelsen eller slutningen af et ord. | G73: Mindstekrav | H73: =IF(G73="Evalueringskrav","Answer",(IF(G73="Krav","Check",(IF(G73="Mindstekrav","Verify",""))))) -> Verify | I73: Ja | L73: Anton | O73: 1. Fully met | P73: ADN Det her lugter af at være målrettet os givet titlen, fordi de ved vi ikke kan i den avancerede søgning - men kravteksten indeholder det ikke, "Avanceret søg" og derfor bør vi være OK med kravet. | V73: Reviewed - Content | W73: =IF(V73="Not Started",0%,IF(V73="Started",50%,IF(V73="Ready for review",70%,IF(V73="Reviewed - Content",80%,IF(V73="Reviewed - Format",90%,IF(V73="Done",100%,"")))))) -> 0.8 | X73: 2026-07-07 | Y73: Cursor / tender-response (MCP-enriched) | Z73: Met | AA73: Lead | AB73: Verify: Trunkering i avanceret søgning — vurderet opfyldt (tool: 1. Fully met). | AC73: ADN Det her lugter af at være målrettet os givet titlen, fordi de ved vi ikke kan i den avancerede søgning - men kravteksten indeholder det ikke, "Avanceret søg" og derfor bør vi være OK med kravet. | Red flag: Det her lugter af at være givet titlen her, fordi de ved vi ikke kan i den avancerede søgning - men kravteksten indeholder det ikke, og derfor bør vi være OK med kravet | AD73: Ratatoskr: Advanced search (admin-en) | Wiki: Build log hotfix packages | AE73: Anton: Confirm verify-tekst; opdatér review status efter tjek. | AG73: Draft | AH73: uim-esdh-full-2026-07-07
A74: 73 | B74: MK-69 | C74: Bilag 1.b | D74: Søgning | E74: Gemte søgninger | F74: ESDH-løsningen skal understøtte, at søgninger kan gemmes i Løsningen og deles af Brugere. | G74: Mindstekrav | H74: =IF(G74="Evalueringskrav","Answer",(IF(G74="Krav","Check",(IF(G74="Mindstekrav","Verify",""))))) -> Verify | I74: Ja | L74: Anton | O74: 1. Fully met | P74: ADN: Configure Share saved search Toggle | V74: Reviewed - Content | W74: =IF(V74="Not Started",0%,IF(V74="Started",50%,IF(V74="Ready for review",70%,IF(V74="Reviewed - Content",80%,IF(V74="Reviewed - Format",90%,IF(V74="Done",100%,"")))))) -> 0.8 | X74: 2026-07-07 | Y74: Cursor / tender-response (batch) | Z74: Met | AA74: Verified | AB74: Verify: Gemte søgninger — vurderet opfyldt (tool: 1. Fully met). | AC74: ADN: Configure Share saved search Toggle | AD74: docs/tender-reference/extracted/KK Tender tool.txt; docs/tender-reference/extracted/KUM-SLKS/Bilag 3 - Kravspecifikation.txt; docs/tender-reference/extracted/Nationalbanken/Bilag 3.i Leverandørens Løsningsbeskrivelse.txt | AE74: Anton: Confirm verify-tekst; opdatér review status efter tjek. | AG74: Draft | AH74: uim-esdh-full-2026-07-07
A75: 74 | B75: MK-70 | C75: Bilag 1.b | D75: Søgning | E75: Søgeresultater | F75: ESDH-løsningen skal understøtte, at alle felter kan vises i søgeresultaternes visningslister. | G75: Mindstekrav | H75: =IF(G75="Evalueringskrav","Answer",(IF(G75="Krav","Check",(IF(G75="Mindstekrav","Verify",""))))) -> Verify | I75: Ja | L75: Claus | O75: 2. Partly met | P75: ADN: ”Alle felter” - godt nok afgrænset til søgeresultater, men stadig en stor risc, fra en ondsindet kunde. Vi må spørge willy CHM: Dette kræver et commitment, at "View selector" implementeres på lister ligesom i resultatlisten på søgning. | Q75: 433882 | R75: Yes | S75: Yes | V75: Started | W75: =IF(V75="Not Started",0%,IF(V75="Started",50%,IF(V75="Ready for review",70%,IF(V75="Reviewed - Content",80%,IF(V75="Reviewed - Format",90%,IF(V75="Done",100%,"")))))) -> 0.5 | X75: 2026-07-07 | Y75: Cursor / tender-response (MCP-enriched) | Z75: Partial | AA75: Lead | AB75: Verify: Søgeresultater — delvist opfyldt; afklar scope og scoring. | AC75: ADN: ”Alle felter” - godt nok afgrænset til søgeresultater, men stadig en stor risc, fra en ondsindet kunde. Vi må spørge willy | Red flag: ”Alle felter” - godt nok afgrænset til søgeresultater, men stadig en stor risc, fra en ondsindet kunde. | AD75: Ratatoskr: Search and Result lists (admin-en) | Wiki: CIM - How to create Reports | AE75: Claus: Afklar delkrav; align tool-rating (O) med AI compliance. | AG75: Draft | AH75: uim-esdh-full-2026-07-07
A76: 75 | B76: MK-71 | C76: Bilag 1.b | D76: Søgning | E76: Søgning i dropdown-felter ved registrering | F76: ESDH-løsningen skal understøtte, at der kan søges på værdier i alle dropdown-felter. | G76: Mindstekrav | H76: =IF(G76="Evalueringskrav","Answer",(IF(G76="Krav","Check",(IF(G76="Mindstekrav","Verify",""))))) -> Verify | I76: Ja | L76: Anton | O76: 1. Fully met | P76: ADN: Requirement contains the word "All" but i cant come up with anywhere, where we dont support this. | S76: Yes | V76: Reviewed - Content | W76: =IF(V76="Not Started",0%,IF(V76="Started",50%,IF(V76="Ready for review",70%,IF(V76="Reviewed - Content",80%,IF(V76="Reviewed - Format",90%,IF(V76="Done",100%,"")))))) -> 0.8 | X76: 2026-07-07 | Y76: Cursor / tender-response (batch) | Z76: Met | AA76: Verified | AB76: Verify: Søgning i dropdown-felter ved registrering — vurderet opfyldt (tool: 1. Fully met). | AC76: ADN: Requirement contains the word "All" but i cant come up with anywhere, where we dont support this. | AD76: docs/tender-reference/extracted/KUM-SLKS/Bilag 3 - Kravspecifikation.txt; docs/tender-reference/extracted/Nationalbanken/Bilag 3.i Leverandørens Løsningsbeskrivelse.txt; docs/tender-reference/extracted/KK Tender tool.txt | AE76: Anton: Confirm verify-tekst; opdatér review status efter tjek. | AG76: Draft | AH76: uim-esdh-full-2026-07-07
A77: 76 | B77: MK-72 | C77: Bilag 1.b | D77: Søgning | E77: Søgning på alle niveauer i journalplan | F77: ESDH-løsningen skal understøtte, at der kan søges på alle niveauer i journalplanen. | G77: Mindstekrav | H77: =IF(G77="Evalueringskrav","Answer",(IF(G77="Krav","Check",(IF(G77="Mindstekrav","Verify",""))))) -> Verify | I77: Ja | L77: Anton | O77: 1. Fully met | P77: ADN: We got the commitment on KUM | V77: Reviewed - Content | W77: =IF(V77="Not Started",0%,IF(V77="Started",50%,IF(V77="Ready for review",70%,IF(V77="Reviewed - Content",80%,IF(V77="Reviewed - Format",90%,IF(V77="Done",100%,"")))))) -> 0.8 | X77: 2026-07-07 | Y77: Cursor / tender-response (batch) | Z77: Met | AA77: Verified | AB77: Verify: Søgning på alle niveauer i journalplan — vurderet opfyldt (tool: 1. Fully met). | AC77: ADN: We got the commitment on KUM | AD77: docs/tender-reference/extracted/KUM-SLKS/Bilag 3 - Kravspecifikation.txt; docs/tender-reference/extracted/Nationalbanken/Bilag 3.i Leverandørens Løsningsbeskrivelse.txt; docs/tender-reference/extracted/KK Tender tool.txt | AE77: Anton: Confirm verify-tekst; opdatér review status efter tjek. | AG77: Draft | AH77: uim-esdh-full-2026-07-07
A78: 77 | B78: MK-73 | C78: Bilag 1.b | D78: Søgning | E78: Søgning på tværs af Entiteter | F78: ESDH-løsningen skal understøtte, at der kan søges på tværs af Entiteter. | G78: Mindstekrav | H78: =IF(G78="Evalueringskrav","Answer",(IF(G78="Krav","Check",(IF(G78="Mindstekrav","Verify",""))))) -> Verify | I78: Ja | L78: Anton | O78: 1. Fully met | P78: MJ: Den optimale løsning er, at bygge en ny søgeoplevelse gennem query builderen I search assistant. Torben kan lave et eksperiement med at eksponerere hele viewmeta I search assistanmt | V78: Reviewed - Content | W78: =IF(V78="Not Started",0%,IF(V78="Started",50%,IF(V78="Ready for review",70%,IF(V78="Reviewed - Content",80%,IF(V78="Reviewed - Format",90%,IF(V78="Done",100%,"")))))) -> 0.8 | X78: 2026-07-07 | Y78: Cursor / tender-response (batch) | Z78: Met | AA78: Verified | AB78: Verify: Søgning på tværs af Entiteter — vurderet opfyldt (tool: 1. Fully met). | AD78: docs/tender-reference/extracted/Nationalbanken/Bilag 3.i Leverandørens Løsningsbeskrivelse.txt; docs/tender-reference/extracted/KK Tender tool.txt; docs/tender-reference/extracted/KUM-SLKS/Bilag 3 - Kravspecifikation.txt | AE78: Anton: Confirm verify-tekst; opdatér review status efter tjek. | AG78: Draft | AH78: uim-esdh-full-2026-07-07
A79: 78 | B79: MK-74 | C79: Bilag 1.b | D79: Søgning | E79: Søgebilleder - Entiteter | F79: ESDH-løsningen skal understøtte, at Kunden kan opsætte og konfigurere søgebilleder for alle Løsningens standard- og Kundeoprettede Entiteter. | G79: Mindstekrav | H79: =IF(G79="Evalueringskrav","Answer",(IF(G79="Krav","Check",(IF(G79="Mindstekrav","Verify",""))))) -> Verify | I79: Ja | L79: Claus | O79: 2. Partly met | P79: ADN: Det understøtter vi ikke. COuld we argue, that it doesnt state it should remember these configurations, and therefore we live up to it? CHM: Kriteriet er gemt i databasen, så det "burde" ikke være en stor udviklingsopgave at udtrække feltet inkl. værdi, og vise det i redigerings-mode. | Q79: 433882 | R79: Yes | V79: Started | W79: =IF(V79="Not Started",0%,IF(V79="Started",50%,IF(V79="Ready for review",70%,IF(V79="Reviewed - Content",80%,IF(V79="Reviewed - Format",90%,IF(V79="Done",100%,"")))))) -> 0.5 | X79: 2026-07-07 | Y79: Cursor / tender-response (MCP-enriched) | Z79: Partial | AA79: Lead | AB79: Verify: Søgebilleder - Entiteter — delvist opfyldt; afklar scope og scoring. | AC79: ADN: Det understøtter vi ikke. COuld we argue, that it doesnt state it should remember these configurations, and therefore we live up to it? | Red flag: Det understøtter vi ikke. | AD79: Ratatoskr: Advanced search (admin-en); Search and Result lists (admin-en) | Wiki: 5.11 release information | AE79: Claus: Afklar delkrav; align tool-rating (O) med AI compliance. | AG79: Draft | AH79: uim-esdh-full-2026-07-07
A80: 79 | B80: MK-75 | C80: Bilag 1.b | D80: Søgning | E80: Søgebilleder - Felter | F80: ESDH-løsningen skal understøtte, at Kunden selv kan definere og konfigurere, hvilke standard- og Kundeoprettede felter søgebilledet skal indeholde. | G80: Mindstekrav | H80: =IF(G80="Evalueringskrav","Answer",(IF(G80="Krav","Check",(IF(G80="Mindstekrav","Verify",""))))) -> Verify | I80: Ja | L80: Claus | O80: 2. Partly met | P80: ADN: Det understøtter vi ikke. COuld we argue, that it doesnt state it should remember these configurations, and therefore we live up to it? CHM: Kriteriet er gemt i databasen, så det "burde" ikke være en stor udviklingsopgave at udtrække feltet inkl. værdi, og vise det i redigerings-mode. MJ: Minimumsløsningen må være man laver en property på customfelter kaldet "Show in advanced search" | Q80: 433882 | R80: Yes | V80: Started | W80: =IF(V80="Not Started",0%,IF(V80="Started",50%,IF(V80="Ready for review",70%,IF(V80="Reviewed - Content",80%,IF(V80="Reviewed - Format",90%,IF(V80="Done",100%,"")))))) -> 0.5 | X80: 2026-07-07 | Y80: Cursor / tender-response (MCP-enriched) | Z80: Partial | AA80: Lead | AB80: Verify: Søgebilleder - Felter — delvist opfyldt; afklar scope og scoring. | AC80: ADN: Det understøtter vi ikke. COuld we argue, that it doesnt state it should remember these configurations, and therefore we live up to it? | Red flag: Det understøtter vi ikke | AD80: Ratatoskr: Advanced search (admin-en) | Wiki: Build log hotfix packages | AE80: Claus: Afklar delkrav; align tool-rating (O) med AI compliance. | AG80: Draft | AH80: uim-esdh-full-2026-07-07
A81: 80 | B81: K-4 | C81: Bilag 1.b | D81: Søgning | E81: Søgeoperatorer | F81: ESDH-løsningen skal understøtte, at Brugere kan anvende følgende søgeoperatorer ved fritekstsøgning og søgning i strukturerede felter: ”Og”, ”Eller” og ”Ikke”-søgning Større end / mindre end (f.eks. ved dato- eller talfelter) Indeholder Lig med (præcis match) | G81: Krav | H81: =IF(G81="Evalueringskrav","Answer",(IF(G81="Krav","Check",(IF(G81="Mindstekrav","Verify",""))))) -> Check | I81: Ja | L81: Anton | O81: 1. Fully met | P81: ADN: We support this in a combination of global search and advanced search - it isnt specified to be in 1 place. | V81: Reviewed - Content | W81: =IF(V81="Not Started",0%,IF(V81="Started",50%,IF(V81="Ready for review",70%,IF(V81="Reviewed - Content",80%,IF(V81="Reviewed - Format",90%,IF(V81="Done",100%,"")))))) -> 0.8 | X81: 2026-07-07 | Y81: Cursor / tender-response (batch) | Z81: Met | AA81: Verified | AB81: Check: Søgeoperatorer — vurderet opfyldt (tool: 1. Fully met). | AC81: ADN: We support this in a combination of global search and advanced search - it isnt specified to be in 1 place. | AD81: docs/tender-reference/extracted/Nationalbanken/Bilag 3.i Leverandørens Løsningsbeskrivelse.txt; docs/tender-reference/extracted/KK Tender tool.txt; docs/tender-reference/extracted/KUM-SLKS/Bilag 3 - Kravspecifikation.txt | AE81: Anton: Confirm verify-tekst; opdatér review status efter tjek. | AG81: Draft | AH81: uim-esdh-full-2026-07-07
A82: 81 | B82: K-5 | C82: Bilag 1.b | D82: Søgning | E82: Abonnementer | F82: ESDH-løsningen skal understøtte, at Brugere kan abonnere på søgninger. | G82: Krav | H82: =IF(G82="Evalueringskrav","Answer",(IF(G82="Krav","Check",(IF(G82="Mindstekrav","Verify",""))))) -> Check | I82: Ja | L82: Anton | O82: 1. Fully met | V82: Reviewed - Content | W82: =IF(V82="Not Started",0%,IF(V82="Started",50%,IF(V82="Ready for review",70%,IF(V82="Reviewed - Content",80%,IF(V82="Reviewed - Format",90%,IF(V82="Done",100%,"")))))) -> 0.8 | X82: 2026-07-07 | Y82: Cursor / tender-response (batch) | Z82: Met | AA82: Lead | AB82: Check: Abonnementer — vurderet opfyldt (tool: 1. Fully met). | AD82: docs/tender-reference/extracted/KK Tender tool.txt; docs/tender-reference/extracted/KUM-SLKS/Bilag 3 - Kravspecifikation.txt; docs/tender-reference/extracted/Nationalbanken/Bilag 3.i Leverandørens Løsningsbeskrivelse.txt | AE82: Anton: Confirm verify-tekst; opdatér review status efter tjek. | AG82: Draft | AH82: uim-esdh-full-2026-07-07
A83: 82 | B83: K-6 | C83: Bilag 1.b | D83: Søgning | E83: Eksport af søgning | F83: ESDH-løsningen skal understøtte eksport af det komplette søgeresultat fra brugergrænsefladen til regnearksprogram anvendt af Kundens, men må dog ikke overstige regnearksprogrammets maksimum rækkekapacitet. | G83: Krav | H83: =IF(G83="Evalueringskrav","Answer",(IF(G83="Krav","Check",(IF(G83="Mindstekrav","Verify",""))))) -> Check | I83: Ja | L83: Claus | O83: 2. Partly met | P83: ADN: This means we must support pretty much "unlimited export to Excel" løsningen CHM: Vi understøtter eksport til Excel/regneark inden for konfigurerede systemgrænser (default 3000). Store udtræk kan håndteres asynkront/batch-orienteret eller via rapport-/dataudtræksfunktion. Kan vi implementere "eDoc Big Search" som udtrækker store søgninger i "off-peak hours"? | S83: Yes | V83: Started | W83: =IF(V83="Not Started",0%,IF(V83="Started",50%,IF(V83="Ready for review",70%,IF(V83="Reviewed - Content",80%,IF(V83="Reviewed - Format",90%,IF(V83="Done",100%,"")))))) -> 0.5 | X83: 2026-07-07 | Y83: Cursor / tender-response (MCP-enriched) | Z83: Partial | AA83: Verified | AB83: Check: Eksport af søgning — delvist opfyldt; afklar scope og scoring. | AC83: ADN: This means we must support pretty much "unlimited export to Excel" | AD83: Wiki: 360° settings - internal reference | AE83: Claus: Afklar delkrav; align tool-rating (O) med AI compliance. | AG83: Draft | AH83: uim-esdh-full-2026-07-07
A84: 83 | B84: EK-2 | C84: Bilag 1.b | D84: Dashboards | E84: Dashboards | F84: ESDH-løsningen skal understøtte realtidsbaserede dashboards, der giver Kundens Brugere et hurtigt og overskueligt overblik over relevante data i ESDH-løsningen. Dashboard i ESDH-løsningen skal understøtte visualiseringer og udtræk af statistiske data til brug for konkret sagsbehandling, Myndighedsarbejde, ledelsestilsyn og politiske beslutninger. Leverandøren skal beskrive, hvordan den tilbudte ESDH-løsning understøtter realtidsbaserede dashboards. Leverandøren skal gennem konkrete skærmbilleder demonstrere om og hvordan ESDH-løsningen understøtter de stillede krav og møder Kundens behov. Leverandøren skal redegøre for: Hvordan ESDH-løsningen understøtter, at Administrator og Bruger kan oprette egne realtidsbaserede dashboards til sags- og driftsstyring Hvordan ESDH-løsningen understøtter visning af både individuelle og afdelingsspecifikke frister med farver eller ikoner, når en frist for eksempel nærmer sig udløb Hvilke visualiseringer som ESDH-løsningen understøtter Hvordan ESDH-løsningen understøtter effektiv og brugervenlig navigation til underliggende detaljer fra dashboards Hvordan ESDH-løsningen understøtter dashboards på Dokument og kontaktniveau Hvordan dashboards på en let og intuitiv måde kan oprettes og vedligeholdes af Administrator Hvordan dashboards på en let og intuitiv måde kan deles på organisatorisk niveau samt brugerniveau Evalueringskriterier: Det vægtes positivt, i hvor høj grad Brugere og Administratorer kan personalisere og konfigurere dashboards efter individuelle og organisatoriske behov, samt at disse kan deles på en intuitiv og brugervenlig måde. Det vægtes positivt, i hvor høj grad dashboard-visninger kan tilpasses forskellige brugerroller, medarbejderniveauer og organisatorisk opdeling. Det vægtes positivt, i hvor høj grad dashboards kan udstilles på forskellige visuelle måder herunder, at der er mulighed for at konfigurere kolonner i visningen samt, at data kan eksporteres i relevante formater. Det vægtes positivt, i hvor høj grad ESDH-løsningens dashboards kan udstille resultater i dashboard-widgets. Det vægtes positivt, i hvor høj grad dashboards kan tilpasses med en grafisk udstilling, der indeholder: Listevisninger Søjlediagrammer Cirkeldiagrammer Tællere Det vægtes positivt, i hvor høj grad data og søgeresultater, der udstilles på dashboards, opdateres automatisk i realtid uden behov for manuel opdatering (refresh). Det vægtes positivt, i hvor høj grad en Administrator kan udrulle dashboads til organisationen, afdelinger, teams og Brugere, som styres centralt. | G84: Evalueringskrav | H84: =IF(G84="Evalueringskrav","Answer",(IF(G84="Krav","Check",(IF(G84="Mindstekrav","Verify",""))))) -> Answer | I84: Ja | L84: Torben | V84: Not Started | W84: =IF(V84="Not Started",0%,IF(V84="Started",50%,IF(V84="Ready for review",70%,IF(V84="Reviewed - Content",80%,IF(V84="Reviewed - Format",90%,IF(V84="Done",100%,"")))))) -> 0 | X84: 2026-07-07 | Y84: Cursor / tender-response (MCP-enriched) | Z84: Draft needed | AA84: Lead | AB84: Answer: Dashboards — informationskrav; udkast bilag/dokumentation mangler. | AC84: Mangler link til svar-bilag i kolonne T. | AD84: Wiki: Build log hotfix packages | AE84: Torben: Opret/link svar-bilag; draft IK-tekst fra prior art. | AG84: Draft | AH84: uim-esdh-full-2026-07-07
A85: 84 | B85: MK-76 | C85: Bilag 1.b | D85: Brugergrænsefladen | E85: Browser-baseret brugergrænseflade | F85: ESDH-løsningen skal understøtte afvikling i en af nedenstående standardbrowsere uden løsnings-specifikt plugin: Microsoft Edge Google Chrome | G85: Mindstekrav | H85: =IF(G85="Evalueringskrav","Answer",(IF(G85="Krav","Check",(IF(G85="Mindstekrav","Verify",""))))) -> Verify | I85: Ja | L85: Anton | O85: 1. Fully met | P85: ADN: Påvirker ikke os - men det her krav er et godt eksempel på en Kunde der beskriver en løsning frem for et behov. Hvorfor skal det være browserbaseret? AOP: Meget standard i udbud. Baggrunden er, at det anses som værende fremtiden og lettere for kunden at administrere selv. | V85: Reviewed - Content | W85: =IF(V85="Not Started",0%,IF(V85="Started",50%,IF(V85="Ready for review",70%,IF(V85="Reviewed - Content",80%,IF(V85="Reviewed - Format",90%,IF(V85="Done",100%,"")))))) -> 0.8 | X85: 2026-07-07 | Y85: Cursor / tender-response (MCP-enriched) | Z85: Met | AA85: Verified | AB85: Verify: Browser-baseret brugergrænseflade — vurderet opfyldt (tool: 1. Fully met). | AC85: ADN: Påvirker ikke os - men det her krav er et godt eksempel på en Kunde der beskriver en løsning frem for et behov. Hvorfor skal det være browserbaseret? AOP: Meget standard i udbud. Baggrunden er, at det anses som værende fremtiden og lettere for kunden at administrere selv. | Red flag: Påvirker ikke os - men det her krav er et godt eksempel på en Kunde der beskriver en løsning frem for et behov. Hvorfor skal det være browserbaseret? | AD85: Wiki: Frontend guidelines for modern web applications; BSP design goals and technical changes | AE85: Anton: Confirm verify-tekst; opdatér review status efter tjek. | AG85: Draft | AH85: uim-esdh-full-2026-07-07
A86: 85 | B86: MK-77 | C86: Bilag 1.b | D86: Brugergrænsefladen | E86: Visning af store mængder | F86: ESDH-løsningen skal understøtte, at alle listevisninger fra standard og Kundeoprettede Entiteter eller i søgningsresultater ikke har begrænsning i antal resultater. Resultaterne kan opdeles på flere sider jf. arkitekturmønsteret pagination (processen med at opdele store mængder indhold, data eller søgeresultater i mindre, overskuelige bidder). | G86: Mindstekrav | H86: =IF(G86="Evalueringskrav","Answer",(IF(G86="Krav","Check",(IF(G86="Mindstekrav","Verify",""))))) -> Verify | I86: Ja | L86: Claus | O86: 3. Not able to meet | P86: ADN: Issue - ”Alle” og ”ingen begrænsning” i samme sætning.. CHM: I princippet kan vi vel sætte "Max query rows" til 1 mio., selvom konsekvensen vil være en SQL timeout. De fleste lister i GUI har allerede implementeret pagination. | Q86: 435257 | S86: Yes | V86: Started | W86: =IF(V86="Not Started",0%,IF(V86="Started",50%,IF(V86="Ready for review",70%,IF(V86="Reviewed - Content",80%,IF(V86="Reviewed - Format",90%,IF(V86="Done",100%,"")))))) -> 0.5 | X86: 2026-07-07 | Y86: Cursor / tender-response (MCP-enriched) | Z86: Not met | AA86: Lead | AB86: Verify: Visning af store mængder — gap ift. kravtekst; eskalér commitment eller afklaring. | AC86: ADN: Issue - ”Alle” og ”ingen begrænsning” i samme sætning.. | Red flag: Issue - ”Alle” og ”ingen begrænsning” i samme sætning.. | AD86: Ratatoskr: Search and Result lists (admin-en) | Wiki: 5.14 release information | AE86: Claus: Commitment/no-bid beslutning; overvej Q&A til ordregiver. | AG86: Draft | AH86: uim-esdh-full-2026-07-07
A87: 86 | B87: MK-78 | C87: Bilag 1.b | D87: Brugergrænsefladen | E87: Genvejstaster | F87: ESDH-løsningen skal understøtte brugen af genvejstaster, funktionstaster eller tastekombinationer. Genvejstaster skal være dokumenteret i hjælpefunktionen. | G87: Mindstekrav | H87: =IF(G87="Evalueringskrav","Answer",(IF(G87="Krav","Check",(IF(G87="Mindstekrav","Verify",""))))) -> Verify | I87: Ja | L87: Anton | O87: 1. Fully met | P87: ADN: Det her bevæger vi os væk fra, fordi det ikke er særligt WCAG-compliant. MEN - vi skal bemærke de ikke definere det skal gælde alt, eller hvad man skal kunne, så hvis vi har en genvejstast ét sted i løsningen, kan vi principielt sige ja til dette krav. Vi understøtter brugen af "Tab" og "Enter" - vi skal bare sikre os det står i onlinehjælpen. Tjek op med Core UI - de har commitment på løsning til edoc kunderne. | V87: Reviewed - Content | W87: =IF(V87="Not Started",0%,IF(V87="Started",50%,IF(V87="Ready for review",70%,IF(V87="Reviewed - Content",80%,IF(V87="Reviewed - Format",90%,IF(V87="Done",100%,"")))))) -> 0.8 | X87: 2026-07-07 | Y87: Cursor / tender-response (MCP-enriched) | Z87: Met | AA87: Lead | AB87: Verify: Genvejstaster — vurderet opfyldt (tool: 1. Fully met). | AC87: ADN: Det her bevæger vi os væk fra, fordi det ikke er særligt WCAG-compliant. MEN - vi skal bemærke de ikke definere det skal gælde alt, eller hvad man skal kunne, så hvis vi har en genvejstast ét sted i løsningen, kan vi principielt sige ja til dette krav. Vi understøtter brugen af "Tab" og "Enter" - vi skal bare sikre os det står i onlinehjælpen. | Red flag: Det her bevæger vi os væk fra, fordi det ikke er særligt WCAG-compliant. MEN - vi skal bemærke de ikke definere det skal gælde alt, eller hvad man skal kunne, så hvis vi har en genvejstast ét sted i løsningen, kan vi principielt sige ja til dette krav. | AD87: No keyboard shortcut documentation in help or wiki | AE87: Anton: Confirm verify-tekst; opdatér review status efter tjek. | AG87: Draft | AH87: uim-esdh-full-2026-07-07
A88: 87 | B88: MK-79 | C88: Bilag 1.b | D88: Brugergrænsefladen | E88: Obligatoriske felter | F88: ESDH-løsningen skal understøtte en tydelig marker af obligatoriske felter i forbindelse med oprettelse eller redigering af Entiteter. | G88: Mindstekrav | H88: =IF(G88="Evalueringskrav","Answer",(IF(G88="Krav","Check",(IF(G88="Mindstekrav","Verify",""))))) -> Verify | I88: Ja | L88: Anton | O88: 1. Fully met | V88: Reviewed - Content | W88: =IF(V88="Not Started",0%,IF(V88="Started",50%,IF(V88="Ready for review",70%,IF(V88="Reviewed - Content",80%,IF(V88="Reviewed - Format",90%,IF(V88="Done",100%,"")))))) -> 0.8 | X88: 2026-07-07 | Y88: Cursor / tender-response (batch) | Z88: Met | AA88: Verified | AB88: Verify: Obligatoriske felter — vurderet opfyldt (tool: 1. Fully met). | AD88: docs/tender-reference/extracted/Nationalbanken/Bilag 3.i Leverandørens Løsningsbeskrivelse.txt; docs/product/RFP_Leverandørens_svar_utdrag.txt; docs/tender-reference/extracted/HSØ/02.00-Tietoevry-SSA-L-Bilag 2-Leverandørens beskrivelse av Tjenesten.txt | AE88: Anton: Confirm verify-tekst; opdatér review status efter tjek. | AG88: Draft | AH88: uim-esdh-full-2026-07-07
A89: 88 | B89: MK-80 | C89: Bilag 1.b | D89: Brugergrænsefladen | E89: Masseændring | F89: ESDH-løsningen skal understøtte, at en Bruger via brugergrænsefladen kan foretage masseændringer af tilknyttede standard- og Kundeoprettede felter på sager, Dokumenter, kontakter og Kundeoprettede Entiteter. | G89: Mindstekrav | H89: =IF(G89="Evalueringskrav","Answer",(IF(G89="Krav","Check",(IF(G89="Mindstekrav","Verify",""))))) -> Verify | I89: Ja | L89: Torben | O89: 3. Not able to meet | P89: ADN: Vi skal bemærke de ikke bruger ordet ”Alle” i denne sætning - meeeen.. Vi har det slet ikke for Kontakter, projekter, ejendomme og aktiviteter, og vi har det ingen steder for kundeoprettede felter. (De specificere heller ikke at det skal være på alle kundeoprettede entiteter) Måske vi kan bruge det til noget. | Q89: 433883 | R89: Yes | V89: Not Started | W89: =IF(V89="Not Started",0%,IF(V89="Started",50%,IF(V89="Ready for review",70%,IF(V89="Reviewed - Content",80%,IF(V89="Reviewed - Format",90%,IF(V89="Done",100%,"")))))) -> 0 | X89: 2026-07-07 | Y89: Cursor / tender-response (MCP-enriched) | Z89: Not met | AA89: Lead | AB89: Verify: Masseændring — gap ift. kravtekst; eskalér commitment eller afklaring. | AC89: ADN: Vi skal bemærke de ikke bruger ordet ”Alle” i denne sætning - meeeen.. Vi har det slet ikke for Kontakter, projekter, ejendomme og aktiviteter, og vi har det ingen steder for kundeoprettede felter. (De specificere heller ikke at det skal være på alle kundeoprettede entiteter) Måske vi kan bruge det til noget. | Red flag: Vi skal bemærke de ikke bruger ordet ”Alle” i denne sætning - meeeen.. Vi har det slet ikke for Kontakter, projekter, ejendomme og aktiviteter, og vi har det ingen steder for kundeoprettede felter. (De specificere heller ikke at det skal være på alle kundeoprettede entiteter) Måske vi kan bruge det til noget. | AD89: Wiki: 5.14 release information; 6.0 release information | AE89: Torben: Commitment/no-bid beslutning; overvej Q&A til ordregiver. | AG89: Draft | AH89: uim-esdh-full-2026-07-07
A90: 89 | B90: MK-81 | C90: Bilag 1.b | D90: Brugergrænsefladen | E90: Visuel visning på Dokument metadata | F90: ESDH-løsningen skal understøtte en visuel adskillelse af indgående og udgående Dokumenter, f.eks. via opmærkning. | G90: Mindstekrav | H90: =IF(G90="Evalueringskrav","Answer",(IF(G90="Krav","Check",(IF(G90="Mindstekrav","Verify",""))))) -> Verify | I90: Ja | L90: Anton | O90: 1. Fully met | P90: ADN: Hvornår er noget ”Visuelt adskilt”? - er det nok at der står ”Indgående” og/eller ”Udgående”? hos os står der "Dokument ind", eller "dokument ud" - det er vel visuelt adskildt.. Jeg kan se at der ikke står det samme? | V90: Reviewed - Content | W90: =IF(V90="Not Started",0%,IF(V90="Started",50%,IF(V90="Ready for review",70%,IF(V90="Reviewed - Content",80%,IF(V90="Reviewed - Format",90%,IF(V90="Done",100%,"")))))) -> 0.8 | X90: 2026-07-07 | Y90: Cursor / tender-response (MCP-enriched) | Z90: Met | AA90: Lead | AB90: Verify: Visuel visning på Dokument metadata — vurderet opfyldt (tool: 1. Fully met). | AC90: ADN: Hvornår er noget ”Visuelt adskilt”? - er det nok at der står ”Indgående” og/eller ”Udgående”? hos os står der "Dokument ind", eller "dokument ud" - det er vel visuelt adskildt.. Jeg kan se at der ikke står det samme? | Red flag: Hvornår er noget ”Visuelt adskilt”? - er det nok at der står ”Indgående” og/eller ”Udgående”? | AD90: Wiki: 6.8 release information; EDoc Documentation for Support | AE90: Anton: Confirm verify-tekst; opdatér review status efter tjek. | AG90: Draft | AH90: uim-esdh-full-2026-07-07
A91: 90 | B91: MK-82 | C91: Bilag 1.b | D91: Brugergrænsefladen | E91: Markering af obligatoriske felter | F91: ESDH-løsningen skal understøtte en tydelig markering af, om felter er obligatoriske. Det skal være gældende for Løsningens standard- og Kundeoprettede felter. | G91: Mindstekrav | H91: =IF(G91="Evalueringskrav","Answer",(IF(G91="Krav","Check",(IF(G91="Mindstekrav","Verify",""))))) -> Verify | I91: Ja | L91: Anton | O91: 1. Fully met | V91: Reviewed - Content | W91: =IF(V91="Not Started",0%,IF(V91="Started",50%,IF(V91="Ready for review",70%,IF(V91="Reviewed - Content",80%,IF(V91="Reviewed - Format",90%,IF(V91="Done",100%,"")))))) -> 0.8 | X91: 2026-07-07 | Y91: Cursor / tender-response (batch) | Z91: Met | AA91: Verified | AB91: Verify: Markering af obligatoriske felter — vurderet opfyldt (tool: 1. Fully met). | AD91: docs/tender-reference/extracted/KK Tender tool.txt; docs/tender-reference/extracted/KUM-SLKS/Bilag 3 - Kravspecifikation.txt; docs/tender-reference/extracted/Nationalbanken/Bilag 3.i Leverandørens Løsningsbeskrivelse.txt | AE91: Anton: Confirm verify-tekst; opdatér review status efter tjek. | AG91: Draft | AH91: uim-esdh-full-2026-07-07
A92: 91 | B92: MK-83 | C92: Bilag 1.b | D92: Brugergrænsefladen | E92: Kolonnevisninger - Standard | F92: ESDH-løsningen skal understøtte at Kunden kan tilvælge og fravælge kolonnevisninger på sager, Dokumenter, kontakt-billeder. | G92: Mindstekrav | H92: =IF(G92="Evalueringskrav","Answer",(IF(G92="Krav","Check",(IF(G92="Mindstekrav","Verify",""))))) -> Verify | I92: Ja | L92: Torben | O92: 3. Not able to meet | P92: ADN Det understøtter vi ikke - jeg tænker de mener kolonner inde i webparts på vores overbliksbilleder. "quick-and-dirty" fix er at tilføje visningslisten, så kuden kan vælge visning ligesom de kan i maksimeret visning for dokumenter | Q92: 433884 | R92: Yes | V92: Not Started | W92: =IF(V92="Not Started",0%,IF(V92="Started",50%,IF(V92="Ready for review",70%,IF(V92="Reviewed - Content",80%,IF(V92="Reviewed - Format",90%,IF(V92="Done",100%,"")))))) -> 0 | X92: 2026-07-07 | Y92: Cursor / tender-response (MCP-enriched) | Z92: Not met | AA92: Lead | AB92: Verify: Kolonnevisninger - Standard — gap ift. kravtekst; eskalér commitment eller afklaring. | AC92: ADN Det understøtter vi ikke - jeg tænker de mener kolonner inde i webparts på vores overbliksbilleder. | Red flag: Det understøtter vi ikke - jeg tænker de mener kolonner inde i webparts på vores overbliksbilleder. | AD92: Wiki: 360° Version 5 changes in detail views and wizards | AE92: Torben: Commitment/no-bid beslutning; overvej Q&A til ordregiver. | AG92: Draft | AH92: uim-esdh-full-2026-07-07
A93: 92 | B93: MK-84 | C93: Bilag 1.b | D93: Brugergrænsefladen | E93: Kolonnevisninger - Kundeoprettede | F93: ESDH-løsningen skal understøtte, at Kunden kan tilvælge og fravælge kolonnevisninger på Kundeoprettede Entiteter. | G93: Mindstekrav | H93: =IF(G93="Evalueringskrav","Answer",(IF(G93="Krav","Check",(IF(G93="Mindstekrav","Verify",""))))) -> Verify | I93: Ja | L93: Torben | O93: 3. Not able to meet | P93: ADN: Det understøtter vi ikke - jeg tænker de mener kolonner inde i webparts på vores overbliksbilleder. "quick-and-dirty" fix er at tilføje visningslisten, så kuden kan vælge visning ligesom de kan i maksimeret visning for dokumenter | Q93: 433884 | R93: Yes | V93: Not Started | W93: =IF(V93="Not Started",0%,IF(V93="Started",50%,IF(V93="Ready for review",70%,IF(V93="Reviewed - Content",80%,IF(V93="Reviewed - Format",90%,IF(V93="Done",100%,"")))))) -> 0 | X93: 2026-07-07 | Y93: Cursor / tender-response (MCP-enriched) | Z93: Not met | AA93: Lead | AB93: Verify: Kolonnevisninger - Kundeoprettede — gap ift. kravtekst; eskalér commitment eller afklaring. | AC93: ADN: Det understøtter vi ikke - jeg tænker de mener kolonner inde i webparts på vores overbliksbilleder. | Red flag: Det understøtter vi ikke - jeg tænker de mener kolonner inde i webparts på vores overbliksbilleder. | AD93: Wiki: 360° Version 5 changes in detail views and wizards | AE93: Torben: Commitment/no-bid beslutning; overvej Q&A til ordregiver. | AG93: Draft | AH93: uim-esdh-full-2026-07-07
A94: 93 | B94: MK-85 | C94: Bilag 1.b | D94: Brugergrænsefladen | E94: Kundeoprettede felter på kolonnevisning | F94: ESDH-løsningen skal understøtte, at Kundeoprettede felter skal kunne anvendes i kolonnevisningerne på standard Entiteter og Kundeoprettede Entiteter. | G94: Mindstekrav | H94: =IF(G94="Evalueringskrav","Answer",(IF(G94="Krav","Check",(IF(G94="Mindstekrav","Verify",""))))) -> Verify | I94: Ja | L94: Torben | O94: 3. Not able to meet | P94: ADN: Det understøtter vi ikke - jeg tænker de mener kolonner inde i webparts på vores overbliksbilleder.Vi gemmer ikke sorteringer og filtreringer "quick-and-dirty" fix er at tilføje visningslisten, så kuden kan vælge visning ligesom de kan i maksimeret visning for dokumenter | Q94: 433884 | R94: Yes | V94: Not Started | W94: =IF(V94="Not Started",0%,IF(V94="Started",50%,IF(V94="Ready for review",70%,IF(V94="Reviewed - Content",80%,IF(V94="Reviewed - Format",90%,IF(V94="Done",100%,"")))))) -> 0 | X94: 2026-07-07 | Y94: Cursor / tender-response (MCP-enriched) | Z94: Not met | AA94: Lead | AB94: Verify: Kundeoprettede felter på kolonnevisning — gap ift. kravtekst; eskalér commitment eller afklaring. | AC94: ADN: Det understøtter vi ikke - jeg tænker de mener kolonner inde i webparts på vores overbliksbilleder.Vi gemmer ikke sorteringer og filtreringer | Red flag: Det understøtter vi ikke - jeg tænker de mener kolonner inde i webparts på vores overbliksbilleder. | AD94: Ratatoskr: Custom fields (admin-en) | Wiki: Build log hotfix packages; 6.0 release information | AE94: Torben: Commitment/no-bid beslutning; overvej Q&A til ordregiver. | AG94: Draft | AH94: uim-esdh-full-2026-07-07
A95: 94 | B95: MK-86 | C95: Bilag 1.b | D95: Brugergrænsefladen | E95: Filtrering og sortering på kolonnevisninger | F95: ESDH-løsningen skal understøtte filtrering og sortering på kolonnevisninger. Brugerens valgte indstillinger skal kunne gemmes som standardvisning for Brugeren. | G95: Mindstekrav | H95: =IF(G95="Evalueringskrav","Answer",(IF(G95="Krav","Check",(IF(G95="Mindstekrav","Verify",""))))) -> Verify | I95: Ja | L95: Torben | O95: 3. Not able to meet | P95: ADN: Det understøtter vi ikke - jeg tænker de mener kolonner inde i webparts på vores overbliksbilleder.Vi gemmer ikke sorteringer og filtreringer MJ: mulige løsninger kunne være cookies eller "gem" lignende funktionalitet af mine opsætninger Torben tester noget.. | Q95: 433884 | R95: Yes | V95: Not Started | W95: =IF(V95="Not Started",0%,IF(V95="Started",50%,IF(V95="Ready for review",70%,IF(V95="Reviewed - Content",80%,IF(V95="Reviewed - Format",90%,IF(V95="Done",100%,"")))))) -> 0 | X95: 2026-07-07 | Y95: Cursor / tender-response (MCP-enriched) | Z95: Not met | AA95: Lead | AB95: Verify: Filtrering og sortering på kolonnevisninger — gap ift. kravtekst; eskalér commitment eller afklaring. | AC95: ADN: Det understøtter vi ikke - jeg tænker de mener kolonner inde i webparts på vores overbliksbilleder.Vi gemmer ikke sorteringer og filtreringer | Red flag: Det understøtter vi ikke - jeg tænker de mener kolonner inde i webparts på vores overbliksbilleder.Vi gemmer ikke sorteringer og filtreringer | AD95: Wiki: Build log hotfix packages; 5.9 release information | AE95: Torben: Commitment/no-bid beslutning; overvej Q&A til ordregiver. | AG95: Draft | AH95: uim-esdh-full-2026-07-07
A96: 95 | B96: MK-87 | C96: Bilag 1.b | D96: Brugergrænsefladen | E96: Faner og widgets | F96: ESDH-løsningen skal understøtte, at Kunden kan opsætte Kundeoprettede faner/widgets på både standard- og Kundeoprettede Entiteter. | G96: Mindstekrav | H96: =IF(G96="Evalueringskrav","Answer",(IF(G96="Krav","Check",(IF(G96="Mindstekrav","Verify",""))))) -> Verify | I96: Ja | L96: Torben | O96: 3. Not able to meet | P96: ADN: ”kundeoprettede faner” på overbliksbilleder kræver en voldsomt udvidelse af FFUI Overbliksbilleder Widgets kan tolkes som webparts, men kunden skal selv kunne opsætte dem. Vi mangler et konfig interface for en "iframe" hvor kunden kan vælge hvad der skal vises | Q96: 433884 | R96: Yes | V96: Not Started | W96: =IF(V96="Not Started",0%,IF(V96="Started",50%,IF(V96="Ready for review",70%,IF(V96="Reviewed - Content",80%,IF(V96="Reviewed - Format",90%,IF(V96="Done",100%,"")))))) -> 0 | X96: 2026-07-07 | Y96: Cursor / tender-response (MCP-enriched) | Z96: Not met | AA96: Lead | AB96: Verify: Faner og widgets — gap ift. kravtekst; eskalér commitment eller afklaring. | AC96: ADN: ”kundeoprettede faner” på overbliksbilleder kræver en voldsomt udvidelse af FFUI Overbliksbilleder | Red flag: ”kundeoprettede faner” på overbliksbilleder kræver en voldsomt udvidelse af FFUI Overbliksbilleder | AD96: No custom tabs/widgets on entity overviews documentation | AE96: Torben: Commitment/no-bid beslutning; overvej Q&A til ordregiver. | AG96: Draft | AH96: uim-esdh-full-2026-07-07
A97: 96 | B97: MK-88 | C97: Bilag 1.b | D97: Brugergrænsefladen | E97: Fleksibilitet | F97: ESDH-løsningen skal understøtte, at Kunden har fuld fleksibilitet til vælge, hvor Kundeoprettede Entiteter og Kundeoprettede felter vises i brugergrænsefladen. | G97: Mindstekrav | H97: =IF(G97="Evalueringskrav","Answer",(IF(G97="Krav","Check",(IF(G97="Mindstekrav","Verify",""))))) -> Verify | I97: Ja | L97: Torben | O97: 3. Not able to meet | P97: ADN: Hvis vi nu tolker det her til webparten "brugerdefinerede felter" og webparten: "Ejendomme", "Projekter" og "Aktiviteter" - så kan kunden jo godt på sags- og dokumentoversigter bestemme hvor disse vises. Vi har det dog ikke på kontaktoverblik. | Q97: 433884 | R97: Yes | V97: Not Started | W97: =IF(V97="Not Started",0%,IF(V97="Started",50%,IF(V97="Ready for review",70%,IF(V97="Reviewed - Content",80%,IF(V97="Reviewed - Format",90%,IF(V97="Done",100%,"")))))) -> 0 | X97: 2026-07-07 | Y97: Cursor / tender-response (MCP-enriched) | Z97: Not met | AA97: Lead | AB97: Verify: Fleksibilitet — gap ift. kravtekst; eskalér commitment eller afklaring. | AC97: ADN: Hvis vi nu tolker det her til webparten "brugerdefinerede felter" og webparten: "Ejendomme", "Projekter" og "Aktiviteter" - så kan kunden jo godt på sags- og dokumentoversigter bestemme hvor disse vises. Vi har det dog ikke på kontaktoverblik. | Red flag: Understøttes ikke | AD97: Wiki: Flexibility initiatives; Full-Flex UI entity creation | AE97: Torben: Commitment/no-bid beslutning; overvej Q&A til ordregiver. | AG97: Draft | AH97: uim-esdh-full-2026-07-07
A98: 97 | B98: K-7 | C98: Bilag 1.b | D98: Brugergrænsefladen | E98: Relationer skal være navigerbare | F98: Løsningen skal understøtte, at relationer mellem standardentiteter og Kundens egne oprettede Entiteter er aktive og navigerbare i brugergrænsefladen. Det skal være muligt for Brugeren at klikke på en reference til en relateret Entitet og blive ledt direkte til den pågældende Entitets indhold, metadata og tilknyttede relationer. Eksempelvis skal en Bruger, der står på en sag, kunne vælge et relateret Dokument og blive ledt direkte til Dokumentet og dets metadata. Hvis Dokumentet er tilknyttet en kontakt, f.eks. en Udlænding, skal Brugeren tilsvarende kunne klikke på kontakten og blive ledt til kontaktens stamdata, metadata og relaterede sager, Dokumenter eller øvrige relevante Entiteter. | G98: Krav | H98: =IF(G98="Evalueringskrav","Answer",(IF(G98="Krav","Check",(IF(G98="Mindstekrav","Verify",""))))) -> Check | I98: Ja | L98: Anton | O98: 1. Fully met | V98: Reviewed - Content | W98: =IF(V98="Not Started",0%,IF(V98="Started",50%,IF(V98="Ready for review",70%,IF(V98="Reviewed - Content",80%,IF(V98="Reviewed - Format",90%,IF(V98="Done",100%,"")))))) -> 0.8 | X98: 2026-07-07 | Y98: Cursor / tender-response (batch) | Z98: Met | AA98: Verified | AB98: Check: Relationer skal være navigerbare — vurderet opfyldt (tool: 1. Fully met). | AD98: docs/tender-reference/extracted/Nationalbanken/Bilag 3.i Leverandørens Løsningsbeskrivelse.txt; docs/tender-reference/extracted/KK Tender tool.txt; docs/tender-reference/extracted/KUM-SLKS/Bilag 3 - Kravspecifikation.txt | AE98: Anton: Confirm verify-tekst; opdatér review status efter tjek. | AG98: Draft | AH98: uim-esdh-full-2026-07-07
A99: 98 | B99: EK-3 | C99: Bilag 1.b | D99: Brugergrænsefladen | E99: Bruger-grænseflade | F99: I forbindelse med Kundens daglige anvendelse af ESDH-løsningen er det væsentligt, at brugergrænsefladen kan tilpasses den enkelte Brugers og organisationens behov, herunder ved tilpasning, filtrering og sortering af faner/widgets, felter og kolonner. Leverandøren skal beskrive, hvordan den tilbudte ESDH-løsning understøtter tilpasning af brugergrænsefladen. Leverandøren skal gennem konkrete skærmbilleder demonstrere om og hvordan ESDH-løsningen understøtter de stillede krav og møder Kundens behov. Leverandøren skal redegøre for: Hvordan ESDH-løsningen giver Brugeren hurtig og overskuelig adgang til relevante oplysninger i forbindelse med sagsbehandling Hvordan Brugeren kan personalisere brugergrænsefladen f.eks. via tilpasning af kolonner på alle Entiteter og søgebilleder Hvordan Brugeren kan personalisere visningsbilleder via filtrering og sortering Hvilke muligheder Administratoren har for at tilpasse udstillingen af data på sager, Dokumenter og kontakter Hvordan Administratoren kan tilpasse søgebilleder og resultatlister Hvordan Administratoren kan konfigurere og udrulle opsætning til hele organisationen samt udvalgte teams og medarbejdere Evalueringskriterier: Det vægtes positivt, i hvor høj grad Brugeren kan personalisere brugergrænsefladen til egne behov f.eks. tilpasning af kolonner i alle visningsbilleder. Det vægtes positivt, i hvor høj grad Administratoren kan tilpasse brugergrænsefladen på alle Entiteter, visningsbilleder, resultatlister og søgebilleder f.eks. tilpasning af kolonner, filtreringer og placering af felter. Det vægtes positivt, i hvor høj grad Administratoren kan udrulle opsætninger og tilpasninger på flere organisatoriske niveauer samt at Administratoren kan begrænse muligheden for bruger-personalisering af den udrullede opsætning. Det vægtes positivt, i hvor høj grad Administratoren kan tilføje og fjerne både standardfelter og Kundeoprettede felter fra alle Entiteters visnings- og søgebilleder. | G99: Evalueringskrav | H99: =IF(G99="Evalueringskrav","Answer",(IF(G99="Krav","Check",(IF(G99="Mindstekrav","Verify",""))))) -> Answer | I99: Ja | L99: Claus | Q99: 435253 | V99: Not Started | W99: =IF(V99="Not Started",0%,IF(V99="Started",50%,IF(V99="Ready for review",70%,IF(V99="Reviewed - Content",80%,IF(V99="Reviewed - Format",90%,IF(V99="Done",100%,"")))))) -> 0 | X99: 2026-07-07 | Y99: Cursor / tender-response (MCP-enriched) | Z99: Draft needed | AA99: Lead | AB99: Answer: Bruger-grænseflade — informationskrav; udkast bilag/dokumentation mangler. | AC99: Mangler link til svar-bilag i kolonne T. | AD99: Wiki: Full-Flex UI entity creation; Flexibility initiatives | AE99: Claus: Opret/link svar-bilag; draft IK-tekst fra prior art. | AG99: Draft | AH99: uim-esdh-full-2026-07-07
A100: 99 | B100: MK-89 | C100: Bilag 1.b | D100: Aktindsigt | E100: Oprettelse og behandling af aktindsigter | F100: ESDH-løsningen skal understøtte oprettelse og behandling af aktindsigter som sagstyper i ESDH-løsningen i henhold til både Forvaltningsloven og Offentlighedsloven. | G100: Mindstekrav | H100: =IF(G100="Evalueringskrav","Answer",(IF(G100="Krav","Check",(IF(G100="Mindstekrav","Verify",""))))) -> Verify | I100: Ja | L100: Anton | O100: 1. Fully met | V100: Reviewed - Content | W100: =IF(V100="Not Started",0%,IF(V100="Started",50%,IF(V100="Ready for review",70%,IF(V100="Reviewed - Content",80%,IF(V100="Reviewed - Format",90%,IF(V100="Done",100%,"")))))) -> 0.8 | X100: 2026-07-07 | Y100: Cursor / tender-response (batch) | Z100: Met | AA100: Verified | AB100: Verify: Oprettelse og behandling af aktindsigter — vurderet opfyldt (tool: 1. Fully met). | AD100: docs/tender-reference/extracted/KK Tender tool.txt; docs/tender-reference/extracted/Nationalbanken/Bilag 3.i Leverandørens Løsningsbeskrivelse.txt; docs/tender-reference/extracted/KUM-SLKS/Bilag 3 - Kravspecifikation.txt | AE100: Anton: Confirm verify-tekst; opdatér review status efter tjek. | AG100: Draft | AH100: uim-esdh-full-2026-07-07
...

Sheet Red flags
A1: Krav nr. | B1: Kravtekst | C1: Kommentar
A2: MK-30 | B2: MK-30 | C2: Det er kludret formuleret - men jeg tolker det til, at de fra en søgning på et projekt, skal kunne se relaterede sager i resultatlisterne.. Det er udfordrende
A3: MK-35 | B3: ESDH-løsningen skal understøtte, at alle Dokumenter, Filer, Hoveddokumenter og Bilag har hver deres unikke ID, som skal være synligt i brugergrænsefladen. | C3: Hvornår er noget ”synligt i brugergrænsefladen”… vi har recno på filer, men de kræver ”vis egenskaber” for at være synlige.
A4: MK-49 | B4: ESDH-løsningen skal understøtte en integreret dokumentviewer i brugergrænsefladen. Løsningen skal understøtte forhåndsvisning af Dokumenter fra sager, søgninger og listevisninger. ESDH-løsningen skal understøtte, at Brugeren får præsenteret Dokumentets tekst/indhold direkte i Løsningen. | C4: ”Direkte” er problematisk, hvis det forbyder os fra et nyt vindue.
A5: MK-50 | B5: ESDH-løsningen skal understøtte, at Brugeren kan navigere og scrolle i dokument- og fillistevisninger, og at forhåndsvisningen automatisk opdateres og viser det Dokument/Fil, som Brugeren har navigeret til. | C5: Vores forhåndsvisning ”opdateres ikke automatisk”. Kræver aktivt klik på det dokument/fil der ønskes forhåndsvist.
A6: MK-56 | B6: ESDH-løsningen skal understøtte, at en Bruger ikke kan oprette en kontakt, hvis kontaktens unikke ID allerede findes i kontaktregisteret. | C6: Vi advarer, men vi forbyder ikke. CPR/CVR er ikke så unikt at det ikke kan duplikeres.
A7: MK-66 | B7: ESDH-løsningen skal understøtte, at der kan søges på alle standard- og Kundeoprettede felter på samme tid i ESDH-løsningen. | C7: Det her krav er formuleret uden logiske begræsninger mellem entiteter, hvilke tikke giver mening. Det kan vi ikke understøtte.
A8: MK-68 | B8: Trunkering i avanceret søgning | C8: Det her lugter af at være givet titlen her, fordi de ved vi ikke kan i den avancerede søgning - men kravteksten indeholder det ikke, og derfor bør vi være OK med kravet
A9: MK-70 | B9: ESDH-løsningen skal understøtte, at alle felter kan vises i søgeresultaternes visningslister. | C9: ”Alle felter” - godt nok afgrænset til søgeresultater, men stadig en stor risc, fra en ondsindet kunde.
A10: MK-74 | B10: ESDH-løsningen skal understøtte, at Kunden kan opsætte og konfigurere søgebilleder for alle Løsningens standard- og Kundeoprettede Entiteter. | C10: Det understøtter vi ikke.
A11: MK-75 | B11: ESDH-løsningen skal understøtte, at Kunden selv kan definere og konfigurere, hvilke standard- og Kundeoprettede felter søgebilledet skal indeholde. | C11: Det understøtter vi ikke
A12: MK-76 | B12: MK-76 | C12: Påvirker ikke os - men det her krav er et godt eksempel på en Kunde der beskriver en løsning frem for et behov. Hvorfor skal det være browserbaseret?
... A53: Fordeling af krav | B53: I udbudsmaterialet findes der følgende fordeling af krav: - ca. 217 krav (83 %) er klassificeret som Mindstekrav, - ca. 33 krav (13 %) er klassificeret som Krav, - kun ca. 12 krav (4 %) er klassificeret som Evalueringskrav. | C53: Tommelfingerreglen for offentlige udbud er, at kun omkring 10% af et udbuds totale antal krav bør være mindstekrav.

Sheet Q&A
A1: # | B1: Relates to requirement ID | C1: Sender | D1: Question | E1: Sent Date | F1: Answer | G1: Received Date | H1: Customer answer ID | I1: Comment
A2: 1 | B2: Leveringskontrakten: Punkt 16.1 (Forsinkelse) Punkt 16.3 (Bod) Punkt 16.4 (Erstatning) Bilag 1.h Servicemål (SLA-bod) Bilag 5 CSR (CSR-bod) Bilag 6 Trepartsaftale (bod ved mangelfuld rapportering til SKI) | C2: Tieto | D2: Spørgsmål vedrørende kumulation af bod Leveringskontrakten og de tilhørende bilag indeholder flere selvstændige bodsregimer, herunder bod ved forsinkelse og mangler efter Leveringskontraktens pkt. 16.3, bod efter Bilag 1.h Servicemål, CSR-relateret bod efter Bilag 5 og bod efter Bilag 6 Trepartsaftale. Tilbudsgiver kan ikke entydigt fastslå, om samme hændelse eller samme underliggende misligholdelse kan udløse bod efter flere af disse bestemmelser samtidig, eller om de enkelte bodsregimer skal anses som alternative. Ordregiver bedes derfor præcisere, om bod kan kumuleres på tværs af Leveringskontrakten og bilagene for samme hændelse eller samme underliggende misligholdelse. Såfremt bod kan kumuleres, bedes Ordregiver samtidig oplyse, om der gælder et samlet maksimum for den bod, som Leverandøren kan pålægges på tværs af Leveringskontrakten, Bilag 1.h, Bilag 5 og Bilag 6. Hvis der ikke gælder et sådant samlet loft, bedes Ordregiver overveje at indføre dette, således at Leverandørens samlede bodeksponering kan fastlægges entydigt ved tilbudsafgivelsen. | I2: Omformuleret.
A3: 2 | B3: Bilag 1 Kundens opgavebeskrivelse Punkt 2.2 Support og vedligeholdelse Punkt 2.3 Implementering Punkt 3 Eksisterende it-miljø Punkt 4 Tidsplan Bilag 1.c Kundens eksisterende it-landskab Bilag 1.g Samarbejde under Leveringskontrakten Bilag 1.h Servicemål Bilag 1.l Statens IT's driftsmodeller | C3: Tieto | D3: Spørgsmål vendrørende ansvar for forhold hos Statens IT Det fremgår af Bilag 1.l, at ansvaret for driften under Driftsmodel 3 er fordelt mellem Kunden/Leverandøren og Statens IT, herunder således at Statens IT har ansvar for operativsystem, server/storage og netværk, mens Kunden har ansvar for applikation og middleware. Tilbudsgiver bemærker samtidig, at Leverandøren er underlagt servicemål og potentielle bodskrav efter Bilag 1.h. Tilbudsgiver kan ikke entydigt fastslå, hvordan servicemål og misligholdelsesbeføjelser håndteres, hvis manglende tilgængelighed, performance eller anden manglende opfyldelse helt eller delvist skyldes forhold ved de komponenter eller driftsopgaver, som Statens IT er ansvarlig for. Ordregiver bedes derfor bekræfte, at Leverandøren ikke ifalder bod, erstatningsansvar eller øvrige misligholdelsesbeføjelser i det omfang en manglende opfyldelse skyldes forhold, som henhører under Statens IT's ansvarsområde. Ordregiver bedes samtidig præcisere, hvordan årsagen til en sådan hændelse fastlægges, og hvordan servicemålsberegningen håndteres, mens det undersøges, om hændelsen skyldes ESDH-løsningen eller Statens IT's infrastruktur. | I3: Omformuleret.
A4: 4 | B4: Bilag 1.b Krav til standardsoftware Samtlige MK, K og EK Bilag 1.e Krav til IT- og informationssikkerhed Samtlige MK og K Opfordringsskrivelsen Afsnit om evaluering Afsnit om konditionsmæssighed | C4: Tieto | D4: I udbudsmaterialet findes der følgende fordeling af krav: - ca. 217 krav (83 %) er klassificeret som Mindstekrav, - ca. 33 krav (13 %) er klassificeret som Krav, - kun ca. 12 krav (4 %) er klassificeret som Evalueringskrav. Det betyder, at langt hovedparten af kravene er ufravigelige Mindstekrav, som tilbudsgiver skal opfylde, mens kun en meget begrænset del af kravene giver mulighed for, at Ordregiver kan evaluere forskellige løsningsforslag og deres kvalitet. Tommelfingerreglen for offentlige udbud er, at kun omkring 10% af et udbuds totale antal krav bør være mindstekrav. Efter vores opfattelse indebærer en så høj andel af detaljerede Mindstekrav en risiko for, at konkurrencen begrænses unødigt, idet leverandørerne kun i begrænset omfang får mulighed for at konkurrere på forskellige standardfunktionaliteter, arkitekturvalg og løsningsmetoder. Dette gælder særligt, når Mindstekravene omfatter detaljerede krav til funktionalitet, brugergrænseflade og systemarkitektur frem for de bagvedliggende forretningsmæssige behov. Ordregiver bedes derfor oplyse: Hvilke overvejelser ligger til grund for, at ca. 83 % af kravene er udformet som Mindstekrav? Har Ordregiver vurderet, om alle disse krav er nødvendige som ufravigelige Mindstekrav, eller om en del af kravene kunne være udformet som Krav eller Evalueringskrav, således at forskellige standardløsninger kunne konkurrere på deres respektive styrker? Hvordan har Ordregiver sikret, at kravspecifikationen er udformet i overensstemmelse med udbudslovens § 42 om tekniske specifikationer, således at kravene ikke i praksis favoriserer bestemte produkter eller leverandører, men giver alle relevante standardløsninger mulighed for at konkurrere på lige vilkår? Hvordan har Ordregiver vurderet, at den valgte kravstruktur er forenelig med udbudslovens § 2 om ligebehandling og proportionalitet, når langt størstedelen af kravene er gjort til ufravigelige Mindstekrav? Baggrunden for spørgsmålene er, at en kravspecifikation med en meget høj andel af detaljerede Mindstekrav kan medføre, at konkurrencen i praksis begrænses til standardløsninger, som allerede er indrettet efter netop disse krav. Leverandører, der kan opfylde Ordregivers behov gennem andre standardfunktionaliteter eller en anden systemarkitektur, kan dermed få vanskeligere ved at konkurrere, selv om løsningen opfylder de bagvedliggende forretningsmæssige behov. Ordregiver bedes derfor redegøre for, hvilke konkrete vurderinger der er foretaget for at sikre, at kravspecifikationen ikke begrænser konkurrencen mere end nødvendigt, og at de opstillede Mindstekrav er proportionale og objektivt nødvendige for at opfylde Ordregivers behov. | I4: Udgår - er blevet spurgt af konkurrent - kunden fastholder.
A5: 5 | B5: Opfordringsskrivelsen Afsnit 3 Skriftlige spørgsmål Tidsplanen for spørgsmål og svar Tilbudsfrister | C5: Tieto | D5: Ordregiver har anført, at tilbudsgiverne i perioden fra den 10. juli 2026 til den 2. august 2026 ikke kan forvente at modtage svar på indsendte spørgsmål. Udbudsmaterialet er omfattende og indeholder et betydeligt antal detaljerede tekniske, kontraktuelle og sikkerhedsmæssige krav. For at kunne udarbejde et kvalificeret og konkurrencedygtigt tilbud er tilbudsgiverne afhængige af løbende afklaring af spørgsmål til udbudsmaterialet. Ordregiver bedes derfor redegøre for, hvordan det er vurderet, at den lange periode uden mulighed for afklaring giver tilbudsgiverne tilstrækkelige muligheder for at udarbejde et fuldt oplyst og konkurrencedygtigt tilbud på lige vilkår. Har Ordregiver overvejet enten: at besvare spørgsmål løbende i ferieperioden, at forlænge tilbudsfristen tilsvarende, eller at forlænge fristen for indsendelse af spørgsmål, således at tilbudsgiverne reelt har mulighed for at få afklaret væsentlige forhold i udbudsmaterialet inden tilbudsafgivelsen? | I5: Udgår
A6: 6 | B6: Bilag 1 Kundens opgavebeskrivelse Punkt 2.3 Implementering Punkt 4 Tidsplan Bilag 1.g Samarbejde under Leveringskontrakten Kapitel 3 Samarbejdsorganisation i implementeringsfasen Punkt 3.5 Projektledelse | C6: Tieto | D6: Udbudsmaterialet beskriver, at implementeringen skal gennemføres i et tæt samarbejde mellem Ordregiver og Leverandøren, og at begge parter har væsentlige roller i projektets gennemførelse. Ordregiver bedes derfor oplyse, hvem der forventes at varetage projektlederrollen på Ordregivers side under implementeringsfasen. Er det Ordregivers forventning, at projektledelsen varetages af interne medarbejdere, eller forventes projektledelsen helt eller delvist varetaget af en ekstern rådgiver? Såfremt Ordregiver forventer at anvende en ekstern rådgiver, bedes Ordregiver oplyse, om denne vil være den samme rådgiver, som har bistået Ordregiver med udarbejdelsen af udbudsmaterialet og den forudgående anskaffelsesproces. Baggrunden for spørgsmålet er, at projektorganisationen, projektledelsens rolle og graden af kontinuitet mellem udbudsfasen og implementeringsfasen har væsentlig betydning for implementeringsrisikoen, governance, beslutningsprocesser og samarbejdsmodellen. Disse forhold indgår direkte i tilbudsgivernes vurdering af risiko og dermed i prissætningen af implementeringsopgaven. En afklaring vil derfor bidrage til en mere ensartet risikovurdering og prissætning blandt tilbudsgiverne.
A7: 7 | B7: Bilag 1 Kundens opgavebeskrivelse Punkt 4.1 Faser i tidsplanen Punkt 4.2 Nedbrydning af faserne Aktiviteten "Kontraktunderskrivelse" Leveringskontrakten Punkt 13 Varighed | C7: Tieto | D7: Det fremgår af Bilag 1, at afklaringsfasen omfatter en række aktiviteter, herunder planlægning, afklaringer, projektopstart, miljøopsætning og etablering af testmiljø, og at afklaringsfasen afsluttes med "Kontraktunderskrivelse". Tilbudsgiver forstår dette således, at den endelige kontrakt først underskrives efter gennemførelsen af afklaringsfasen. Er denne forståelse korrekt? Såfremt dette er tilfældet, bedes Ordregiver redegøre for: Hvilket kontraktgrundlag regulerer Parternes rettigheder og forpligtelser under afklaringsfasen. Hvordan Ordregiver har vurderet denne model i forhold til almindelig udbuds- og kontraktpraksis, hvor kontrakten typisk indgås forud for projektets opstart. Hvilke konsekvenser det har, hvis Parterne ikke kan opnå enighed om de forhold, der afklares i afklaringsfasen, herunder om Ordregiver i så fald kan vælge ikke at underskrive kontrakten, selv om leverandøren er blevet tildelt kontrakten efter gennemført udbud.
A8: 8 | B8: Option 5 – Databasedrift hos Statens IT Bilag 1 Kundens opgavebeskrivelse Punkt 7 Optioner Option 5 Databasedrift hos Statens IT Bilag 1.i Vederlag og betalingsplan Prissætning af optioner Bilag 1.l Statens IT's driftsmodeller Bilag 1.h Servicemål (hvis optionen aktiveres) | C8: Tieto | D8: Det fremgår af Option 5, at Ordregiver ønsker mulighed for at overdrage ansvaret for drift og vedligeholdelse af ESDH-løsningens database (middleware) til Leverandøren i Ordregivers miljø hos Statens IT. Ordregiver bedes oplyse, om Statens IT har bekræftet, at den beskrevne driftsmodel er teknisk, kontraktuelt og driftsmæssigt mulig inden for Statens IT's gældende driftsmodeller og rammevilkår. Såfremt dette er tilfældet, bedes Ordregiver oplyse, om den nødvendige afklaring og accept fra Statens IT allerede foreligger, eller om dette først skal ske i forbindelse med en eventuel aktivering af optionen. Baggrunden for spørgsmålet er, at optionens gennemførlighed afhænger af Statens IT's rammer og godkendelser. | E8: 46227 | F8: Ordregiver præciserer, at Option 5 fortsat vil høre under Driftsmodel 3 (DM3 – Infrastrukturservice) hos Statens It, hvor Leverandøren vil få overdraget ansvaret for drift og vedligeholdelse fra Kunden af middleware, herunder vedligeholdelse, overvågning og øvrige driftsrelaterede aktiviteter. Tilbudsgiver skal prissætte de konsulentydelser, der vurderes nødvendige for at varetage dette ansvar, som en månedlig ydelse. Prissætningen skal således afspejle den indsats og de ressourcer, som Tilbudsgiver forventer at skulle anvende for at opfylde de opgaver og det ansvar, som beskrevet i Option 5. Driftspersonalet vil konkret være tilknyttet Kunden på konsulentbasis og her varetage drift og vedligehold af middleware for Kunden. Konsulentydelserne skal leveres i overensstemmelse med Statens It’s gældende regler og principper for konsulentanvendelse i produktionsmiljøer samt MK-10 fra Bilag 1.b Krav til IT- og informationssikkerhed, herunder krav til sikkerhedsgodkendelser mv. Ordregiver præciserer endvidere, at Driftsmodel 3 (DM3 – Infrastrukturservice), hvor Leverandøren er ansvarlig for drift og vedligeholdelse af middleware, er teknisk, driftsmæssigt og kontraktuelt mulig inden for Statens It’s gældende driftsmodel og rammevilkår. Option 5 ændrer således ikke de overordnede driftsmæssige eller kontraktuelle rammer men omfatter alene ansvarsfordelingen for drift og vedligeholdelse af middleware. | G8: 46241 | H8: 26-A015
A9: 9 | B9: Erklæring om Ruslands-forordningen. | C9: Tieto | D9: Tilbudsgiver har bemærket, at erklæringen vedrørende Ruslands-forordningen tilsyneladende mangler i udbudsmaterialet. Har Ordregiver mulighed for at uploade denne? | E9: 46227 | F9: Ordregiver oplyser, at Tilbudsgiverne skal se bort fra henvisninger til Bilag 7 Ruslandsforordningen. Rusland-erklæringen skal således ikke indsendes i forbindelse med tilbudsafgivelsen, men indhentes af Ordregiver fra den vindende tilbudsgiver som led i Ordregivers dokumentationsindhentelse. | G9: 46241 | H9: 26-A014
A10: 10 | B10: Bilag 1.f | C10: Anton | D10: Det fremgår af Bilag 1.f, pkt. 12.1 og 12.2, at Driftsprøven først kan påbegyndes, når den fulde løsning er klar, herunder når både Proces- og regelstyringskomponenten samt Integrationsplatformen har gennemført og bestået deres respektive overtagelsesprøver. Samtidig fremgår det af Leveringskontrakten, at Ordregiver har adgang til at gøre misligholdelsesbeføjelser gældende ved væsentlige forsinkelser, herunder hvis leveringen overskrider de kontraktuelle frister. Ordregiver bedes derfor oplyse, hvordan denne afhængighed håndteres, hvis Proces- og regelstyringskomponenten og/eller Integrationsplatformen leveres af en anden leverandør, og en forsinkelse hos denne leverandør medfører, at Driftsprøven for ESDH-løsningen ikke kan påbegyndes eller afsluttes rettidigt. Bekræfter Ordregiver, at Leverandøren ikke kan ifalde bod, misligholdelsesansvar eller risikere ophævelse som følge af forsinkelser, der udelukkende skyldes manglende levering eller godkendelse af disse øvrige komponenter? | E10: 46227 | F10: Ordregiver bekræfter, at Leverandøren af ESDH-løsningen ikke kan ifalde bod, misligholdelsesansvar eller risikere ophævelse som følge af forsinkelser, der udelukkende skyldes manglende levering eller godkendelse af Proces- og regelstyringskomponenten og/eller Integrationsplatformen, hvis disse leveres af en anden leverandør, og en forsinkelse hos denne leverandør medfører, at Driftsprøven for ESDH-løsningen ikke kan påbegyndes eller afsluttes rettidigt. | G10: 46241 | H10: 26-A016
A11: 11 | B11: Bilag 1.f | C11: Tieto | D11: Det fremgår af Bilag 1.f, pkt. 12.1 og 12.2, at Driftsprøven for ESDH-løsningen først kan gennemføres, når den fulde løsning er klar, og når Overtagelsesprøven for både Proces- og regelstyringskomponenten og Integrationsplatformen er gennemført og godkendt. Ordregiver har i svar 26-A016 bekræftet, at Leverandøren af ESDH-løsningen ikke kan ifalde bod, misligholdelsesansvar eller risikere ophævelse som følge af forsinkelser, der udelukkende skyldes de øvrige komponenter. Tilbudsgiver bemærker imidlertid, at den kontraktuelle afslutning af prøveforløbet for ESDH-løsningen fortsat er gjort direkte afhængig af leverancer under andre anskaffelser og potentielt fra andre leverandører. Ordregiver bedes derfor redegøre for, hvilke overvejelser der ligger til grund for at gøre den endelige godkendelse af ESDH-løsningen afhængig af to leverancer, der ikke er omfattet af nærværende udbud. Ordregiver bedes samtidig præcisere, hvilke kontraktuelle og økonomiske konsekvenser denne afhængighed kan få for Leverandøren, ud over de forhold vedrørende bod, misligholdelsesansvar og ophævelse, som allerede er afklaret i svar 26-A016. | I11: Omformuleret ud fra tidligere besvarelser. Det er teknisk set lovligt at have udbud, der er afhængige af hinanden. Afhængigheden skal dog være sagligt begrundet, gennemsigtig og beskrives klart fra begyndelsen. Det er især vigtigt at skelne mellem: Delaftaler i samme udbud: Ordregiver kan fastsætte, at bestemte delaftaler skal tildeles samlet eller efter bestemte kombinationer. Reglerne for kombinationen skal fremgå af udbudsmaterialet og være objektive, proportionale og ikke-diskriminerende. Udbudslovens § 49 og vejledningen Separate udbud: Det skal fremgå, hvis udbud B afhænger af resultatet eller leverancen fra udbud A. Det bør også beskrives, hvad der sker, hvis udbud A ikke gennemføres, eller hvis en anden leverandør vinder. Værdiansættelse: Hvis udbuddene vedrører samme projekt eller behov, har tidsmæssig og indholdsmæssig sammenhæng eller skal anvendes sammen, skal kontrakternes værdi som udgangspunkt vurderes samlet. De må ikke opdeles for at undgå udbudsreglerne. Vejledningen, afsnit 4.5.1 Jo stærkere afhængigheden er, jo mere nærliggende kan det være at gennemføre ét udbud med flere delaftaler. En skjult eller upræcist beskrevet afhængighed kan skabe problemer efter ligebehandlings- og gennemsigtighedsprincippet.
A12: 12 | B12: Bilag 1.b | C12: Anton | D12: MK-189 fremstår selvmodsigende. Kravet angiver, at Leverandøren ved afslutningen af hypercare-perioden skal udarbejde en rapport, samtidig med at rapporten senest skal overleveres til Kunden ved afslutningen af hypercare-perioden. Leverandøren kan derfor ikke entydigt fastlægge den forventede leveranceproces. Vil Ordregiver præcisere, hvornår rapporten skal udarbejdes, og hvornår den skal afleveres til Kunden? | E12: 46227 | F12: Ordregiver præciserer følgende vedrørende MK-189: Leverandøren skal senest 5 arbejdsdage efter hypercareperiodens afslutning fremsende en rapport til Kunden, som beskriver status og håndtering af samtlige registrerede fejl. Kunden har herefter 5 arbejdsdage til at gennemgå og kommentere rapporten. Leverandøren skal inden for 3 arbejdsdage efter modtagelse af Kundens kommentarer indarbejde disse og fremsende den endelige rapport til godkendelse hos Kunden. | G12: 46241 | H12: 26-A017
A13: 13 | B13: Bilag 1.b | C13: Hans | D13: Ordregiver bedes præcisere, hvordan kravet om, at "Brugeren kan navigere og scrolle i dokument- og fillistevisninger, og at forhåndsvisningen automatisk opdateres og viser det Dokument/Fil, som Brugeren har navigeret til", skal forstås. Er det Ordregivers forventning, at forhåndsvisningen løbende skal skifte i takt med, at Brugeren scroller gennem listen, eller er kravet opfyldt, når forhåndsvisningen automatisk opdateres, efter at Brugeren har navigeret til og valgt et andet dokument eller en anden fil? Baggrunden for spørgsmålet er, at de to fortolkninger medfører forskellige krav til brugergrænsefladens adfærd, og en præcisering vil sikre en ensartet vurdering af tilbuddene. | I13: Udgår
A14: 14 | B14: MK-112 | C14: Konkurrent | D14: MK-112 angiver, at "ESDH-løsningens administratormodul skal understøtte fuld no-code funktionalitet". Tilbudsgiver er usikker på, hvordan Ordregiver afgrænser begrebet "fuld no-code funktionalitet". Vil Ordregiver præcisere, hvilke konkrete administrative opgaver eller konfigurationsaktiviteter der skal kunne gennemføres uden kode for at opfylde nærværende krav? | E14: - | F14: Ordregiver forstår ”fuld no code funktionalitet” i et administratormodul, som funktionalitet, der gør det muligt for administrator uden programmeringskendskab at konfigurere, tilpasse og udvide løsningen gennem visuelle værktøjer, drag-and-drop og konfigurationsindstillinger, uden at skulle skrive kode. Opgaver og konfigurationsaktiviteter, der skal kunne gennemføres for at opfylde nærværende krav indeholder, men er ikke begrænset til: • Oprettelse og vedligeholdelse af entiteter • Oprettelse og vedligeholdelse af værdilister • Oprettelse og vedligeholdelse af felter • Oprettelse og vedligeholdelse af ESDH-opsætninger fx journalplan, sagsnummerformat mv. • Oprettelse og vedligeholdelse af sags- og kontakttyper Dertil øvrige MK-krav omhandlende konfiguration. Ordregiver understreger, at fuld no code funktionalitet forudsætter, at der ikke er behov for udvikler-ressourcer. | G14: 46213 | H14: 26-A009
A15: 15 | B15: MK-110 | C15: Konkurrent | D15: MK-110 angiver, at "ESDH-løsningen skal understøtte Konfiguration via en fuldskærmsbaseret brugergrænseflade". Tilbudsgiver er usikker på, hvad Ordregiver nærmere forstår ved "fuldskærmsbaseret brugergrænseflade". Vil Ordregiver præcisere, hvilke konkrete egenskaber eller funktionelle behov der ligger til grund for dette krav, herunder om kravet vedrører brugeroplevelsen, den tekniske implementering eller andre forhold? | E15: - | F15: Kravet i MK-110 vedrører brugergrænsefladen til konfiguration af ESDH-løsningen. Med ”fuldskærmbaseret brugergrænseflade” forstås, at konfigurationsfunktionaliteten skal være tilgængelige via en konfigurationsgrænseflade, der udnytter den tilgængelige skærmplads hensigtsmæssigt, og som understøtter en effektiv og brugervenlig udførelse af konfigurationsarbejde ved at fokusere brugerens opmærksomhed på indholdet eller handlingen. Baggrunden for mindstekravet er en forventning om, at konfigurationsarbejde kan udføres i en sammenhængende brugergrænseflade, hvor information, indstillinger, konfigurationsfunktionalitet og andet præsenteres overskueligt. Mindre dialogbokse, pop up-vinduer eller tilsvarende brugergrænseflader med et begrænset arbejdsområde skal have en klar gem- eller exit-knap, så brugeren ikke kan minimere billedet uden aktivt at lukke eller udføre en handling for at vende tilbage. Ordregiver stiller ikke krav til en bestemt teknisk implementering, men alene krav om, at konfigurationsgrænsefladen understøtter en effektiv og overskuelig udførelse af konfigurationsopgaver ved hensigtsmæssig anvendelse af den tilgængelige skærmplads. | G15: 46213 | H15: 26-A007
A16: 16 | B16: MK-76 og MK-143 | C16: Konkurrent | D16: Ordregiver fastsætter i MK-76, at ESDH-løsningen skal kunne afvikles uden løsningsspecifikke plugins, mens Ordregiver samtidig i MK-143 stiller krav om integration til Microsoft Outlook via plugin. Tilbudsgiver har derfor vanskeligt ved at afgrænse, hvilke klientnære komponenter Ordregiver anser for acceptable. Vil Ordregiver præcisere forholdet mellem MK-76 og MK-143, herunder om kravet i MK-76 alene vedrører den primære ESDH-klient og således ikke udelukker klientnære komponenter eller plugins, hvor disse er nødvendige for integration med tredjepartsprodukter som Microsoft Outlook? | E16: - | F16: Ordregiver bekræfter, at MK-76 alene vedrører den primære ESDH-klients afvikling i en standardbrowser (Microsoft Edge eller Google Chrome). Mindstekravet om, at ESDH-løsningen skal kunne afvikles uden løsningsspecifikke plugins, gælder således alene den browserbaserede ESDH-klient, og dens anvendelse i de angivne browsere. MK-76 udelukker ikke anvendelse af andre klientnære komponenter eller plugins, hvor disse er nødvendige for at understøtte integration til tredjepartsprodukter. Dette omfatter eksempelvis det i MK-143 krævede Outlook-plugin, som skal muliggøre direkte journalisering af e-mails fra Outlook til ESDH-løsningen. MK-76 omhandler krav til afvikling af ESDH-klienten i browser, mens MK-143 omhandler integrationen mellem Outlook og ESDH-løsningen. Ordregiver anser derfor klientnære komponenter og plugins for acceptable, når disse understøtter nødvendige integration til tredjepartssystemer. | G16: 46213 | H16: 26-A006
A17: 17 | B17: MK-76 | C17: Konkurrent | D17: Ordregiver har i MK-76 fastsat som minimumskrav, at ESDH-løsningen skal være browserbaseret og kunne afvikles i Microsoft Edge eller Google Chrome uden løsningsspecifikke plugins. Tilbudsgiver bemærker, at browserbaseret brugergrænseflade ikke blev identificeret som et behov i den gennemførte markedsdialog. Tilbudsgiver bemærker derudover, at browserbaseret brugergrænseflade ikke fremgår som et arkitekturprincip i Ordregivers målarkitektur, hvor fokus derimod er på standardplatforme, åbne API'er, komponentbaseret arkitektur, konfiguration og leverandøruafhængighed. Tilbudsgiver bemærker endvidere, at brugergrænsefladen samtidig indgår som et selvstændigt kvalitativt evalueringsområde i EK-3, hvor Ordregiver bl.a. evaluerer anvendelighed, konfigurationsmuligheder og brugeroplevelse. Tilbudsgiver har derfor vanskeligt ved at se den saglige begrundelse for, at browserbaseret afvikling uden løsningsspecifikke plugins er gjort til et minimumskrav, når browserbaseret brugergrænseflade hverken indgik som et identificeret behov i markedsdialogen eller som et arkitekturprincip i målarkitekturen. Hvis Ordregiver vurderer, at browserbaseret afvikling uden løsningsspecifikke plugins er en ufravigelig forudsætning for kontraktens opfyldelse, anmodes Ordregiver om at redegøre for den konkrete saglige begrundelse herfor, herunder hvorfor dette behov først er introduceret i kravspecifikationen og ikke indgik i den gennemførte markedsdialog eller i Ordregivers beskrevne målarkitektur. Hvis ikke, opfordres Ordregiver til at ændre MK-76 til et K-krav, således at browserbaseret brugergrænseflade kan indgå som et kvalitetsparameter under evalueringen frem for som et adgangskrav. | E17: - | F17: Det er korrekt, at Ordregiver, ikke i markedsdialogen, eksplicit nævnte, et mindstekrav om en browserbaseret løsning uden løsningsspecifikke plug-ins. Markedsdialogen blev anvendt til at afsøge, hvilke løsninger der er tilgængelige på markedet, og hvilke funktionaliteter markedet kan tilbyde. Ordregiver har på den baggrund fundet et behov for at være specifik i, hvilken teknologi Ordregiver ønsker, fordi dette har betydning for drift, sikkerhed og økonomi på lang sigt. Den vedlagte arkitekturtegning er en high level tegning udarbejdet til at understøtte forståelsen af Ordregivers målarkitektur. Arkitekturtegningen er leverandør-agnostisk, og beskriver, hvad løsningen skal gøre, og hvilken organisering løsningen skal indgå i. Arkitekturtegningen skal ikke angive, hvordan brugergrænsefladen skal implementeres eller hvilken teknologi leverandøren skal bruge til at bygge løsningen. Mindstekravet om en browserbaseret brugergrænseflade er et implementeringskrav, der specificerer teknologiske valg, som Ordregiver ønsker. Ordregiver bemærker, at mindstekravet om en browserbaseret løsning ikke udelukker evalueringskrav om funktionalitet og konfigurationsmuligheder i brugergrænsefladen. Ordregiver henviser til, at mindstekravet handler om implementeringen af den teknologiske løsning. Mindstekravet om en browserbaseret brugergrænseflade er forankret i Ordregivers fokus på fremtidssikring af den tilbudte løsning, hvor Ordregiver ikke ønsker at påtage sig risikoen for en teknologisk forældet løsning indenfor en kort årrække. Ved at anvende browserbaseret teknologi, der er en åben standard, minimeres denne risiko for Ordregiver. Dertil har Ordregiver mange brugere, som vil skulle supporteres med installation og vedligeholdes af desktop-klienter, en opgave som Ordregiver ikke ønsker at påtage sig i driftsøjemed. | G17: 46213 | H17: 26-A005 | I17: Lyder som Ekegren - klassisk cBrain indsigelse, da deres løsning ikke er browser-baseret.
A18: 18 | B18: Bilag 1.b | C18: Konkurrent | D18: Tilbudsgiver bemærker, at Bilag 1.b (Krav til standardsoftware) indeholder ca. 190 minimumskrav (86%), mens alene en begrænset del af kravene indgår som K-krav eller evalueringskrav (14%). Konsekvensen af klassificeringen jf. Bilag 1.b pkt. 1.1 er, at tilbud, som ikke opfylder et enkelt minimumskrav, bliver ukonditionsmæssige og dermed ikke indgår i den efterfølgende konkurrence om pris og kvalitet. Ordregiver har valgt at gennemføre udbuddet som et miniudbud under SKI 02.06 kategori 2, hvor leveringskontrakten tildeles efter en konkurrence om den standardsoftware, der giver det bedste forhold mellem pris og kvalitet, herunder funktionalitet, implementering og brugsvilkår. Det følger hertil af Udbudslovens § 41, at de tekniske specifikationer skal give de økonomiske aktører lige adgang til udbudsproceduren og ikke må skabe uberettigede hindringer for konkurrencen, ligesom de tekniske specifikationer bl.a. kan fastlægges ved funktionskrav eller krav til funktionsdygtighed. Tilbudsgiver konstaterer samtidig, at en række minimumskrav vedrører de samme egenskaber ved standardsoftwaren, som Ordregiver efterfølgende har valgt at evaluere kvalitativt gennem evalueringskravene. Disse eksempler forekommer ikke enkeltstående, men illustrerer en gennemgående metode ved klassificeringen af minimumskrav i Bilag 1.b. Dette gælder eksempelvis: MK-74-MK-75 + MK-83-MK-88 sammenholdt med EK-3 (Brugergrænseflade), MK-106;109;114;115;119;121;124 sammenholdt med EK-5 (Administratormodul), MK-109;112;118;124 sammenholdt med EK-6 (Datamodel), MK-118 sammenholdt med EK-7 (Konfiguration af brugergrænseflade). Når Ordregiver vælger at klassificere et krav som minimumskrav, indebærer det samtidig, at Ordregiver har vurderet, at den pågældende egenskab er så væsentlig for kontraktens opfyldelse, at manglende opfyldelse skal medføre ukonditionsmæssighed og dermed udelukke tilbuddet fra den efterfølgende konkurrence. Tilbudsgiver har derfor vanskeligt ved at se den saglige begrundelse for, at en række tekniske specifikationer, som fastlægger bestemte tekniske egenskaber ved standardsoftwaren, er klassificeret som minimumskrav, når de samme tekniske egenskaber samtidig indgår i den kvalitative evaluering. Hvis Ordregiver vurderer, at ovennævnte tekniske specifikationer er så nødvendige for kontraktens opfyldelse, at manglende opfyldelse skal medføre ukonditionsmæssighed, anmodes Ordregiver om at redegøre for de objektive kriterier, der er anvendt ved denne klassificering. Hvis ikke, opfordres Ordregiver til at gennemgå klassificeringen af krav og ændre de minimumskrav, hvor den ønskede funktion eller kvalitet fortsat kan sikres gennem evaluering som K-krav, således at konkurrencen mellem standardsoftwareløsninger under SKI 02.06 kategori 2 styrkes uden at kompromittere Ordregivers funktionelle eller forretningsmæssige behov. | E18: - | F18: Ordregivers mindstekrav i udbudsmaterialet beskriver grundlæggende og væsentlig funktionalitet, som den tilbudte løsning som minimum skal kunne levere. Ordregiver har på baggrund af den gennemførte markedsdialog konstateret, at markedet tilbyder vidt forskellige løsninger, der kan opfylde Ordregivers minimum, og har derfor en legitim interesse i at differentiere mellem løsninger, som alle opfylder minimum, men som gør det i forskellig grad. På den baggrund har Ordregiver udvalgt særlige mindstekrav, der har særlig vigtig betydning for den forretningsmæssige systemunderstøttelse, brugervenlighed og fleksibilitet i løsningen. Disse mindstekrav indgår også som en del af evalueringskrav, hvor leverandør har mulighed for at eksemplificere, hvordan den efterspurgte funktionalitet implementeres i løsningen. Markedsvariationen betyder, at Ordregiver ikke kan nøjes med at fastlægge, hvorvidt en tilbudt løsning opfylder mindstekrav men tillige har behov for at forstå, hvordan udvalgte mindstekrav implementeres, og i hvor høj grad dette understøttes. Denne forståelse er vigtig for Ordregiver for at kunne vælge den rette løsning, der bedst opfylder Ordregivers behov og formål som beskrevet i udbudsmaterialet. Ordregiver har derfor behov for at kunne evaluere meropfyldelsen af udvalgte mindstekrav. Uden denne evaluering vil Ordregiver ikke have tilstrækkelig information til at træffe et kvalificeret valg mellem løsninger, der teknisk set opfylder mindstekravene, men som implementerer dem på meget forskellige niveauer af fleksibilitet og brugervenlighed. Evalueringen af meropfyldelsen af udvalgte mindstekrav vil ske ud fra en nærmere beskrevet evalueringsmodel. Dette indebærer, at der evalueres på, hvordan og i hvor høj grad de udvalgte mindstekrav implementeres i den tilbudte løsning. Evalueringskravene bedømmer alene graden af fleksibilitet, modenhed og konfigurerbarhed udover minimum på de udvalgte mindstekrav. Ordregiver mener, det er tydeliggjort i udbudsmaterialet, hvornår Ordregiver ønsker en uddybelse af implementeringen af et udvalgt mindstekrav. Dette er gjort ved at indarbejde meropfyldelsen i evalueringskravenes vægtninger. Det er eksempelvis angivet, at leverandør skal beskrive hvordan en bruger kan personalisere visningsbilleder samt hvad der vægtes positivt i forbindelse med evalueringen af denne beskrivelse. Ordregiver fastholder således, at mindstekrav skal opfyldes, og at der herudover skal evalueres på meropfyldelsen af udvalgte mindstekrav, og tilbudsgivere kan således forberede sig på at give en grundig besvarelse. | G18: 46213 | H18: 26-A004 | I18: Lyder som Ekegren - cBrain er enige i, at det ikke er en fair konkurrence.
A19: 19 | B19: Bilag 1h, pkt. 2.3 Tilgængelighed | C19: Tieto | D19: Bilag 1h, pkt. 2.3 Tilgængelighed Tilbudsgiver bemærker, at bilaget ikke definerer, hvilke typer af hændelser der skal anses for at udgøre utilgængelighed ved beregningen af servicemålet for tilgængelighed. Kan Kunden bekræfte, at det alene er Prioritet 1-/kritiske hændelser, som medfører, at produktionsmiljøet er utilgængeligt for brugerne, der indgår i beregningen af tilgængeligheden, mens hændelser i de øvrige prioritetskategorier alene følges op via de aftalte reaktionstider og derfor ikke påvirker servicemålet for tilgængelighed? | E19: 46230 | F19: Ordregiver præciserer, at beregningen af tilgængeligheden omfatter samtlige incidents, der medfører utilgængelighed af produktionsmiljøet for brugerne, uanset hvilken prioritet det pågældende incident er klassificeret med. | G19: 46241 | H19: 26-A018
A20: 20 | B20: Bilag 1h, pkt. 2.7 Servicemål | C20: Tieto | D20: Bilag 1h, pkt. 2.7 Servicemål Tilbudsgiver bemærker, at definitionerne af "Reaktionstid" i henholdsvis pkt. 2.5 og pkt. 2.7 ikke fremstår fuldt ud konsistente. Pkt. 2.5 angiver, at reaktionstiden er den tid, inden for hvilken Tilbudsgiver senest skal have påbegyndt afhjælpning af hændelsen, mens pkt. 2.7 angiver, at reaktionstiden måles fra registreringen af hændelsen, til løsning eller afhjælpning påbegyndes hos Tilbudsgiver. Kan Kunden bekræfte, at reaktionstid skal forstås som tiden fra registrering af en hændelse i servicemanagementsystemet, til Tilbudsgiver har påbegyndt afhjælpning eller fejlretning af hændelsen, og at formuleringen i pkt. 2.5, hvor reaktionstid angives at blive målt frem til løsning eller nedgradering af hændelsen, i stedet vedrører afhjælpnings- eller løsningstid og ikke reaktionstid? | E20: 46230 | F20: Ordregiver præciserer, at reaktionstid skal forstås som tiden fra registrering af et incident i servicemanagement-systemet til Leverandøren har påbegyndt afhjælpning eller fejlretning af hændelsen. I forlængelse heraf bekræfter Ordregiver, at formuleringen i pkt. 2.5, hvor reaktionstid angives at blive målt frem til løsning eller nedgradering af hændelsen, skal forstås som afhjælpnings-/løsningstid fremfor reaktionstid. | G20: 46241 | H20: 26-A019
A21: 21 | B21: Bilag 1h, pkt. 2.7 Servicemål | C21: Tieto | D21: Bilag 1h, pkt. 2.7 Servicemål Tilbudsgiver bemærker, at reaktionstiden for Prioritet 2 udtrykkeligt er angivet til at gælde inden for den aftalte driftstid, mens en tilsvarende præcisering ikke fremgår for Prioritet 1. Samtidig fremgår det, at Kunden skal kunne kontakte Tilbudsgiver uden for normal driftstid ved kritiske hændelser, og at Tilbudsgiver skal arbejde uafbrudt på løsning af Prioritet 1-hændelser, også uden for den aftalte driftstid. Kan Kunden præcisere, om reaktionstiden for Prioritet 1 ("omgående og mindre end 2 timer") også gælder uden for den aftalte driftstid? Såfremt Prioritet 1-hændelser skal håndteres med krav om bemanding, reaktionstid eller påbegyndt afhjælpning uden for den aftalte driftstid, bedes Kunden samtidig præcisere, om sådanne ydelser er omfattet af det faste aftalevederlag, eller om de kan bestilles og afregnes efter Tilbudsgivers til enhver tid gældende priser for arbejde uden for normal driftstid. | E21: 46230 | F21: Ordregiver præciserer, at reaktionstiden for Prioritet 1 ("omgående og mindre end 2 timer") også gælder uden for den aftalte driftstid, og at sådanne ydelser er omfattet af det faste månedlige vederlag for Kundens brug af Leverandørens ESDH-løsning samt Leverandørens løbende support og vedligeholdelse af ESDH-løsningen. | G21: 46241 | H21: 26-A020
A22: 22 | B22: Bilag 1h, pkt. 2.5 | C22: Tieto | D22: Bilag 1h, pkt. 2.5 Tilbudsgiver bemærker, at begrebet "Servicetid" anvendes i pkt. 2.5, mens alene "Driftstid" er defineret i bilaget. Kan Kunden bekræfte, at "Servicetid" i pkt. 2.5 skal forstås som den aftalte driftstid i pkt. 2.2 (kl. 08.00-16.00 på hverdage)? | E22: 46230 | F22: Ordregiver præciserer, at termen "Servicetid" anvendt i pkt. 2.5 Servicemål for support ved incidents i ESDH-løsningen i bilag 1.h Servicemål skal forstås som den aftalte driftstid (kl. 08.00-16.00 på hverdage) anført under pkt. 2.2 Driftstid i samme bilag. | G22: 46241 | H22: 26-A021
A23: 23 | B23: Leveringskontrakt, pkt. 16.3.2 Bod ved mangler | C23: Tieto | D23: Det fremgår, at den maksimale bod for mangler udgør 5 % af Leveringsaftalens evalueringstekniske pris. Da manglerne vedrører levering af support og vedligeholdelse, vurderer Tilbudsgiver, at en eventuel bod bør beregnes på baggrund af det månedlige vederlag for den berørte tjeneste. Kan Kunden bekræfte, at den maksimale bod efter denne bestemmelse i stedet skal beregnes på grundlag af det månedlige vederlag, jf. Bilag 1.i Vederlag og betalingsplan, pkt. 2.2 Månedligt vederlag? | E23: 46230
A24: 24 | B24: Bilag 1 | C24: Cristina | D24: Er det korrekt forstået, at Ordregiver ikke ønsker, at der indgives en tidsplan i forbindelse med udbuddet, men at der i stedet skal laves en detaljeret tidsplan i Afklaringsfasen på baggrund af den i Bilag 1 - Kundens opgavebeskrivelse? | E24: 46231 | F24: Ordregiver bekræfter, at der ikke skal indgives en detaljeret tidsplan som en del af tilbuddet. Den detaljerede tidsplan udarbejdes i samarbejde mellem Leverandøren og Kunden i afklaringsfasen med udgangspunkt i Bilag 1. Kundens opgavebeskrivelse. Tidsplanen skal udarbejdes i overensstemmelse med de krav, der fremgår af materialet. Leverandøren skal overholde de tidsangivende perioder angivet under punkt 4.1 Faser i tidsplanen i Bilag 1 Kundens opgavebeskrivelse. Der er tale om kritiske milepæle for idriftsættelsen af den samlede løsning senest pr. 1. oktober 2027. Faserne skal indgå som milepæle i den detaljerede tidsplan. | G24: 46241 | H24: 26-A023
A25: 25 | B25: Bilag 1.j | C25: Cristina | D25: Spørgsmål vedrørende Bilag 1.j Tilbudsgiver forstår Bilag 1.j således, at Leverandøren ikke er berettiget til særskilt vederlag for behandling af en ændringsanmodning og udarbejdelse af løsningsforslaget, men at Leverandøren er berettiget til vederlag for selve gennemførelsen af en ændring, når løsningsforslaget og de tilhørende vederlagsmæssige konsekvenser er godkendt af Kunden. Kan Ordregiver bekræfte, at denne forståelse er korrekt? | I25: Omformuleret.
A26: 26 | B26: Bilag 1.g | C26: Cristina | D26: I pkt. 4.4.3 fremgår det under bemanding alene, at "Leverandøren" deltager i driftsgruppen. Kan Kunden præcisere, hvilke roller hos Tilbudsgiver der forventes at deltage i driftsgruppen og de ugentlige driftsmøder? | I26: Udgår
A27: 27 | B27: Bilag 1.g | C27: Cristina | D27: Bilaget angiver indledningsvist, at Tilbudsgiver ikke har krav på særskilt vederlag for aktiviteter omfattet af bilaget. Er det korrekt forstået, at samtlige roller og aktiviteter, der er beskrevet i Bilag 1.g, herunder deltagelse i styregrupper, driftsmøder, projektledelse, Service Delivery Manager, leveringskontraktansvarlig og øvrige møde- og samarbejdsaktiviteter, anses for omfattet af Leveringskontraktens faste vederlag? Tilbudsgiver bemærker, at en sådan forståelse vil medføre, at omkostningerne nødvendigvis må indregnes i andre vederlagsposter, hvilket reducerer prisgennemsigtigheden for Kunden. | E27: 46239 | I27: send
A28: 28 | B28: Bilag 1.g | C28: Cristina | D28: Tilbudsgiver bemærker, at rollen som projektleder alene er beskrevet i implementeringsfasen, mens projektlederen ikke indgår blandt de beskrevne roller i driftsfasen. Kan Kunden bekræfte, at dette er tilsigtet, og at Tilbudsgiver ikke forventes at stille en dedikeret projektleder til rådighed efter afsluttet implementering? | I28: Jeg tror, at de i virkeligheden mener, at det er Service Delivery Manageren, der har hvad vi plejer at kalde en projektleder.
A29: 29 | B29: punkt 5 i Leveringsaftalen – Immaterielle rettigheder | C29: Mandip | D29: Spørgsmål vedrørende punkt 5 i Leveringskontrakten – Immaterielle rettigheder Punkt 5 fastslår, at Kundens erhvervelse af immaterielle rettigheder til standardsoftware sker i henhold til Standardvilkårene. Immaterielle rettigheder til standardsoftware udgør en central del af en leverandørs forretningsgrundlag og er en forudsætning for løbende vedligeholdelse, videreudvikling og support af softwaren. Kan Ordregiveren bekræfte, at ejendomsretten til standardsoftware, herunder underliggende kildekode, algoritmer og platformskomponenter, forbliver hos Leverandøren eller relevante tredjepartslicensgivere, og at Kunden opnår en ikke-eksklusiv brugsret i overensstemmelse med de gældende licensvilkår? Tilbudsgiveren foreslår, at sondringen mellem standardsoftware og kundespecifikke leverancer præciseres i aftalen. | E29: 46239 | I29: send
A30: 30 | B30: punkt 10 i Leveringsaftalen – Fortrolighed og tavshedserklæringer | C30: Mandip | D30: Spørgsmål vedrørende punkt 10 i Leveringskontrakten – Fortrolighed og tavshedserklæringer Punkt 10.2 kræver, at hver enkelt af Leverandørens og underleverantørers medarbejdere udfylder og underskriver en individuel tavshedserklæring til Kunden. Ved større leverancer kan kravet blive betydeligt, da det omfatter samtlige medarbejdere, herunder også medarbejdere uden adgang til fortrolige oplysninger. Kan Ordregiveren oplyse, om det kan accepteres, at Leverandøren i stedet sikrer tilstrækkelige fortrolighedsforpligtelser via eksisterende ansættelses- og underleverandøraftaler? Tilbudsgiveren foreslår, at individuelle tavshedserklæringer alene kræves for konkrete nøglepersoner, som parterne skriftligt udpeger. | E30: 46239
A31: 31 | B31: punkt 11 i Leveringsaftalen – Sikkerhedsgodkendelse af personale | C31: Mandip | D31: Spørgsmål vedrørende punkt 11 i Leveringsaftalen – Sikkerhedsgodkendelse af personale Punkt 11 kræver, at samtlige medarbejdere hos Leverandøren og underleverantørerne, der bistår med levering af ydelser, skal sikkerhedsgodkendes. Sikkerhedsgodkendelse kan være forbundet med væsentlige omkostninger og tidsmæssige forudsætninger for Leverandøren, og det er derfor centralt, at det relevante sikkerhedsniveau er klarlagt inden kontraktindgåelse. Kan Ordregiveren oplyse, hvilket sikkerhedsniveau (Fortroligt eller Hemmeligt) der kræves, og om kravet kan begrænses til de medarbejdere, der faktisk får adgang til klassificerede oplysninger eller systemer? Tilbudsgiveren foreslår, at parterne inden kontraktindgåelse i fællesskab afstemmer, hvilke roller og sikkerhedsniveauer der er relevante, og at dette anføres i et bilag. | I31: Udgår
A32: 32 | B32: punkt 12.1 i Leveringsaftalen – Leverandørskifte og solidarisk ansvar | C32: Mandip | D32: Spørgsmål vedrørende punkt 12.1 i Leveringsaftalen – Leverandørskifte og solidarisk ansvar Punkt 12.1 indebærer, at Leverandøren og en ny leverandør solidarisk skal friholde Kunden for tab ved overdragelse. En leverandør kan alene påtage sig ansvar for egne ydelser og egen opfyldelse af kontraktens krav, men kan ikke hæfte for en ny leverandørs handlinger, som den aftrædende leverandør ikke har indflydelse på. Kan Ordregiveren tage stilling til, om Leverandøren i stedet alene hæfter for egne leveranceforpligtelser og for, at kontraktens krav fortsat er opfyldt frem til overgangsperiodens afslutning, og om hver part afholder egne omkostninger? | I32: afventer - snak med Mandip.
A33: 33 | B33: punkt 12.2 i Leveringsaftalen – Ny myndighed som ordregiver | C33: Mandip | D33: Spørgsmål vedrørende punkt 12.2 i Leveringsaftalen – Ny myndighed som ordregiver Punkt 12.2 giver mulighed for, at andre myndigheder overtager aftalen ved organisatoriske ændringer, uden at der stilles krav om forudgående underretning til Leverandøren. Kan Ordregiveren oplyse, om Leverandøren vil blive underrettet skriftligt inden en overtagelse? Tilbudsgiveren foreslår, at overtagelse forudsætter skriftligt varsel på mindst [30] dage, og at der gennemføres en ændringsproces, såfremt overtagelsen medfører ændrede krav til f.eks. sikkerhedsgodkendelsesniveau eller leverancens omfang. | I33: overload
A34: 34 | B34: punkt 13.3 i Leveringsaftalen – Opsigelse som følge af klage | C34: Mandip | D34: Spørgsmål vedrørende punkt 13.3 i Leveringsaftalen – Opsigelse som følge af klage Punkt 13.3 giver Kunden ret til at opsige aftalen med 30 dages varsel, hvis tildelingsbeslutningen annulleres, "uanset om afgørelsen er endelig". Af hensyn til proportionalitet, objektivitet og gennemsigtighed for begge parter bør en så vidtgående beføjelse som opsigelse være knyttet til et objektivt og endeligt grundlag. Kan Ordregiveren bekræfte, at opsigelsesretten først aktualiseres ved en endelig afgørelse? Tilbudsgiveren foreslår desuden, at opsigelsesvarslet forlænges til [90] dage for at sikre en ordnet overgang for begge parter. | I34: overload
A35: 35 | B35: punkt 13.4 i Leveringsaftalen – Opsigelse ved uden virkning og påbud | C35: Mandip | D35: Spørgsmål vedrørende punkt 13.4 i Leveringsaftalen – Opsigelse ved uden virkning og påbud Punkt 13.4 giver Kunden ret til at videreføre yderligere betingelser eller krav fra et påbud over for Leverandøren, som Leverandøren er forpligtet til at efterleve. Kan Ordregiveren bekræfte, at sådanne yderligere vilkår håndteres som ændringer i overensstemmelse med aftalens ændringsbestemmelser, og at Leverandøren har ret til kompensation for dokumenterede meromkostninger? | I35: overload
A36: 36 | B36: punkt 13.5 i Leveringsaftalen – Opsigelse i særlige tilfælde og vederlag | C36: Mandip | D36: Spørgsmål vedrørende punkt 13.5 i Leveringsaftalen – Opsigelse i særlige tilfælde og vederlag Punkt 13.5 giver Kunden ret til at opsige aftalen uden varsel i visse tilfælde og fastslår, at Leverandøren "ikke er berettiget til nogen anden form for godtgørelse eller erstatning, herunder erstatning for driftstab, avancetab eller andet indirekte tab, øvrigt vederlag eller lignende". Formuleringen er bred, og det er uklart, om den også afskærer Leverandørens ret til vederlag for allerede udført arbejde og leverede ydelser. Kan Ordregiveren bekræfte, at Leverandøren ved opsigelse i medfør af denne bestemmelse bevarer retten til fuldt vederlag for arbejde udført og ydelser leveret frem til opsigelsestidspunktet? | I36: overload
A37: 37 | B37: punkt 15 i Leveringsaftalen – Ansvar for krænkelse af immaterielle rettigheder | C37: Mandip | D37: Spørgsmål vedrørende punkt 15 i Leveringskontrakten – Ansvar for krænkelse af immaterielle rettigheder Punkt 15 pålægger Leverandøren at friholde Kunden for ethvert krav fra tredjemand vedrørende krænkelse af rettigheder, uden sædvanlige undtagelser. Kan Ordregiveren bekræfte, at friholdelsespligten betinges af (i) rettidig skriftlig underretning fra Kunden, (ii) at Leverandøren gives kontrol over forsvaret, og at der indføres undtagelser for krænkelser forårsaget af Kundens ændringer, kombination med ikke-godkendte tredjepartsprodukter eller brug i strid med Leverandørens anvisninger? | E37: 46239
A38: 38 | B38: punkt 16.2.1.2 i Leveringsaftalen – Prisnedslag og bod | C38: Mandip | D38: Spørgsmål vedrørende punkt 16.2.1.2 i Leveringskontrakten – Prisnedslag og bod Punkt 16.2.1.2 vedrører forholdsmæssigt afslag som misligholdelsesbeføjelse. Kan Ordregiveren bekræfte, at prisnedslag (forholdsmæssigt afslag) og bod ikke kan pålægges parallelt for det samme kontraktbrud? | E38: 46239
A39: 39 | B39: punkt 16.3 i Leveringsaftalen – Bod: definition og beregning | C39: Mandip | D39: Spørgsmål vedrørende punkt 16.3 i Leveringsaftalen – Bod: definition og beregning Punkt 16.3 fastsætter et samlet bod-loft på 10 % af Leveringskontraktens evalueringstekniske pris. Af proportionalitetshensyn bør bod for en given misligholdelse stå i et rimeligt forhold til den berørte dels værdi og ikke beregnes på grundlag af hele kontraktens værdi. Tilbudsgiveren anmoder Ordregiveren om at afklare følgende: (a) Kan forsinkelsesbodens beregning (punkt 16.3.1) begrænses til den forsinkede dels forholdsmæssige kontraktværdi? (b) Kan opsigelsesretten ved forsinkelse knyttes til bod-loftet (50 dages forsinkelse) i stedet for den faste frist på 30 dage i punkt 16.1? (c) Kan beregningsgrundlaget for bod ved SLA-overtrædelser (punkt 16.3.2) præciseres som det månedlige vederlag for support og vedligeholdelse? | I39: afventer/overload spørgsmål c udgår fordi det allerede er besvaret.
A40: 40 | B40: punkt 16.4.1 i Leveringsaftalen – Erstatningsloft og modregning | C40: Mandip | D40: Spørgsmål vedrørende punkt 16.4.1 i Leveringskontrakten – Erstatningsloft og modregning Punkt 16.4.1 fastsætter et erstatningsloft på 100 % af den evalueringstekniske pris, men undtager bl.a. tab som følge af krænkelse af tredjemands rettigheder (punkt 15) og overtrædelse af persondataregler (punkt 4). Erstatningsloftet bør stå i et rimeligt og proportionalt forhold til kontraktens værdi. Tilbudsgiveren foreslår, at erstatningsloftet fastsættes til 50 % af det årlige vederlag for den berørte del af leverancen. Påløben bod og forholdsmæssigt afslag (prisnedslag) bør afregnes mod erstatningsloftet, således at Leverandørens samlede ansvar i form af bod, prisnedslag og erstatning tilsammen ikke overskrider loftet. For så vidt angår det ubegrænsede ansvar for overtrædelse af persondataregler: en ubegrænset kontraktuel eksponering for databeskyttelsesretlige krav er ikke proportional med det underliggende kontraktforhold. Leverandøren er allerede underlagt Datatilsynets selvstændige håndhævelse og eventuelle bødepåbud i medfør af databeskyttelsesforordningens artikel 82 og 83, hvilket i sig selv udgør en betydelig sanktionsrisiko uden for kontrakten. En yderligere ubegrænset kontraktuel eksponering er på denne baggrund ikke nødvendig for at sikre Kundens interesser. Det er endvidere ikke muligt for Leverandøren at forsikre sig fuldt ud mod et sådant ansvar, da markedet for cyberansvarsforsikring opererer med definerede dækningslofter. Tilbudsgiveren anmoder Ordregiveren om at bekræfte, at erstatningsloftet også finder anvendelse på krav, der udspringer af Leverandørens manglende overholdelse af databeskyttelseslovgivningen, dog med undtagelse af tilfælde, der kan henføres til grov uagtsomhed eller forsætlige forhold hos Leverandøren. | E40: 46239
A41: 41 | B41: punkt 19 i Leveringsaftalen – Tredjepartsvilkår | C41: Mandip | D41: Spørgsmål vedrørende punkt 19 i Leveringsaftalen – Tredjepartsvilkår Punkt 19 fastslår, at Standardvilkårene udgør en integreret del af Leveringskontrakten, og pålægger Leverandøren at skadesløsholde Kunden for krav fra Producenten eller andre, der støttes på Standardvilkårene. Tredjepartsvilkår må nødvendigvis gælde for tredjepartssoftware — særligt når aftaleforholdet består direkte mellem Kunden og licensgiveren. Et skadesløsholdelsesansvar for Leverandøren i dette tilfælde er ikke proportionalt, da Leverandøren hverken er part i aftaleforholdet mellem Kunden og licensgiveren eller har mulighed for at kontrollere Kundens faktiske anvendelse af softwaren. Leverandørens rolle er at gøre de relevante vilkår tilgængelige for Kunden og orientere om ændringer, men ansvaret for efterlevelse må påhvile den part, der anvender softwaren. Kan Ordregiveren bekræfte, at skadesløsholdelsesforpligtelsen i punkt 19 ikke finder anvendelse, og at Kunden selv bærer ansvaret for overholdelse af de gældende tredjepartsvilkår? | I41: overload
A42: 42 | B42: 1.e-K-1 | C42: Mandip | D42: Teknisk umuligt certificeringskrav (1.e-K-1) 1.e-K-1 stiller krav om, at tilbudsgiver er "certificeret ISO/IEC 27001:2022 og 27002:2022". ISO/IEC 27002:2022 er en vejledningsstandard (code of practice) for informationssikkerhedskontroller og er ikke genstand for certificering. Der eksisterer intet akkrediteret certificeringsskema for ISO 27002. Kravet er som formuleret teknisk umuligt at opfylde for enhver tilbudsgiver, uanset dennes kompetencer eller sikkerhedsniveau. Kravet overlapper desuden med 1.e-K-5, der selvstændigt kræver ISO 27001-certificering. Et krav, der ikke kan opfyldes af nogen tilbudsgiver, er uforeneligt med gennemsigtighedsprincippet og ligebehandlingsprincippet i udbudslovens § 2 og direktiv 2014/24/EU art. 18. Tilbudsgiver anmoder om berigtigelse, således at referencen til ISO/IEC 27002:2022-certificering udgår af 1.e-K-1, og at kravet præciseres til alene at vedrøre ISO/IEC 27001:2022-certificering, som er det eneste certificerbare element. | I42: overload
A43: 43 | B43: 1.b-MK-11 og 1.b-MK-161 | C43: Mandip | D43: Spørgsmål vedrørende MK-11 og MK-161, produktspecifikke referencer MK-11 henviser til "Dynamic Template", og MK-161 henviser specifikt til "Dynamics Template fra Omnidocs". Der er således i ufravigelige mindstekrav anvendt betegnelser for en konkret kommerciel løsning. Tilbudsgiver bemærker, at tekniske specifikationer efter udbudsreglerne som udgangspunkt skal udformes på en måde, der giver økonomiske aktører lige adgang til udbuddet og ikke skaber uberettigede hindringer for konkurrencen. Henvisninger til et bestemt fabrikat, produkt eller oprindelse kræver derfor særlig opmærksomhed på muligheden for at tilbyde tilsvarende løsninger. Tilbudsgiver er opmærksom på den generelle angivelse i Opfordringsskrivelsen om, at fabrikatshenvisninger skal læses med "eller tilsvarende". Det fremgår imidlertid ikke tilstrækkeligt klart af MK-11 og MK-161, hvilke funktionelle egenskaber ved Dynamic Template/Omnidocs der konkret skal opfyldes, for at en anden løsning kan anses for tilsvarende. Ordregiver bedes derfor præcisere udtømmende, hvilke funktionelle og tekniske egenskaber der skal være opfyldt, for at en alternativ løsning kan anses for "tilsvarende" efter MK-11 og MK-161. Tilbudsgiver bedes endvidere få bekræftet, at opfyldelse af disse objektivt beskrevne egenskaber er tilstrækkelig til at opfylde mindstekravene, og at anvendelse af selve Dynamic Template/Omnidocs-produktet ikke er påkrævet. Såfremt Ordregiver ikke kan opstille sådanne produktneutrale kriterier, bedes Ordregiver overveje at omformulere kravene som funktionsbaserede krav uden henvisning til et konkret produkt. | I43: Omformuleret.
A44: 44 | B44: Bilag 1.h | C44: Mandip | D44: Brudte krydshenvisninger i bodsgrundlaget (Bilag 1.h) Bodsbestemmelserne i Bilag 1.h, punkt 3, indeholder ved beregningen af bodspoint for henholdsvis tilgængelighed, svartider og API-svartider henvisninger markeret "Fejl! Henvisningskilde ikke fundet.". De relevante afsnit, der definerer, hvornår bod udløses, kan dermed ikke identificeres entydigt. Bilag 1.h indeholder i alt 11 forekomster af brudte henvisninger, og det samme gælder Leveringskontrakten (32 steder) og Bilag 4 (3 steder). Bod er en væsentlig kontraktuel sanktionsmekanisme. At det ikke fremgår klart af udbudsmaterialet, hvornår bod udløses og på hvilken beregningsmetode, er uforeneligt med gennemsigtighedsprincippet i udbudslovens § 2, stk. 1, og forhindrer tilbudsgivere i at prissætte kontraktrisikoen korrekt. Klagenævnet for Udbud har i fast praksis understreget, at grundlaget for kontraktuelle sanktioner skal fremgå klart og utvetydigt af udbudsmaterialet. Tilbudsgiver anmoder om berigtigelse, således at samtlige brudte henvisninger erstattes af korrekte afsnitshenvisninger, og at Ordregiver bekræfter, hvilke konkrete bestemmelser der er tiltænkt henvist til i hvert enkelt tilfælde. | E44: 46239
A45: 45 | B45: 1.b-MK-187 og 1.b-MK-188 | C45: Mandip | D45: Intern modstrid om hypercare-periode (1.b-MK-187 og 1.b-MK-188) 1.b-MK-187 fastsætter hypercare-perioden til 10 arbejdsdage. 1.b-MK-188 forudsætter imidlertid, at forlængelse sker "ved udløb af de 5 Dage", hvilket er uforeneligt med MK-187's 10-dages periode. De to ufravigelige mindstekrav er dermed indbyrdes modstridende. Modstriden gør det umuligt for tilbudsgiver at forstå kontraktens reelle krav til hypercare og dermed at prissætte ydelsen korrekt. Dette er uforeneligt med gennemsigtighedsprincippet i udbudslovens § 2, stk. 1. Tilbudsgiver anmoder om berigtigelse, således at den korrekte hypercare-periode fremgår entydigt og konsistent af begge bestemmelser, og at det præciseres, under hvilke betingelser en forlængelse udløses. | I45: overload
A46: 46 | B46: 1.e-MK-10 | C46: Mandip | D46: Afbrudt og ufuldstændig sætning (1.e-MK-10) 1.e-MK-10 indeholder en sætning, der fremstår afbrudt og ufuldendt: "Ved drift skal det gå gennem Statens IT leverandøradgang. adgang til UIM's infrastruktur." Det er uklart, hvad kravet præcist forpligter tilbudsgiver til. Et ufravigeligt mindstekrav, hvis indhold ikke kan fastlægges entydigt, opfylder ikke kravene til gennemsigtighed i udbudslovens § 2, stk. 1, og giver tilbudsgiver utilstrækkelig information til at vurdere og prissætte opfyldelse af kravet. Tilbudsgiver anmoder om berigtigelse, således at 1.e-MK-10 omformuleres til en klar og fuldstændig sætning, der entydigt beskriver, hvad kravet indebærer. | I46: overload
A47: 47 | B47: 1.b-MK-118 | C47: Mandip | D47: Definition af "HELE brugergrænsefladen" (1.b-MK-118) 1.b-MK-118 stiller som ufravigeligt mindstekrav krav om, at administrator kan konfigurere "HELE brugergrænsefladen". Begrebet "brugergrænsefladen" er hverken defineret i Bilag 0 (Definitionsliste) eller i udbudsmaterialet i øvrigt, og det fremgår ikke af kravet, hvad der nærmere forstås ved "HELE" brugergrænsefladen, herunder hvilke konkrete elementer, lag eller funktioner der er omfattet. For at tilbudsgiver kan vurdere og prissætte opfyldelsen af kravet, anmodes Ordregiver om at besvare følgende: (i) hvilke konkrete elementer i brugergrænsefladen der er omfattet af kravet, herunder om det vedrører layout, felter, faneblade, menuer, ikoner, sprogelementer, rettigheds- og rollestyring eller andet, (ii) om kravet omfatter elementer, der er faste i standardsoftwarens kernearkitektur og ikke normalt eksponeres for administratorkonfiguration, og (iii) om begrebet "HELE" skal forstås bogstaveligt som samtlige elementer i brugergrænsefladen, eller om der er elementer, som Ordregiver ikke forventer konfigureret. Tilbudsgiver bemærker, at en entydig besvarelse er nødvendig for at afgive et konditionsmæssigt tilbud, jf. gennemsigtighedsprincippet i udbudslovens § 2, stk. 1. | E47: 46239
A48: 48 | B48: Bilag 1.b | C48: Mandip | D48: Mindstekrav med multiple selvstændige delkrav (dobbeltkrav) Tilbudsgiver har ved gennemgang af udbudsmaterialet konstateret, at et betydeligt antal mindstekrav (MK) i Bilag 1.b indeholder to eller flere selvstændige delkrav pakket ind i ét samlet mindstekrav. Tilbudsgiver har identificeret 61 mindstekrav med mindst to delkrav, heraf 17 med tre eller flere. Blandt de tungeste eksempler kan nævnes: • 1.b-MK-175 (Opsætning af miljøer): 10 selvstændige delkrav • 1.b-MK-160 (Udlæsning af data til analytiske formål): 7 selvstændige delkrav • 1.b-MK-4 (GDPR, ret til indsigt): 4 selvstændige delkrav, herunder fremsøgning, sammenstilling, udlevering i læsbart format, forsendelse via Digital Post/sikker e-mail/fjernprint Da mindstekrav er ufravigelige og ikke genstand for evaluering, indebærer den valgte konstruktion, at et enkelt svagt delkrav — uanset om dette delkrav er centralt for Kundens forretningsbehov eller ej — kan medføre, at et i øvrigt fuldt kvalificeret tilbud erklæres ikke-konditionsmæssigt. Dette reducerer konkurrencen og indebærer en risiko for, at ordregivers reelle behov ikke afspejles i de krav, der reelt er ufravigelige. Proportionalitetsprincippet i udbudslovens § 2, stk. 1, og direktiv 2014/24/EU art. 18, stk. 1, kræver, at krav ikke går videre end nødvendigt for at opfylde det pågældende indkøbs formål. Når et mindstekrav sammenpakker en lang række selvstændige elementer, uden at det fremgår, hvilke der er bærende for Kundens behov, er det ikke muligt for tilbudsgiver at vurdere, om hvert enkelt delkrav er proportionalt og nødvendigt. Tilbudsgiver anmoder Ordregiver om at: 1. Bekræfte, at samtlige delkrav inden for hvert enkelt MK er ufravigelige og ligestillede, således at manglende opfyldelse af ét delkrav medfører, at tilbuddet i sin helhed er ikke-konditionsmæssigt, og 2. Redegøre for den forretningsmæssige begrundelse for at sammenpakke selvstændige krav i ét ufravigeligt mindstekrav frem for at formulere delkravene som selvstændige krav, herunder at oplyse, hvilke konkrete skadevirkninger for Kunden der vil opstå, såfremt et enkelt delkrav ikke opfyldes. Såfremt Ordregiver ikke kan godtgøre, at samtlige delkrav individuelt er nødvendige og proportionale som ufravigelige mindstekrav, anmoder Tilbudsgiver om berigtigelse, således at de sammenpakkede MK enten opdeles i selvstændige krav eller omklassificeres til evalueringskrav (K-krav), hvor det er relevant. | I48: overload
